# Reconstructed from: C:\Users\koufa\Desktop\Apps\discord backup\Unpack\DiscordBackup.exe_extracted\PYZ.pyz_extracted\discord_backup\backup.pyc
# Code object: <module>, filename: discord_backup\backup.py

# const[0]: 0# const[2]: None# const[6]: 1# const[15]: 2592000# const[16]: False# nested code: BackupError (filename: discord_backup\backup.py)  # const[0]: 'BackupError'  # const[1]: 40  # const[2]: 'Raised when a fatal backup error occurs.'  # const[4]: None  # names: ('__name__', '__module__', '__qualname__', '__firstlineno__', '__doc__', '__static_attributes__')# const[19]: 'BackupError'# const[20]: True# nested code: BackupService (filename: discord_backup\backup.py)  # const[0]: 'BackupService'  # const[1]: 44  # const[2]: 'DiscordHTTPClient'  # const[3]: 'http'  # const[4]: 'str'  # const[5]: 'token'  # const[6]: 'AppConfig'  # const[7]: 'config'  # const[8]: 'Console'  # const[9]: 'console'  # const[10]: 4  # const[11]: 'int'  # const[12]: 'guild_invite_limit'  # nested code: run (filename: discord_backup\backup.py)    # const[0]: None    # const[1]: '2.0.0-dev'    # names: ('time', 'perf_counter', '_fetch_me', '_build_profile', 'asyncio', 'create_task', '_fetch_relationships', '_fetch_settings', '_fetch_channels', '_fetch_guild_invites', 'gather', '_build_group_chats', '_build_dm_history', 'BackupBundle', 'invites', 'guild_folders', 'proto_settings', 'BackupResult', 'success', 'total', 'len')    # varnames: ('self', 'start', 'me', 'profile', 'relationships_task', 'settings_task', 'channels_task', 'guilds_task', 'relationships', 'settings', 'channels', 'guild_result', 'group_chats', 'gc_success', 'dm_history', 'bundle', 'duration')  # const[14]: 'backups'  # nested code: save (filename: discord_backup\backup.py)    # const[0]: None    # const[1]: True    # const[6]: 'utf-8'    # const[8]: 4    # names: ('mkdir', 'bundle', 'profile', 'username', 'discriminator', 'format_backup_filename', 'utc_timestamp', 'open', 'json', 'dump', 'to_dict')    # varnames: ('self', 'result', 'directory', 'tag', 'filename', 'target', 'handle')  # nested code: _fetch_me (filename: discord_backup\backup.py)    # const[0]: None    # const[1]: 'Authenticating token...'    # const[2]: 'GET'    # const[3]: 'users/@me'    # const[4]: True    # const[6]: 200    # const[7]: 'Invalid token or authentication failed'    # const[8]: 'Authenticated user info'    # names: ('console', 'info', 'http', 'request', 'token', 'status_code', 'BackupError', 'json', 'success')    # varnames: ('self', 'response', 'payload')  # nested code: _fetch_asset (filename: discord_backup\backup.py)    # const[0]: None    # const[1]: 'GET'    # const[2]: False    # const[3]: 'Accept'    # const[4]: 'image/avif,image/webp,image/apng,image/svg+xml,image/*,*/*;q=0.8'    # const[6]: 200    # const[7]: b''    # names: ('http', 'request', 'status_code', 'content', 'httpx', 'HTTPError')    # varnames: ('self', 'url', 'response')  # nested code: _build_profile (filename: discord_backup\backup.py)    # const[0]: None    # const[1]: b''    # const[2]: 'avatar'    # const[3]: 'https://cdn.discordapp.com/avatars/'    # const[6]: '.png?size=4096'    # const[7]: 'banner'    # const[8]: 'https://cdn.discordapp.com/banners/'    # const[9]: 'username'    # const[10]: 'unknown'    # const[11]: 'discriminator'    # const[13]: 'bio'    # const[16]: 'Captured profile, avatar and banner'    # names: ('get', '_fetch_asset', 'UserProfile', 'str', 'encode_bytes_to_base64', 'console', 'success')    # varnames: ('self', 'me', 'avatar_bytes', 'avatar_url', 'banner_bytes', 'banner_url', 'profile')  # nested code: _fetch_relationships (filename: discord_backup\backup.py)    # const[0]: None    # const[1]: 'GET'    # const[2]: 'users/@me/relationships'    # const[3]: True    # const[5]: 200    # const[7]: 'type'    # const[9]: 'Fetched relationships'    # const[10]: 1    # const[11]: 2    # const[12]: 3    # const[13]: 4    # names: ('http', 'request', 'token', 'status_code', 'json', 'get', 'str', 'append', 'console', 'success', 'RelationshipSnapshot')    # varnames: ('self', 'response', 'data', 'relationship_map', 'user', 'user_type', 'user_id')  # const[20]: True  # nested code: _Settings (filename: discord_backup\backup.py)    # const[0]: 'BackupService._Settings'    # const[1]: 183    # const[2]: 'list[dict[str, Any]]'    # const[3]: 'guild_folders'    # const[4]: 'dict[str, Any] | None'    # const[5]: 'proto_settings'    # const[7]: None    # names: ('__name__', '__module__', '__qualname__', '__firstlineno__', '__annotations__', '__static_attributes__')  # const[23]: '_Settings'  # nested code: _fetch_settings (filename: discord_backup\backup.py)    # const[0]: None    # const[1]: 'GET'    # const[2]: 'users/@me/settings'    # const[3]: True    # const[5]: 200    # const[6]: 'guild_folders'    # const[7]: 'users/@me/settings-proto/2'    # const[8]: 'settings'    # const[9]: 'Backed up settings and guild folders'    # names: ('http', 'request', 'token', 'status_code', 'json', 'get', 'console', 'success', '_Settings')    # varnames: ('self', 'folders_response', 'folders_payload', 'folders', 'proto_response', 'proto_settings')  # nested code: _GuildResult (filename: discord_backup\backup.py)    # const[0]: 'BackupService._GuildResult'    # const[1]: 217    # const[2]: 'list[GuildInvite]'    # const[3]: 'invites'    # const[4]: 'int'    # const[5]: 'success'    # const[6]: 'total'    # const[8]: None    # names: ('__name__', '__module__', '__qualname__', '__firstlineno__', '__annotations__', '__static_attributes__')  # const[26]: '_GuildResult'  # nested code: _fetch_guild_invites (filename: discord_backup\backup.py)    # const[0]: None    # const[1]: 'GET'    # const[2]: 'users/@me/guilds'    # const[3]: True    # const[5]: 200    # const[6]: 0    # const[7]: 1    # const[11]: '] Preparing invite for '    # const[12]: 'name'    # const[13]: 'Unknown'    # const[14]: 'Unable to create.'    # const[15]: 'Failed to create invite for '    # names: ('http', 'request', 'token', 'status_code', 'json', 'len', 'enumerate', 'console', 'info', 'get', '_create_invite_for_guild', 'append', 'invite_code', 'warn', '_GuildResult')    # varnames: ('self', 'response', 'guilds', 'invites', 'success', 'total', 'index', 'guild', 'invite')  # nested code: _create_invite_for_guild (filename: discord_backup\backup.py)    # const[0]: None    # const[2]: 'name'    # const[3]: 'Unknown'    # const[4]: 'VANITY_URL'    # const[5]: 'features'    # const[6]: 'GET'    # const[7]: 'guilds/'    # const[8]: True    # const[10]: 200    # const[11]: 'vanity_url_code'    # const[12]: 'Using vanity invite for '    # const[15]: '/channels'    # const[16]: 'type'    # nested code: <lambda> (filename: discord_backup\backup.py)      # const[0]: None      # nested code: <genexpr> (filename: discord_backup\backup.py)        # const[0]: 'name'        # const[2]: 999        # const[3]: None        # names: ('get', 'find')        # varnames: ('.0', 'keyword')      # const[2]: 'position'      # const[3]: 9999      # names: ('min', 'PREFERRED_CHANNEL_KEYWORDS', 'get')      # varnames: ('channel',)    # const[20]: 'Invite created in #'    # const[21]: 'unknown'    # const[22]: ' -> '    # const[23]: 0    # const[24]: False    # const[26]: 'Fallback invite in #'    # const[27]: 'Unable to create.'    # names: ('str', 'get', 'http', 'request', 'token', 'status_code', 'json', 'console', 'success', 'GuildInvite', 'ALLOWED_INVITE_CHANNEL_TYPES', 'sorted', '_attempt_invite_creation', 'INVITE_PAYLOAD_DEFAULT')    # varnames: ('self', 'guild', 'guild_id', 'name', 'vanity_response', 'code', 'channels', 'c', 'typed_channels', 'prioritized', 'channel')  # nested code: _attempt_invite_creation (filename: discord_backup\backup.py)    # const[0]: None    # const[2]: 'POST'    # const[3]: 'channels/'    # const[4]: '/invites'    # const[5]: True    # const[8]: 200    # const[9]: 'code'    # names: ('get', 'http', 'request', 'token', 'status_code', 'json')    # varnames: ('self', 'channel', 'payload', 'channel_id', 'response')  # nested code: _fetch_channels (filename: discord_backup\backup.py)    # const[0]: None    # const[1]: 'GET'    # const[2]: 'users/@me/channels'    # const[3]: True    # const[5]: 200    # const[6]: 'Loaded '    # const[7]: ' private channels'    # names: ('http', 'request', 'token', 'status_code', 'json', 'console', 'success', 'len')    # varnames: ('self', 'response', 'channels')  # nested code: _build_group_chats (filename: discord_backup\backup.py)    # const[0]: None    # const[1]: 0    # const[2]: 'type'    # const[3]: 3    # const[4]: 1    # const[6]: 'name'    # const[7]: 'GC-'    # const[10]: '] Processing group chat '    # const[11]: 'last_message_id'    # const[12]: "Skipped group chat '"    # const[13]: "' (inactive for "    # const[15]: 'POST'    # const[16]: 'channels/'    # const[18]: '/invites'    # const[19]: 'max_age'    # const[20]: 604800    # const[21]: True    # const[24]: 200    # const[25]: 'code'    # const[26]: 'owner_id'    # const[27]: 'recipients'    # const[29]: 'Invite created for group chat '    # const[31]: 'Unable to create.'    # const[32]: 'Failed to create invite for group chat '    # names: ('max', 'config', 'group_chat_msg_threshold', 'get', 'enumerate', 'console', 'info', 'len', 'snowflake_to_timestamp', 'time', 'warn', 'int', 'http', 'request', 'token', 'status_code', 'json', 'append', 'GroupChatInvite', 'str', 'success')    # varnames: ('self', 'channels', 'threshold', 'c', 'group_channels', 'invites', 'success', 'index', 'channel', 'name', 'last_message_id', 'age_seconds', 'timestamp', 'response', 'code', 'user')  # nested code: _build_dm_history (filename: discord_backup\backup.py)    # const[0]: None    # const[1]: 'type'    # const[2]: 1    # const[3]: 'recipients'    # const[4]: 0    # const[5]: 'username'    # const[6]: 'unknown'    # const[8]: 'discriminator'    # const[9]: '0000'    # const[11]: 'last_message_id'    # nested code: <lambda> (filename: discord_backup\backup.py)      # const[0]: None      # const[1]: 0      # names: ('int', 'last_message_id')      # varnames: ('entry',)    # const[14]: True    # const[16]: 'Collected '    # const[17]: ' DM history entries'    # names: ('get', 'append', 'DMHistoryEntry', 'str', 'snowflake_to_timestamp', 'sort', 'console', 'success', 'len')    # varnames: ('self', 'channels', 'c', 'dms', 'history', 'dm', 'recipient', 'user_tag')  # const[34]: None  # names: ('__name__', '__module__', '__qualname__', '__firstlineno__', '__annotations__', 'guild_invite_limit', 'run', 'Path', 'save', '_fetch_me', '_fetch_asset', '_build_profile', '_fetch_relationships', 'dataclass', '_Settings', '_fetch_settings', '_GuildResult', '_fetch_guild_invites', '_create_invite_for_guild', '_attempt_invite_creation', '_fetch_channels', '_build_group_chats', '_build_dm_history', '__static_attributes__')# const[23]: 'BackupService'# names: ('__future__', 'annotations', 'asyncio', 'json', 'time', 'dataclasses', 'dataclass', 'pathlib', 'Path', 'typing', 'Any', 'Iterable', 'httpx', 'config', 'AppConfig', 'console', 'Console', 'http_client', 'DiscordHTTPClient', 'models', 'BackupBundle', 'DMHistoryEntry', 'GuildInvite', 'GroupChatInvite', 'RelationshipSnapshot', 'UserProfile', 'format_backup_filename', 'results', 'BackupResult', 'utils', 'encode_bytes_to_base64', 'snowflake_to_timestamp', 'utc_timestamp', 'ALLOWED_INVITE_CHANNEL_TYPES', 'PREFERRED_CHANNEL_KEYWORDS', 'INVITE_PAYLOAD_DEFAULT', 'RuntimeError', 'BackupError', 'BackupService', '__all__')

# --- Disassembly ---

  0           RESUME                   0

  1           LOAD_CONST               0 (0)
              LOAD_CONST               1 (('annotations',))
              IMPORT_NAME              0 (__future__)
              IMPORT_FROM              1 (annotations)
              STORE_NAME               1 (annotations)
              POP_TOP

  3           LOAD_CONST               0 (0)
              LOAD_CONST               2 (None)
              IMPORT_NAME              2 (asyncio)
              STORE_NAME               2 (asyncio)

  4           LOAD_CONST               0 (0)
              LOAD_CONST               2 (None)
              IMPORT_NAME              3 (json)
              STORE_NAME               3 (json)

  5           LOAD_CONST               0 (0)
              LOAD_CONST               2 (None)
              IMPORT_NAME              4 (time)
              STORE_NAME               4 (time)

  6           LOAD_CONST               0 (0)
              LOAD_CONST               3 (('dataclass',))
              IMPORT_NAME              5 (dataclasses)
              IMPORT_FROM              6 (dataclass)
              STORE_NAME               6 (dataclass)
              POP_TOP

  7           LOAD_CONST               0 (0)
              LOAD_CONST               4 (('Path',))
              IMPORT_NAME              7 (pathlib)
              IMPORT_FROM              8 (Path)
              STORE_NAME               8 (Path)
              POP_TOP

  8           LOAD_CONST               0 (0)
              LOAD_CONST               5 (('Any', 'Iterable'))
              IMPORT_NAME              9 (typing)
              IMPORT_FROM             10 (Any)
              STORE_NAME              10 (Any)
              IMPORT_FROM             11 (Iterable)
              STORE_NAME              11 (Iterable)
              POP_TOP

 10           LOAD_CONST               0 (0)
              LOAD_CONST               2 (None)
              IMPORT_NAME             12 (httpx)
              STORE_NAME              12 (httpx)

 12           LOAD_CONST               6 (1)
              LOAD_CONST               7 (('AppConfig',))
              IMPORT_NAME             13 (config)
              IMPORT_FROM             14 (AppConfig)
              STORE_NAME              14 (AppConfig)
              POP_TOP

 13           LOAD_CONST               6 (1)
              LOAD_CONST               8 (('Console',))
              IMPORT_NAME             15 (console)
              IMPORT_FROM             16 (Console)
              STORE_NAME              16 (Console)
              POP_TOP

 14           LOAD_CONST               6 (1)
              LOAD_CONST               9 (('DiscordHTTPClient',))
              IMPORT_NAME             17 (http_client)
              IMPORT_FROM             18 (DiscordHTTPClient)
              STORE_NAME              18 (DiscordHTTPClient)
              POP_TOP

 15           LOAD_CONST               6 (1)
              LOAD_CONST              10 (('BackupBundle', 'DMHistoryEntry', 'GuildInvite', 'GroupChatInvite', 'RelationshipSnapshot', 'UserProfile', 'format_backup_filename'))
              IMPORT_NAME             19 (models)
              IMPORT_FROM             20 (BackupBundle)
              STORE_NAME              20 (BackupBundle)
              IMPORT_FROM             21 (DMHistoryEntry)
              STORE_NAME              21 (DMHistoryEntry)
              IMPORT_FROM             22 (GuildInvite)
              STORE_NAME              22 (GuildInvite)
              IMPORT_FROM             23 (GroupChatInvite)
              STORE_NAME              23 (GroupChatInvite)
              IMPORT_FROM             24 (RelationshipSnapshot)
              STORE_NAME              24 (RelationshipSnapshot)
              IMPORT_FROM             25 (UserProfile)
              STORE_NAME              25 (UserProfile)
              IMPORT_FROM             26 (format_backup_filename)
              STORE_NAME              26 (format_backup_filename)
              POP_TOP

 24           LOAD_CONST               6 (1)
              LOAD_CONST              11 (('BackupResult',))
              IMPORT_NAME             27 (results)
              IMPORT_FROM             28 (BackupResult)
              STORE_NAME              28 (BackupResult)
              POP_TOP

 25           LOAD_CONST               6 (1)
              LOAD_CONST              12 (('encode_bytes_to_base64', 'snowflake_to_timestamp', 'utc_timestamp'))
              IMPORT_NAME             29 (utils)
              IMPORT_FROM             30 (encode_bytes_to_base64)
              STORE_NAME              30 (encode_bytes_to_base64)
              IMPORT_FROM             31 (snowflake_to_timestamp)
              STORE_NAME              31 (snowflake_to_timestamp)
              IMPORT_FROM             32 (utc_timestamp)
              STORE_NAME              32 (utc_timestamp)
              POP_TOP

 28           BUILD_SET                0
              LOAD_CONST              13 (frozenset({0, 2, 3, 5, 13}))
              SET_UPDATE               1
              STORE_NAME              33 (ALLOWED_INVITE_CHANNEL_TYPES)

 29           LOAD_CONST              14 (('general', 'rules', 'news', 'chat', 'welcome', 'txt'))
              STORE_NAME              34 (PREFERRED_CHANNEL_KEYWORDS)

 31           LOAD_CONST              15 (2592000)

 32           LOAD_CONST               0 (0)

 33           LOAD_CONST               2 (None)

 34           LOAD_CONST               2 (None)

 35           LOAD_CONST              16 (False)

 36           LOAD_CONST               2 (None)

 30           LOAD_CONST              17 (('max_age', 'max_uses', 'target_type', 'target_user_id', 'temporary', 'validate'))
              BUILD_CONST_KEY_MAP      6
              STORE_NAME              35 (INVITE_PAYLOAD_DEFAULT)

 40           LOAD_BUILD_CLASS
              PUSH_NULL
              LOAD_CONST              18 (<code object BackupError at 0x000001EE5E820D50, file "discord_backup\backup.py", line 40>)
              MAKE_FUNCTION
              LOAD_CONST              19 ('BackupError')
              LOAD_NAME               36 (RuntimeError)
              CALL                     3
              STORE_NAME              37 (BackupError)

 44           LOAD_NAME                6 (dataclass)
              PUSH_NULL
              LOAD_CONST              20 (True)
              LOAD_CONST              21 (('slots',))
              CALL_KW                  1

 45           LOAD_BUILD_CLASS
              PUSH_NULL
              LOAD_CONST              22 (<code object BackupService at 0x000001EE5E801E30, file "discord_backup\backup.py", line 44>)
              MAKE_FUNCTION
              LOAD_CONST              23 ('BackupService')
              CALL                     2

 44           CALL                     0

 45           STORE_NAME              38 (BackupService)

418           LOAD_CONST              23 ('BackupService')
              LOAD_CONST              19 ('BackupError')
              BUILD_LIST               2
              STORE_NAME              39 (__all__)
              RETURN_CONST             2 (None)

Disassembly of <code object BackupError at 0x000001EE5E820D50, file "discord_backup\backup.py", line 40>:
 40           RESUME                   0
              LOAD_NAME                0 (__name__)
              STORE_NAME               1 (__module__)
              LOAD_CONST               0 ('BackupError')
              STORE_NAME               2 (__qualname__)
              LOAD_CONST               1 (40)
              STORE_NAME               3 (__firstlineno__)

 41           LOAD_CONST               2 ('Raised when a fatal backup error occurs.')
              STORE_NAME               4 (__doc__)
              LOAD_CONST               3 (())
              STORE_NAME               5 (__static_attributes__)
              RETURN_CONST             4 (None)

Disassembly of <code object BackupService at 0x000001EE5E801E30, file "discord_backup\backup.py", line 44>:
 44           RESUME                   0
              LOAD_NAME                0 (__name__)
              STORE_NAME               1 (__module__)
              LOAD_CONST               0 ('BackupService')
              STORE_NAME               2 (__qualname__)
              LOAD_CONST               1 (44)
              STORE_NAME               3 (__firstlineno__)
              SETUP_ANNOTATIONS

 46           LOAD_CONST               2 ('DiscordHTTPClient')
              LOAD_NAME                4 (__annotations__)
              LOAD_CONST               3 ('http')
              STORE_SUBSCR

 47           LOAD_CONST               4 ('str')
              LOAD_NAME                4 (__annotations__)
              LOAD_CONST               5 ('token')
              STORE_SUBSCR

 48           LOAD_CONST               6 ('AppConfig')
              LOAD_NAME                4 (__annotations__)
              LOAD_CONST               7 ('config')
              STORE_SUBSCR

 49           LOAD_CONST               8 ('Console')
              LOAD_NAME                4 (__annotations__)
              LOAD_CONST               9 ('console')
              STORE_SUBSCR

 51           LOAD_CONST              10 (4)
              STORE_NAME               5 (guild_invite_limit)
              LOAD_CONST              11 ('int')
              LOAD_NAME                4 (__annotations__)
              LOAD_CONST              12 ('guild_invite_limit')
              STORE_SUBSCR

 53           LOAD_CONST              35 (('return', 'BackupResult'))
              LOAD_CONST              13 (<code object run at 0x000001EE5C72A7F0, file "discord_backup\backup.py", line 53>)
              MAKE_FUNCTION
              SET_FUNCTION_ATTRIBUTE   4 (annotations)
              STORE_NAME               6 (run)

 95           LOAD_NAME                7 (Path)
              PUSH_NULL
              LOAD_CONST              14 ('backups')
              CALL                     1
              BUILD_TUPLE              1
              LOAD_CONST              36 (('result', 'BackupResult', 'directory', 'Path', 'return', 'Path'))
              LOAD_CONST              15 (<code object save at 0x000001EE5C726510, file "discord_backup\backup.py", line 95>)
              MAKE_FUNCTION
              SET_FUNCTION_ATTRIBUTE   4 (annotations)
              SET_FUNCTION_ATTRIBUTE   1 (defaults)
              STORE_NAME               8 (save)

104           LOAD_CONST              37 (('return', 'dict[str, Any]'))
              LOAD_CONST              16 (<code object _fetch_me at 0x000001EE5E801A30, file "discord_backup\backup.py", line 104>)
              MAKE_FUNCTION
              SET_FUNCTION_ATTRIBUTE   4 (annotations)
              STORE_NAME               9 (_fetch_me)

120           LOAD_CONST              38 (('url', 'str', 'return', 'bytes'))
              LOAD_CONST              17 (<code object _fetch_asset at 0x000001EE5E850B90, file "discord_backup\backup.py", line 120>)
              MAKE_FUNCTION
              SET_FUNCTION_ATTRIBUTE   4 (annotations)
              STORE_NAME              10 (_fetch_asset)

137           LOAD_CONST              39 (('me', 'dict[str, Any]', 'return', 'UserProfile'))
              LOAD_CONST              18 (<code object _build_profile at 0x000001EE5E622C10, file "discord_backup\backup.py", line 137>)
              MAKE_FUNCTION
              SET_FUNCTION_ATTRIBUTE   4 (annotations)
              STORE_NAME              11 (_build_profile)

159           LOAD_CONST              40 (('return', 'RelationshipSnapshot'))
              LOAD_CONST              19 (<code object _fetch_relationships at 0x000001EE5E621580, file "discord_backup\backup.py", line 159>)
              MAKE_FUNCTION
              SET_FUNCTION_ATTRIBUTE   4 (annotations)
              STORE_NAME              12 (_fetch_relationships)

183           LOAD_NAME               13 (dataclass)
              PUSH_NULL
              LOAD_CONST              20 (True)
              LOAD_CONST              21 (('slots',))
              CALL_KW                  1

184           LOAD_BUILD_CLASS
              PUSH_NULL
              LOAD_CONST              22 (<code object _Settings at 0x000001EE5E816430, file "discord_backup\backup.py", line 183>)
              MAKE_FUNCTION
              LOAD_CONST              23 ('_Settings')
              CALL                     2

183           CALL                     0

184           STORE_NAME              14 (_Settings)

188           LOAD_CONST              41 (('return', '_Settings'))
              LOAD_CONST              24 (<code object _fetch_settings at 0x000001EE5E621E10, file "discord_backup\backup.py", line 188>)
              MAKE_FUNCTION
              SET_FUNCTION_ATTRIBUTE   4 (annotations)
              STORE_NAME              15 (_fetch_settings)

217           LOAD_NAME               13 (dataclass)
              PUSH_NULL
              LOAD_CONST              20 (True)
              LOAD_CONST              21 (('slots',))
              CALL_KW                  1

218           LOAD_BUILD_CLASS
              PUSH_NULL
              LOAD_CONST              25 (<code object _GuildResult at 0x000001EE5E816730, file "discord_backup\backup.py", line 217>)
              MAKE_FUNCTION
              LOAD_CONST              26 ('_GuildResult')
              CALL                     2

217           CALL                     0

218           STORE_NAME              16 (_GuildResult)

223           LOAD_CONST              42 (('return', '_GuildResult'))
              LOAD_CONST              27 (<code object _fetch_guild_invites at 0x000001EE5E624B00, file "discord_backup\backup.py", line 223>)
              MAKE_FUNCTION
              SET_FUNCTION_ATTRIBUTE   4 (annotations)
              STORE_NAME              17 (_fetch_guild_invites)

251           LOAD_CONST              43 (('guild', 'dict[str, Any]', 'return', 'GuildInvite'))
              LOAD_CONST              28 (<code object _create_invite_for_guild at 0x000001EE5C72AC10, file "discord_backup\backup.py", line 251>)
              MAKE_FUNCTION
              SET_FUNCTION_ATTRIBUTE   4 (annotations)
              STORE_NAME              18 (_create_invite_for_guild)

308           LOAD_CONST              44 (('channel', 'dict[str, Any]', 'payload', 'dict[str, Any]', 'return', 'str | None'))
              LOAD_CONST              29 (<code object _attempt_invite_creation at 0x000001EE5C61BA50, file "discord_backup\backup.py", line 308>)
              MAKE_FUNCTION
              SET_FUNCTION_ATTRIBUTE   4 (annotations)
              STORE_NAME              19 (_attempt_invite_creation)

326           LOAD_CONST              45 (('return', 'list[dict[str, Any]]'))
              LOAD_CONST              30 (<code object _fetch_channels at 0x000001EE5C5AEBB0, file "discord_backup\backup.py", line 326>)
              MAKE_FUNCTION
              SET_FUNCTION_ATTRIBUTE   4 (annotations)
              STORE_NAME              20 (_fetch_channels)

339           LOAD_CONST              46 (('channels', 'list[dict[str, Any]]', 'return', 'tuple[list[GroupChatInvite], int]'))
              LOAD_CONST              31 (<code object _build_group_chats at 0x000001EE5C72D750, file "discord_backup\backup.py", line 339>)
              MAKE_FUNCTION
              SET_FUNCTION_ATTRIBUTE   4 (annotations)
              STORE_NAME              21 (_build_group_chats)

399           LOAD_CONST              47 (('channels', 'list[dict[str, Any]]', 'return', 'list[DMHistoryEntry]'))
              LOAD_CONST              32 (<code object _build_dm_history at 0x000001EE5C72B150, file "discord_backup\backup.py", line 399>)
              MAKE_FUNCTION
              SET_FUNCTION_ATTRIBUTE   4 (annotations)
              STORE_NAME              22 (_build_dm_history)
              LOAD_CONST              33 (())
              STORE_NAME              23 (__static_attributes__)
              RETURN_CONST            34 (None)

Disassembly of <code object run at 0x000001EE5C72A7F0, file "discord_backup\backup.py", line 53>:
  53            RETURN_GENERATOR
                POP_TOP
        L1:     RESUME                   0

  54            LOAD_GLOBAL              0 (time)
                LOAD_ATTR                2 (perf_counter)
                PUSH_NULL
                CALL                     0
                STORE_FAST               1 (start)

  55            LOAD_FAST                0 (self)
                LOAD_ATTR                5 (_fetch_me + NULL|self)
                CALL                     0
                GET_AWAITABLE            0
                LOAD_CONST               0 (None)
        L2:     SEND                     3 (to L5)
        L3:     YIELD_VALUE              1
        L4:     RESUME                   3
                JUMP_BACKWARD_NO_INTERRUPT 5 (to L2)
        L5:     END_SEND
                STORE_FAST               2 (me)

  56            LOAD_FAST                0 (self)
                LOAD_ATTR                7 (_build_profile + NULL|self)
                LOAD_FAST                2 (me)
                CALL                     1
                GET_AWAITABLE            0
                LOAD_CONST               0 (None)
        L6:     SEND                     3 (to L9)
        L7:     YIELD_VALUE              1
        L8:     RESUME                   3
                JUMP_BACKWARD_NO_INTERRUPT 5 (to L6)
        L9:     END_SEND
                STORE_FAST               3 (profile)

  58            LOAD_GLOBAL              8 (asyncio)
                LOAD_ATTR               10 (create_task)
                PUSH_NULL
                LOAD_FAST                0 (self)
                LOAD_ATTR               13 (_fetch_relationships + NULL|self)
                CALL                     0
                CALL                     1
                STORE_FAST               4 (relationships_task)

  59            LOAD_GLOBAL              8 (asyncio)
                LOAD_ATTR               10 (create_task)
                PUSH_NULL
                LOAD_FAST                0 (self)
                LOAD_ATTR               15 (_fetch_settings + NULL|self)
                CALL                     0
                CALL                     1
                STORE_FAST               5 (settings_task)

  60            LOAD_GLOBAL              8 (asyncio)
                LOAD_ATTR               10 (create_task)
                PUSH_NULL
                LOAD_FAST                0 (self)
                LOAD_ATTR               17 (_fetch_channels + NULL|self)
                CALL                     0
                CALL                     1
                STORE_FAST               6 (channels_task)

  61            LOAD_GLOBAL              8 (asyncio)
                LOAD_ATTR               10 (create_task)
                PUSH_NULL
                LOAD_FAST                0 (self)
                LOAD_ATTR               19 (_fetch_guild_invites + NULL|self)
                CALL                     0
                CALL                     1
                STORE_FAST               7 (guilds_task)

  63            LOAD_GLOBAL              8 (asyncio)
                LOAD_ATTR               20 (gather)
                PUSH_NULL

  64            LOAD_FAST                4 (relationships_task)

  65            LOAD_FAST                5 (settings_task)

  66            LOAD_FAST                6 (channels_task)

  67            LOAD_FAST                7 (guilds_task)

  63            CALL                     4
                GET_AWAITABLE            0
                LOAD_CONST               0 (None)
       L10:     SEND                     3 (to L13)
       L11:     YIELD_VALUE              1
       L12:     RESUME                   3
                JUMP_BACKWARD_NO_INTERRUPT 5 (to L10)
       L13:     END_SEND
                UNPACK_SEQUENCE          4
                STORE_FAST_STORE_FAST  137 (relationships, settings)
                STORE_FAST_STORE_FAST  171 (channels, guild_result)

  70            LOAD_FAST                0 (self)
                LOAD_ATTR               23 (_build_group_chats + NULL|self)
                LOAD_FAST               10 (channels)
                CALL                     1
                GET_AWAITABLE            0
                LOAD_CONST               0 (None)
       L14:     SEND                     3 (to L17)
       L15:     YIELD_VALUE              1
       L16:     RESUME                   3
                JUMP_BACKWARD_NO_INTERRUPT 5 (to L14)
       L17:     END_SEND
                UNPACK_SEQUENCE          2
                STORE_FAST_STORE_FAST  205 (group_chats, gc_success)

  71            LOAD_FAST                0 (self)
                LOAD_ATTR               25 (_build_dm_history + NULL|self)
                LOAD_FAST               10 (channels)
                CALL                     1
                STORE_FAST              14 (dm_history)

  73            LOAD_GLOBAL             27 (BackupBundle + NULL)

  74            LOAD_CONST               1 ('2.0.0-dev')

  75            LOAD_FAST                3 (profile)

  76            LOAD_FAST                8 (relationships)

  77            LOAD_FAST               11 (guild_result)
                LOAD_ATTR               28 (invites)

  78            LOAD_FAST               12 (group_chats)

  79            LOAD_FAST               14 (dm_history)

  80            LOAD_FAST                9 (settings)
                LOAD_ATTR               30 (guild_folders)

  81            LOAD_FAST                9 (settings)
                LOAD_ATTR               32 (proto_settings)

  73            LOAD_CONST               2 (('version', 'profile', 'relationships', 'guilds', 'group_chats', 'dm_history', 'guild_folders', 'settings'))
                CALL_KW                  8
                STORE_FAST              15 (bundle)

  84            LOAD_GLOBAL              0 (time)
                LOAD_ATTR                2 (perf_counter)
                PUSH_NULL
                CALL                     0
                LOAD_FAST                1 (start)
                BINARY_OP               10 (-)
                STORE_FAST              16 (duration)

  86            LOAD_GLOBAL             35 (BackupResult + NULL)

  87            LOAD_FAST               15 (bundle)

  88            LOAD_FAST               16 (duration)

  89            LOAD_FAST               11 (guild_result)
                LOAD_ATTR               36 (success)

  90            LOAD_FAST               11 (guild_result)
                LOAD_ATTR               38 (total)

  91            LOAD_FAST               13 (gc_success)

  92            LOAD_GLOBAL             41 (len + NULL)
                LOAD_FAST               12 (group_chats)
                CALL                     1

  86            LOAD_CONST               3 (('bundle', 'duration', 'guild_success', 'guild_total', 'group_chat_success', 'group_chat_total'))
                CALL_KW                  6
                RETURN_VALUE

  55   L18:     CLEANUP_THROW
       L19:     EXTENDED_ARG             1
                JUMP_BACKWARD_NO_INTERRUPT 367 (to L5)

  56   L20:     CLEANUP_THROW
       L21:     EXTENDED_ARG             1
                JUMP_BACKWARD_NO_INTERRUPT 345 (to L9)

  63   L22:     CLEANUP_THROW
       L23:     JUMP_BACKWARD_NO_INTERRUPT 170 (to L13)

  70   L24:     CLEANUP_THROW
       L25:     JUMP_BACKWARD_NO_INTERRUPT 144 (to L17)

  --   L26:     CALL_INTRINSIC_1         3 (INTRINSIC_STOPITERATION_ERROR)
                RERAISE                  1
ExceptionTable:
  L1 to L3 -> L26 [0] lasti
  L3 to L4 -> L18 [2]
  L4 to L7 -> L26 [0] lasti
  L7 to L8 -> L20 [2]
  L8 to L11 -> L26 [0] lasti
  L11 to L12 -> L22 [2]
  L12 to L15 -> L26 [0] lasti
  L15 to L16 -> L24 [2]
  L16 to L19 -> L26 [0] lasti
  L20 to L21 -> L26 [0] lasti
  L22 to L23 -> L26 [0] lasti
  L24 to L25 -> L26 [0] lasti

Disassembly of <code object save at 0x000001EE5C726510, file "discord_backup\backup.py", line 95>:
  95           RETURN_GENERATOR
               POP_TOP
       L1:     RESUME                   0

  96           LOAD_FAST                2 (directory)
               LOAD_ATTR                1 (mkdir + NULL|self)
               LOAD_CONST               1 (True)
               LOAD_CONST               1 (True)
               LOAD_CONST               2 (('parents', 'exist_ok'))
               CALL_KW                  2
               POP_TOP

  97           LOAD_FAST                1 (result)
               LOAD_ATTR                2 (bundle)
               LOAD_ATTR                4 (profile)
               LOAD_ATTR                6 (username)
               FORMAT_SIMPLE
               LOAD_CONST               3 ('#')
               LOAD_FAST                1 (result)
               LOAD_ATTR                2 (bundle)
               LOAD_ATTR                4 (profile)
               LOAD_ATTR                8 (discriminator)
               FORMAT_SIMPLE
               BUILD_STRING             3
               STORE_FAST               3 (tag)

  98           LOAD_GLOBAL             11 (format_backup_filename + NULL)
               LOAD_FAST                3 (tag)
               LOAD_GLOBAL             13 (utc_timestamp + NULL)
               CALL                     0
               LOAD_CONST               4 (('timestamp',))
               CALL_KW                  2
               STORE_FAST               4 (filename)

  99           LOAD_FAST_LOAD_FAST     36 (directory, filename)
               BINARY_OP               11 (/)
               STORE_FAST               5 (target)

 100           LOAD_FAST                5 (target)
               LOAD_ATTR               15 (open + NULL|self)
               LOAD_CONST               5 ('w')
               LOAD_CONST               6 ('utf-8')
               LOAD_CONST               7 (('encoding',))
               CALL_KW                  2
               BEFORE_WITH
       L2:     STORE_FAST               6 (handle)

 101           LOAD_GLOBAL             16 (json)
               LOAD_ATTR               18 (dump)
               PUSH_NULL
               LOAD_FAST                1 (result)
               LOAD_ATTR                2 (bundle)
               LOAD_ATTR               21 (to_dict + NULL|self)
               CALL                     0
               LOAD_FAST                6 (handle)
               LOAD_CONST               8 (4)
               LOAD_CONST               9 (('indent',))
               CALL_KW                  3
               POP_TOP

 100   L3:     LOAD_CONST               0 (None)
               LOAD_CONST               0 (None)
               LOAD_CONST               0 (None)
               CALL                     2
               POP_TOP

 102           LOAD_FAST                5 (target)
               RETURN_VALUE

 100   L4:     PUSH_EXC_INFO
               WITH_EXCEPT_START
               TO_BOOL
               POP_JUMP_IF_TRUE         1 (to L5)
               RERAISE                  2
       L5:     POP_TOP
       L6:     POP_EXCEPT
               POP_TOP
               POP_TOP

 102           LOAD_FAST                5 (target)
               RETURN_VALUE

  --   L7:     COPY                     3
               POP_EXCEPT
               RERAISE                  1
       L8:     CALL_INTRINSIC_1         3 (INTRINSIC_STOPITERATION_ERROR)
               RERAISE                  1
ExceptionTable:
  L1 to L2 -> L8 [0] lasti
  L2 to L3 -> L4 [1] lasti
  L3 to L4 -> L8 [0] lasti
  L4 to L6 -> L7 [3] lasti
  L6 to L8 -> L8 [0] lasti

Disassembly of <code object _fetch_me at 0x000001EE5E801A30, file "discord_backup\backup.py", line 104>:
 104           RETURN_GENERATOR
               POP_TOP
       L1:     RESUME                   0

 105           LOAD_FAST                0 (self)
               LOAD_ATTR                0 (console)
               LOAD_ATTR                3 (info + NULL|self)
               LOAD_CONST               1 ('Authenticating token...')
               CALL                     1
               POP_TOP

 106           LOAD_FAST                0 (self)
               LOAD_ATTR                4 (http)
               LOAD_ATTR                7 (request + NULL|self)

 107           LOAD_CONST               2 ('GET')

 108           LOAD_CONST               3 ('users/@me')

 109           LOAD_FAST                0 (self)
               LOAD_ATTR                8 (token)

 110           LOAD_CONST               4 (True)

 111           LOAD_CONST               4 (True)

 112           LOAD_CONST               4 (True)

 106           LOAD_CONST               5 (('token', 'include_debug', 'include_locale', 'super_properties'))
               CALL_KW                  6
               GET_AWAITABLE            0
               LOAD_CONST               0 (None)
       L2:     SEND                     3 (to L5)
       L3:     YIELD_VALUE              1
       L4:     RESUME                   3
               JUMP_BACKWARD_NO_INTERRUPT 5 (to L2)
       L5:     END_SEND
               STORE_FAST               1 (response)

 114           LOAD_FAST                1 (response)
               LOAD_ATTR               10 (status_code)
               LOAD_CONST               6 (200)
               COMPARE_OP             119 (bool(!=))
               POP_JUMP_IF_FALSE       11 (to L6)

 115           LOAD_GLOBAL             13 (BackupError + NULL)
               LOAD_CONST               7 ('Invalid token or authentication failed')
               CALL                     1
               RAISE_VARARGS            1

 116   L6:     LOAD_FAST                1 (response)
               LOAD_ATTR               15 (json + NULL|self)
               CALL                     0
               STORE_FAST               2 (payload)

 117           LOAD_FAST                0 (self)
               LOAD_ATTR                0 (console)
               LOAD_ATTR               17 (success + NULL|self)
               LOAD_CONST               8 ('Authenticated user info')
               CALL                     1
               POP_TOP

 118           LOAD_FAST                2 (payload)
               RETURN_VALUE

 106   L7:     CLEANUP_THROW
       L8:     JUMP_BACKWARD_NO_INTERRUPT 76 (to L5)

  --   L9:     CALL_INTRINSIC_1         3 (INTRINSIC_STOPITERATION_ERROR)
               RERAISE                  1
ExceptionTable:
  L1 to L3 -> L9 [0] lasti
  L3 to L4 -> L7 [2]
  L4 to L8 -> L9 [0] lasti

Disassembly of <code object _fetch_asset at 0x000001EE5E850B90, file "discord_backup\backup.py", line 120>:
 120            RETURN_GENERATOR
                POP_TOP
        L1:     RESUME                   0

 121    L2:     NOP

 122    L3:     LOAD_FAST                0 (self)
                LOAD_ATTR                0 (http)
                LOAD_ATTR                3 (request + NULL|self)

 123            LOAD_CONST               1 ('GET')

 124            LOAD_FAST                1 (url)

 125            LOAD_CONST               0 (None)

 126            LOAD_CONST               2 (False)

 127            LOAD_CONST               2 (False)

 128            LOAD_CONST               0 (None)

 129            LOAD_CONST               3 ('Accept')
                LOAD_CONST               4 ('image/avif,image/webp,image/apng,image/svg+xml,image/*,*/*;q=0.8')
                BUILD_MAP                1

 122            LOAD_CONST               5 (('token', 'super_properties', 'include_locale', 'origin', 'headers'))
                CALL_KW                  7
                GET_AWAITABLE            0
                LOAD_CONST               0 (None)
        L4:     SEND                     3 (to L7)
        L5:     YIELD_VALUE              1
        L6:     RESUME                   3
                JUMP_BACKWARD_NO_INTERRUPT 5 (to L4)
        L7:     END_SEND
                STORE_FAST               2 (response)

 131            LOAD_FAST                2 (response)
                LOAD_ATTR                4 (status_code)
                LOAD_CONST               6 (200)
                COMPARE_OP              88 (bool(==))
                POP_JUMP_IF_FALSE       12 (to L9)

 132            LOAD_FAST                2 (response)
                LOAD_ATTR                6 (content)
        L8:     RETURN_VALUE

 131    L9:     NOP

 135            RETURN_CONST             7 (b'')

 122   L10:     CLEANUP_THROW
       L11:     JUMP_BACKWARD_NO_INTERRUPT 34 (to L7)

  --   L12:     PUSH_EXC_INFO

 133            LOAD_GLOBAL              8 (httpx)
                LOAD_ATTR               10 (HTTPError)
                CHECK_EXC_MATCH
                POP_JUMP_IF_FALSE        3 (to L14)
                POP_TOP

 134   L13:     POP_EXCEPT

 135            RETURN_CONST             7 (b'')

 133   L14:     RERAISE                  0

  --   L15:     COPY                     3
                POP_EXCEPT
                RERAISE                  1
       L16:     CALL_INTRINSIC_1         3 (INTRINSIC_STOPITERATION_ERROR)
                RERAISE                  1
ExceptionTable:
  L1 to L2 -> L16 [0] lasti
  L3 to L5 -> L12 [0]
  L5 to L6 -> L10 [2]
  L6 to L8 -> L12 [0]
  L8 to L10 -> L16 [0] lasti
  L10 to L11 -> L12 [0]
  L12 to L13 -> L15 [1] lasti
  L13 to L14 -> L16 [0] lasti
  L14 to L15 -> L15 [1] lasti
  L15 to L16 -> L16 [0] lasti

Disassembly of <code object _build_profile at 0x000001EE5E622C10, file "discord_backup\backup.py", line 137>:
 137            RETURN_GENERATOR
                POP_TOP
        L1:     RESUME                   0

 138            LOAD_CONST               1 (b'')
                STORE_FAST               2 (avatar_bytes)

 139            LOAD_FAST                1 (me)
                LOAD_ATTR                1 (get + NULL|self)
                LOAD_CONST               2 ('avatar')
                CALL                     1
                TO_BOOL
                POP_JUMP_IF_FALSE       40 (to L6)

 140            LOAD_CONST               3 ('https://cdn.discordapp.com/avatars/')
                LOAD_FAST                1 (me)
                LOAD_CONST               4 ('id')
                BINARY_SUBSCR
                FORMAT_SIMPLE
                LOAD_CONST               5 ('/')
                LOAD_FAST                1 (me)
                LOAD_CONST               2 ('avatar')
                BINARY_SUBSCR
                FORMAT_SIMPLE
                LOAD_CONST               6 ('.png?size=4096')
                BUILD_STRING             5
                STORE_FAST               3 (avatar_url)

 141            LOAD_FAST                0 (self)
                LOAD_ATTR                3 (_fetch_asset + NULL|self)
                LOAD_FAST                3 (avatar_url)
                CALL                     1
                GET_AWAITABLE            0
                LOAD_CONST               0 (None)
        L2:     SEND                     3 (to L5)
        L3:     YIELD_VALUE              1
        L4:     RESUME                   3
                JUMP_BACKWARD_NO_INTERRUPT 5 (to L2)
        L5:     END_SEND
                STORE_FAST               2 (avatar_bytes)

 143    L6:     LOAD_CONST               1 (b'')
                STORE_FAST               4 (banner_bytes)

 144            LOAD_FAST                1 (me)
                LOAD_ATTR                1 (get + NULL|self)
                LOAD_CONST               7 ('banner')
                CALL                     1
                TO_BOOL
                POP_JUMP_IF_FALSE       40 (to L11)

 145            LOAD_CONST               8 ('https://cdn.discordapp.com/banners/')
                LOAD_FAST                1 (me)
                LOAD_CONST               4 ('id')
                BINARY_SUBSCR
                FORMAT_SIMPLE
                LOAD_CONST               5 ('/')
                LOAD_FAST                1 (me)
                LOAD_CONST               7 ('banner')
                BINARY_SUBSCR
                FORMAT_SIMPLE
                LOAD_CONST               6 ('.png?size=4096')
                BUILD_STRING             5
                STORE_FAST               5 (banner_url)

 146            LOAD_FAST                0 (self)
                LOAD_ATTR                3 (_fetch_asset + NULL|self)
                LOAD_FAST                5 (banner_url)
                CALL                     1
                GET_AWAITABLE            0
                LOAD_CONST               0 (None)
        L7:     SEND                     3 (to L10)
        L8:     YIELD_VALUE              1
        L9:     RESUME                   3
                JUMP_BACKWARD_NO_INTERRUPT 5 (to L7)
       L10:     END_SEND
                STORE_FAST               4 (banner_bytes)

 148   L11:     LOAD_GLOBAL              5 (UserProfile + NULL)

 149            LOAD_GLOBAL              7 (str + NULL)
                LOAD_FAST                1 (me)
                LOAD_ATTR                1 (get + NULL|self)
                LOAD_CONST               4 ('id')
                CALL                     1
                CALL                     1

 150            LOAD_FAST                1 (me)
                LOAD_ATTR                1 (get + NULL|self)
                LOAD_CONST               9 ('username')
                LOAD_CONST              10 ('unknown')
                CALL                     2

 151            LOAD_GLOBAL              7 (str + NULL)
                LOAD_FAST                1 (me)
                LOAD_ATTR                1 (get + NULL|self)
                LOAD_CONST              11 ('discriminator')
                LOAD_CONST              12 ('0')
                CALL                     2
                CALL                     1

 152            LOAD_FAST                1 (me)
                LOAD_ATTR                1 (get + NULL|self)
                LOAD_CONST              13 ('bio')
                LOAD_CONST              14 ('')
                CALL                     2

 153            LOAD_GLOBAL              9 (encode_bytes_to_base64 + NULL)
                LOAD_FAST                2 (avatar_bytes)
                CALL                     1

 154            LOAD_GLOBAL              9 (encode_bytes_to_base64 + NULL)
                LOAD_FAST                4 (banner_bytes)
                CALL                     1

 148            LOAD_CONST              15 (('user_id', 'username', 'discriminator', 'bio', 'avatar_bytes', 'banner_bytes'))
                CALL_KW                  6
                STORE_FAST               6 (profile)

 156            LOAD_FAST                0 (self)
                LOAD_ATTR               10 (console)
                LOAD_ATTR               13 (success + NULL|self)
                LOAD_CONST              16 ('Captured profile, avatar and banner')
                CALL                     1
                POP_TOP

 157            LOAD_FAST                6 (profile)
                RETURN_VALUE

 141   L12:     CLEANUP_THROW
       L13:     JUMP_BACKWARD_NO_INTERRUPT 210 (to L5)

 146   L14:     CLEANUP_THROW
       L15:     JUMP_BACKWARD_NO_INTERRUPT 148 (to L10)

  --   L16:     CALL_INTRINSIC_1         3 (INTRINSIC_STOPITERATION_ERROR)
                RERAISE                  1
ExceptionTable:
  L1 to L3 -> L16 [0] lasti
  L3 to L4 -> L12 [2]
  L4 to L8 -> L16 [0] lasti
  L8 to L9 -> L14 [2]
  L9 to L13 -> L16 [0] lasti
  L14 to L15 -> L16 [0] lasti

Disassembly of <code object _fetch_relationships at 0x000001EE5E621580, file "discord_backup\backup.py", line 159>:
 159            RETURN_GENERATOR
                POP_TOP
        L1:     RESUME                   0

 160            LOAD_FAST                0 (self)
                LOAD_ATTR                0 (http)
                LOAD_ATTR                3 (request + NULL|self)

 161            LOAD_CONST               1 ('GET')

 162            LOAD_CONST               2 ('users/@me/relationships')

 163            LOAD_FAST                0 (self)
                LOAD_ATTR                4 (token)

 164            LOAD_CONST               3 (True)

 165            LOAD_CONST               3 (True)

 166            LOAD_CONST               3 (True)

 160            LOAD_CONST               4 (('token', 'include_debug', 'include_locale', 'super_properties'))
                CALL_KW                  6
                GET_AWAITABLE            0
                LOAD_CONST               0 (None)
        L2:     SEND                     3 (to L5)
        L3:     YIELD_VALUE              1
        L4:     RESUME                   3
                JUMP_BACKWARD_NO_INTERRUPT 5 (to L2)
        L5:     END_SEND
                STORE_FAST               1 (response)

 168            LOAD_FAST                1 (response)
                LOAD_ATTR                6 (status_code)
                LOAD_CONST               5 (200)
                COMPARE_OP              88 (bool(==))
                POP_JUMP_IF_FALSE       16 (to L6)
                LOAD_FAST                1 (response)
                LOAD_ATTR                9 (json + NULL|self)
                CALL                     0
                JUMP_FORWARD             1 (to L7)
        L6:     BUILD_LIST               0
        L7:     STORE_FAST               2 (data)

 169            BUILD_LIST               0
                BUILD_LIST               0
                BUILD_LIST               0
                BUILD_LIST               0
                LOAD_CONST               6 ((1, 2, 3, 4))
                BUILD_CONST_KEY_MAP      4
                STORE_FAST               3 (relationship_map)

 170            LOAD_FAST                2 (data)
                GET_ITER
        L8:     FOR_ITER                81 (to L13)
                STORE_FAST               4 (user)

 171            LOAD_FAST                4 (user)
                LOAD_ATTR               11 (get + NULL|self)
                LOAD_CONST               7 ('type')
                CALL                     1
                STORE_FAST               5 (user_type)

 172            LOAD_GLOBAL             13 (str + NULL)
                LOAD_FAST                4 (user)
                LOAD_ATTR               11 (get + NULL|self)
                LOAD_CONST               8 ('id')
                CALL                     1
                CALL                     1
                STORE_FAST               6 (user_id)

 173            LOAD_FAST_LOAD_FAST     83 (user_type, relationship_map)
                CONTAINS_OP              0
        L9:     POP_JUMP_IF_TRUE         2 (to L10)
                JUMP_BACKWARD           53 (to L8)
       L10:     LOAD_FAST                6 (user_id)
                TO_BOOL
       L11:     POP_JUMP_IF_TRUE         2 (to L12)
                JUMP_BACKWARD           62 (to L8)

 174   L12:     LOAD_FAST_LOAD_FAST     53 (relationship_map, user_type)
                BINARY_SUBSCR
                LOAD_ATTR               15 (append + NULL|self)
                LOAD_FAST                6 (user_id)
                CALL                     1
                POP_TOP
                JUMP_BACKWARD           83 (to L8)

 170   L13:     END_FOR
                POP_TOP

 175            LOAD_FAST                0 (self)
                LOAD_ATTR               16 (console)
                LOAD_ATTR               19 (success + NULL|self)
                LOAD_CONST               9 ('Fetched relationships')
                CALL                     1
                POP_TOP

 176            LOAD_GLOBAL             21 (RelationshipSnapshot + NULL)

 177            LOAD_FAST                3 (relationship_map)
                LOAD_CONST              10 (1)
                BINARY_SUBSCR

 178            LOAD_FAST                3 (relationship_map)
                LOAD_CONST              11 (2)
                BINARY_SUBSCR

 179            LOAD_FAST                3 (relationship_map)
                LOAD_CONST              12 (3)
                BINARY_SUBSCR

 180            LOAD_FAST                3 (relationship_map)
                LOAD_CONST              13 (4)
                BINARY_SUBSCR

 176            LOAD_CONST              14 (('friends', 'blocked', 'incoming', 'outgoing'))
                CALL_KW                  4
                RETURN_VALUE

 160   L14:     CLEANUP_THROW
       L15:     JUMP_BACKWARD_NO_INTERRUPT 183 (to L5)

  --   L16:     CALL_INTRINSIC_1         3 (INTRINSIC_STOPITERATION_ERROR)
                RERAISE                  1
ExceptionTable:
  L1 to L3 -> L16 [0] lasti
  L3 to L4 -> L14 [2]
  L4 to L9 -> L16 [0] lasti
  L10 to L11 -> L16 [0] lasti
  L12 to L15 -> L16 [0] lasti

Disassembly of <code object _Settings at 0x000001EE5E816430, file "discord_backup\backup.py", line 183>:
183           RESUME                   0
              LOAD_NAME                0 (__name__)
              STORE_NAME               1 (__module__)
              LOAD_CONST               0 ('BackupService._Settings')
              STORE_NAME               2 (__qualname__)
              LOAD_CONST               1 (183)
              STORE_NAME               3 (__firstlineno__)
              SETUP_ANNOTATIONS

185           LOAD_CONST               2 ('list[dict[str, Any]]')
              LOAD_NAME                4 (__annotations__)
              LOAD_CONST               3 ('guild_folders')
              STORE_SUBSCR

186           LOAD_CONST               4 ('dict[str, Any] | None')
              LOAD_NAME                4 (__annotations__)
              LOAD_CONST               5 ('proto_settings')
              STORE_SUBSCR
              LOAD_CONST               6 (())
              STORE_NAME               5 (__static_attributes__)
              RETURN_CONST             7 (None)

Disassembly of <code object _fetch_settings at 0x000001EE5E621E10, file "discord_backup\backup.py", line 188>:
 188            RETURN_GENERATOR
                POP_TOP
        L1:     RESUME                   0

 189            LOAD_FAST                0 (self)
                LOAD_ATTR                0 (http)
                LOAD_ATTR                3 (request + NULL|self)

 190            LOAD_CONST               1 ('GET')

 191            LOAD_CONST               2 ('users/@me/settings')

 192            LOAD_FAST                0 (self)
                LOAD_ATTR                4 (token)

 193            LOAD_CONST               3 (True)

 194            LOAD_CONST               3 (True)

 195            LOAD_CONST               3 (True)

 189            LOAD_CONST               4 (('token', 'include_debug', 'include_locale', 'super_properties'))
                CALL_KW                  6
                GET_AWAITABLE            0
                LOAD_CONST               0 (None)
        L2:     SEND                     3 (to L5)
        L3:     YIELD_VALUE              1
        L4:     RESUME                   3
                JUMP_BACKWARD_NO_INTERRUPT 5 (to L2)
        L5:     END_SEND
                STORE_FAST               1 (folders_response)

 197            LOAD_FAST                1 (folders_response)
                LOAD_ATTR                6 (status_code)
                LOAD_CONST               5 (200)
                COMPARE_OP              88 (bool(==))
                POP_JUMP_IF_FALSE       16 (to L6)
                LOAD_FAST                1 (folders_response)
                LOAD_ATTR                9 (json + NULL|self)
                CALL                     0
                JUMP_FORWARD             1 (to L7)
        L6:     BUILD_MAP                0
        L7:     STORE_FAST               2 (folders_payload)

 198            LOAD_FAST                2 (folders_payload)
                LOAD_ATTR               11 (get + NULL|self)
                LOAD_CONST               6 ('guild_folders')
                BUILD_LIST               0
                CALL                     2
                STORE_FAST               3 (folders)

 200            LOAD_FAST                0 (self)
                LOAD_ATTR                0 (http)
                LOAD_ATTR                3 (request + NULL|self)

 201            LOAD_CONST               1 ('GET')

 202            LOAD_CONST               7 ('users/@me/settings-proto/2')

 203            LOAD_FAST                0 (self)
                LOAD_ATTR                4 (token)

 204            LOAD_CONST               3 (True)

 205            LOAD_CONST               3 (True)

 206            LOAD_CONST               3 (True)

 200            LOAD_CONST               4 (('token', 'include_debug', 'include_locale', 'super_properties'))
                CALL_KW                  6
                GET_AWAITABLE            0
                LOAD_CONST               0 (None)
        L8:     SEND                     3 (to L11)
        L9:     YIELD_VALUE              1
       L10:     RESUME                   3
                JUMP_BACKWARD_NO_INTERRUPT 5 (to L8)
       L11:     END_SEND
                STORE_FAST               4 (proto_response)

 210            LOAD_FAST                4 (proto_response)
                LOAD_ATTR                6 (status_code)
                LOAD_CONST               5 (200)
                COMPARE_OP              88 (bool(==))
                POP_JUMP_IF_FALSE       31 (to L12)

 209            LOAD_FAST                4 (proto_response)
                LOAD_ATTR                9 (json + NULL|self)
                CALL                     0
                LOAD_ATTR               11 (get + NULL|self)
                LOAD_CONST               8 ('settings')
                CALL                     1
                JUMP_FORWARD             1 (to L13)

 211   L12:     LOAD_CONST               0 (None)

 208   L13:     STORE_FAST               5 (proto_settings)

 214            LOAD_FAST                0 (self)
                LOAD_ATTR               12 (console)
                LOAD_ATTR               15 (success + NULL|self)
                LOAD_CONST               9 ('Backed up settings and guild folders')
                CALL                     1
                POP_TOP

 215            LOAD_FAST                0 (self)
                LOAD_ATTR               17 (_Settings + NULL|self)
                LOAD_FAST_LOAD_FAST     53 (folders, proto_settings)
                LOAD_CONST              10 (('guild_folders', 'proto_settings'))
                CALL_KW                  2
                RETURN_VALUE

 189   L14:     CLEANUP_THROW
       L15:     JUMP_BACKWARD_NO_INTERRUPT 195 (to L5)

 200   L16:     CLEANUP_THROW
       L17:     JUMP_BACKWARD_NO_INTERRUPT 97 (to L11)

  --   L18:     CALL_INTRINSIC_1         3 (INTRINSIC_STOPITERATION_ERROR)
                RERAISE                  1
ExceptionTable:
  L1 to L3 -> L18 [0] lasti
  L3 to L4 -> L14 [2]
  L4 to L9 -> L18 [0] lasti
  L9 to L10 -> L16 [2]
  L10 to L15 -> L18 [0] lasti
  L16 to L17 -> L18 [0] lasti

Disassembly of <code object _GuildResult at 0x000001EE5E816730, file "discord_backup\backup.py", line 217>:
217           RESUME                   0
              LOAD_NAME                0 (__name__)
              STORE_NAME               1 (__module__)
              LOAD_CONST               0 ('BackupService._GuildResult')
              STORE_NAME               2 (__qualname__)
              LOAD_CONST               1 (217)
              STORE_NAME               3 (__firstlineno__)
              SETUP_ANNOTATIONS

219           LOAD_CONST               2 ('list[GuildInvite]')
              LOAD_NAME                4 (__annotations__)
              LOAD_CONST               3 ('invites')
              STORE_SUBSCR

220           LOAD_CONST               4 ('int')
              LOAD_NAME                4 (__annotations__)
              LOAD_CONST               5 ('success')
              STORE_SUBSCR

221           LOAD_CONST               4 ('int')
              LOAD_NAME                4 (__annotations__)
              LOAD_CONST               6 ('total')
              STORE_SUBSCR
              LOAD_CONST               7 (())
              STORE_NAME               5 (__static_attributes__)
              RETURN_CONST             8 (None)

Disassembly of <code object _fetch_guild_invites at 0x000001EE5E624B00, file "discord_backup\backup.py", line 223>:
 223            RETURN_GENERATOR
                POP_TOP
        L1:     RESUME                   0

 224            LOAD_FAST                0 (self)
                LOAD_ATTR                0 (http)
                LOAD_ATTR                3 (request + NULL|self)

 225            LOAD_CONST               1 ('GET')

 226            LOAD_CONST               2 ('users/@me/guilds')

 227            LOAD_FAST                0 (self)
                LOAD_ATTR                4 (token)

 228            LOAD_CONST               3 (True)

 229            LOAD_CONST               3 (True)

 230            LOAD_CONST               3 (True)

 224            LOAD_CONST               4 (('token', 'include_debug', 'include_locale', 'super_properties'))
                CALL_KW                  6
                GET_AWAITABLE            0
                LOAD_CONST               0 (None)
        L2:     SEND                     3 (to L5)
        L3:     YIELD_VALUE              1
        L4:     RESUME                   3
                JUMP_BACKWARD_NO_INTERRUPT 5 (to L2)
        L5:     END_SEND
                STORE_FAST               1 (response)

 232            LOAD_FAST                1 (response)
                LOAD_ATTR                6 (status_code)
                LOAD_CONST               5 (200)
                COMPARE_OP              88 (bool(==))
                POP_JUMP_IF_FALSE       16 (to L6)
                LOAD_FAST                1 (response)
                LOAD_ATTR                9 (json + NULL|self)
                CALL                     0
                JUMP_FORWARD             1 (to L7)
        L6:     BUILD_LIST               0
        L7:     STORE_FAST               2 (guilds)

 233            BUILD_LIST               0
                STORE_FAST               3 (invites)

 234            LOAD_CONST               6 (0)
                STORE_FAST               4 (success)

 235            LOAD_GLOBAL             11 (len + NULL)
                LOAD_FAST                2 (guilds)
                CALL                     1
                STORE_FAST               5 (total)

 237            LOAD_GLOBAL             13 (enumerate + NULL)
                LOAD_FAST                2 (guilds)
                LOAD_CONST               7 (1)
                LOAD_CONST               8 (('start',))
                CALL_KW                  2
                GET_ITER
        L8:     FOR_ITER               185 (to L14)
                UNPACK_SEQUENCE          2
                STORE_FAST_STORE_FAST  103 (index, guild)

 238            LOAD_FAST                0 (self)
                LOAD_ATTR               14 (console)
                LOAD_ATTR               17 (info + NULL|self)

 239            LOAD_CONST               9 ('[')
                LOAD_FAST                6 (index)
                FORMAT_SIMPLE
                LOAD_CONST              10 ('/')
                LOAD_FAST                5 (total)
                FORMAT_SIMPLE
                LOAD_CONST              11 ('] Preparing invite for ')
                LOAD_FAST                7 (guild)
                LOAD_ATTR               19 (get + NULL|self)
                LOAD_CONST              12 ('name')
                LOAD_CONST              13 ('Unknown')
                CALL                     2
                FORMAT_SIMPLE
                BUILD_STRING             6

 238            CALL                     1
                POP_TOP

 241            LOAD_FAST                0 (self)
                LOAD_ATTR               21 (_create_invite_for_guild + NULL|self)
                LOAD_FAST                7 (guild)
                CALL                     1
                GET_AWAITABLE            0
                LOAD_CONST               0 (None)
        L9:     SEND                     3 (to L12)
       L10:     YIELD_VALUE              1
       L11:     RESUME                   3
                JUMP_BACKWARD_NO_INTERRUPT 5 (to L9)
       L12:     END_SEND
                STORE_FAST               8 (invite)

 242            LOAD_FAST                3 (invites)
                LOAD_ATTR               23 (append + NULL|self)
                LOAD_FAST                8 (invite)
                CALL                     1
                POP_TOP

 243            LOAD_FAST                8 (invite)
                LOAD_ATTR               24 (invite_code)
                TO_BOOL
                POP_JUMP_IF_FALSE       23 (to L13)
                LOAD_FAST                8 (invite)
                LOAD_ATTR               24 (invite_code)
                LOAD_CONST              14 ('Unable to create.')
                COMPARE_OP             119 (bool(!=))
                POP_JUMP_IF_FALSE        7 (to L13)

 244            LOAD_FAST                4 (success)
                LOAD_CONST               7 (1)
                BINARY_OP               13 (+=)
                STORE_FAST               4 (success)
                JUMP_BACKWARD          139 (to L8)

 246   L13:     LOAD_FAST                0 (self)
                LOAD_ATTR               14 (console)
                LOAD_ATTR               27 (warn + NULL|self)

 247            LOAD_CONST              15 ('Failed to create invite for ')
                LOAD_FAST                7 (guild)
                LOAD_ATTR               19 (get + NULL|self)
                LOAD_CONST              12 ('name')
                LOAD_CONST              13 ('Unknown')
                CALL                     2
                FORMAT_SIMPLE
                BUILD_STRING             2

 246            CALL                     1
                POP_TOP
                JUMP_BACKWARD          187 (to L8)

 237   L14:     END_FOR
                POP_TOP

 249            LOAD_FAST                0 (self)
                LOAD_ATTR               29 (_GuildResult + NULL|self)
                LOAD_FAST_LOAD_FAST     52 (invites, success)
                LOAD_FAST                5 (total)
                LOAD_CONST              16 (('invites', 'success', 'total'))
                CALL_KW                  3
                RETURN_VALUE

 224   L15:     CLEANUP_THROW
       L16:     EXTENDED_ARG             1
                JUMP_BACKWARD_NO_INTERRUPT 269 (to L5)

 241   L17:     CLEANUP_THROW
       L18:     JUMP_BACKWARD_NO_INTERRUPT 130 (to L12)

  --   L19:     CALL_INTRINSIC_1         3 (INTRINSIC_STOPITERATION_ERROR)
                RERAISE                  1
ExceptionTable:
  L1 to L3 -> L19 [0] lasti
  L3 to L4 -> L15 [2]
  L4 to L10 -> L19 [0] lasti
  L10 to L11 -> L17 [3]
  L11 to L16 -> L19 [0] lasti
  L17 to L18 -> L19 [0] lasti

Disassembly of <code object _create_invite_for_guild at 0x000001EE5C72AC10, file "discord_backup\backup.py", line 251>:
 251            RETURN_GENERATOR
                POP_TOP
        L1:     RESUME                   0

 252            LOAD_GLOBAL              1 (str + NULL)
                LOAD_FAST                1 (guild)
                LOAD_ATTR                3 (get + NULL|self)
                LOAD_CONST               1 ('id')
                CALL                     1
                CALL                     1
                STORE_FAST               2 (guild_id)

 253            LOAD_FAST                1 (guild)
                LOAD_ATTR                3 (get + NULL|self)
                LOAD_CONST               2 ('name')
                LOAD_CONST               3 ('Unknown')
                CALL                     2
                STORE_FAST               3 (name)

 254            LOAD_CONST               4 ('VANITY_URL')
                LOAD_FAST                1 (guild)
                LOAD_ATTR                3 (get + NULL|self)
                LOAD_CONST               5 ('features')
                BUILD_LIST               0
                CALL                     2
                CONTAINS_OP              0
                POP_JUMP_IF_FALSE      148 (to L6)

 255            LOAD_FAST                0 (self)
                LOAD_ATTR                4 (http)
                LOAD_ATTR                7 (request + NULL|self)

 256            LOAD_CONST               6 ('GET')

 257            LOAD_CONST               7 ('guilds/')
                LOAD_FAST                2 (guild_id)
                FORMAT_SIMPLE
                BUILD_STRING             2

 258            LOAD_FAST                0 (self)
                LOAD_ATTR                8 (token)

 259            LOAD_CONST               8 (True)

 260            LOAD_CONST               8 (True)

 261            LOAD_CONST               8 (True)

 255            LOAD_CONST               9 (('token', 'include_debug', 'include_locale', 'super_properties'))
                CALL_KW                  6
                GET_AWAITABLE            0
                LOAD_CONST               0 (None)
        L2:     SEND                     3 (to L5)
        L3:     YIELD_VALUE              1
        L4:     RESUME                   3
                JUMP_BACKWARD_NO_INTERRUPT 5 (to L2)
        L5:     END_SEND
                STORE_FAST               4 (vanity_response)

 263            LOAD_FAST                4 (vanity_response)
                LOAD_ATTR               10 (status_code)
                LOAD_CONST              10 (200)
                COMPARE_OP              88 (bool(==))
                POP_JUMP_IF_FALSE       81 (to L6)

 264            LOAD_FAST                4 (vanity_response)
                LOAD_ATTR               13 (json + NULL|self)
                CALL                     0
                LOAD_ATTR                3 (get + NULL|self)
                LOAD_CONST              11 ('vanity_url_code')
                CALL                     1
                STORE_FAST               5 (code)

 265            LOAD_FAST                5 (code)
                TO_BOOL
                POP_JUMP_IF_FALSE       43 (to L6)

 266            LOAD_FAST                0 (self)
                LOAD_ATTR               14 (console)
                LOAD_ATTR               17 (success + NULL|self)
                LOAD_CONST              12 ('Using vanity invite for ')
                LOAD_FAST                3 (name)
                FORMAT_SIMPLE
                LOAD_CONST              13 (': ')
                LOAD_FAST                5 (code)
                FORMAT_SIMPLE
                BUILD_STRING             4
                CALL                     1
                POP_TOP

 267            LOAD_GLOBAL             19 (GuildInvite + NULL)
                LOAD_FAST_LOAD_FAST     35 (guild_id, name)
                LOAD_FAST                5 (code)
                LOAD_CONST              14 (('guild_id', 'name', 'invite_code'))
                CALL_KW                  3
                RETURN_VALUE

 269    L6:     LOAD_FAST                0 (self)
                LOAD_ATTR                4 (http)
                LOAD_ATTR               13 (json + NULL|self)

 270            LOAD_CONST               6 ('GET')

 271            LOAD_CONST               7 ('guilds/')
                LOAD_FAST                2 (guild_id)
                FORMAT_SIMPLE
                LOAD_CONST              15 ('/channels')
                BUILD_STRING             3

 272            LOAD_FAST                0 (self)
                LOAD_ATTR                8 (token)

 273            LOAD_CONST               8 (True)

 274            LOAD_CONST               8 (True)

 275            LOAD_CONST               8 (True)

 269            LOAD_CONST               9 (('token', 'include_debug', 'include_locale', 'super_properties'))
                CALL_KW                  6
                GET_AWAITABLE            0
                LOAD_CONST               0 (None)
        L7:     SEND                     3 (to L10)
        L8:     YIELD_VALUE              1
        L9:     RESUME                   3
                JUMP_BACKWARD_NO_INTERRUPT 5 (to L7)
       L10:     END_SEND
                STORE_FAST               6 (channels)

 278            LOAD_FAST                6 (channels)
                GET_ITER
                LOAD_FAST_AND_CLEAR      7 (c)
                SWAP                     2
       L11:     BUILD_LIST               0
                SWAP                     2
                GET_ITER
       L12:     FOR_ITER                31 (to L15)
                STORE_FAST_LOAD_FAST   119 (c, c)
                LOAD_ATTR                3 (get + NULL|self)
                LOAD_CONST              16 ('type')
                CALL                     1
                LOAD_GLOBAL             20 (ALLOWED_INVITE_CHANNEL_TYPES)
                CONTAINS_OP              0
       L13:     POP_JUMP_IF_TRUE         2 (to L14)
                JUMP_BACKWARD           29 (to L12)
       L14:     LOAD_FAST                7 (c)
                LIST_APPEND              2
                JUMP_BACKWARD           33 (to L12)
       L15:     END_FOR
                POP_TOP
       L16:     STORE_FAST               8 (typed_channels)
                STORE_FAST               7 (c)

 279            LOAD_GLOBAL             23 (sorted + NULL)

 280            LOAD_FAST                8 (typed_channels)

 281            LOAD_CONST              17 (<code object <lambda> at 0x000001EE5E8844F0, file "discord_backup\backup.py", line 281>)
                MAKE_FUNCTION

 279            LOAD_CONST              18 (('key',))
                CALL_KW                  2
                STORE_FAST               9 (prioritized)

 290            LOAD_FAST                9 (prioritized)
                GET_ITER
       L17:     FOR_ITER                99 (to L24)
                STORE_FAST              10 (channel)

 291            LOAD_FAST                0 (self)
                LOAD_ATTR               25 (_attempt_invite_creation + NULL|self)
                LOAD_FAST               10 (channel)
                LOAD_GLOBAL             26 (INVITE_PAYLOAD_DEFAULT)
                LOAD_CONST              19 (('payload',))
                CALL_KW                  2
                GET_AWAITABLE            0
                LOAD_CONST               0 (None)
       L18:     SEND                     3 (to L21)
       L19:     YIELD_VALUE              1
       L20:     RESUME                   3
                JUMP_BACKWARD_NO_INTERRUPT 5 (to L18)
       L21:     END_SEND
                STORE_FAST               5 (code)

 292            LOAD_FAST                5 (code)
                TO_BOOL
       L22:     POP_JUMP_IF_TRUE         2 (to L23)
                JUMP_BACKWARD           40 (to L17)

 293   L23:     LOAD_FAST                0 (self)
                LOAD_ATTR               14 (console)
                LOAD_ATTR               17 (success + NULL|self)

 294            LOAD_CONST              20 ('Invite created in #')
                LOAD_FAST               10 (channel)
                LOAD_ATTR                3 (get + NULL|self)
                LOAD_CONST               2 ('name')
                LOAD_CONST              21 ('unknown')
                CALL                     2
                FORMAT_SIMPLE
                LOAD_CONST              22 (' -> ')
                LOAD_FAST                5 (code)
                FORMAT_SIMPLE
                BUILD_STRING             4

 293            CALL                     1
                POP_TOP

 296            LOAD_GLOBAL             19 (GuildInvite + NULL)
                LOAD_FAST_LOAD_FAST     35 (guild_id, name)
                LOAD_FAST                5 (code)
                LOAD_CONST              14 (('guild_id', 'name', 'invite_code'))
                CALL_KW                  3
                SWAP                     2
                POP_TOP
                RETURN_VALUE

 290   L24:     END_FOR
                POP_TOP

 298            LOAD_FAST                9 (prioritized)
                GET_ITER
       L25:     FOR_ITER                99 (to L32)
                STORE_FAST              10 (channel)

 299            LOAD_FAST                0 (self)
                LOAD_ATTR               25 (_attempt_invite_creation + NULL|self)
                LOAD_FAST               10 (channel)
                LOAD_CONST              23 (0)
                LOAD_CONST              23 (0)
                LOAD_CONST              24 (False)
                LOAD_CONST              25 (('max_age', 'max_uses', 'temporary'))
                BUILD_CONST_KEY_MAP      3
                LOAD_CONST              19 (('payload',))
                CALL_KW                  2
                GET_AWAITABLE            0
                LOAD_CONST               0 (None)
       L26:     SEND                     3 (to L29)
       L27:     YIELD_VALUE              1
       L28:     RESUME                   3
                JUMP_BACKWARD_NO_INTERRUPT 5 (to L26)
       L29:     END_SEND
                STORE_FAST               5 (code)

 300            LOAD_FAST                5 (code)
                TO_BOOL
       L30:     POP_JUMP_IF_TRUE         2 (to L31)
                JUMP_BACKWARD           40 (to L25)

 301   L31:     LOAD_FAST                0 (self)
                LOAD_ATTR               14 (console)
                LOAD_ATTR               17 (success + NULL|self)

 302            LOAD_CONST              26 ('Fallback invite in #')
                LOAD_FAST               10 (channel)
                LOAD_ATTR                3 (get + NULL|self)
                LOAD_CONST               2 ('name')
                LOAD_CONST              21 ('unknown')
                CALL                     2
                FORMAT_SIMPLE
                LOAD_CONST              22 (' -> ')
                LOAD_FAST                5 (code)
                FORMAT_SIMPLE
                BUILD_STRING             4

 301            CALL                     1
                POP_TOP

 304            LOAD_GLOBAL             19 (GuildInvite + NULL)
                LOAD_FAST_LOAD_FAST     35 (guild_id, name)
                LOAD_FAST                5 (code)
                LOAD_CONST              14 (('guild_id', 'name', 'invite_code'))
                CALL_KW                  3
                SWAP                     2
                POP_TOP
                RETURN_VALUE

 298   L32:     END_FOR
                POP_TOP

 306            LOAD_GLOBAL             19 (GuildInvite + NULL)
                LOAD_FAST_LOAD_FAST     35 (guild_id, name)
                LOAD_CONST              27 ('Unable to create.')
                LOAD_CONST              14 (('guild_id', 'name', 'invite_code'))
                CALL_KW                  3
                RETURN_VALUE

 255   L33:     CLEANUP_THROW
       L34:     EXTENDED_ARG             1
                JUMP_BACKWARD_NO_INTERRUPT 429 (to L5)

 269   L35:     CLEANUP_THROW
       L36:     EXTENDED_ARG             1
                JUMP_BACKWARD_NO_INTERRUPT 283 (to L10)

  --   L37:     SWAP                     2
                POP_TOP

 278            SWAP                     2
                STORE_FAST               7 (c)
                RERAISE                  0

 291   L38:     CLEANUP_THROW
       L39:     JUMP_BACKWARD_NO_INTERRUPT 202 (to L21)

 299   L40:     CLEANUP_THROW
       L41:     JUMP_BACKWARD_NO_INTERRUPT 99 (to L29)

  --   L42:     CALL_INTRINSIC_1         3 (INTRINSIC_STOPITERATION_ERROR)
                RERAISE                  1
ExceptionTable:
  L1 to L3 -> L42 [0] lasti
  L3 to L4 -> L33 [2]
  L4 to L8 -> L42 [0] lasti
  L8 to L9 -> L35 [2]
  L9 to L11 -> L42 [0] lasti
  L11 to L13 -> L37 [2]
  L14 to L16 -> L37 [2]
  L16 to L19 -> L42 [0] lasti
  L19 to L20 -> L38 [3]
  L20 to L22 -> L42 [0] lasti
  L23 to L27 -> L42 [0] lasti
  L27 to L28 -> L40 [3]
  L28 to L30 -> L42 [0] lasti
  L31 to L34 -> L42 [0] lasti
  L35 to L36 -> L42 [0] lasti
  L37 to L39 -> L42 [0] lasti
  L40 to L41 -> L42 [0] lasti

Disassembly of <code object <lambda> at 0x000001EE5E8844F0, file "discord_backup\backup.py", line 281>:
  --           MAKE_CELL                0 (channel)

 281           RESUME                   0

 282           LOAD_GLOBAL              1 (min + NULL)
               LOAD_FAST                0 (channel)
               BUILD_TUPLE              1
               LOAD_CONST               1 (<code object <genexpr> at 0x000001EE5E786AD0, file "discord_backup\backup.py", line 282>)
               MAKE_FUNCTION
               SET_FUNCTION_ATTRIBUTE   8 (closure)

 284           LOAD_GLOBAL              2 (PREFERRED_CHANNEL_KEYWORDS)
               GET_ITER

 282           CALL                     0
               CALL                     1

 286           LOAD_DEREF               0 (channel)
               LOAD_ATTR                5 (get + NULL|self)
               LOAD_CONST               2 ('position')
               LOAD_CONST               3 (9999)
               CALL                     2

 281           BUILD_TUPLE              2
               RETURN_VALUE

Disassembly of <code object <genexpr> at 0x000001EE5E786AD0, file "discord_backup\backup.py", line 282>:
  --           COPY_FREE_VARS           1

 282           RETURN_GENERATOR
               POP_TOP
       L1:     RESUME                   0
               LOAD_FAST                0 (.0)

 284           GET_ITER
       L2:     FOR_ITER                62 (to L5)
               STORE_FAST               1 (keyword)

 283           LOAD_FAST                1 (keyword)
               LOAD_DEREF               2 (channel)
               LOAD_ATTR                1 (get + NULL|self)
               LOAD_CONST               0 ('name')
               LOAD_CONST               1 ('')
               CALL                     2
               CONTAINS_OP              0
               POP_JUMP_IF_FALSE       33 (to L3)
               LOAD_DEREF               2 (channel)
               LOAD_ATTR                1 (get + NULL|self)
               LOAD_CONST               0 ('name')
               LOAD_CONST               1 ('')
               CALL                     2
               LOAD_ATTR                3 (find + NULL|self)
               LOAD_FAST                1 (keyword)
               CALL                     1
               JUMP_FORWARD             1 (to L4)
       L3:     LOAD_CONST               2 (999)
       L4:     YIELD_VALUE              0
               RESUME                   5
               POP_TOP
               JUMP_BACKWARD           64 (to L2)

 284   L5:     END_FOR
               POP_TOP
               RETURN_CONST             3 (None)

  --   L6:     CALL_INTRINSIC_1         3 (INTRINSIC_STOPITERATION_ERROR)
               RERAISE                  1
ExceptionTable:
  L1 to L6 -> L6 [0] lasti

Disassembly of <code object _attempt_invite_creation at 0x000001EE5C61BA50, file "discord_backup\backup.py", line 308>:
 308            RETURN_GENERATOR
                POP_TOP
        L1:     RESUME                   0

 309            LOAD_FAST                1 (channel)
                LOAD_ATTR                1 (get + NULL|self)
                LOAD_CONST               1 ('id')
                CALL                     1
                STORE_FAST               3 (channel_id)

 310            LOAD_FAST                3 (channel_id)
                TO_BOOL
                POP_JUMP_IF_TRUE         1 (to L2)

 311            RETURN_CONST             0 (None)

 312    L2:     LOAD_FAST                0 (self)
                LOAD_ATTR                2 (http)
                LOAD_ATTR                5 (request + NULL|self)

 313            LOAD_CONST               2 ('POST')

 314            LOAD_CONST               3 ('channels/')
                LOAD_FAST                3 (channel_id)
                FORMAT_SIMPLE
                LOAD_CONST               4 ('/invites')
                BUILD_STRING             3

 315            LOAD_FAST                0 (self)
                LOAD_ATTR                6 (token)

 316            LOAD_FAST                2 (payload)

 317            LOAD_CONST               5 (True)

 318            LOAD_CONST               5 (True)

 319            LOAD_CONST               5 (True)

 320            LOAD_CONST               6 ((200,))

 312            LOAD_CONST               7 (('token', 'json_payload', 'include_debug', 'include_locale', 'super_properties', 'expected_status'))
                CALL_KW                  8
                GET_AWAITABLE            0
                LOAD_CONST               0 (None)
        L3:     SEND                     3 (to L6)
        L4:     YIELD_VALUE              1
        L5:     RESUME                   3
                JUMP_BACKWARD_NO_INTERRUPT 5 (to L3)
        L6:     END_SEND
                STORE_FAST               4 (response)

 322            LOAD_FAST                4 (response)
                LOAD_ATTR                8 (status_code)
                LOAD_CONST               8 (200)
                COMPARE_OP              88 (bool(==))
                POP_JUMP_IF_FALSE       31 (to L7)

 323            LOAD_FAST                4 (response)
                LOAD_ATTR               11 (json + NULL|self)
                CALL                     0
                LOAD_ATTR                1 (get + NULL|self)
                LOAD_CONST               9 ('code')
                CALL                     1
                RETURN_VALUE

 324    L7:     RETURN_CONST             0 (None)

 312    L8:     CLEANUP_THROW
        L9:     JUMP_BACKWARD_NO_INTERRUPT 52 (to L6)

  --   L10:     CALL_INTRINSIC_1         3 (INTRINSIC_STOPITERATION_ERROR)
                RERAISE                  1
ExceptionTable:
  L1 to L4 -> L10 [0] lasti
  L4 to L5 -> L8 [2]
  L5 to L9 -> L10 [0] lasti

Disassembly of <code object _fetch_channels at 0x000001EE5C5AEBB0, file "discord_backup\backup.py", line 326>:
 326            RETURN_GENERATOR
                POP_TOP
        L1:     RESUME                   0

 327            LOAD_FAST                0 (self)
                LOAD_ATTR                0 (http)
                LOAD_ATTR                3 (request + NULL|self)

 328            LOAD_CONST               1 ('GET')

 329            LOAD_CONST               2 ('users/@me/channels')

 330            LOAD_FAST                0 (self)
                LOAD_ATTR                4 (token)

 331            LOAD_CONST               3 (True)

 332            LOAD_CONST               3 (True)

 333            LOAD_CONST               3 (True)

 327            LOAD_CONST               4 (('token', 'include_debug', 'include_locale', 'super_properties'))
                CALL_KW                  6
                GET_AWAITABLE            0
                LOAD_CONST               0 (None)
        L2:     SEND                     3 (to L5)
        L3:     YIELD_VALUE              1
        L4:     RESUME                   3
                JUMP_BACKWARD_NO_INTERRUPT 5 (to L2)
        L5:     END_SEND
                STORE_FAST               1 (response)

 335            LOAD_FAST                1 (response)
                LOAD_ATTR                6 (status_code)
                LOAD_CONST               5 (200)
                COMPARE_OP              88 (bool(==))
                POP_JUMP_IF_FALSE       16 (to L6)
                LOAD_FAST                1 (response)
                LOAD_ATTR                9 (json + NULL|self)
                CALL                     0
                JUMP_FORWARD             1 (to L7)
        L6:     BUILD_LIST               0
        L7:     STORE_FAST               2 (channels)

 336            LOAD_FAST                0 (self)
                LOAD_ATTR               10 (console)
                LOAD_ATTR               13 (success + NULL|self)
                LOAD_CONST               6 ('Loaded ')
                LOAD_GLOBAL             15 (len + NULL)
                LOAD_FAST                2 (channels)
                CALL                     1
                FORMAT_SIMPLE
                LOAD_CONST               7 (' private channels')
                BUILD_STRING             3
                CALL                     1
                POP_TOP

 337            LOAD_FAST                2 (channels)
                RETURN_VALUE

 327    L8:     CLEANUP_THROW
        L9:     JUMP_BACKWARD_NO_INTERRUPT 80 (to L5)

  --   L10:     CALL_INTRINSIC_1         3 (INTRINSIC_STOPITERATION_ERROR)
                RERAISE                  1
ExceptionTable:
  L1 to L3 -> L10 [0] lasti
  L3 to L4 -> L8 [2]
  L4 to L9 -> L10 [0] lasti

Disassembly of <code object _build_group_chats at 0x000001EE5C72D750, file "discord_backup\backup.py", line 339>:
 339            RETURN_GENERATOR
                POP_TOP
        L1:     RESUME                   0

 340            LOAD_GLOBAL              1 (max + NULL)
                LOAD_CONST               1 (0)
                LOAD_FAST                0 (self)
                LOAD_ATTR                2 (config)
                LOAD_ATTR                4 (group_chat_msg_threshold)
                CALL                     2
                STORE_FAST               2 (threshold)

 341            LOAD_FAST                1 (channels)
                GET_ITER
                LOAD_FAST_AND_CLEAR      3 (c)
                SWAP                     2
        L2:     BUILD_LIST               0
                SWAP                     2
                GET_ITER
        L3:     FOR_ITER                27 (to L6)
                STORE_FAST_LOAD_FAST    51 (c, c)
                LOAD_ATTR                7 (get + NULL|self)
                LOAD_CONST               2 ('type')
                CALL                     1
                LOAD_CONST               3 (3)
                COMPARE_OP              88 (bool(==))
        L4:     POP_JUMP_IF_TRUE         2 (to L5)
                JUMP_BACKWARD           25 (to L3)
        L5:     LOAD_FAST                3 (c)
                LIST_APPEND              2
                JUMP_BACKWARD           29 (to L3)
        L6:     END_FOR
                POP_TOP
        L7:     STORE_FAST               4 (group_channels)
                STORE_FAST               3 (c)

 342            BUILD_LIST               0
                STORE_FAST               5 (invites)

 343            LOAD_CONST               1 (0)
                STORE_FAST               6 (success)

 344            LOAD_GLOBAL              9 (enumerate + NULL)
                LOAD_FAST                4 (group_channels)
                LOAD_CONST               4 (1)
                LOAD_CONST               5 (('start',))
                CALL_KW                  2
                GET_ITER
        L8:     EXTENDED_ARG             2
                FOR_ITER               635 (to L24)
                UNPACK_SEQUENCE          2
                STORE_FAST_STORE_FAST  120 (index, channel)

 345            LOAD_FAST                8 (channel)
                LOAD_ATTR                7 (get + NULL|self)
                LOAD_CONST               6 ('name')
                LOAD_CONST               7 ('GC-')
                LOAD_FAST                7 (index)
                FORMAT_SIMPLE
                BUILD_STRING             2
                CALL                     2
                STORE_FAST               9 (name)

 346            LOAD_FAST                0 (self)
                LOAD_ATTR               10 (console)
                LOAD_ATTR               13 (info + NULL|self)

 347            LOAD_CONST               8 ('[')
                LOAD_FAST                7 (index)
                FORMAT_SIMPLE
                LOAD_CONST               9 ('/')
                LOAD_GLOBAL             15 (len + NULL)
                LOAD_FAST                4 (group_channels)
                CALL                     1
                FORMAT_SIMPLE
                LOAD_CONST              10 ('] Processing group chat ')
                LOAD_FAST                9 (name)
                FORMAT_SIMPLE
                BUILD_STRING             6

 346            CALL                     1
                POP_TOP

 349            LOAD_FAST                8 (channel)
                LOAD_ATTR                7 (get + NULL|self)
                LOAD_CONST              11 ('last_message_id')
                CALL                     1
                STORE_FAST              10 (last_message_id)

 350            LOAD_CONST               1 (0)
                STORE_FAST              11 (age_seconds)

 351            LOAD_GLOBAL             17 (snowflake_to_timestamp + NULL)
                LOAD_FAST               10 (last_message_id)
                CALL                     1
                STORE_FAST              12 (timestamp)

 352            LOAD_FAST               12 (timestamp)
                TO_BOOL
                POP_JUMP_IF_FALSE       24 (to L9)

 353            LOAD_GLOBAL             18 (time)
                LOAD_ATTR               18 (time)
                PUSH_NULL
                CALL                     0
                LOAD_FAST               12 (timestamp)
                BINARY_OP               10 (-)
                STORE_FAST              11 (age_seconds)

 355    L9:     LOAD_FAST                2 (threshold)
                TO_BOOL
                POP_JUMP_IF_FALSE       50 (to L10)
                LOAD_FAST_LOAD_FAST    178 (age_seconds, threshold)
                COMPARE_OP             148 (bool(>))
                POP_JUMP_IF_FALSE       45 (to L10)

 356            LOAD_FAST                0 (self)
                LOAD_ATTR               10 (console)
                LOAD_ATTR               21 (warn + NULL|self)

 357            LOAD_CONST              12 ("Skipped group chat '")
                LOAD_FAST                9 (name)
                FORMAT_SIMPLE
                LOAD_CONST              13 ("' (inactive for ")
                LOAD_GLOBAL             23 (int + NULL)
                LOAD_FAST               11 (age_seconds)
                CALL                     1
                FORMAT_SIMPLE
                LOAD_CONST              14 ('s)')
                BUILD_STRING             5

 356            CALL                     1
                POP_TOP

 359            JUMP_BACKWARD          190 (to L8)

 361   L10:     LOAD_FAST                0 (self)
                LOAD_ATTR               24 (http)
                LOAD_ATTR               27 (request + NULL|self)

 362            LOAD_CONST              15 ('POST')

 363            LOAD_CONST              16 ('channels/')
                LOAD_FAST                8 (channel)
                LOAD_CONST              17 ('id')
                BINARY_SUBSCR
                FORMAT_SIMPLE
                LOAD_CONST              18 ('/invites')
                BUILD_STRING             3

 364            LOAD_FAST                0 (self)
                LOAD_ATTR               28 (token)

 365            LOAD_CONST              19 ('max_age')
                LOAD_CONST              20 (604800)
                BUILD_MAP                1

 366            LOAD_CONST              21 (True)

 367            LOAD_CONST              21 (True)

 368            LOAD_CONST              21 (True)

 369            LOAD_CONST              22 ((200,))

 361            LOAD_CONST              23 (('token', 'json_payload', 'include_debug', 'include_locale', 'super_properties', 'expected_status'))
                CALL_KW                  8
                GET_AWAITABLE            0
                LOAD_CONST               0 (None)
       L11:     SEND                     3 (to L14)
       L12:     YIELD_VALUE              1
       L13:     RESUME                   3
                JUMP_BACKWARD_NO_INTERRUPT 5 (to L11)
       L14:     END_SEND
                STORE_FAST              13 (response)

 371            LOAD_FAST               13 (response)
                LOAD_ATTR               30 (status_code)
                LOAD_CONST              24 (200)
                COMPARE_OP              88 (bool(==))
                POP_JUMP_IF_FALSE      206 (to L19)

 372            LOAD_FAST               13 (response)
                LOAD_ATTR               33 (json + NULL|self)
                CALL                     0
                LOAD_ATTR                7 (get + NULL|self)
                LOAD_CONST              25 ('code')
                CALL                     1
                STORE_FAST              14 (code)

 373            LOAD_FAST                5 (invites)
                LOAD_ATTR               35 (append + NULL|self)

 374            LOAD_GLOBAL             37 (GroupChatInvite + NULL)

 375            LOAD_GLOBAL             39 (str + NULL)
                LOAD_FAST                8 (channel)
                LOAD_ATTR                7 (get + NULL|self)
                LOAD_CONST              17 ('id')
                CALL                     1
                CALL                     1

 376            LOAD_FAST                9 (name)

 377            LOAD_FAST               14 (code)

 378            LOAD_GLOBAL             39 (str + NULL)
                LOAD_FAST                8 (channel)
                LOAD_ATTR                7 (get + NULL|self)
                LOAD_CONST              26 ('owner_id')
                CALL                     1
                CALL                     1

 379            LOAD_FAST                8 (channel)
                LOAD_ATTR                7 (get + NULL|self)
                LOAD_CONST              27 ('recipients')
                BUILD_LIST               0
                CALL                     2
                GET_ITER
                LOAD_FAST_AND_CLEAR     15 (user)
                SWAP                     2
       L15:     BUILD_LIST               0
                SWAP                     2
                GET_ITER
       L16:     FOR_ITER                29 (to L17)
                STORE_FAST              15 (user)
                LOAD_GLOBAL             39 (str + NULL)
                LOAD_FAST               15 (user)
                LOAD_ATTR                7 (get + NULL|self)
                LOAD_CONST              17 ('id')
                CALL                     1
                CALL                     1
                LIST_APPEND              2
                JUMP_BACKWARD           31 (to L16)
       L17:     END_FOR
                POP_TOP
       L18:     SWAP                     2
                STORE_FAST              15 (user)

 380            LOAD_FAST               10 (last_message_id)

 374            LOAD_CONST              28 (('channel_id', 'name', 'invite_code', 'owner_id', 'recipients', 'last_message_id'))
                CALL_KW                  6

 373            CALL                     1
                POP_TOP

 383            LOAD_FAST                6 (success)
                LOAD_CONST               4 (1)
                BINARY_OP               13 (+=)
                STORE_FAST               6 (success)

 384            LOAD_FAST                0 (self)
                LOAD_ATTR               10 (console)
                LOAD_ATTR               41 (success + NULL|self)
                LOAD_CONST              29 ('Invite created for group chat ')
                LOAD_FAST                9 (name)
                FORMAT_SIMPLE
                LOAD_CONST              30 (': ')
                LOAD_FAST               14 (code)
                FORMAT_SIMPLE
                BUILD_STRING             4
                CALL                     1
                POP_TOP
                EXTENDED_ARG             1
                JUMP_BACKWARD          471 (to L8)

 386   L19:     LOAD_FAST                5 (invites)
                LOAD_ATTR               35 (append + NULL|self)

 387            LOAD_GLOBAL             37 (GroupChatInvite + NULL)

 388            LOAD_GLOBAL             39 (str + NULL)
                LOAD_FAST                8 (channel)
                LOAD_ATTR                7 (get + NULL|self)
                LOAD_CONST              17 ('id')
                CALL                     1
                CALL                     1

 389            LOAD_FAST                9 (name)

 390            LOAD_CONST              31 ('Unable to create.')

 391            LOAD_GLOBAL             39 (str + NULL)
                LOAD_FAST                8 (channel)
                LOAD_ATTR                7 (get + NULL|self)
                LOAD_CONST              26 ('owner_id')
                CALL                     1
                CALL                     1

 392            LOAD_FAST                8 (channel)
                LOAD_ATTR                7 (get + NULL|self)
                LOAD_CONST              27 ('recipients')
                BUILD_LIST               0
                CALL                     2
                GET_ITER
                LOAD_FAST_AND_CLEAR     15 (user)
                SWAP                     2
       L20:     BUILD_LIST               0
                SWAP                     2
                GET_ITER
       L21:     FOR_ITER                29 (to L22)
                STORE_FAST              15 (user)
                LOAD_GLOBAL             39 (str + NULL)
                LOAD_FAST               15 (user)
                LOAD_ATTR                7 (get + NULL|self)
                LOAD_CONST              17 ('id')
                CALL                     1
                CALL                     1
                LIST_APPEND              2
                JUMP_BACKWARD           31 (to L21)
       L22:     END_FOR
                POP_TOP
       L23:     SWAP                     2
                STORE_FAST              15 (user)

 393            LOAD_FAST               10 (last_message_id)

 387            LOAD_CONST              28 (('channel_id', 'name', 'invite_code', 'owner_id', 'recipients', 'last_message_id'))
                CALL_KW                  6

 386            CALL                     1
                POP_TOP

 396            LOAD_FAST                0 (self)
                LOAD_ATTR               10 (console)
                LOAD_ATTR               21 (warn + NULL|self)
                LOAD_CONST              32 ('Failed to create invite for group chat ')
                LOAD_FAST                9 (name)
                FORMAT_SIMPLE
                BUILD_STRING             2
                CALL                     1
                POP_TOP
                EXTENDED_ARG             2
                JUMP_BACKWARD          638 (to L8)

 344   L24:     END_FOR
                POP_TOP

 397            LOAD_FAST_LOAD_FAST     86 (invites, success)
                BUILD_TUPLE              2
                RETURN_VALUE

  --   L25:     SWAP                     2
                POP_TOP

 341            SWAP                     2
                STORE_FAST               3 (c)
                RERAISE                  0

 361   L26:     CLEANUP_THROW
       L27:     EXTENDED_ARG             1
                JUMP_BACKWARD_NO_INTERRUPT 404 (to L14)

  --   L28:     SWAP                     2
                POP_TOP

 379            SWAP                     2
                STORE_FAST              15 (user)
                RERAISE                  0

  --   L29:     SWAP                     2
                POP_TOP

 392            SWAP                     2
                STORE_FAST              15 (user)
                RERAISE                  0

  --   L30:     CALL_INTRINSIC_1         3 (INTRINSIC_STOPITERATION_ERROR)
                RERAISE                  1
ExceptionTable:
  L1 to L2 -> L30 [0] lasti
  L2 to L4 -> L25 [2]
  L5 to L7 -> L25 [2]
  L7 to L12 -> L30 [0] lasti
  L12 to L13 -> L26 [3]
  L13 to L15 -> L30 [0] lasti
  L15 to L18 -> L28 [11]
  L18 to L20 -> L30 [0] lasti
  L20 to L23 -> L29 [11]
  L23 to L27 -> L30 [0] lasti
  L28 to L30 -> L30 [0] lasti

Disassembly of <code object _build_dm_history at 0x000001EE5C72B150, file "discord_backup\backup.py", line 399>:
 399            RESUME                   0

 400            LOAD_FAST                1 (channels)
                GET_ITER
                LOAD_FAST_AND_CLEAR      2 (c)
                SWAP                     2
        L1:     BUILD_LIST               0
                SWAP                     2
                GET_ITER
        L2:     FOR_ITER                27 (to L5)
                STORE_FAST_LOAD_FAST    34 (c, c)
                LOAD_ATTR                1 (get + NULL|self)
                LOAD_CONST               1 ('type')
                CALL                     1
                LOAD_CONST               2 (1)
                COMPARE_OP              88 (bool(==))
        L3:     POP_JUMP_IF_TRUE         2 (to L4)
                JUMP_BACKWARD           25 (to L2)
        L4:     LOAD_FAST                2 (c)
                LIST_APPEND              2
                JUMP_BACKWARD           29 (to L2)
        L5:     END_FOR
                POP_TOP
        L6:     STORE_FAST               3 (dms)
                STORE_FAST               2 (c)

 401            BUILD_LIST               0
                STORE_FAST               4 (history)

 402            LOAD_FAST                3 (dms)
                GET_ITER
        L7:     FOR_ITER               162 (to L9)
                STORE_FAST               5 (dm)

 403            LOAD_FAST                5 (dm)
                LOAD_ATTR                1 (get + NULL|self)
                LOAD_CONST               3 ('recipients')
                CALL                     1
                COPY                     1
                TO_BOOL
                POP_JUMP_IF_TRUE         3 (to L8)
                POP_TOP
                BUILD_MAP                0
                BUILD_LIST               1
        L8:     LOAD_CONST               4 (0)
                BINARY_SUBSCR
                STORE_FAST               6 (recipient)

 404            LOAD_FAST                6 (recipient)
                LOAD_ATTR                1 (get + NULL|self)
                LOAD_CONST               5 ('username')
                LOAD_CONST               6 ('unknown')
                CALL                     2
                FORMAT_SIMPLE
                LOAD_CONST               7 ('#')
                LOAD_FAST                6 (recipient)
                LOAD_ATTR                1 (get + NULL|self)
                LOAD_CONST               8 ('discriminator')
                LOAD_CONST               9 ('0000')
                CALL                     2
                FORMAT_SIMPLE
                BUILD_STRING             3
                STORE_FAST               7 (user_tag)

 405            LOAD_FAST                4 (history)
                LOAD_ATTR                3 (append + NULL|self)

 406            LOAD_GLOBAL              5 (DMHistoryEntry + NULL)

 407            LOAD_GLOBAL              7 (str + NULL)
                LOAD_FAST                6 (recipient)
                LOAD_ATTR                1 (get + NULL|self)
                LOAD_CONST              10 ('id')
                CALL                     1
                CALL                     1

 408            LOAD_FAST                7 (user_tag)

 409            LOAD_FAST                5 (dm)
                LOAD_ATTR                1 (get + NULL|self)
                LOAD_CONST              11 ('last_message_id')
                CALL                     1

 410            LOAD_GLOBAL              9 (snowflake_to_timestamp + NULL)
                LOAD_FAST                5 (dm)
                LOAD_ATTR                1 (get + NULL|self)
                LOAD_CONST              11 ('last_message_id')
                CALL                     1
                CALL                     1

 406            LOAD_CONST              12 (('user_id', 'user_tag', 'last_message_id', 'timestamp'))
                CALL_KW                  4

 405            CALL                     1
                POP_TOP
                JUMP_BACKWARD          164 (to L7)

 402    L9:     END_FOR
                POP_TOP

 413            LOAD_FAST                4 (history)
                LOAD_ATTR               11 (sort + NULL|self)
                LOAD_CONST              13 (<code object <lambda> at 0x000001EE5E78F770, file "discord_backup\backup.py", line 413>)
                MAKE_FUNCTION
                LOAD_CONST              14 (True)
                LOAD_CONST              15 (('key', 'reverse'))
                CALL_KW                  2
                POP_TOP

 414            LOAD_FAST                0 (self)
                LOAD_ATTR               12 (console)
                LOAD_ATTR               15 (success + NULL|self)
                LOAD_CONST              16 ('Collected ')
                LOAD_GLOBAL             17 (len + NULL)
                LOAD_FAST                4 (history)
                CALL                     1
                FORMAT_SIMPLE
                LOAD_CONST              17 (' DM history entries')
                BUILD_STRING             3
                CALL                     1
                POP_TOP

 415            LOAD_FAST                4 (history)
                RETURN_VALUE

  --   L10:     SWAP                     2
                POP_TOP

 400            SWAP                     2
                STORE_FAST               2 (c)
                RERAISE                  0
ExceptionTable:
  L1 to L3 -> L10 [2]
  L4 to L6 -> L10 [2]

Disassembly of <code object <lambda> at 0x000001EE5E78F770, file "discord_backup\backup.py", line 413>:
413           RESUME                   0
              LOAD_GLOBAL              1 (int + NULL)
              LOAD_FAST                0 (entry)
              LOAD_ATTR                2 (last_message_id)
              COPY                     1
              TO_BOOL
              POP_JUMP_IF_TRUE         2 (to L1)
              POP_TOP
              LOAD_CONST               1 (0)
      L1:     CALL                     1
              RETURN_VALUE


# --- Nested: BackupError ---

 40           RESUME                   0
              LOAD_NAME                0 (__name__)
              STORE_NAME               1 (__module__)
              LOAD_CONST               0 ('BackupError')
              STORE_NAME               2 (__qualname__)
              LOAD_CONST               1 (40)
              STORE_NAME               3 (__firstlineno__)

 41           LOAD_CONST               2 ('Raised when a fatal backup error occurs.')
              STORE_NAME               4 (__doc__)
              LOAD_CONST               3 (())
              STORE_NAME               5 (__static_attributes__)
              RETURN_CONST             4 (None)


# --- Nested: BackupService ---

 44           RESUME                   0
              LOAD_NAME                0 (__name__)
              STORE_NAME               1 (__module__)
              LOAD_CONST               0 ('BackupService')
              STORE_NAME               2 (__qualname__)
              LOAD_CONST               1 (44)
              STORE_NAME               3 (__firstlineno__)
              SETUP_ANNOTATIONS

 46           LOAD_CONST               2 ('DiscordHTTPClient')
              LOAD_NAME                4 (__annotations__)
              LOAD_CONST               3 ('http')
              STORE_SUBSCR

 47           LOAD_CONST               4 ('str')
              LOAD_NAME                4 (__annotations__)
              LOAD_CONST               5 ('token')
              STORE_SUBSCR

 48           LOAD_CONST               6 ('AppConfig')
              LOAD_NAME                4 (__annotations__)
              LOAD_CONST               7 ('config')
              STORE_SUBSCR

 49           LOAD_CONST               8 ('Console')
              LOAD_NAME                4 (__annotations__)
              LOAD_CONST               9 ('console')
              STORE_SUBSCR

 51           LOAD_CONST              10 (4)
              STORE_NAME               5 (guild_invite_limit)
              LOAD_CONST              11 ('int')
              LOAD_NAME                4 (__annotations__)
              LOAD_CONST              12 ('guild_invite_limit')
              STORE_SUBSCR

 53           LOAD_CONST              35 (('return', 'BackupResult'))
              LOAD_CONST              13 (<code object run at 0x000001EE5C72A7F0, file "discord_backup\backup.py", line 53>)
              MAKE_FUNCTION
              SET_FUNCTION_ATTRIBUTE   4 (annotations)
              STORE_NAME               6 (run)

 95           LOAD_NAME                7 (Path)
              PUSH_NULL
              LOAD_CONST              14 ('backups')
              CALL                     1
              BUILD_TUPLE              1
              LOAD_CONST              36 (('result', 'BackupResult', 'directory', 'Path', 'return', 'Path'))
              LOAD_CONST              15 (<code object save at 0x000001EE5C726510, file "discord_backup\backup.py", line 95>)
              MAKE_FUNCTION
              SET_FUNCTION_ATTRIBUTE   4 (annotations)
              SET_FUNCTION_ATTRIBUTE   1 (defaults)
              STORE_NAME               8 (save)

104           LOAD_CONST              37 (('return', 'dict[str, Any]'))
              LOAD_CONST              16 (<code object _fetch_me at 0x000001EE5E801A30, file "discord_backup\backup.py", line 104>)
              MAKE_FUNCTION
              SET_FUNCTION_ATTRIBUTE   4 (annotations)
              STORE_NAME               9 (_fetch_me)

120           LOAD_CONST              38 (('url', 'str', 'return', 'bytes'))
              LOAD_CONST              17 (<code object _fetch_asset at 0x000001EE5E850B90, file "discord_backup\backup.py", line 120>)
              MAKE_FUNCTION
              SET_FUNCTION_ATTRIBUTE   4 (annotations)
              STORE_NAME              10 (_fetch_asset)

137           LOAD_CONST              39 (('me', 'dict[str, Any]', 'return', 'UserProfile'))
              LOAD_CONST              18 (<code object _build_profile at 0x000001EE5E622C10, file "discord_backup\backup.py", line 137>)
              MAKE_FUNCTION
              SET_FUNCTION_ATTRIBUTE   4 (annotations)
              STORE_NAME              11 (_build_profile)

159           LOAD_CONST              40 (('return', 'RelationshipSnapshot'))
              LOAD_CONST              19 (<code object _fetch_relationships at 0x000001EE5E621580, file "discord_backup\backup.py", line 159>)
              MAKE_FUNCTION
              SET_FUNCTION_ATTRIBUTE   4 (annotations)
              STORE_NAME              12 (_fetch_relationships)

183           LOAD_NAME               13 (dataclass)
              PUSH_NULL
              LOAD_CONST              20 (True)
              LOAD_CONST              21 (('slots',))
              CALL_KW                  1

184           LOAD_BUILD_CLASS
              PUSH_NULL
              LOAD_CONST              22 (<code object _Settings at 0x000001EE5E816430, file "discord_backup\backup.py", line 183>)
              MAKE_FUNCTION
              LOAD_CONST              23 ('_Settings')
              CALL                     2

183           CALL                     0

184           STORE_NAME              14 (_Settings)

188           LOAD_CONST              41 (('return', '_Settings'))
              LOAD_CONST              24 (<code object _fetch_settings at 0x000001EE5E621E10, file "discord_backup\backup.py", line 188>)
              MAKE_FUNCTION
              SET_FUNCTION_ATTRIBUTE   4 (annotations)
              STORE_NAME              15 (_fetch_settings)

217           LOAD_NAME               13 (dataclass)
              PUSH_NULL
              LOAD_CONST              20 (True)
              LOAD_CONST              21 (('slots',))
              CALL_KW                  1

218           LOAD_BUILD_CLASS
              PUSH_NULL
              LOAD_CONST              25 (<code object _GuildResult at 0x000001EE5E816730, file "discord_backup\backup.py", line 217>)
              MAKE_FUNCTION
              LOAD_CONST              26 ('_GuildResult')
              CALL                     2

217           CALL                     0

218           STORE_NAME              16 (_GuildResult)

223           LOAD_CONST              42 (('return', '_GuildResult'))
              LOAD_CONST              27 (<code object _fetch_guild_invites at 0x000001EE5E624B00, file "discord_backup\backup.py", line 223>)
              MAKE_FUNCTION
              SET_FUNCTION_ATTRIBUTE   4 (annotations)
              STORE_NAME              17 (_fetch_guild_invites)

251           LOAD_CONST              43 (('guild', 'dict[str, Any]', 'return', 'GuildInvite'))
              LOAD_CONST              28 (<code object _create_invite_for_guild at 0x000001EE5C72AC10, file "discord_backup\backup.py", line 251>)
              MAKE_FUNCTION
              SET_FUNCTION_ATTRIBUTE   4 (annotations)
              STORE_NAME              18 (_create_invite_for_guild)

308           LOAD_CONST              44 (('channel', 'dict[str, Any]', 'payload', 'dict[str, Any]', 'return', 'str | None'))
              LOAD_CONST              29 (<code object _attempt_invite_creation at 0x000001EE5C61BA50, file "discord_backup\backup.py", line 308>)
              MAKE_FUNCTION
              SET_FUNCTION_ATTRIBUTE   4 (annotations)
              STORE_NAME              19 (_attempt_invite_creation)

326           LOAD_CONST              45 (('return', 'list[dict[str, Any]]'))
              LOAD_CONST              30 (<code object _fetch_channels at 0x000001EE5C5AEBB0, file "discord_backup\backup.py", line 326>)
              MAKE_FUNCTION
              SET_FUNCTION_ATTRIBUTE   4 (annotations)
              STORE_NAME              20 (_fetch_channels)

339           LOAD_CONST              46 (('channels', 'list[dict[str, Any]]', 'return', 'tuple[list[GroupChatInvite], int]'))
              LOAD_CONST              31 (<code object _build_group_chats at 0x000001EE5C72D750, file "discord_backup\backup.py", line 339>)
              MAKE_FUNCTION
              SET_FUNCTION_ATTRIBUTE   4 (annotations)
              STORE_NAME              21 (_build_group_chats)

399           LOAD_CONST              47 (('channels', 'list[dict[str, Any]]', 'return', 'list[DMHistoryEntry]'))
              LOAD_CONST              32 (<code object _build_dm_history at 0x000001EE5C72B150, file "discord_backup\backup.py", line 399>)
              MAKE_FUNCTION
              SET_FUNCTION_ATTRIBUTE   4 (annotations)
              STORE_NAME              22 (_build_dm_history)
              LOAD_CONST              33 (())
              STORE_NAME              23 (__static_attributes__)
              RETURN_CONST            34 (None)

Disassembly of <code object run at 0x000001EE5C72A7F0, file "discord_backup\backup.py", line 53>:
  53            RETURN_GENERATOR
                POP_TOP
        L1:     RESUME                   0

  54            LOAD_GLOBAL              0 (time)
                LOAD_ATTR                2 (perf_counter)
                PUSH_NULL
                CALL                     0
                STORE_FAST               1 (start)

  55            LOAD_FAST                0 (self)
                LOAD_ATTR                5 (_fetch_me + NULL|self)
                CALL                     0
                GET_AWAITABLE            0
                LOAD_CONST               0 (None)
        L2:     SEND                     3 (to L5)
        L3:     YIELD_VALUE              1
        L4:     RESUME                   3
                JUMP_BACKWARD_NO_INTERRUPT 5 (to L2)
        L5:     END_SEND
                STORE_FAST               2 (me)

  56            LOAD_FAST                0 (self)
                LOAD_ATTR                7 (_build_profile + NULL|self)
                LOAD_FAST                2 (me)
                CALL                     1
                GET_AWAITABLE            0
                LOAD_CONST               0 (None)
        L6:     SEND                     3 (to L9)
        L7:     YIELD_VALUE              1
        L8:     RESUME                   3
                JUMP_BACKWARD_NO_INTERRUPT 5 (to L6)
        L9:     END_SEND
                STORE_FAST               3 (profile)

  58            LOAD_GLOBAL              8 (asyncio)
                LOAD_ATTR               10 (create_task)
                PUSH_NULL
                LOAD_FAST                0 (self)
                LOAD_ATTR               13 (_fetch_relationships + NULL|self)
                CALL                     0
                CALL                     1
                STORE_FAST               4 (relationships_task)

  59            LOAD_GLOBAL              8 (asyncio)
                LOAD_ATTR               10 (create_task)
                PUSH_NULL
                LOAD_FAST                0 (self)
                LOAD_ATTR               15 (_fetch_settings + NULL|self)
                CALL                     0
                CALL                     1
                STORE_FAST               5 (settings_task)

  60            LOAD_GLOBAL              8 (asyncio)
                LOAD_ATTR               10 (create_task)
                PUSH_NULL
                LOAD_FAST                0 (self)
                LOAD_ATTR               17 (_fetch_channels + NULL|self)
                CALL                     0
                CALL                     1
                STORE_FAST               6 (channels_task)

  61            LOAD_GLOBAL              8 (asyncio)
                LOAD_ATTR               10 (create_task)
                PUSH_NULL
                LOAD_FAST                0 (self)
                LOAD_ATTR               19 (_fetch_guild_invites + NULL|self)
                CALL                     0
                CALL                     1
                STORE_FAST               7 (guilds_task)

  63            LOAD_GLOBAL              8 (asyncio)
                LOAD_ATTR               20 (gather)
                PUSH_NULL

  64            LOAD_FAST                4 (relationships_task)

  65            LOAD_FAST                5 (settings_task)

  66            LOAD_FAST                6 (channels_task)

  67            LOAD_FAST                7 (guilds_task)

  63            CALL                     4
                GET_AWAITABLE            0
                LOAD_CONST               0 (None)
       L10:     SEND                     3 (to L13)
       L11:     YIELD_VALUE              1
       L12:     RESUME                   3
                JUMP_BACKWARD_NO_INTERRUPT 5 (to L10)
       L13:     END_SEND
                UNPACK_SEQUENCE          4
                STORE_FAST_STORE_FAST  137 (relationships, settings)
                STORE_FAST_STORE_FAST  171 (channels, guild_result)

  70            LOAD_FAST                0 (self)
                LOAD_ATTR               23 (_build_group_chats + NULL|self)
                LOAD_FAST               10 (channels)
                CALL                     1
                GET_AWAITABLE            0
                LOAD_CONST               0 (None)
       L14:     SEND                     3 (to L17)
       L15:     YIELD_VALUE              1
       L16:     RESUME                   3
                JUMP_BACKWARD_NO_INTERRUPT 5 (to L14)
       L17:     END_SEND
                UNPACK_SEQUENCE          2
                STORE_FAST_STORE_FAST  205 (group_chats, gc_success)

  71            LOAD_FAST                0 (self)
                LOAD_ATTR               25 (_build_dm_history + NULL|self)
                LOAD_FAST               10 (channels)
                CALL                     1
                STORE_FAST              14 (dm_history)

  73            LOAD_GLOBAL             27 (BackupBundle + NULL)

  74            LOAD_CONST               1 ('2.0.0-dev')

  75            LOAD_FAST                3 (profile)

  76            LOAD_FAST                8 (relationships)

  77            LOAD_FAST               11 (guild_result)
                LOAD_ATTR               28 (invites)

  78            LOAD_FAST               12 (group_chats)

  79            LOAD_FAST               14 (dm_history)

  80            LOAD_FAST                9 (settings)
                LOAD_ATTR               30 (guild_folders)

  81            LOAD_FAST                9 (settings)
                LOAD_ATTR               32 (proto_settings)

  73            LOAD_CONST               2 (('version', 'profile', 'relationships', 'guilds', 'group_chats', 'dm_history', 'guild_folders', 'settings'))
                CALL_KW                  8
                STORE_FAST              15 (bundle)

  84            LOAD_GLOBAL              0 (time)
                LOAD_ATTR                2 (perf_counter)
                PUSH_NULL
                CALL                     0
                LOAD_FAST                1 (start)
                BINARY_OP               10 (-)
                STORE_FAST              16 (duration)

  86            LOAD_GLOBAL             35 (BackupResult + NULL)

  87            LOAD_FAST               15 (bundle)

  88            LOAD_FAST               16 (duration)

  89            LOAD_FAST               11 (guild_result)
                LOAD_ATTR               36 (success)

  90            LOAD_FAST               11 (guild_result)
                LOAD_ATTR               38 (total)

  91            LOAD_FAST               13 (gc_success)

  92            LOAD_GLOBAL             41 (len + NULL)
                LOAD_FAST               12 (group_chats)
                CALL                     1

  86            LOAD_CONST               3 (('bundle', 'duration', 'guild_success', 'guild_total', 'group_chat_success', 'group_chat_total'))
                CALL_KW                  6
                RETURN_VALUE

  55   L18:     CLEANUP_THROW
       L19:     EXTENDED_ARG             1
                JUMP_BACKWARD_NO_INTERRUPT 367 (to L5)

  56   L20:     CLEANUP_THROW
       L21:     EXTENDED_ARG             1
                JUMP_BACKWARD_NO_INTERRUPT 345 (to L9)

  63   L22:     CLEANUP_THROW
       L23:     JUMP_BACKWARD_NO_INTERRUPT 170 (to L13)

  70   L24:     CLEANUP_THROW
       L25:     JUMP_BACKWARD_NO_INTERRUPT 144 (to L17)

  --   L26:     CALL_INTRINSIC_1         3 (INTRINSIC_STOPITERATION_ERROR)
                RERAISE                  1
ExceptionTable:
  L1 to L3 -> L26 [0] lasti
  L3 to L4 -> L18 [2]
  L4 to L7 -> L26 [0] lasti
  L7 to L8 -> L20 [2]
  L8 to L11 -> L26 [0] lasti
  L11 to L12 -> L22 [2]
  L12 to L15 -> L26 [0] lasti
  L15 to L16 -> L24 [2]
  L16 to L19 -> L26 [0] lasti
  L20 to L21 -> L26 [0] lasti
  L22 to L23 -> L26 [0] lasti
  L24 to L25 -> L26 [0] lasti

Disassembly of <code object save at 0x000001EE5C726510, file "discord_backup\backup.py", line 95>:
  95           RETURN_GENERATOR
               POP_TOP
       L1:     RESUME                   0

  96           LOAD_FAST                2 (directory)
               LOAD_ATTR                1 (mkdir + NULL|self)
               LOAD_CONST               1 (True)
               LOAD_CONST               1 (True)
               LOAD_CONST               2 (('parents', 'exist_ok'))
               CALL_KW                  2
               POP_TOP

  97           LOAD_FAST                1 (result)
               LOAD_ATTR                2 (bundle)
               LOAD_ATTR                4 (profile)
               LOAD_ATTR                6 (username)
               FORMAT_SIMPLE
               LOAD_CONST               3 ('#')
               LOAD_FAST                1 (result)
               LOAD_ATTR                2 (bundle)
               LOAD_ATTR                4 (profile)
               LOAD_ATTR                8 (discriminator)
               FORMAT_SIMPLE
               BUILD_STRING             3
               STORE_FAST               3 (tag)

  98           LOAD_GLOBAL             11 (format_backup_filename + NULL)
               LOAD_FAST                3 (tag)
               LOAD_GLOBAL             13 (utc_timestamp + NULL)
               CALL                     0
               LOAD_CONST               4 (('timestamp',))
               CALL_KW                  2
               STORE_FAST               4 (filename)

  99           LOAD_FAST_LOAD_FAST     36 (directory, filename)
               BINARY_OP               11 (/)
               STORE_FAST               5 (target)

 100           LOAD_FAST                5 (target)
               LOAD_ATTR               15 (open + NULL|self)
               LOAD_CONST               5 ('w')
               LOAD_CONST               6 ('utf-8')
               LOAD_CONST               7 (('encoding',))
               CALL_KW                  2
               BEFORE_WITH
       L2:     STORE_FAST               6 (handle)

 101           LOAD_GLOBAL             16 (json)
               LOAD_ATTR               18 (dump)
               PUSH_NULL
               LOAD_FAST                1 (result)
               LOAD_ATTR                2 (bundle)
               LOAD_ATTR               21 (to_dict + NULL|self)
               CALL                     0
               LOAD_FAST                6 (handle)
               LOAD_CONST               8 (4)
               LOAD_CONST               9 (('indent',))
               CALL_KW                  3
               POP_TOP

 100   L3:     LOAD_CONST               0 (None)
               LOAD_CONST               0 (None)
               LOAD_CONST               0 (None)
               CALL                     2
               POP_TOP

 102           LOAD_FAST                5 (target)
               RETURN_VALUE

 100   L4:     PUSH_EXC_INFO
               WITH_EXCEPT_START
               TO_BOOL
               POP_JUMP_IF_TRUE         1 (to L5)
               RERAISE                  2
       L5:     POP_TOP
       L6:     POP_EXCEPT
               POP_TOP
               POP_TOP

 102           LOAD_FAST                5 (target)
               RETURN_VALUE

  --   L7:     COPY                     3
               POP_EXCEPT
               RERAISE                  1
       L8:     CALL_INTRINSIC_1         3 (INTRINSIC_STOPITERATION_ERROR)
               RERAISE                  1
ExceptionTable:
  L1 to L2 -> L8 [0] lasti
  L2 to L3 -> L4 [1] lasti
  L3 to L4 -> L8 [0] lasti
  L4 to L6 -> L7 [3] lasti
  L6 to L8 -> L8 [0] lasti

Disassembly of <code object _fetch_me at 0x000001EE5E801A30, file "discord_backup\backup.py", line 104>:
 104           RETURN_GENERATOR
               POP_TOP
       L1:     RESUME                   0

 105           LOAD_FAST                0 (self)
               LOAD_ATTR                0 (console)
               LOAD_ATTR                3 (info + NULL|self)
               LOAD_CONST               1 ('Authenticating token...')
               CALL                     1
               POP_TOP

 106           LOAD_FAST                0 (self)
               LOAD_ATTR                4 (http)
               LOAD_ATTR                7 (request + NULL|self)

 107           LOAD_CONST               2 ('GET')

 108           LOAD_CONST               3 ('users/@me')

 109           LOAD_FAST                0 (self)
               LOAD_ATTR                8 (token)

 110           LOAD_CONST               4 (True)

 111           LOAD_CONST               4 (True)

 112           LOAD_CONST               4 (True)

 106           LOAD_CONST               5 (('token', 'include_debug', 'include_locale', 'super_properties'))
               CALL_KW                  6
               GET_AWAITABLE            0
               LOAD_CONST               0 (None)
       L2:     SEND                     3 (to L5)
       L3:     YIELD_VALUE              1
       L4:     RESUME                   3
               JUMP_BACKWARD_NO_INTERRUPT 5 (to L2)
       L5:     END_SEND
               STORE_FAST               1 (response)

 114           LOAD_FAST                1 (response)
               LOAD_ATTR               10 (status_code)
               LOAD_CONST               6 (200)
               COMPARE_OP             119 (bool(!=))
               POP_JUMP_IF_FALSE       11 (to L6)

 115           LOAD_GLOBAL             13 (BackupError + NULL)
               LOAD_CONST               7 ('Invalid token or authentication failed')
               CALL                     1
               RAISE_VARARGS            1

 116   L6:     LOAD_FAST                1 (response)
               LOAD_ATTR               15 (json + NULL|self)
               CALL                     0
               STORE_FAST               2 (payload)

 117           LOAD_FAST                0 (self)
               LOAD_ATTR                0 (console)
               LOAD_ATTR               17 (success + NULL|self)
               LOAD_CONST               8 ('Authenticated user info')
               CALL                     1
               POP_TOP

 118           LOAD_FAST                2 (payload)
               RETURN_VALUE

 106   L7:     CLEANUP_THROW
       L8:     JUMP_BACKWARD_NO_INTERRUPT 76 (to L5)

  --   L9:     CALL_INTRINSIC_1         3 (INTRINSIC_STOPITERATION_ERROR)
               RERAISE                  1
ExceptionTable:
  L1 to L3 -> L9 [0] lasti
  L3 to L4 -> L7 [2]
  L4 to L8 -> L9 [0] lasti

Disassembly of <code object _fetch_asset at 0x000001EE5E850B90, file "discord_backup\backup.py", line 120>:
 120            RETURN_GENERATOR
                POP_TOP
        L1:     RESUME                   0

 121    L2:     NOP

 122    L3:     LOAD_FAST                0 (self)
                LOAD_ATTR                0 (http)
                LOAD_ATTR                3 (request + NULL|self)

 123            LOAD_CONST               1 ('GET')

 124            LOAD_FAST                1 (url)

 125            LOAD_CONST               0 (None)

 126            LOAD_CONST               2 (False)

 127            LOAD_CONST               2 (False)

 128            LOAD_CONST               0 (None)

 129            LOAD_CONST               3 ('Accept')
                LOAD_CONST               4 ('image/avif,image/webp,image/apng,image/svg+xml,image/*,*/*;q=0.8')
                BUILD_MAP                1

 122            LOAD_CONST               5 (('token', 'super_properties', 'include_locale', 'origin', 'headers'))
                CALL_KW                  7
                GET_AWAITABLE            0
                LOAD_CONST               0 (None)
        L4:     SEND                     3 (to L7)
        L5:     YIELD_VALUE              1
        L6:     RESUME                   3
                JUMP_BACKWARD_NO_INTERRUPT 5 (to L4)
        L7:     END_SEND
                STORE_FAST               2 (response)

 131            LOAD_FAST                2 (response)
                LOAD_ATTR                4 (status_code)
                LOAD_CONST               6 (200)
                COMPARE_OP              88 (bool(==))
                POP_JUMP_IF_FALSE       12 (to L9)

 132            LOAD_FAST                2 (response)
                LOAD_ATTR                6 (content)
        L8:     RETURN_VALUE

 131    L9:     NOP

 135            RETURN_CONST             7 (b'')

 122   L10:     CLEANUP_THROW
       L11:     JUMP_BACKWARD_NO_INTERRUPT 34 (to L7)

  --   L12:     PUSH_EXC_INFO

 133            LOAD_GLOBAL              8 (httpx)
                LOAD_ATTR               10 (HTTPError)
                CHECK_EXC_MATCH
                POP_JUMP_IF_FALSE        3 (to L14)
                POP_TOP

 134   L13:     POP_EXCEPT

 135            RETURN_CONST             7 (b'')

 133   L14:     RERAISE                  0

  --   L15:     COPY                     3
                POP_EXCEPT
                RERAISE                  1
       L16:     CALL_INTRINSIC_1         3 (INTRINSIC_STOPITERATION_ERROR)
                RERAISE                  1
ExceptionTable:
  L1 to L2 -> L16 [0] lasti
  L3 to L5 -> L12 [0]
  L5 to L6 -> L10 [2]
  L6 to L8 -> L12 [0]
  L8 to L10 -> L16 [0] lasti
  L10 to L11 -> L12 [0]
  L12 to L13 -> L15 [1] lasti
  L13 to L14 -> L16 [0] lasti
  L14 to L15 -> L15 [1] lasti
  L15 to L16 -> L16 [0] lasti

Disassembly of <code object _build_profile at 0x000001EE5E622C10, file "discord_backup\backup.py", line 137>:
 137            RETURN_GENERATOR
                POP_TOP
        L1:     RESUME                   0

 138            LOAD_CONST               1 (b'')
                STORE_FAST               2 (avatar_bytes)

 139            LOAD_FAST                1 (me)
                LOAD_ATTR                1 (get + NULL|self)
                LOAD_CONST               2 ('avatar')
                CALL                     1
                TO_BOOL
                POP_JUMP_IF_FALSE       40 (to L6)

 140            LOAD_CONST               3 ('https://cdn.discordapp.com/avatars/')
                LOAD_FAST                1 (me)
                LOAD_CONST               4 ('id')
                BINARY_SUBSCR
                FORMAT_SIMPLE
                LOAD_CONST               5 ('/')
                LOAD_FAST                1 (me)
                LOAD_CONST               2 ('avatar')
                BINARY_SUBSCR
                FORMAT_SIMPLE
                LOAD_CONST               6 ('.png?size=4096')
                BUILD_STRING             5
                STORE_FAST               3 (avatar_url)

 141            LOAD_FAST                0 (self)
                LOAD_ATTR                3 (_fetch_asset + NULL|self)
                LOAD_FAST                3 (avatar_url)
                CALL                     1
                GET_AWAITABLE            0
                LOAD_CONST               0 (None)
        L2:     SEND                     3 (to L5)
        L3:     YIELD_VALUE              1
        L4:     RESUME                   3
                JUMP_BACKWARD_NO_INTERRUPT 5 (to L2)
        L5:     END_SEND
                STORE_FAST               2 (avatar_bytes)

 143    L6:     LOAD_CONST               1 (b'')
                STORE_FAST               4 (banner_bytes)

 144            LOAD_FAST                1 (me)
                LOAD_ATTR                1 (get + NULL|self)
                LOAD_CONST               7 ('banner')
                CALL                     1
                TO_BOOL
                POP_JUMP_IF_FALSE       40 (to L11)

 145            LOAD_CONST               8 ('https://cdn.discordapp.com/banners/')
                LOAD_FAST                1 (me)
                LOAD_CONST               4 ('id')
                BINARY_SUBSCR
                FORMAT_SIMPLE
                LOAD_CONST               5 ('/')
                LOAD_FAST                1 (me)
                LOAD_CONST               7 ('banner')
                BINARY_SUBSCR
                FORMAT_SIMPLE
                LOAD_CONST               6 ('.png?size=4096')
                BUILD_STRING             5
                STORE_FAST               5 (banner_url)

 146            LOAD_FAST                0 (self)
                LOAD_ATTR                3 (_fetch_asset + NULL|self)
                LOAD_FAST                5 (banner_url)
                CALL                     1
                GET_AWAITABLE            0
                LOAD_CONST               0 (None)
        L7:     SEND                     3 (to L10)
        L8:     YIELD_VALUE              1
        L9:     RESUME                   3
                JUMP_BACKWARD_NO_INTERRUPT 5 (to L7)
       L10:     END_SEND
                STORE_FAST               4 (banner_bytes)

 148   L11:     LOAD_GLOBAL              5 (UserProfile + NULL)

 149            LOAD_GLOBAL              7 (str + NULL)
                LOAD_FAST                1 (me)
                LOAD_ATTR                1 (get + NULL|self)
                LOAD_CONST               4 ('id')
                CALL                     1
                CALL                     1

 150            LOAD_FAST                1 (me)
                LOAD_ATTR                1 (get + NULL|self)
                LOAD_CONST               9 ('username')
                LOAD_CONST              10 ('unknown')
                CALL                     2

 151            LOAD_GLOBAL              7 (str + NULL)
                LOAD_FAST                1 (me)
                LOAD_ATTR                1 (get + NULL|self)
                LOAD_CONST              11 ('discriminator')
                LOAD_CONST              12 ('0')
                CALL                     2
                CALL                     1

 152            LOAD_FAST                1 (me)
                LOAD_ATTR                1 (get + NULL|self)
                LOAD_CONST              13 ('bio')
                LOAD_CONST              14 ('')
                CALL                     2

 153            LOAD_GLOBAL              9 (encode_bytes_to_base64 + NULL)
                LOAD_FAST                2 (avatar_bytes)
                CALL                     1

 154            LOAD_GLOBAL              9 (encode_bytes_to_base64 + NULL)
                LOAD_FAST                4 (banner_bytes)
                CALL                     1

 148            LOAD_CONST              15 (('user_id', 'username', 'discriminator', 'bio', 'avatar_bytes', 'banner_bytes'))
                CALL_KW                  6
                STORE_FAST               6 (profile)

 156            LOAD_FAST                0 (self)
                LOAD_ATTR               10 (console)
                LOAD_ATTR               13 (success + NULL|self)
                LOAD_CONST              16 ('Captured profile, avatar and banner')
                CALL                     1
                POP_TOP

 157            LOAD_FAST                6 (profile)
                RETURN_VALUE

 141   L12:     CLEANUP_THROW
       L13:     JUMP_BACKWARD_NO_INTERRUPT 210 (to L5)

 146   L14:     CLEANUP_THROW
       L15:     JUMP_BACKWARD_NO_INTERRUPT 148 (to L10)

  --   L16:     CALL_INTRINSIC_1         3 (INTRINSIC_STOPITERATION_ERROR)
                RERAISE                  1
ExceptionTable:
  L1 to L3 -> L16 [0] lasti
  L3 to L4 -> L12 [2]
  L4 to L8 -> L16 [0] lasti
  L8 to L9 -> L14 [2]
  L9 to L13 -> L16 [0] lasti
  L14 to L15 -> L16 [0] lasti

Disassembly of <code object _fetch_relationships at 0x000001EE5E621580, file "discord_backup\backup.py", line 159>:
 159            RETURN_GENERATOR
                POP_TOP
        L1:     RESUME                   0

 160            LOAD_FAST                0 (self)
                LOAD_ATTR                0 (http)
                LOAD_ATTR                3 (request + NULL|self)

 161            LOAD_CONST               1 ('GET')

 162            LOAD_CONST               2 ('users/@me/relationships')

 163            LOAD_FAST                0 (self)
                LOAD_ATTR                4 (token)

 164            LOAD_CONST               3 (True)

 165            LOAD_CONST               3 (True)

 166            LOAD_CONST               3 (True)

 160            LOAD_CONST               4 (('token', 'include_debug', 'include_locale', 'super_properties'))
                CALL_KW                  6
                GET_AWAITABLE            0
                LOAD_CONST               0 (None)
        L2:     SEND                     3 (to L5)
        L3:     YIELD_VALUE              1
        L4:     RESUME                   3
                JUMP_BACKWARD_NO_INTERRUPT 5 (to L2)
        L5:     END_SEND
                STORE_FAST               1 (response)

 168            LOAD_FAST                1 (response)
                LOAD_ATTR                6 (status_code)
                LOAD_CONST               5 (200)
                COMPARE_OP              88 (bool(==))
                POP_JUMP_IF_FALSE       16 (to L6)
                LOAD_FAST                1 (response)
                LOAD_ATTR                9 (json + NULL|self)
                CALL                     0
                JUMP_FORWARD             1 (to L7)
        L6:     BUILD_LIST               0
        L7:     STORE_FAST               2 (data)

 169            BUILD_LIST               0
                BUILD_LIST               0
                BUILD_LIST               0
                BUILD_LIST               0
                LOAD_CONST               6 ((1, 2, 3, 4))
                BUILD_CONST_KEY_MAP      4
                STORE_FAST               3 (relationship_map)

 170            LOAD_FAST                2 (data)
                GET_ITER
        L8:     FOR_ITER                81 (to L13)
                STORE_FAST               4 (user)

 171            LOAD_FAST                4 (user)
                LOAD_ATTR               11 (get + NULL|self)
                LOAD_CONST               7 ('type')
                CALL                     1
                STORE_FAST               5 (user_type)

 172            LOAD_GLOBAL             13 (str + NULL)
                LOAD_FAST                4 (user)
                LOAD_ATTR               11 (get + NULL|self)
                LOAD_CONST               8 ('id')
                CALL                     1
                CALL                     1
                STORE_FAST               6 (user_id)

 173            LOAD_FAST_LOAD_FAST     83 (user_type, relationship_map)
                CONTAINS_OP              0
        L9:     POP_JUMP_IF_TRUE         2 (to L10)
                JUMP_BACKWARD           53 (to L8)
       L10:     LOAD_FAST                6 (user_id)
                TO_BOOL
       L11:     POP_JUMP_IF_TRUE         2 (to L12)
                JUMP_BACKWARD           62 (to L8)

 174   L12:     LOAD_FAST_LOAD_FAST     53 (relationship_map, user_type)
                BINARY_SUBSCR
                LOAD_ATTR               15 (append + NULL|self)
                LOAD_FAST                6 (user_id)
                CALL                     1
                POP_TOP
                JUMP_BACKWARD           83 (to L8)

 170   L13:     END_FOR
                POP_TOP

 175            LOAD_FAST                0 (self)
                LOAD_ATTR               16 (console)
                LOAD_ATTR               19 (success + NULL|self)
                LOAD_CONST               9 ('Fetched relationships')
                CALL                     1
                POP_TOP

 176            LOAD_GLOBAL             21 (RelationshipSnapshot + NULL)

 177            LOAD_FAST                3 (relationship_map)
                LOAD_CONST              10 (1)
                BINARY_SUBSCR

 178            LOAD_FAST                3 (relationship_map)
                LOAD_CONST              11 (2)
                BINARY_SUBSCR

 179            LOAD_FAST                3 (relationship_map)
                LOAD_CONST              12 (3)
                BINARY_SUBSCR

 180            LOAD_FAST                3 (relationship_map)
                LOAD_CONST              13 (4)
                BINARY_SUBSCR

 176            LOAD_CONST              14 (('friends', 'blocked', 'incoming', 'outgoing'))
                CALL_KW                  4
                RETURN_VALUE

 160   L14:     CLEANUP_THROW
       L15:     JUMP_BACKWARD_NO_INTERRUPT 183 (to L5)

  --   L16:     CALL_INTRINSIC_1         3 (INTRINSIC_STOPITERATION_ERROR)
                RERAISE                  1
ExceptionTable:
  L1 to L3 -> L16 [0] lasti
  L3 to L4 -> L14 [2]
  L4 to L9 -> L16 [0] lasti
  L10 to L11 -> L16 [0] lasti
  L12 to L15 -> L16 [0] lasti

Disassembly of <code object _Settings at 0x000001EE5E816430, file "discord_backup\backup.py", line 183>:
183           RESUME                   0
              LOAD_NAME                0 (__name__)
              STORE_NAME               1 (__module__)
              LOAD_CONST               0 ('BackupService._Settings')
              STORE_NAME               2 (__qualname__)
              LOAD_CONST               1 (183)
              STORE_NAME               3 (__firstlineno__)
              SETUP_ANNOTATIONS

185           LOAD_CONST               2 ('list[dict[str, Any]]')
              LOAD_NAME                4 (__annotations__)
              LOAD_CONST               3 ('guild_folders')
              STORE_SUBSCR

186           LOAD_CONST               4 ('dict[str, Any] | None')
              LOAD_NAME                4 (__annotations__)
              LOAD_CONST               5 ('proto_settings')
              STORE_SUBSCR
              LOAD_CONST               6 (())
              STORE_NAME               5 (__static_attributes__)
              RETURN_CONST             7 (None)

Disassembly of <code object _fetch_settings at 0x000001EE5E621E10, file "discord_backup\backup.py", line 188>:
 188            RETURN_GENERATOR
                POP_TOP
        L1:     RESUME                   0

 189            LOAD_FAST                0 (self)
                LOAD_ATTR                0 (http)
                LOAD_ATTR                3 (request + NULL|self)

 190            LOAD_CONST               1 ('GET')

 191            LOAD_CONST               2 ('users/@me/settings')

 192            LOAD_FAST                0 (self)
                LOAD_ATTR                4 (token)

 193            LOAD_CONST               3 (True)

 194            LOAD_CONST               3 (True)

 195            LOAD_CONST               3 (True)

 189            LOAD_CONST               4 (('token', 'include_debug', 'include_locale', 'super_properties'))
                CALL_KW                  6
                GET_AWAITABLE            0
                LOAD_CONST               0 (None)
        L2:     SEND                     3 (to L5)
        L3:     YIELD_VALUE              1
        L4:     RESUME                   3
                JUMP_BACKWARD_NO_INTERRUPT 5 (to L2)
        L5:     END_SEND
                STORE_FAST               1 (folders_response)

 197            LOAD_FAST                1 (folders_response)
                LOAD_ATTR                6 (status_code)
                LOAD_CONST               5 (200)
                COMPARE_OP              88 (bool(==))
                POP_JUMP_IF_FALSE       16 (to L6)
                LOAD_FAST                1 (folders_response)
                LOAD_ATTR                9 (json + NULL|self)
                CALL                     0
                JUMP_FORWARD             1 (to L7)
        L6:     BUILD_MAP                0
        L7:     STORE_FAST               2 (folders_payload)

 198            LOAD_FAST                2 (folders_payload)
                LOAD_ATTR               11 (get + NULL|self)
                LOAD_CONST               6 ('guild_folders')
                BUILD_LIST               0
                CALL                     2
                STORE_FAST               3 (folders)

 200            LOAD_FAST                0 (self)
                LOAD_ATTR                0 (http)
                LOAD_ATTR                3 (request + NULL|self)

 201            LOAD_CONST               1 ('GET')

 202            LOAD_CONST               7 ('users/@me/settings-proto/2')

 203            LOAD_FAST                0 (self)
                LOAD_ATTR                4 (token)

 204            LOAD_CONST               3 (True)

 205            LOAD_CONST               3 (True)

 206            LOAD_CONST               3 (True)

 200            LOAD_CONST               4 (('token', 'include_debug', 'include_locale', 'super_properties'))
                CALL_KW                  6
                GET_AWAITABLE            0
                LOAD_CONST               0 (None)
        L8:     SEND                     3 (to L11)
        L9:     YIELD_VALUE              1
       L10:     RESUME                   3
                JUMP_BACKWARD_NO_INTERRUPT 5 (to L8)
       L11:     END_SEND
                STORE_FAST               4 (proto_response)

 210            LOAD_FAST                4 (proto_response)
                LOAD_ATTR                6 (status_code)
                LOAD_CONST               5 (200)
                COMPARE_OP              88 (bool(==))
                POP_JUMP_IF_FALSE       31 (to L12)

 209            LOAD_FAST                4 (proto_response)
                LOAD_ATTR                9 (json + NULL|self)
                CALL                     0
                LOAD_ATTR               11 (get + NULL|self)
                LOAD_CONST               8 ('settings')
                CALL                     1
                JUMP_FORWARD             1 (to L13)

 211   L12:     LOAD_CONST               0 (None)

 208   L13:     STORE_FAST               5 (proto_settings)

 214            LOAD_FAST                0 (self)
                LOAD_ATTR               12 (console)
                LOAD_ATTR               15 (success + NULL|self)
                LOAD_CONST               9 ('Backed up settings and guild folders')
                CALL                     1
                POP_TOP

 215            LOAD_FAST                0 (self)
                LOAD_ATTR               17 (_Settings + NULL|self)
                LOAD_FAST_LOAD_FAST     53 (folders, proto_settings)
                LOAD_CONST              10 (('guild_folders', 'proto_settings'))
                CALL_KW                  2
                RETURN_VALUE

 189   L14:     CLEANUP_THROW
       L15:     JUMP_BACKWARD_NO_INTERRUPT 195 (to L5)

 200   L16:     CLEANUP_THROW
       L17:     JUMP_BACKWARD_NO_INTERRUPT 97 (to L11)

  --   L18:     CALL_INTRINSIC_1         3 (INTRINSIC_STOPITERATION_ERROR)
                RERAISE                  1
ExceptionTable:
  L1 to L3 -> L18 [0] lasti
  L3 to L4 -> L14 [2]
  L4 to L9 -> L18 [0] lasti
  L9 to L10 -> L16 [2]
  L10 to L15 -> L18 [0] lasti
  L16 to L17 -> L18 [0] lasti

Disassembly of <code object _GuildResult at 0x000001EE5E816730, file "discord_backup\backup.py", line 217>:
217           RESUME                   0
              LOAD_NAME                0 (__name__)
              STORE_NAME               1 (__module__)
              LOAD_CONST               0 ('BackupService._GuildResult')
              STORE_NAME               2 (__qualname__)
              LOAD_CONST               1 (217)
              STORE_NAME               3 (__firstlineno__)
              SETUP_ANNOTATIONS

219           LOAD_CONST               2 ('list[GuildInvite]')
              LOAD_NAME                4 (__annotations__)
              LOAD_CONST               3 ('invites')
              STORE_SUBSCR

220           LOAD_CONST               4 ('int')
              LOAD_NAME                4 (__annotations__)
              LOAD_CONST               5 ('success')
              STORE_SUBSCR

221           LOAD_CONST               4 ('int')
              LOAD_NAME                4 (__annotations__)
              LOAD_CONST               6 ('total')
              STORE_SUBSCR
              LOAD_CONST               7 (())
              STORE_NAME               5 (__static_attributes__)
              RETURN_CONST             8 (None)

Disassembly of <code object _fetch_guild_invites at 0x000001EE5E624B00, file "discord_backup\backup.py", line 223>:
 223            RETURN_GENERATOR
                POP_TOP
        L1:     RESUME                   0

 224            LOAD_FAST                0 (self)
                LOAD_ATTR                0 (http)
                LOAD_ATTR                3 (request + NULL|self)

 225            LOAD_CONST               1 ('GET')

 226            LOAD_CONST               2 ('users/@me/guilds')

 227            LOAD_FAST                0 (self)
                LOAD_ATTR                4 (token)

 228            LOAD_CONST               3 (True)

 229            LOAD_CONST               3 (True)

 230            LOAD_CONST               3 (True)

 224            LOAD_CONST               4 (('token', 'include_debug', 'include_locale', 'super_properties'))
                CALL_KW                  6
                GET_AWAITABLE            0
                LOAD_CONST               0 (None)
        L2:     SEND                     3 (to L5)
        L3:     YIELD_VALUE              1
        L4:     RESUME                   3
                JUMP_BACKWARD_NO_INTERRUPT 5 (to L2)
        L5:     END_SEND
                STORE_FAST               1 (response)

 232            LOAD_FAST                1 (response)
                LOAD_ATTR                6 (status_code)
                LOAD_CONST               5 (200)
                COMPARE_OP              88 (bool(==))
                POP_JUMP_IF_FALSE       16 (to L6)
                LOAD_FAST                1 (response)
                LOAD_ATTR                9 (json + NULL|self)
                CALL                     0
                JUMP_FORWARD             1 (to L7)
        L6:     BUILD_LIST               0
        L7:     STORE_FAST               2 (guilds)

 233            BUILD_LIST               0
                STORE_FAST               3 (invites)

 234            LOAD_CONST               6 (0)
                STORE_FAST               4 (success)

 235            LOAD_GLOBAL             11 (len + NULL)
                LOAD_FAST                2 (guilds)
                CALL                     1
                STORE_FAST               5 (total)

 237            LOAD_GLOBAL             13 (enumerate + NULL)
                LOAD_FAST                2 (guilds)
                LOAD_CONST               7 (1)
                LOAD_CONST               8 (('start',))
                CALL_KW                  2
                GET_ITER
        L8:     FOR_ITER               185 (to L14)
                UNPACK_SEQUENCE          2
                STORE_FAST_STORE_FAST  103 (index, guild)

 238            LOAD_FAST                0 (self)
                LOAD_ATTR               14 (console)
                LOAD_ATTR               17 (info + NULL|self)

 239            LOAD_CONST               9 ('[')
                LOAD_FAST                6 (index)
                FORMAT_SIMPLE
                LOAD_CONST              10 ('/')
                LOAD_FAST                5 (total)
                FORMAT_SIMPLE
                LOAD_CONST              11 ('] Preparing invite for ')
                LOAD_FAST                7 (guild)
                LOAD_ATTR               19 (get + NULL|self)
                LOAD_CONST              12 ('name')
                LOAD_CONST              13 ('Unknown')
                CALL                     2
                FORMAT_SIMPLE
                BUILD_STRING             6

 238            CALL                     1
                POP_TOP

 241            LOAD_FAST                0 (self)
                LOAD_ATTR               21 (_create_invite_for_guild + NULL|self)
                LOAD_FAST                7 (guild)
                CALL                     1
                GET_AWAITABLE            0
                LOAD_CONST               0 (None)
        L9:     SEND                     3 (to L12)
       L10:     YIELD_VALUE              1
       L11:     RESUME                   3
                JUMP_BACKWARD_NO_INTERRUPT 5 (to L9)
       L12:     END_SEND
                STORE_FAST               8 (invite)

 242            LOAD_FAST                3 (invites)
                LOAD_ATTR               23 (append + NULL|self)
                LOAD_FAST                8 (invite)
                CALL                     1
                POP_TOP

 243            LOAD_FAST                8 (invite)
                LOAD_ATTR               24 (invite_code)
                TO_BOOL
                POP_JUMP_IF_FALSE       23 (to L13)
                LOAD_FAST                8 (invite)
                LOAD_ATTR               24 (invite_code)
                LOAD_CONST              14 ('Unable to create.')
                COMPARE_OP             119 (bool(!=))
                POP_JUMP_IF_FALSE        7 (to L13)

 244            LOAD_FAST                4 (success)
                LOAD_CONST               7 (1)
                BINARY_OP               13 (+=)
                STORE_FAST               4 (success)
                JUMP_BACKWARD          139 (to L8)

 246   L13:     LOAD_FAST                0 (self)
                LOAD_ATTR               14 (console)
                LOAD_ATTR               27 (warn + NULL|self)

 247            LOAD_CONST              15 ('Failed to create invite for ')
                LOAD_FAST                7 (guild)
                LOAD_ATTR               19 (get + NULL|self)
                LOAD_CONST              12 ('name')
                LOAD_CONST              13 ('Unknown')
                CALL                     2
                FORMAT_SIMPLE
                BUILD_STRING             2

 246            CALL                     1
                POP_TOP
                JUMP_BACKWARD          187 (to L8)

 237   L14:     END_FOR
                POP_TOP

 249            LOAD_FAST                0 (self)
                LOAD_ATTR               29 (_GuildResult + NULL|self)
                LOAD_FAST_LOAD_FAST     52 (invites, success)
                LOAD_FAST                5 (total)
                LOAD_CONST              16 (('invites', 'success', 'total'))
                CALL_KW                  3
                RETURN_VALUE

 224   L15:     CLEANUP_THROW
       L16:     EXTENDED_ARG             1
                JUMP_BACKWARD_NO_INTERRUPT 269 (to L5)

 241   L17:     CLEANUP_THROW
       L18:     JUMP_BACKWARD_NO_INTERRUPT 130 (to L12)

  --   L19:     CALL_INTRINSIC_1         3 (INTRINSIC_STOPITERATION_ERROR)
                RERAISE                  1
ExceptionTable:
  L1 to L3 -> L19 [0] lasti
  L3 to L4 -> L15 [2]
  L4 to L10 -> L19 [0] lasti
  L10 to L11 -> L17 [3]
  L11 to L16 -> L19 [0] lasti
  L17 to L18 -> L19 [0] lasti

Disassembly of <code object _create_invite_for_guild at 0x000001EE5C72AC10, file "discord_backup\backup.py", line 251>:
 251            RETURN_GENERATOR
                POP_TOP
        L1:     RESUME                   0

 252            LOAD_GLOBAL              1 (str + NULL)
                LOAD_FAST                1 (guild)
                LOAD_ATTR                3 (get + NULL|self)
                LOAD_CONST               1 ('id')
                CALL                     1
                CALL                     1
                STORE_FAST               2 (guild_id)

 253            LOAD_FAST                1 (guild)
                LOAD_ATTR                3 (get + NULL|self)
                LOAD_CONST               2 ('name')
                LOAD_CONST               3 ('Unknown')
                CALL                     2
                STORE_FAST               3 (name)

 254            LOAD_CONST               4 ('VANITY_URL')
                LOAD_FAST                1 (guild)
                LOAD_ATTR                3 (get + NULL|self)
                LOAD_CONST               5 ('features')
                BUILD_LIST               0
                CALL                     2
                CONTAINS_OP              0
                POP_JUMP_IF_FALSE      148 (to L6)

 255            LOAD_FAST                0 (self)
                LOAD_ATTR                4 (http)
                LOAD_ATTR                7 (request + NULL|self)

 256            LOAD_CONST               6 ('GET')

 257            LOAD_CONST               7 ('guilds/')
                LOAD_FAST                2 (guild_id)
                FORMAT_SIMPLE
                BUILD_STRING             2

 258            LOAD_FAST                0 (self)
                LOAD_ATTR                8 (token)

 259            LOAD_CONST               8 (True)

 260            LOAD_CONST               8 (True)

 261            LOAD_CONST               8 (True)

 255            LOAD_CONST               9 (('token', 'include_debug', 'include_locale', 'super_properties'))
                CALL_KW                  6
                GET_AWAITABLE            0
                LOAD_CONST               0 (None)
        L2:     SEND                     3 (to L5)
        L3:     YIELD_VALUE              1
        L4:     RESUME                   3
                JUMP_BACKWARD_NO_INTERRUPT 5 (to L2)
        L5:     END_SEND
                STORE_FAST               4 (vanity_response)

 263            LOAD_FAST                4 (vanity_response)
                LOAD_ATTR               10 (status_code)
                LOAD_CONST              10 (200)
                COMPARE_OP              88 (bool(==))
                POP_JUMP_IF_FALSE       81 (to L6)

 264            LOAD_FAST                4 (vanity_response)
                LOAD_ATTR               13 (json + NULL|self)
                CALL                     0
                LOAD_ATTR                3 (get + NULL|self)
                LOAD_CONST              11 ('vanity_url_code')
                CALL                     1
                STORE_FAST               5 (code)

 265            LOAD_FAST                5 (code)
                TO_BOOL
                POP_JUMP_IF_FALSE       43 (to L6)

 266            LOAD_FAST                0 (self)
                LOAD_ATTR               14 (console)
                LOAD_ATTR               17 (success + NULL|self)
                LOAD_CONST              12 ('Using vanity invite for ')
                LOAD_FAST                3 (name)
                FORMAT_SIMPLE
                LOAD_CONST              13 (': ')
                LOAD_FAST                5 (code)
                FORMAT_SIMPLE
                BUILD_STRING             4
                CALL                     1
                POP_TOP

 267            LOAD_GLOBAL             19 (GuildInvite + NULL)
                LOAD_FAST_LOAD_FAST     35 (guild_id, name)
                LOAD_FAST                5 (code)
                LOAD_CONST              14 (('guild_id', 'name', 'invite_code'))
                CALL_KW                  3
                RETURN_VALUE

 269    L6:     LOAD_FAST                0 (self)
                LOAD_ATTR                4 (http)
                LOAD_ATTR               13 (json + NULL|self)

 270            LOAD_CONST               6 ('GET')

 271            LOAD_CONST               7 ('guilds/')
                LOAD_FAST                2 (guild_id)
                FORMAT_SIMPLE
                LOAD_CONST              15 ('/channels')
                BUILD_STRING             3

 272            LOAD_FAST                0 (self)
                LOAD_ATTR                8 (token)

 273            LOAD_CONST               8 (True)

 274            LOAD_CONST               8 (True)

 275            LOAD_CONST               8 (True)

 269            LOAD_CONST               9 (('token', 'include_debug', 'include_locale', 'super_properties'))
                CALL_KW                  6
                GET_AWAITABLE            0
                LOAD_CONST               0 (None)
        L7:     SEND                     3 (to L10)
        L8:     YIELD_VALUE              1
        L9:     RESUME                   3
                JUMP_BACKWARD_NO_INTERRUPT 5 (to L7)
       L10:     END_SEND
                STORE_FAST               6 (channels)

 278            LOAD_FAST                6 (channels)
                GET_ITER
                LOAD_FAST_AND_CLEAR      7 (c)
                SWAP                     2
       L11:     BUILD_LIST               0
                SWAP                     2
                GET_ITER
       L12:     FOR_ITER                31 (to L15)
                STORE_FAST_LOAD_FAST   119 (c, c)
                LOAD_ATTR                3 (get + NULL|self)
                LOAD_CONST              16 ('type')
                CALL                     1
                LOAD_GLOBAL             20 (ALLOWED_INVITE_CHANNEL_TYPES)
                CONTAINS_OP              0
       L13:     POP_JUMP_IF_TRUE         2 (to L14)
                JUMP_BACKWARD           29 (to L12)
       L14:     LOAD_FAST                7 (c)
                LIST_APPEND              2
                JUMP_BACKWARD           33 (to L12)
       L15:     END_FOR
                POP_TOP
       L16:     STORE_FAST               8 (typed_channels)
                STORE_FAST               7 (c)

 279            LOAD_GLOBAL             23 (sorted + NULL)

 280            LOAD_FAST                8 (typed_channels)

 281            LOAD_CONST              17 (<code object <lambda> at 0x000001EE5E8844F0, file "discord_backup\backup.py", line 281>)
                MAKE_FUNCTION

 279            LOAD_CONST              18 (('key',))
                CALL_KW                  2
                STORE_FAST               9 (prioritized)

 290            LOAD_FAST                9 (prioritized)
                GET_ITER
       L17:     FOR_ITER                99 (to L24)
                STORE_FAST              10 (channel)

 291            LOAD_FAST                0 (self)
                LOAD_ATTR               25 (_attempt_invite_creation + NULL|self)
                LOAD_FAST               10 (channel)
                LOAD_GLOBAL             26 (INVITE_PAYLOAD_DEFAULT)
                LOAD_CONST              19 (('payload',))
                CALL_KW                  2
                GET_AWAITABLE            0
                LOAD_CONST               0 (None)
       L18:     SEND                     3 (to L21)
       L19:     YIELD_VALUE              1
       L20:     RESUME                   3
                JUMP_BACKWARD_NO_INTERRUPT 5 (to L18)
       L21:     END_SEND
                STORE_FAST               5 (code)

 292            LOAD_FAST                5 (code)
                TO_BOOL
       L22:     POP_JUMP_IF_TRUE         2 (to L23)
                JUMP_BACKWARD           40 (to L17)

 293   L23:     LOAD_FAST                0 (self)
                LOAD_ATTR               14 (console)
                LOAD_ATTR               17 (success + NULL|self)

 294            LOAD_CONST              20 ('Invite created in #')
                LOAD_FAST               10 (channel)
                LOAD_ATTR                3 (get + NULL|self)
                LOAD_CONST               2 ('name')
                LOAD_CONST              21 ('unknown')
                CALL                     2
                FORMAT_SIMPLE
                LOAD_CONST              22 (' -> ')
                LOAD_FAST                5 (code)
                FORMAT_SIMPLE
                BUILD_STRING             4

 293            CALL                     1
                POP_TOP

 296            LOAD_GLOBAL             19 (GuildInvite + NULL)
                LOAD_FAST_LOAD_FAST     35 (guild_id, name)
                LOAD_FAST                5 (code)
                LOAD_CONST              14 (('guild_id', 'name', 'invite_code'))
                CALL_KW                  3
                SWAP                     2
                POP_TOP
                RETURN_VALUE

 290   L24:     END_FOR
                POP_TOP

 298            LOAD_FAST                9 (prioritized)
                GET_ITER
       L25:     FOR_ITER                99 (to L32)
                STORE_FAST              10 (channel)

 299            LOAD_FAST                0 (self)
                LOAD_ATTR               25 (_attempt_invite_creation + NULL|self)
                LOAD_FAST               10 (channel)
                LOAD_CONST              23 (0)
                LOAD_CONST              23 (0)
                LOAD_CONST              24 (False)
                LOAD_CONST              25 (('max_age', 'max_uses', 'temporary'))
                BUILD_CONST_KEY_MAP      3
                LOAD_CONST              19 (('payload',))
                CALL_KW                  2
                GET_AWAITABLE            0
                LOAD_CONST               0 (None)
       L26:     SEND                     3 (to L29)
       L27:     YIELD_VALUE              1
       L28:     RESUME                   3
                JUMP_BACKWARD_NO_INTERRUPT 5 (to L26)
       L29:     END_SEND
                STORE_FAST               5 (code)

 300            LOAD_FAST                5 (code)
                TO_BOOL
       L30:     POP_JUMP_IF_TRUE         2 (to L31)
                JUMP_BACKWARD           40 (to L25)

 301   L31:     LOAD_FAST                0 (self)
                LOAD_ATTR               14 (console)
                LOAD_ATTR               17 (success + NULL|self)

 302            LOAD_CONST              26 ('Fallback invite in #')
                LOAD_FAST               10 (channel)
                LOAD_ATTR                3 (get + NULL|self)
                LOAD_CONST               2 ('name')
                LOAD_CONST              21 ('unknown')
                CALL                     2
                FORMAT_SIMPLE
                LOAD_CONST              22 (' -> ')
                LOAD_FAST                5 (code)
                FORMAT_SIMPLE
                BUILD_STRING             4

 301            CALL                     1
                POP_TOP

 304            LOAD_GLOBAL             19 (GuildInvite + NULL)
                LOAD_FAST_LOAD_FAST     35 (guild_id, name)
                LOAD_FAST                5 (code)
                LOAD_CONST              14 (('guild_id', 'name', 'invite_code'))
                CALL_KW                  3
                SWAP                     2
                POP_TOP
                RETURN_VALUE

 298   L32:     END_FOR
                POP_TOP

 306            LOAD_GLOBAL             19 (GuildInvite + NULL)
                LOAD_FAST_LOAD_FAST     35 (guild_id, name)
                LOAD_CONST              27 ('Unable to create.')
                LOAD_CONST              14 (('guild_id', 'name', 'invite_code'))
                CALL_KW                  3
                RETURN_VALUE

 255   L33:     CLEANUP_THROW
       L34:     EXTENDED_ARG             1
                JUMP_BACKWARD_NO_INTERRUPT 429 (to L5)

 269   L35:     CLEANUP_THROW
       L36:     EXTENDED_ARG             1
                JUMP_BACKWARD_NO_INTERRUPT 283 (to L10)

  --   L37:     SWAP                     2
                POP_TOP

 278            SWAP                     2
                STORE_FAST               7 (c)
                RERAISE                  0

 291   L38:     CLEANUP_THROW
       L39:     JUMP_BACKWARD_NO_INTERRUPT 202 (to L21)

 299   L40:     CLEANUP_THROW
       L41:     JUMP_BACKWARD_NO_INTERRUPT 99 (to L29)

  --   L42:     CALL_INTRINSIC_1         3 (INTRINSIC_STOPITERATION_ERROR)
                RERAISE                  1
ExceptionTable:
  L1 to L3 -> L42 [0] lasti
  L3 to L4 -> L33 [2]
  L4 to L8 -> L42 [0] lasti
  L8 to L9 -> L35 [2]
  L9 to L11 -> L42 [0] lasti
  L11 to L13 -> L37 [2]
  L14 to L16 -> L37 [2]
  L16 to L19 -> L42 [0] lasti
  L19 to L20 -> L38 [3]
  L20 to L22 -> L42 [0] lasti
  L23 to L27 -> L42 [0] lasti
  L27 to L28 -> L40 [3]
  L28 to L30 -> L42 [0] lasti
  L31 to L34 -> L42 [0] lasti
  L35 to L36 -> L42 [0] lasti
  L37 to L39 -> L42 [0] lasti
  L40 to L41 -> L42 [0] lasti

Disassembly of <code object <lambda> at 0x000001EE5E8844F0, file "discord_backup\backup.py", line 281>:
  --           MAKE_CELL                0 (channel)

 281           RESUME                   0

 282           LOAD_GLOBAL              1 (min + NULL)
               LOAD_FAST                0 (channel)
               BUILD_TUPLE              1
               LOAD_CONST               1 (<code object <genexpr> at 0x000001EE5E786AD0, file "discord_backup\backup.py", line 282>)
               MAKE_FUNCTION
               SET_FUNCTION_ATTRIBUTE   8 (closure)

 284           LOAD_GLOBAL              2 (PREFERRED_CHANNEL_KEYWORDS)
               GET_ITER

 282           CALL                     0
               CALL                     1

 286           LOAD_DEREF               0 (channel)
               LOAD_ATTR                5 (get + NULL|self)
               LOAD_CONST               2 ('position')
               LOAD_CONST               3 (9999)
               CALL                     2

 281           BUILD_TUPLE              2
               RETURN_VALUE

Disassembly of <code object <genexpr> at 0x000001EE5E786AD0, file "discord_backup\backup.py", line 282>:
  --           COPY_FREE_VARS           1

 282           RETURN_GENERATOR
               POP_TOP
       L1:     RESUME                   0
               LOAD_FAST                0 (.0)

 284           GET_ITER
       L2:     FOR_ITER                62 (to L5)
               STORE_FAST               1 (keyword)

 283           LOAD_FAST                1 (keyword)
               LOAD_DEREF               2 (channel)
               LOAD_ATTR                1 (get + NULL|self)
               LOAD_CONST               0 ('name')
               LOAD_CONST               1 ('')
               CALL                     2
               CONTAINS_OP              0
               POP_JUMP_IF_FALSE       33 (to L3)
               LOAD_DEREF               2 (channel)
               LOAD_ATTR                1 (get + NULL|self)
               LOAD_CONST               0 ('name')
               LOAD_CONST               1 ('')
               CALL                     2
               LOAD_ATTR                3 (find + NULL|self)
               LOAD_FAST                1 (keyword)
               CALL                     1
               JUMP_FORWARD             1 (to L4)
       L3:     LOAD_CONST               2 (999)
       L4:     YIELD_VALUE              0
               RESUME                   5
               POP_TOP
               JUMP_BACKWARD           64 (to L2)

 284   L5:     END_FOR
               POP_TOP
               RETURN_CONST             3 (None)

  --   L6:     CALL_INTRINSIC_1         3 (INTRINSIC_STOPITERATION_ERROR)
               RERAISE                  1
ExceptionTable:
  L1 to L6 -> L6 [0] lasti

Disassembly of <code object _attempt_invite_creation at 0x000001EE5C61BA50, file "discord_backup\backup.py", line 308>:
 308            RETURN_GENERATOR
                POP_TOP
        L1:     RESUME                   0

 309            LOAD_FAST                1 (channel)
                LOAD_ATTR                1 (get + NULL|self)
                LOAD_CONST               1 ('id')
                CALL                     1
                STORE_FAST               3 (channel_id)

 310            LOAD_FAST                3 (channel_id)
                TO_BOOL
                POP_JUMP_IF_TRUE         1 (to L2)

 311            RETURN_CONST             0 (None)

 312    L2:     LOAD_FAST                0 (self)
                LOAD_ATTR                2 (http)
                LOAD_ATTR                5 (request + NULL|self)

 313            LOAD_CONST               2 ('POST')

 314            LOAD_CONST               3 ('channels/')
                LOAD_FAST                3 (channel_id)
                FORMAT_SIMPLE
                LOAD_CONST               4 ('/invites')
                BUILD_STRING             3

 315            LOAD_FAST                0 (self)
                LOAD_ATTR                6 (token)

 316            LOAD_FAST                2 (payload)

 317            LOAD_CONST               5 (True)

 318            LOAD_CONST               5 (True)

 319            LOAD_CONST               5 (True)

 320            LOAD_CONST               6 ((200,))

 312            LOAD_CONST               7 (('token', 'json_payload', 'include_debug', 'include_locale', 'super_properties', 'expected_status'))
                CALL_KW                  8
                GET_AWAITABLE            0
                LOAD_CONST               0 (None)
        L3:     SEND                     3 (to L6)
        L4:     YIELD_VALUE              1
        L5:     RESUME                   3
                JUMP_BACKWARD_NO_INTERRUPT 5 (to L3)
        L6:     END_SEND
                STORE_FAST               4 (response)

 322            LOAD_FAST                4 (response)
                LOAD_ATTR                8 (status_code)
                LOAD_CONST               8 (200)
                COMPARE_OP              88 (bool(==))
                POP_JUMP_IF_FALSE       31 (to L7)

 323            LOAD_FAST                4 (response)
                LOAD_ATTR               11 (json + NULL|self)
                CALL                     0
                LOAD_ATTR                1 (get + NULL|self)
                LOAD_CONST               9 ('code')
                CALL                     1
                RETURN_VALUE

 324    L7:     RETURN_CONST             0 (None)

 312    L8:     CLEANUP_THROW
        L9:     JUMP_BACKWARD_NO_INTERRUPT 52 (to L6)

  --   L10:     CALL_INTRINSIC_1         3 (INTRINSIC_STOPITERATION_ERROR)
                RERAISE                  1
ExceptionTable:
  L1 to L4 -> L10 [0] lasti
  L4 to L5 -> L8 [2]
  L5 to L9 -> L10 [0] lasti

Disassembly of <code object _fetch_channels at 0x000001EE5C5AEBB0, file "discord_backup\backup.py", line 326>:
 326            RETURN_GENERATOR
                POP_TOP
        L1:     RESUME                   0

 327            LOAD_FAST                0 (self)
                LOAD_ATTR                0 (http)
                LOAD_ATTR                3 (request + NULL|self)

 328            LOAD_CONST               1 ('GET')

 329            LOAD_CONST               2 ('users/@me/channels')

 330            LOAD_FAST                0 (self)
                LOAD_ATTR                4 (token)

 331            LOAD_CONST               3 (True)

 332            LOAD_CONST               3 (True)

 333            LOAD_CONST               3 (True)

 327            LOAD_CONST               4 (('token', 'include_debug', 'include_locale', 'super_properties'))
                CALL_KW                  6
                GET_AWAITABLE            0
                LOAD_CONST               0 (None)
        L2:     SEND                     3 (to L5)
        L3:     YIELD_VALUE              1
        L4:     RESUME                   3
                JUMP_BACKWARD_NO_INTERRUPT 5 (to L2)
        L5:     END_SEND
                STORE_FAST               1 (response)

 335            LOAD_FAST                1 (response)
                LOAD_ATTR                6 (status_code)
                LOAD_CONST               5 (200)
                COMPARE_OP              88 (bool(==))
                POP_JUMP_IF_FALSE       16 (to L6)
                LOAD_FAST                1 (response)
                LOAD_ATTR                9 (json + NULL|self)
                CALL                     0
                JUMP_FORWARD             1 (to L7)
        L6:     BUILD_LIST               0
        L7:     STORE_FAST               2 (channels)

 336            LOAD_FAST                0 (self)
                LOAD_ATTR               10 (console)
                LOAD_ATTR               13 (success + NULL|self)
                LOAD_CONST               6 ('Loaded ')
                LOAD_GLOBAL             15 (len + NULL)
                LOAD_FAST                2 (channels)
                CALL                     1
                FORMAT_SIMPLE
                LOAD_CONST               7 (' private channels')
                BUILD_STRING             3
                CALL                     1
                POP_TOP

 337            LOAD_FAST                2 (channels)
                RETURN_VALUE

 327    L8:     CLEANUP_THROW
        L9:     JUMP_BACKWARD_NO_INTERRUPT 80 (to L5)

  --   L10:     CALL_INTRINSIC_1         3 (INTRINSIC_STOPITERATION_ERROR)
                RERAISE                  1
ExceptionTable:
  L1 to L3 -> L10 [0] lasti
  L3 to L4 -> L8 [2]
  L4 to L9 -> L10 [0] lasti

Disassembly of <code object _build_group_chats at 0x000001EE5C72D750, file "discord_backup\backup.py", line 339>:
 339            RETURN_GENERATOR
                POP_TOP
        L1:     RESUME                   0

 340            LOAD_GLOBAL              1 (max + NULL)
                LOAD_CONST               1 (0)
                LOAD_FAST                0 (self)
                LOAD_ATTR                2 (config)
                LOAD_ATTR                4 (group_chat_msg_threshold)
                CALL                     2
                STORE_FAST               2 (threshold)

 341            LOAD_FAST                1 (channels)
                GET_ITER
                LOAD_FAST_AND_CLEAR      3 (c)
                SWAP                     2
        L2:     BUILD_LIST               0
                SWAP                     2
                GET_ITER
        L3:     FOR_ITER                27 (to L6)
                STORE_FAST_LOAD_FAST    51 (c, c)
                LOAD_ATTR                7 (get + NULL|self)
                LOAD_CONST               2 ('type')
                CALL                     1
                LOAD_CONST               3 (3)
                COMPARE_OP              88 (bool(==))
        L4:     POP_JUMP_IF_TRUE         2 (to L5)
                JUMP_BACKWARD           25 (to L3)
        L5:     LOAD_FAST                3 (c)
                LIST_APPEND              2
                JUMP_BACKWARD           29 (to L3)
        L6:     END_FOR
                POP_TOP
        L7:     STORE_FAST               4 (group_channels)
                STORE_FAST               3 (c)

 342            BUILD_LIST               0
                STORE_FAST               5 (invites)

 343            LOAD_CONST               1 (0)
                STORE_FAST               6 (success)

 344            LOAD_GLOBAL              9 (enumerate + NULL)
                LOAD_FAST                4 (group_channels)
                LOAD_CONST               4 (1)
                LOAD_CONST               5 (('start',))
                CALL_KW                  2
                GET_ITER
        L8:     EXTENDED_ARG             2
                FOR_ITER               635 (to L24)
                UNPACK_SEQUENCE          2
                STORE_FAST_STORE_FAST  120 (index, channel)

 345            LOAD_FAST                8 (channel)
                LOAD_ATTR                7 (get + NULL|self)
                LOAD_CONST               6 ('name')
                LOAD_CONST               7 ('GC-')
                LOAD_FAST                7 (index)
                FORMAT_SIMPLE
                BUILD_STRING             2
                CALL                     2
                STORE_FAST               9 (name)

 346            LOAD_FAST                0 (self)
                LOAD_ATTR               10 (console)
                LOAD_ATTR               13 (info + NULL|self)

 347            LOAD_CONST               8 ('[')
                LOAD_FAST                7 (index)
                FORMAT_SIMPLE
                LOAD_CONST               9 ('/')
                LOAD_GLOBAL             15 (len + NULL)
                LOAD_FAST                4 (group_channels)
                CALL                     1
                FORMAT_SIMPLE
                LOAD_CONST              10 ('] Processing group chat ')
                LOAD_FAST                9 (name)
                FORMAT_SIMPLE
                BUILD_STRING             6

 346            CALL                     1
                POP_TOP

 349            LOAD_FAST                8 (channel)
                LOAD_ATTR                7 (get + NULL|self)
                LOAD_CONST              11 ('last_message_id')
                CALL                     1
                STORE_FAST              10 (last_message_id)

 350            LOAD_CONST               1 (0)
                STORE_FAST              11 (age_seconds)

 351            LOAD_GLOBAL             17 (snowflake_to_timestamp + NULL)
                LOAD_FAST               10 (last_message_id)
                CALL                     1
                STORE_FAST              12 (timestamp)

 352            LOAD_FAST               12 (timestamp)
                TO_BOOL
                POP_JUMP_IF_FALSE       24 (to L9)

 353            LOAD_GLOBAL             18 (time)
                LOAD_ATTR               18 (time)
                PUSH_NULL
                CALL                     0
                LOAD_FAST               12 (timestamp)
                BINARY_OP               10 (-)
                STORE_FAST              11 (age_seconds)

 355    L9:     LOAD_FAST                2 (threshold)
                TO_BOOL
                POP_JUMP_IF_FALSE       50 (to L10)
                LOAD_FAST_LOAD_FAST    178 (age_seconds, threshold)
                COMPARE_OP             148 (bool(>))
                POP_JUMP_IF_FALSE       45 (to L10)

 356            LOAD_FAST                0 (self)
                LOAD_ATTR               10 (console)
                LOAD_ATTR               21 (warn + NULL|self)

 357            LOAD_CONST              12 ("Skipped group chat '")
                LOAD_FAST                9 (name)
                FORMAT_SIMPLE
                LOAD_CONST              13 ("' (inactive for ")
                LOAD_GLOBAL             23 (int + NULL)
                LOAD_FAST               11 (age_seconds)
                CALL                     1
                FORMAT_SIMPLE
                LOAD_CONST              14 ('s)')
                BUILD_STRING             5

 356            CALL                     1
                POP_TOP

 359            JUMP_BACKWARD          190 (to L8)

 361   L10:     LOAD_FAST                0 (self)
                LOAD_ATTR               24 (http)
                LOAD_ATTR               27 (request + NULL|self)

 362            LOAD_CONST              15 ('POST')

 363            LOAD_CONST              16 ('channels/')
                LOAD_FAST                8 (channel)
                LOAD_CONST              17 ('id')
                BINARY_SUBSCR
                FORMAT_SIMPLE
                LOAD_CONST              18 ('/invites')
                BUILD_STRING             3

 364            LOAD_FAST                0 (self)
                LOAD_ATTR               28 (token)

 365            LOAD_CONST              19 ('max_age')
                LOAD_CONST              20 (604800)
                BUILD_MAP                1

 366            LOAD_CONST              21 (True)

 367            LOAD_CONST              21 (True)

 368            LOAD_CONST              21 (True)

 369            LOAD_CONST              22 ((200,))

 361            LOAD_CONST              23 (('token', 'json_payload', 'include_debug', 'include_locale', 'super_properties', 'expected_status'))
                CALL_KW                  8
                GET_AWAITABLE            0
                LOAD_CONST               0 (None)
       L11:     SEND                     3 (to L14)
       L12:     YIELD_VALUE              1
       L13:     RESUME                   3
                JUMP_BACKWARD_NO_INTERRUPT 5 (to L11)
       L14:     END_SEND
                STORE_FAST              13 (response)

 371            LOAD_FAST               13 (response)
                LOAD_ATTR               30 (status_code)
                LOAD_CONST              24 (200)
                COMPARE_OP              88 (bool(==))
                POP_JUMP_IF_FALSE      206 (to L19)

 372            LOAD_FAST               13 (response)
                LOAD_ATTR               33 (json + NULL|self)
                CALL                     0
                LOAD_ATTR                7 (get + NULL|self)
                LOAD_CONST              25 ('code')
                CALL                     1
                STORE_FAST              14 (code)

 373            LOAD_FAST                5 (invites)
                LOAD_ATTR               35 (append + NULL|self)

 374            LOAD_GLOBAL             37 (GroupChatInvite + NULL)

 375            LOAD_GLOBAL             39 (str + NULL)
                LOAD_FAST                8 (channel)
                LOAD_ATTR                7 (get + NULL|self)
                LOAD_CONST              17 ('id')
                CALL                     1
                CALL                     1

 376            LOAD_FAST                9 (name)

 377            LOAD_FAST               14 (code)

 378            LOAD_GLOBAL             39 (str + NULL)
                LOAD_FAST                8 (channel)
                LOAD_ATTR                7 (get + NULL|self)
                LOAD_CONST              26 ('owner_id')
                CALL                     1
                CALL                     1

 379            LOAD_FAST                8 (channel)
                LOAD_ATTR                7 (get + NULL|self)
                LOAD_CONST              27 ('recipients')
                BUILD_LIST               0
                CALL                     2
                GET_ITER
                LOAD_FAST_AND_CLEAR     15 (user)
                SWAP                     2
       L15:     BUILD_LIST               0
                SWAP                     2
                GET_ITER
       L16:     FOR_ITER                29 (to L17)
                STORE_FAST              15 (user)
                LOAD_GLOBAL             39 (str + NULL)
                LOAD_FAST               15 (user)
                LOAD_ATTR                7 (get + NULL|self)
                LOAD_CONST              17 ('id')
                CALL                     1
                CALL                     1
                LIST_APPEND              2
                JUMP_BACKWARD           31 (to L16)
       L17:     END_FOR
                POP_TOP
       L18:     SWAP                     2
                STORE_FAST              15 (user)

 380            LOAD_FAST               10 (last_message_id)

 374            LOAD_CONST              28 (('channel_id', 'name', 'invite_code', 'owner_id', 'recipients', 'last_message_id'))
                CALL_KW                  6

 373            CALL                     1
                POP_TOP

 383            LOAD_FAST                6 (success)
                LOAD_CONST               4 (1)
                BINARY_OP               13 (+=)
                STORE_FAST               6 (success)

 384            LOAD_FAST                0 (self)
                LOAD_ATTR               10 (console)
                LOAD_ATTR               41 (success + NULL|self)
                LOAD_CONST              29 ('Invite created for group chat ')
                LOAD_FAST                9 (name)
                FORMAT_SIMPLE
                LOAD_CONST              30 (': ')
                LOAD_FAST               14 (code)
                FORMAT_SIMPLE
                BUILD_STRING             4
                CALL                     1
                POP_TOP
                EXTENDED_ARG             1
                JUMP_BACKWARD          471 (to L8)

 386   L19:     LOAD_FAST                5 (invites)
                LOAD_ATTR               35 (append + NULL|self)

 387            LOAD_GLOBAL             37 (GroupChatInvite + NULL)

 388            LOAD_GLOBAL             39 (str + NULL)
                LOAD_FAST                8 (channel)
                LOAD_ATTR                7 (get + NULL|self)
                LOAD_CONST              17 ('id')
                CALL                     1
                CALL                     1

 389            LOAD_FAST                9 (name)

 390            LOAD_CONST              31 ('Unable to create.')

 391            LOAD_GLOBAL             39 (str + NULL)
                LOAD_FAST                8 (channel)
                LOAD_ATTR                7 (get + NULL|self)
                LOAD_CONST              26 ('owner_id')
                CALL                     1
                CALL                     1

 392            LOAD_FAST                8 (channel)
                LOAD_ATTR                7 (get + NULL|self)
                LOAD_CONST              27 ('recipients')
                BUILD_LIST               0
                CALL                     2
                GET_ITER
                LOAD_FAST_AND_CLEAR     15 (user)
                SWAP                     2
       L20:     BUILD_LIST               0
                SWAP                     2
                GET_ITER
       L21:     FOR_ITER                29 (to L22)
                STORE_FAST              15 (user)
                LOAD_GLOBAL             39 (str + NULL)
                LOAD_FAST               15 (user)
                LOAD_ATTR                7 (get + NULL|self)
                LOAD_CONST              17 ('id')
                CALL                     1
                CALL                     1
                LIST_APPEND              2
                JUMP_BACKWARD           31 (to L21)
       L22:     END_FOR
                POP_TOP
       L23:     SWAP                     2
                STORE_FAST              15 (user)

 393            LOAD_FAST               10 (last_message_id)

 387            LOAD_CONST              28 (('channel_id', 'name', 'invite_code', 'owner_id', 'recipients', 'last_message_id'))
                CALL_KW                  6

 386            CALL                     1
                POP_TOP

 396            LOAD_FAST                0 (self)
                LOAD_ATTR               10 (console)
                LOAD_ATTR               21 (warn + NULL|self)
                LOAD_CONST              32 ('Failed to create invite for group chat ')
                LOAD_FAST                9 (name)
                FORMAT_SIMPLE
                BUILD_STRING             2
                CALL                     1
                POP_TOP
                EXTENDED_ARG             2
                JUMP_BACKWARD          638 (to L8)

 344   L24:     END_FOR
                POP_TOP

 397            LOAD_FAST_LOAD_FAST     86 (invites, success)
                BUILD_TUPLE              2
                RETURN_VALUE

  --   L25:     SWAP                     2
                POP_TOP

 341            SWAP                     2
                STORE_FAST               3 (c)
                RERAISE                  0

 361   L26:     CLEANUP_THROW
       L27:     EXTENDED_ARG             1
                JUMP_BACKWARD_NO_INTERRUPT 404 (to L14)

  --   L28:     SWAP                     2
                POP_TOP

 379            SWAP                     2
                STORE_FAST              15 (user)
                RERAISE                  0

  --   L29:     SWAP                     2
                POP_TOP

 392            SWAP                     2
                STORE_FAST              15 (user)
                RERAISE                  0

  --   L30:     CALL_INTRINSIC_1         3 (INTRINSIC_STOPITERATION_ERROR)
                RERAISE                  1
ExceptionTable:
  L1 to L2 -> L30 [0] lasti
  L2 to L4 -> L25 [2]
  L5 to L7 -> L25 [2]
  L7 to L12 -> L30 [0] lasti
  L12 to L13 -> L26 [3]
  L13 to L15 -> L30 [0] lasti
  L15 to L18 -> L28 [11]
  L18 to L20 -> L30 [0] lasti
  L20 to L23 -> L29 [11]
  L23 to L27 -> L30 [0] lasti
  L28 to L30 -> L30 [0] lasti

Disassembly of <code object _build_dm_history at 0x000001EE5C72B150, file "discord_backup\backup.py", line 399>:
 399            RESUME                   0

 400            LOAD_FAST                1 (channels)
                GET_ITER
                LOAD_FAST_AND_CLEAR      2 (c)
                SWAP                     2
        L1:     BUILD_LIST               0
                SWAP                     2
                GET_ITER
        L2:     FOR_ITER                27 (to L5)
                STORE_FAST_LOAD_FAST    34 (c, c)
                LOAD_ATTR                1 (get + NULL|self)
                LOAD_CONST               1 ('type')
                CALL                     1
                LOAD_CONST               2 (1)
                COMPARE_OP              88 (bool(==))
        L3:     POP_JUMP_IF_TRUE         2 (to L4)
                JUMP_BACKWARD           25 (to L2)
        L4:     LOAD_FAST                2 (c)
                LIST_APPEND              2
                JUMP_BACKWARD           29 (to L2)
        L5:     END_FOR
                POP_TOP
        L6:     STORE_FAST               3 (dms)
                STORE_FAST               2 (c)

 401            BUILD_LIST               0
                STORE_FAST               4 (history)

 402            LOAD_FAST                3 (dms)
                GET_ITER
        L7:     FOR_ITER               162 (to L9)
                STORE_FAST               5 (dm)

 403            LOAD_FAST                5 (dm)
                LOAD_ATTR                1 (get + NULL|self)
                LOAD_CONST               3 ('recipients')
                CALL                     1
                COPY                     1
                TO_BOOL
                POP_JUMP_IF_TRUE         3 (to L8)
                POP_TOP
                BUILD_MAP                0
                BUILD_LIST               1
        L8:     LOAD_CONST               4 (0)
                BINARY_SUBSCR
                STORE_FAST               6 (recipient)

 404            LOAD_FAST                6 (recipient)
                LOAD_ATTR                1 (get + NULL|self)
                LOAD_CONST               5 ('username')
                LOAD_CONST               6 ('unknown')
                CALL                     2
                FORMAT_SIMPLE
                LOAD_CONST               7 ('#')
                LOAD_FAST                6 (recipient)
                LOAD_ATTR                1 (get + NULL|self)
                LOAD_CONST               8 ('discriminator')
                LOAD_CONST               9 ('0000')
                CALL                     2
                FORMAT_SIMPLE
                BUILD_STRING             3
                STORE_FAST               7 (user_tag)

 405            LOAD_FAST                4 (history)
                LOAD_ATTR                3 (append + NULL|self)

 406            LOAD_GLOBAL              5 (DMHistoryEntry + NULL)

 407            LOAD_GLOBAL              7 (str + NULL)
                LOAD_FAST                6 (recipient)
                LOAD_ATTR                1 (get + NULL|self)
                LOAD_CONST              10 ('id')
                CALL                     1
                CALL                     1

 408            LOAD_FAST                7 (user_tag)

 409            LOAD_FAST                5 (dm)
                LOAD_ATTR                1 (get + NULL|self)
                LOAD_CONST              11 ('last_message_id')
                CALL                     1

 410            LOAD_GLOBAL              9 (snowflake_to_timestamp + NULL)
                LOAD_FAST                5 (dm)
                LOAD_ATTR                1 (get + NULL|self)
                LOAD_CONST              11 ('last_message_id')
                CALL                     1
                CALL                     1

 406            LOAD_CONST              12 (('user_id', 'user_tag', 'last_message_id', 'timestamp'))
                CALL_KW                  4

 405            CALL                     1
                POP_TOP
                JUMP_BACKWARD          164 (to L7)

 402    L9:     END_FOR
                POP_TOP

 413            LOAD_FAST                4 (history)
                LOAD_ATTR               11 (sort + NULL|self)
                LOAD_CONST              13 (<code object <lambda> at 0x000001EE5E78F770, file "discord_backup\backup.py", line 413>)
                MAKE_FUNCTION
                LOAD_CONST              14 (True)
                LOAD_CONST              15 (('key', 'reverse'))
                CALL_KW                  2
                POP_TOP

 414            LOAD_FAST                0 (self)
                LOAD_ATTR               12 (console)
                LOAD_ATTR               15 (success + NULL|self)
                LOAD_CONST              16 ('Collected ')
                LOAD_GLOBAL             17 (len + NULL)
                LOAD_FAST                4 (history)
                CALL                     1
                FORMAT_SIMPLE
                LOAD_CONST              17 (' DM history entries')
                BUILD_STRING             3
                CALL                     1
                POP_TOP

 415            LOAD_FAST                4 (history)
                RETURN_VALUE

  --   L10:     SWAP                     2
                POP_TOP

 400            SWAP                     2
                STORE_FAST               2 (c)
                RERAISE                  0
ExceptionTable:
  L1 to L3 -> L10 [2]
  L4 to L6 -> L10 [2]

Disassembly of <code object <lambda> at 0x000001EE5E78F770, file "discord_backup\backup.py", line 413>:
413           RESUME                   0
              LOAD_GLOBAL              1 (int + NULL)
              LOAD_FAST                0 (entry)
              LOAD_ATTR                2 (last_message_id)
              COPY                     1
              TO_BOOL
              POP_JUMP_IF_TRUE         2 (to L1)
              POP_TOP
              LOAD_CONST               1 (0)
      L1:     CALL                     1
              RETURN_VALUE
