# Reconstructed from: C:\Users\koufa\Desktop\Apps\discord backup\Unpack\DiscordBackup.exe_extracted\PYZ.pyz_extracted\discord_backup\cli.pyc
# Code object: <module>, filename: discord_backup\cli.py

# const[0]: 0# const[2]: None# const[6]: 1# const[15]: False# const[16]: 'Modern Discord backup & restore toolkit.'# const[18]: True# nested code: _load_config_and_console (filename: discord_backup\cli.py)  # const[0]: None  # names: ('AppConfig', 'load', 'Console', 'colour')  # varnames: ('config', 'console')# nested code: _select_token (filename: discord_backup\cli.py)  # const[0]: None  # const[1]: 'No tokens discovered on this system.'  # const[2]: 'Discovered tokens:'  # const[7]: 2  # const[9]: 'Select token index'  # const[12]: 'Selected '  # const[13]: 'Invalid selection'  # names: ('discover_tokens', 'warn', 'info', 'enumerate', 'user_tag', 'source', 'typer', 'prompt', 'int', 'success', 'ValueError', 'IndexError', 'error')  # varnames: ('http', 'console', 'tokens', 'idx', 'info', 'choice', 'selected')# nested code: _run_backup (filename: discord_backup\cli.py)  # const[0]: None  # const[1]: 'Token is required to run a backup.'  # const[3]: 'Backup stored at '  # const[4]: 'Guilds: {success}/{total}'  # const[5]: 'guilds'  # const[6]: 2  # const[8]: 'Group chats: {success}/{total}'  # const[9]: 'group_chats'  # const[10]: 'Duration: '  # const[11]: '.1f'  # names: ('DiscordHTTPClient', 'create', '_select_token', 'aclose', 'token', 'error', 'BackupService', 'run', 'save', 'info', 'summary', 'format', 'duration')  # varnames: ('token', 'config', 'console', 'scan', 'http', 'token_value', 'selection', 'service', 'result', 'path', 'summary')# const[23]: 'Discord user token'# const[25]: '--scan'# const[26]: 'Auto-discover tokens on this machine'# nested code: backup (filename: discord_backup\cli.py)  # const[0]: 'Create a new backup interactively.'  # const[1]: 1  # const[3]: None  # names: ('_load_config_and_console', 'asyncio', 'run', '_run_backup', 'BackupError', 'error', 'str', 'typer', 'Exit')  # varnames: ('token', 'scan', 'config', 'console', 'exc')# nested code: _run_restore (filename: discord_backup\cli.py)  # const[0]: None  # const[1]: 'Backup file not found: '  # const[2]: 'utf-8'  # const[5]: 'version'  # const[7]: 'Restore complete'  # const[8]: 'Backup guild id: '  # const[9]: 'Favourite GIFs: '  # const[10]: 'Folders restored'  # const[11]: 'Folders skipped'  # const[12]: 2  # const[14]: 'Duration: '  # const[15]: '.1f'  # names: ('exists', 'error', 'json', 'loads', 'read_text', 'DiscordHTTPClient', 'create', 'RestoreService', 'run', 'get', 'success', 'info', 'guild_id', 'favourite_gifs_status', 'folder_restore_attempted', 'duration', 'aclose')  # varnames: ('backup_path', 'token', 'bot_token', 'restore_folders', 'allow_version_mismatch', 'console', 'data', 'http', 'service', 'summary')# const[30]: 'Path to .bkup file'# const[33]: 'Bot token for user lookups'# const[34]: 'Restore guild folders'# const[35]: 'Ignore backup version mismatches'# nested code: restore (filename: discord_backup\cli.py)  # const[0]: 'Restore from a backup file.'  # const[1]: 1  # const[3]: None  # names: ('_load_config_and_console', 'asyncio', 'run', '_run_restore', 'RestoreError', 'error', 'str', 'typer', 'Exit')  # varnames: ('backup_file', 'token', 'bot_token', 'restore_folders', 'allow_version_mismatch', '_', 'console', 'exc')# const[37]: 'Discord account ID to auto-backup'# const[38]: 'Working directory containing config.yml'# nested code: auto_backup (filename: discord_backup\cli.py)  # const[0]: 'Internal helper used by the startup script.'  # const[1]: 0  # const[2]: None  # const[3]: 'Working directory not found: '  # nested code: runner (filename: discord_backup\cli.py)    # const[0]: None    # const[1]: 'Found token for '    # const[2]: 'No matching token found for auto-backup'    # const[4]: 'Auto-backup finished'    # names: ('DiscordHTTPClient', 'create', 'discover_tokens', 'user_id', 'token', 'success', 'user_tag', 'error', 'aclose', 'BackupService', 'run', 'save')    # varnames: ('http', 'tokens', 'token_value', 'item', 'service', 'result')  # names: ('_load_config_and_console', 'resolve', 'exists', 'os', 'chdir', 'warn', 'asyncio', 'run')  # varnames: ('account_id', 'working_dir', 'os', 'runner')# const[40]: 'Scan for tokens to choose from'# nested code: startup_add (filename: discord_backup\cli.py)  # const[0]: 'Add the current executable/script to Windows startup for auto-backup.'  # nested code: runner (filename: discord_backup\cli.py)    # const[0]: None    # const[1]: 'Enter user token for auto-backup'    # const[2]: True    # const[4]: 'Token required for auto-backup'    # const[5]: 'manual'    # const[6]: 'Enter account id'    # const[8]: 'frozen'    # const[9]: False    # const[10]: 'main.py'    # const[11]: '.py'    # const[12]: 'cmd.exe /C python "'    # const[13]: '" auto-backup --account-id '    # const[15]: 'Startup script written to '    # names: ('DiscordHTTPClient', 'create', '_select_token', 'typer', 'prompt', 'error', 'aclose', 'DiscoveredToken', 'Path', 'getattr', 'sys', 'executable', '__file__', 'resolve', 'parent', 'suffix', 'user_id', 'write_startup_script', 'cwd', 'success')    # varnames: ('http', 'selection', 'token_input', 'executable', 'command', 'script_path')  # const[2]: None  # names: ('_load_config_and_console', 'asyncio', 'run')  # varnames: ('scan', 'config', 'runner')# nested code: startup_remove (filename: discord_backup\cli.py)  # const[0]: 'Remove the auto-backup startup script if present.'  # const[1]: 'Startup script removed'  # const[2]: 'No startup script found'  # const[3]: None  # names: ('remove_startup_script', 'typer', 'echo')# nested code: tokens (filename: discord_backup\cli.py)  # const[0]: 'List tokens discovered on this machine.'  # nested code: runner (filename: discord_backup\cli.py)    # const[0]: None    # const[1]: 'No tokens discovered'    # const[3]: ') - '    # names: ('DiscordHTTPClient', 'create', 'discover_tokens', 'warn', 'aclose', 'info', 'user_tag', 'user_id', 'source')    # varnames: ('http', 'tokens', 'item')  # const[2]: None  # names: ('_load_config_and_console', 'asyncio', 'run')  # varnames: ('_', 'runner')# nested code: run (filename: discord_backup\cli.py)  # const[0]: None  # names: ('app',)# const[45]: 'app'# const[46]: 'run'# names: ('__future__', 'annotations', 'asyncio', 'json', 'sys', 'pathlib', 'Path', 'typing', 'Optional', 'typer', 'colorama', 'init', 'colorama_init', 'backup', 'BackupError', 'BackupService', 'config', 'AppConfig', 'console', 'Console', 'http_client', 'DiscordHTTPClient', 'restore', 'RestoreError', 'RestoreService', 'results', 'BackupResult', 'startup', 'remove_startup_script', 'write_startup_script', 'token_discovery', 'DiscoveredToken', 'discover_tokens', 'Typer', 'app', '_load_config_and_console', '_select_token', '_run_backup', 'command', 'Option', '_run_restore', 'Argument', 'cwd', 'auto_backup', 'startup_add', 'startup_remove', 'tokens', 'run', '__all__')

# --- Disassembly ---

  0           RESUME                   0

  1           LOAD_CONST               0 (0)
              LOAD_CONST               1 (('annotations',))
              IMPORT_NAME              0 (__future__)
              IMPORT_FROM              1 (annotations)
              STORE_NAME               1 (annotations)
              POP_TOP

  3           LOAD_CONST               0 (0)
              LOAD_CONST               2 (None)
              IMPORT_NAME              2 (asyncio)
              STORE_NAME               2 (asyncio)

  4           LOAD_CONST               0 (0)
              LOAD_CONST               2 (None)
              IMPORT_NAME              3 (json)
              STORE_NAME               3 (json)

  5           LOAD_CONST               0 (0)
              LOAD_CONST               2 (None)
              IMPORT_NAME              4 (sys)
              STORE_NAME               4 (sys)

  6           LOAD_CONST               0 (0)
              LOAD_CONST               3 (('Path',))
              IMPORT_NAME              5 (pathlib)
              IMPORT_FROM              6 (Path)
              STORE_NAME               6 (Path)
              POP_TOP

  7           LOAD_CONST               0 (0)
              LOAD_CONST               4 (('Optional',))
              IMPORT_NAME              7 (typing)
              IMPORT_FROM              8 (Optional)
              STORE_NAME               8 (Optional)
              POP_TOP

  9           LOAD_CONST               0 (0)
              LOAD_CONST               2 (None)
              IMPORT_NAME              9 (typer)
              STORE_NAME               9 (typer)

 10           LOAD_CONST               0 (0)
              LOAD_CONST               5 (('init',))
              IMPORT_NAME             10 (colorama)
              IMPORT_FROM             11 (init)
              STORE_NAME              12 (colorama_init)
              POP_TOP

 12           LOAD_CONST               6 (1)
              LOAD_CONST               7 (('BackupError', 'BackupService'))
              IMPORT_NAME             13 (backup)
              IMPORT_FROM             14 (BackupError)
              STORE_NAME              14 (BackupError)
              IMPORT_FROM             15 (BackupService)
              STORE_NAME              15 (BackupService)
              POP_TOP

 13           LOAD_CONST               6 (1)
              LOAD_CONST               8 (('AppConfig',))
              IMPORT_NAME             16 (config)
              IMPORT_FROM             17 (AppConfig)
              STORE_NAME              17 (AppConfig)
              POP_TOP

 14           LOAD_CONST               6 (1)
              LOAD_CONST               9 (('Console',))
              IMPORT_NAME             18 (console)
              IMPORT_FROM             19 (Console)
              STORE_NAME              19 (Console)
              POP_TOP

 15           LOAD_CONST               6 (1)
              LOAD_CONST              10 (('DiscordHTTPClient',))
              IMPORT_NAME             20 (http_client)
              IMPORT_FROM             21 (DiscordHTTPClient)
              STORE_NAME              21 (DiscordHTTPClient)
              POP_TOP

 16           LOAD_CONST               6 (1)
              LOAD_CONST              11 (('RestoreError', 'RestoreService'))
              IMPORT_NAME             22 (restore)
              IMPORT_FROM             23 (RestoreError)
              STORE_NAME              23 (RestoreError)
              IMPORT_FROM             24 (RestoreService)
              STORE_NAME              24 (RestoreService)
              POP_TOP

 17           LOAD_CONST               6 (1)
              LOAD_CONST              12 (('BackupResult',))
              IMPORT_NAME             25 (results)
              IMPORT_FROM             26 (BackupResult)
              STORE_NAME              26 (BackupResult)
              POP_TOP

 18           LOAD_CONST               6 (1)
              LOAD_CONST              13 (('remove_startup_script', 'write_startup_script'))
              IMPORT_NAME             27 (startup)
              IMPORT_FROM             28 (remove_startup_script)
              STORE_NAME              28 (remove_startup_script)
              IMPORT_FROM             29 (write_startup_script)
              STORE_NAME              29 (write_startup_script)
              POP_TOP

 19           LOAD_CONST               6 (1)
              LOAD_CONST              14 (('DiscoveredToken', 'discover_tokens'))
              IMPORT_NAME             30 (token_discovery)
              IMPORT_FROM             31 (DiscoveredToken)
              STORE_NAME              31 (DiscoveredToken)
              IMPORT_FROM             32 (discover_tokens)
              STORE_NAME              32 (discover_tokens)
              POP_TOP

 21           LOAD_NAME                9 (typer)
              LOAD_ATTR               66 (Typer)
              PUSH_NULL
              LOAD_CONST              15 (False)
              LOAD_CONST              16 ('Modern Discord backup & restore toolkit.')
              LOAD_CONST              17 (('add_completion', 'help'))
              CALL_KW                  2
              STORE_NAME              34 (app)

 22           LOAD_NAME               12 (colorama_init)
              PUSH_NULL
              LOAD_CONST              18 (True)
              LOAD_CONST              19 (('autoreset',))
              CALL_KW                  1
              POP_TOP

 25           LOAD_CONST              47 (('return', 'tuple[AppConfig, Console]'))
              LOAD_CONST              20 (<code object _load_config_and_console at 0x000001EE5E4F6430, file "discord_backup\cli.py", line 25>)
              MAKE_FUNCTION
              SET_FUNCTION_ATTRIBUTE   4 (annotations)
              STORE_NAME              35 (_load_config_and_console)

 31           LOAD_CONST              48 (('http', 'DiscordHTTPClient', 'console', 'Console', 'return', 'Optional[DiscoveredToken]'))
              LOAD_CONST              21 (<code object _select_token at 0x000001EE5E621580, file "discord_backup\cli.py", line 31>)
              MAKE_FUNCTION
              SET_FUNCTION_ATTRIBUTE   4 (annotations)
              STORE_NAME              36 (_select_token)

 49           LOAD_CONST              49 (('token', 'str | None', 'config', 'AppConfig', 'console', 'Console', 'scan', 'bool', 'return', 'BackupResult | None'))
              LOAD_CONST              22 (<code object _run_backup at 0x000001EE5C7287E0, file "discord_backup\cli.py", line 49>)
              MAKE_FUNCTION
              SET_FUNCTION_ATTRIBUTE   4 (annotations)
              STORE_NAME              37 (_run_backup)

 81           LOAD_NAME               34 (app)
              LOAD_ATTR               77 (command + NULL|self)
              CALL                     0

 83           LOAD_NAME                9 (typer)
              LOAD_ATTR               78 (Option)
              PUSH_NULL
              LOAD_CONST               2 (None)
              LOAD_CONST              23 ('Discord user token')
              LOAD_CONST              24 (('help',))
              CALL_KW                  2

 84           LOAD_NAME                9 (typer)
              LOAD_ATTR               78 (Option)
              PUSH_NULL
              LOAD_CONST              15 (False)
              LOAD_CONST              25 ('--scan')
              LOAD_CONST              26 ('Auto-discover tokens on this machine')
              LOAD_CONST              24 (('help',))
              CALL_KW                  3

 82           BUILD_TUPLE              2

 83           NOP

 82           NOP

 84           NOP

 82           NOP

 85           NOP

 82           LOAD_CONST              50 (('token', 'str | None', 'scan', 'bool', 'return', 'None'))
              LOAD_CONST              27 (<code object backup at 0x000001EE5C63FB40, file "discord_backup\cli.py", line 81>)
              MAKE_FUNCTION
              SET_FUNCTION_ATTRIBUTE   4 (annotations)
              SET_FUNCTION_ATTRIBUTE   1 (defaults)

 81           CALL                     0

 82           STORE_NAME              13 (backup)

 95           NOP

 96           NOP

 95           NOP

 97           NOP

 95           NOP

 98           NOP

 95           NOP

 99           NOP

 95           NOP

100           NOP

 95           NOP

101           NOP

 95           NOP

102           NOP

 95           LOAD_CONST              51 (('backup_path', 'Path', 'token', 'str', 'bot_token', 'str', 'restore_folders', 'bool', 'allow_version_mismatch', 'bool', 'console', 'Console', 'return', 'None'))
              LOAD_CONST              28 (<code object _run_restore at 0x000001EE5C728C20, file "discord_backup\cli.py", line 95>)
              MAKE_FUNCTION
              SET_FUNCTION_ATTRIBUTE   4 (annotations)
              STORE_NAME              40 (_run_restore)

127           LOAD_NAME               34 (app)
              LOAD_ATTR               77 (command + NULL|self)
              CALL                     0

129           LOAD_NAME                9 (typer)
              LOAD_ATTR               82 (Argument)
              PUSH_NULL
              LOAD_CONST              29 (Ellipsis)
              LOAD_CONST              18 (True)
              LOAD_CONST              18 (True)
              LOAD_CONST              30 ('Path to .bkup file')
              LOAD_CONST              31 (('exists', 'readable', 'help'))
              CALL_KW                  4

130           LOAD_NAME                9 (typer)
              LOAD_ATTR               78 (Option)
              PUSH_NULL
              LOAD_CONST              29 (Ellipsis)
              LOAD_CONST              18 (True)
              LOAD_CONST              18 (True)
              LOAD_CONST              23 ('Discord user token')
              LOAD_CONST              32 (('prompt', 'hide_input', 'help'))
              CALL_KW                  4

131           LOAD_NAME                9 (typer)
              LOAD_ATTR               78 (Option)
              PUSH_NULL
              LOAD_CONST              29 (Ellipsis)
              LOAD_CONST              18 (True)
              LOAD_CONST              18 (True)
              LOAD_CONST              33 ('Bot token for user lookups')
              LOAD_CONST              32 (('prompt', 'hide_input', 'help'))
              CALL_KW                  4

132           LOAD_NAME                9 (typer)
              LOAD_ATTR               78 (Option)
              PUSH_NULL
              LOAD_CONST              18 (True)
              LOAD_CONST              34 ('Restore guild folders')
              LOAD_CONST              24 (('help',))
              CALL_KW                  2

133           LOAD_NAME                9 (typer)
              LOAD_ATTR               78 (Option)
              PUSH_NULL
              LOAD_CONST              15 (False)
              LOAD_CONST              35 ('Ignore backup version mismatches')
              LOAD_CONST              24 (('help',))
              CALL_KW                  2

128           BUILD_TUPLE              5

129           NOP

128           NOP

130           NOP

128           NOP

131           NOP

128           NOP

132           NOP

128           NOP

133           NOP

128           NOP

134           NOP

128           LOAD_CONST              52 (('backup_file', 'Path', 'token', 'str', 'bot_token', 'str', 'restore_folders', 'bool', 'allow_version_mismatch', 'bool', 'return', 'None'))
              LOAD_CONST              36 (<code object restore at 0x000001EE5E89C030, file "discord_backup\cli.py", line 127>)
              MAKE_FUNCTION
              SET_FUNCTION_ATTRIBUTE   4 (annotations)
              SET_FUNCTION_ATTRIBUTE   1 (defaults)

127           CALL                     0

128           STORE_NAME              22 (restore)

153           LOAD_NAME               34 (app)
              LOAD_ATTR               77 (command + NULL|self)
              CALL                     0

155           LOAD_NAME                9 (typer)
              LOAD_ATTR               78 (Option)
              PUSH_NULL
              LOAD_CONST              29 (Ellipsis)
              LOAD_CONST              37 ('Discord account ID to auto-backup')
              LOAD_CONST              24 (('help',))
              CALL_KW                  2

156           LOAD_NAME                9 (typer)
              LOAD_ATTR               78 (Option)
              PUSH_NULL
              LOAD_NAME                6 (Path)
              LOAD_ATTR               84 (cwd)
              PUSH_NULL
              CALL                     0
              LOAD_CONST              38 ('Working directory containing config.yml')
              LOAD_CONST              24 (('help',))
              CALL_KW                  2

154           BUILD_TUPLE              2

155           NOP

154           NOP

156           NOP

154           NOP

157           NOP

154           LOAD_CONST              53 (('account_id', 'str', 'working_dir', 'Path', 'return', 'None'))
              LOAD_CONST              39 (<code object auto_backup at 0x000001EE5C61BA50, file "discord_backup\cli.py", line 153>)
              MAKE_FUNCTION
              SET_FUNCTION_ATTRIBUTE   4 (annotations)
              SET_FUNCTION_ATTRIBUTE   1 (defaults)

153           CALL                     0

154           STORE_NAME              43 (auto_backup)

189           LOAD_NAME               34 (app)
              LOAD_ATTR               77 (command + NULL|self)
              CALL                     0

191           LOAD_NAME                9 (typer)
              LOAD_ATTR               78 (Option)
              PUSH_NULL
              LOAD_CONST              18 (True)
              LOAD_CONST              40 ('Scan for tokens to choose from')
              LOAD_CONST              24 (('help',))
              CALL_KW                  2

190           BUILD_TUPLE              1

191           NOP

190           NOP

192           NOP

190           LOAD_CONST              54 (('scan', 'bool', 'return', 'None'))
              LOAD_CONST              41 (<code object startup_add at 0x000001EE5E7F5430, file "discord_backup\cli.py", line 189>)
              MAKE_FUNCTION
              SET_FUNCTION_ATTRIBUTE   4 (annotations)
              SET_FUNCTION_ATTRIBUTE   1 (defaults)

189           CALL                     0

190           STORE_NAME              44 (startup_add)

222           LOAD_NAME               34 (app)
              LOAD_ATTR               77 (command + NULL|self)
              CALL                     0

223           LOAD_CONST              55 (('return', 'None'))
              LOAD_CONST              42 (<code object startup_remove at 0x000001EE5E577DE0, file "discord_backup\cli.py", line 222>)
              MAKE_FUNCTION
              SET_FUNCTION_ATTRIBUTE   4 (annotations)

222           CALL                     0

223           STORE_NAME              45 (startup_remove)

231           LOAD_NAME               34 (app)
              LOAD_ATTR               77 (command + NULL|self)
              CALL                     0

232           LOAD_CONST              55 (('return', 'None'))
              LOAD_CONST              43 (<code object tokens at 0x000001EE5E8844F0, file "discord_backup\cli.py", line 231>)
              MAKE_FUNCTION
              SET_FUNCTION_ATTRIBUTE   4 (annotations)

231           CALL                     0

232           STORE_NAME              46 (tokens)

251           LOAD_CONST              55 (('return', 'None'))
              LOAD_CONST              44 (<code object run at 0x000001EE5E820D50, file "discord_backup\cli.py", line 251>)
              MAKE_FUNCTION
              SET_FUNCTION_ATTRIBUTE   4 (annotations)
              STORE_NAME              47 (run)

255           LOAD_CONST              45 ('app')
              LOAD_CONST              46 ('run')
              BUILD_LIST               2
              STORE_NAME              48 (__all__)
              RETURN_CONST             2 (None)

Disassembly of <code object _load_config_and_console at 0x000001EE5E4F6430, file "discord_backup\cli.py", line 25>:
 25           RESUME                   0

 26           LOAD_GLOBAL              0 (AppConfig)
              LOAD_ATTR                2 (load)
              PUSH_NULL
              CALL                     0
              STORE_FAST               0 (config)

 27           LOAD_GLOBAL              5 (Console + NULL)
              LOAD_FAST                0 (config)
              LOAD_ATTR                6 (colour)
              LOAD_CONST               1 (('accent',))
              CALL_KW                  1
              STORE_FAST               1 (console)

 28           LOAD_FAST_LOAD_FAST      1 (config, console)
              BUILD_TUPLE              2
              RETURN_VALUE

Disassembly of <code object _select_token at 0x000001EE5E621580, file "discord_backup\cli.py", line 31>:
  31            RETURN_GENERATOR
                POP_TOP
        L1:     RESUME                   0

  32            LOAD_GLOBAL              1 (discover_tokens + NULL)
                LOAD_FAST                0 (http)
                CALL                     1
                GET_AWAITABLE            0
                LOAD_CONST               0 (None)
        L2:     SEND                     3 (to L5)
        L3:     YIELD_VALUE              1
        L4:     RESUME                   3
                JUMP_BACKWARD_NO_INTERRUPT 5 (to L2)
        L5:     END_SEND
                STORE_FAST               2 (tokens)

  33            LOAD_FAST                2 (tokens)
                TO_BOOL
                POP_JUMP_IF_TRUE        18 (to L6)

  34            LOAD_FAST                1 (console)
                LOAD_ATTR                3 (warn + NULL|self)
                LOAD_CONST               1 ('No tokens discovered on this system.')
                CALL                     1
                POP_TOP

  35            RETURN_CONST             0 (None)

  36    L6:     LOAD_FAST                1 (console)
                LOAD_ATTR                5 (info + NULL|self)
                LOAD_CONST               2 ('Discovered tokens:')
                CALL                     1
                POP_TOP

  37            LOAD_GLOBAL              7 (enumerate + NULL)
                LOAD_FAST                2 (tokens)
                CALL                     1
                GET_ITER
        L7:     FOR_ITER                51 (to L8)
                UNPACK_SEQUENCE          2
                STORE_FAST_STORE_FAST   52 (idx, info)

  38            LOAD_FAST                1 (console)
                LOAD_ATTR                5 (info + NULL|self)
                LOAD_CONST               3 ('[')
                LOAD_FAST                3 (idx)
                FORMAT_SIMPLE
                LOAD_CONST               4 ('] ')
                LOAD_FAST                4 (info)
                LOAD_ATTR                8 (user_tag)
                FORMAT_SIMPLE
                LOAD_CONST               5 (' (')
                LOAD_FAST                4 (info)
                LOAD_ATTR               10 (source)
                FORMAT_SIMPLE
                LOAD_CONST               6 (')')
                BUILD_STRING             7
                LOAD_CONST               7 (2)
                LOAD_CONST               8 (('indent',))
                CALL_KW                  2
                POP_TOP
                JUMP_BACKWARD           53 (to L7)

  37    L8:     END_FOR
                POP_TOP

  39            LOAD_GLOBAL             12 (typer)
                LOAD_ATTR               14 (prompt)
                PUSH_NULL
                LOAD_CONST               9 ('Select token index')
                LOAD_CONST              10 ('0')
                LOAD_CONST              11 (('default',))
                CALL_KW                  2
                STORE_FAST               5 (choice)

  40    L9:     NOP

  41   L10:     LOAD_FAST                2 (tokens)
                LOAD_GLOBAL             17 (int + NULL)
                LOAD_FAST                5 (choice)
                CALL                     1
                BINARY_SUBSCR
                STORE_FAST               6 (selected)

  42            LOAD_FAST                1 (console)
                LOAD_ATTR               19 (success + NULL|self)
                LOAD_CONST              12 ('Selected ')
                LOAD_FAST                6 (selected)
                LOAD_ATTR                8 (user_tag)
                FORMAT_SIMPLE
                BUILD_STRING             2
                CALL                     1
                POP_TOP

  43            LOAD_FAST                6 (selected)
       L11:     RETURN_VALUE

  32   L12:     CLEANUP_THROW
       L13:     JUMP_BACKWARD_NO_INTERRUPT 180 (to L5)

  --   L14:     PUSH_EXC_INFO

  44            LOAD_GLOBAL             20 (ValueError)
                LOAD_GLOBAL             22 (IndexError)
                BUILD_TUPLE              2
                CHECK_EXC_MATCH
                POP_JUMP_IF_FALSE       20 (to L16)
                POP_TOP

  45            LOAD_FAST                1 (console)
                LOAD_ATTR               25 (error + NULL|self)
                LOAD_CONST              13 ('Invalid selection')
                CALL                     1
                POP_TOP

  46   L15:     POP_EXCEPT
                RETURN_CONST             0 (None)

  44   L16:     RERAISE                  0

  --   L17:     COPY                     3
                POP_EXCEPT
                RERAISE                  1
       L18:     CALL_INTRINSIC_1         3 (INTRINSIC_STOPITERATION_ERROR)
                RERAISE                  1
ExceptionTable:
  L1 to L3 -> L18 [0] lasti
  L3 to L4 -> L12 [2]
  L4 to L9 -> L18 [0] lasti
  L10 to L11 -> L14 [0]
  L11 to L13 -> L18 [0] lasti
  L14 to L15 -> L17 [1] lasti
  L15 to L16 -> L18 [0] lasti
  L16 to L17 -> L17 [1] lasti
  L17 to L18 -> L18 [0] lasti

Disassembly of <code object _run_backup at 0x000001EE5C7287E0, file "discord_backup\cli.py", line 49>:
  49            RETURN_GENERATOR
                POP_TOP
        L1:     RESUME                   0

  50            LOAD_GLOBAL              0 (DiscordHTTPClient)
                LOAD_ATTR                2 (create)
                PUSH_NULL
                CALL                     0
                GET_AWAITABLE            0
                LOAD_CONST               0 (None)
        L2:     SEND                     3 (to L5)
        L3:     YIELD_VALUE              1
        L4:     RESUME                   3
                JUMP_BACKWARD_NO_INTERRUPT 5 (to L2)
        L5:     END_SEND
                STORE_FAST               4 (http)

  51    L6:     NOP

  52    L7:     LOAD_FAST                0 (token)
                STORE_FAST               5 (token_value)

  53            LOAD_FAST                3 (scan)
                TO_BOOL
                POP_JUMP_IF_TRUE         7 (to L8)
                LOAD_FAST                5 (token_value)
                TO_BOOL
                POP_JUMP_IF_TRUE        64 (to L20)

  54    L8:     LOAD_GLOBAL              5 (_select_token + NULL)
                LOAD_FAST_LOAD_FAST     66 (http, console)
                CALL                     2
                GET_AWAITABLE            0
                LOAD_CONST               0 (None)
        L9:     SEND                     3 (to L12)
       L10:     YIELD_VALUE              1
       L11:     RESUME                   3
                JUMP_BACKWARD_NO_INTERRUPT 5 (to L9)
       L12:     END_SEND
                STORE_FAST               6 (selection)

  55            LOAD_FAST                6 (selection)
                TO_BOOL
                POP_JUMP_IF_TRUE        26 (to L19)

  56   L13:     NOP

  78   L14:     LOAD_FAST                4 (http)
                LOAD_ATTR                7 (aclose + NULL|self)
                CALL                     0
                GET_AWAITABLE            0
                LOAD_CONST               0 (None)
       L15:     SEND                     3 (to L18)
       L16:     YIELD_VALUE              1
       L17:     RESUME                   3
                JUMP_BACKWARD_NO_INTERRUPT 5 (to L15)
       L18:     END_SEND
                POP_TOP
                RETURN_CONST             0 (None)

  57   L19:     LOAD_FAST                6 (selection)
                LOAD_ATTR                8 (token)
                STORE_FAST               5 (token_value)

  58   L20:     LOAD_FAST                5 (token_value)
                TO_BOOL
                POP_JUMP_IF_TRUE        43 (to L27)

  59            LOAD_FAST                2 (console)
                LOAD_ATTR               11 (error + NULL|self)
                LOAD_CONST               1 ('Token is required to run a backup.')
                CALL                     1
                POP_TOP

  60   L21:     NOP

  78   L22:     LOAD_FAST                4 (http)
                LOAD_ATTR                7 (aclose + NULL|self)
                CALL                     0
                GET_AWAITABLE            0
                LOAD_CONST               0 (None)
       L23:     SEND                     3 (to L26)
       L24:     YIELD_VALUE              1
       L25:     RESUME                   3
                JUMP_BACKWARD_NO_INTERRUPT 5 (to L23)
       L26:     END_SEND
                POP_TOP
                RETURN_CONST             0 (None)

  62   L27:     LOAD_GLOBAL             13 (BackupService + NULL)
                LOAD_FAST_LOAD_FAST     69 (http, token_value)
                LOAD_FAST_LOAD_FAST     18 (config, console)
                LOAD_CONST               2 (('http', 'token', 'config', 'console'))
                CALL_KW                  4
                STORE_FAST               7 (service)

  63            LOAD_FAST                7 (service)
                LOAD_ATTR               15 (run + NULL|self)
                CALL                     0
                GET_AWAITABLE            0
                LOAD_CONST               0 (None)
       L28:     SEND                     3 (to L31)
       L29:     YIELD_VALUE              1
       L30:     RESUME                   3
                JUMP_BACKWARD_NO_INTERRUPT 5 (to L28)
       L31:     END_SEND
                STORE_FAST               8 (result)

  64            LOAD_FAST                7 (service)
                LOAD_ATTR               17 (save + NULL|self)
                LOAD_FAST                8 (result)
                CALL                     1
                GET_AWAITABLE            0
                LOAD_CONST               0 (None)
       L32:     SEND                     3 (to L35)
       L33:     YIELD_VALUE              1
       L34:     RESUME                   3
                JUMP_BACKWARD_NO_INTERRUPT 5 (to L32)
       L35:     END_SEND
                STORE_FAST               9 (path)

  65            LOAD_FAST                2 (console)
                LOAD_ATTR               19 (info + NULL|self)
                LOAD_CONST               3 ('Backup stored at ')
                LOAD_FAST                9 (path)
                FORMAT_SIMPLE
                BUILD_STRING             2
                CALL                     1
                POP_TOP

  66            LOAD_FAST                8 (result)
                LOAD_ATTR               21 (summary + NULL|self)
                CALL                     0
                STORE_FAST              10 (summary)

  67            LOAD_FAST                2 (console)
                LOAD_ATTR               19 (info + NULL|self)

  68            LOAD_CONST               4 ('Guilds: {success}/{total}')
                LOAD_ATTR               22 (format)
                PUSH_NULL
                LOAD_CONST              13 (())
                BUILD_MAP                0
                LOAD_FAST               10 (summary)
                LOAD_CONST               5 ('guilds')
                BINARY_SUBSCR
                DICT_MERGE               1
                CALL_FUNCTION_EX         1

  69            LOAD_CONST               6 (2)

  67            LOAD_CONST               7 (('indent',))
                CALL_KW                  2
                POP_TOP

  71            LOAD_FAST                2 (console)
                LOAD_ATTR               19 (info + NULL|self)

  72            LOAD_CONST               8 ('Group chats: {success}/{total}')
                LOAD_ATTR               22 (format)
                PUSH_NULL
                LOAD_CONST              13 (())
                BUILD_MAP                0
                LOAD_FAST               10 (summary)
                LOAD_CONST               9 ('group_chats')
                BINARY_SUBSCR
                DICT_MERGE               1
                CALL_FUNCTION_EX         1

  73            LOAD_CONST               6 (2)

  71            LOAD_CONST               7 (('indent',))
                CALL_KW                  2
                POP_TOP

  75            LOAD_FAST                2 (console)
                LOAD_ATTR               19 (info + NULL|self)
                LOAD_CONST              10 ('Duration: ')
                LOAD_FAST                8 (result)
                LOAD_ATTR               24 (duration)
                LOAD_CONST              11 ('.1f')
                FORMAT_WITH_SPEC
                LOAD_CONST              12 ('s')
                BUILD_STRING             3
                LOAD_CONST               6 (2)
                LOAD_CONST               7 (('indent',))
                CALL_KW                  2
                POP_TOP

  76            LOAD_FAST                8 (result)

  78   L36:     LOAD_FAST                4 (http)
                LOAD_ATTR                7 (aclose + NULL|self)
                CALL                     0
                GET_AWAITABLE            0
                LOAD_CONST               0 (None)
       L37:     SEND                     3 (to L40)
       L38:     YIELD_VALUE              1
       L39:     RESUME                   3
                JUMP_BACKWARD_NO_INTERRUPT 5 (to L37)
       L40:     END_SEND
                POP_TOP
                RETURN_VALUE

  50   L41:     CLEANUP_THROW
       L42:     EXTENDED_ARG             1
                JUMP_BACKWARD_NO_INTERRUPT 358 (to L5)

  54   L43:     CLEANUP_THROW
       L44:     EXTENDED_ARG             1
                JUMP_BACKWARD_NO_INTERRUPT 325 (to L12)

  78   L45:     CLEANUP_THROW
       L46:     EXTENDED_ARG             1
                JUMP_BACKWARD_NO_INTERRUPT 296 (to L18)
       L47:     CLEANUP_THROW
       L48:     JUMP_BACKWARD_NO_INTERRUPT 236 (to L26)

  63   L49:     CLEANUP_THROW
       L50:     JUMP_BACKWARD_NO_INTERRUPT 203 (to L31)

  64   L51:     CLEANUP_THROW
       L52:     JUMP_BACKWARD_NO_INTERRUPT 180 (to L35)

  78   L53:     CLEANUP_THROW
       L54:     JUMP_BACKWARD_NO_INTERRUPT 20 (to L40)

  --   L55:     PUSH_EXC_INFO

  78            LOAD_FAST                4 (http)
                LOAD_ATTR                7 (aclose + NULL|self)
                CALL                     0
                GET_AWAITABLE            0
                LOAD_CONST               0 (None)
       L56:     SEND                     4 (to L60)
       L57:     YIELD_VALUE              1
       L58:     RESUME                   3
                JUMP_BACKWARD_NO_INTERRUPT 5 (to L56)
       L59:     CLEANUP_THROW
       L60:     END_SEND
                POP_TOP
                RERAISE                  0

  --   L61:     COPY                     3
                POP_EXCEPT
                RERAISE                  1
       L62:     CALL_INTRINSIC_1         3 (INTRINSIC_STOPITERATION_ERROR)
                RERAISE                  1
ExceptionTable:
  L1 to L3 -> L62 [0] lasti
  L3 to L4 -> L41 [2]
  L4 to L6 -> L62 [0] lasti
  L7 to L10 -> L55 [0]
  L10 to L11 -> L43 [2]
  L11 to L13 -> L55 [0]
  L14 to L16 -> L62 [0] lasti
  L16 to L17 -> L45 [2]
  L17 to L19 -> L62 [0] lasti
  L19 to L21 -> L55 [0]
  L22 to L24 -> L62 [0] lasti
  L24 to L25 -> L47 [2]
  L25 to L27 -> L62 [0] lasti
  L27 to L29 -> L55 [0]
  L29 to L30 -> L49 [2]
  L30 to L33 -> L55 [0]
  L33 to L34 -> L51 [2]
  L34 to L36 -> L55 [0]
  L36 to L38 -> L62 [0] lasti
  L38 to L39 -> L53 [3]
  L39 to L42 -> L62 [0] lasti
  L43 to L44 -> L55 [0]
  L45 to L46 -> L62 [0] lasti
  L47 to L48 -> L62 [0] lasti
  L49 to L50 -> L55 [0]
  L51 to L52 -> L55 [0]
  L53 to L54 -> L62 [0] lasti
  L55 to L57 -> L61 [1] lasti
  L57 to L58 -> L59 [4]
  L58 to L61 -> L61 [1] lasti
  L61 to L62 -> L62 [0] lasti

Disassembly of <code object backup at 0x000001EE5C63FB40, file "discord_backup\cli.py", line 81>:
  81           RESUME                   0

  87           LOAD_GLOBAL              1 (_load_config_and_console + NULL)
               CALL                     0
               UNPACK_SEQUENCE          2
               STORE_FAST_STORE_FAST   35 (config, console)

  88           NOP

  89   L1:     LOAD_GLOBAL              2 (asyncio)
               LOAD_ATTR                4 (run)
               PUSH_NULL
               LOAD_GLOBAL              7 (_run_backup + NULL)
               LOAD_FAST_LOAD_FAST      2 (token, config)
               LOAD_FAST_LOAD_FAST     49 (console, scan)
               CALL                     4
               CALL                     1
               POP_TOP
       L2:     RETURN_CONST             3 (None)

  --   L3:     PUSH_EXC_INFO

  90           LOAD_GLOBAL              8 (BackupError)
               CHECK_EXC_MATCH
               POP_JUMP_IF_FALSE       51 (to L6)
               STORE_FAST               4 (exc)

  91   L4:     LOAD_FAST                3 (console)
               LOAD_ATTR               11 (error + NULL|self)
               LOAD_GLOBAL             13 (str + NULL)
               LOAD_FAST                4 (exc)
               CALL                     1
               CALL                     1
               POP_TOP

  92           LOAD_GLOBAL             14 (typer)
               LOAD_ATTR               16 (Exit)
               PUSH_NULL
               LOAD_CONST               1 (1)
               LOAD_CONST               2 (('code',))
               CALL_KW                  1
               RAISE_VARARGS            1

  --   L5:     LOAD_CONST               3 (None)
               STORE_FAST               4 (exc)
               DELETE_FAST              4 (exc)
               RERAISE                  1

  90   L6:     RERAISE                  0

  --   L7:     COPY                     3
               POP_EXCEPT
               RERAISE                  1
ExceptionTable:
  L1 to L2 -> L3 [0]
  L3 to L4 -> L7 [1] lasti
  L4 to L5 -> L5 [1] lasti
  L5 to L7 -> L7 [1] lasti

Disassembly of <code object _run_restore at 0x000001EE5C728C20, file "discord_backup\cli.py", line 95>:
  95            RETURN_GENERATOR
                POP_TOP
        L1:     RESUME                   0

 103            LOAD_FAST                0 (backup_path)
                LOAD_ATTR                1 (exists + NULL|self)
                CALL                     0
                TO_BOOL
                POP_JUMP_IF_TRUE        21 (to L2)

 104            LOAD_FAST                5 (console)
                LOAD_ATTR                3 (error + NULL|self)
                LOAD_CONST               1 ('Backup file not found: ')
                LOAD_FAST                0 (backup_path)
                FORMAT_SIMPLE
                BUILD_STRING             2
                CALL                     1
                POP_TOP

 105            RETURN_CONST             0 (None)

 106    L2:     LOAD_GLOBAL              4 (json)
                LOAD_ATTR                6 (loads)
                PUSH_NULL
                LOAD_FAST                0 (backup_path)
                LOAD_ATTR                9 (read_text + NULL|self)
                LOAD_CONST               2 ('utf-8')
                LOAD_CONST               3 (('encoding',))
                CALL_KW                  1
                CALL                     1
                STORE_FAST               6 (data)

 107            LOAD_GLOBAL             10 (DiscordHTTPClient)
                LOAD_ATTR               12 (create)
                PUSH_NULL
                CALL                     0
                GET_AWAITABLE            0
                LOAD_CONST               0 (None)
        L3:     SEND                     3 (to L6)
        L4:     YIELD_VALUE              1
        L5:     RESUME                   3
                JUMP_BACKWARD_NO_INTERRUPT 5 (to L3)
        L6:     END_SEND
                STORE_FAST               7 (http)

 108    L7:     NOP

 109    L8:     LOAD_GLOBAL             15 (RestoreService + NULL)
                LOAD_FAST_LOAD_FAST    113 (http, token)
                LOAD_FAST_LOAD_FAST     38 (bot_token, data)
                LOAD_FAST                5 (console)
                LOAD_CONST               4 (('http', 'token', 'bot_token', 'backup', 'console'))
                CALL_KW                  5
                STORE_FAST               8 (service)

 110            LOAD_FAST                8 (service)
                LOAD_ATTR               17 (run + NULL|self)

 111            LOAD_FAST                3 (restore_folders)

 112            LOAD_FAST                6 (data)
                LOAD_ATTR               19 (get + NULL|self)
                LOAD_CONST               5 ('version')
                CALL                     1

 113            LOAD_FAST                4 (allow_version_mismatch)

 110            LOAD_CONST               6 (('restore_folders', 'expected_version', 'allow_mismatch'))
                CALL_KW                  3
                GET_AWAITABLE            0
                LOAD_CONST               0 (None)
        L9:     SEND                     3 (to L12)
       L10:     YIELD_VALUE              1
       L11:     RESUME                   3
                JUMP_BACKWARD_NO_INTERRUPT 5 (to L9)
       L12:     END_SEND
                STORE_FAST               9 (summary)

 115            LOAD_FAST                5 (console)
                LOAD_ATTR               21 (success + NULL|self)
                LOAD_CONST               7 ('Restore complete')
                CALL                     1
                POP_TOP

 116            LOAD_FAST                5 (console)
                LOAD_ATTR               23 (info + NULL|self)
                LOAD_CONST               8 ('Backup guild id: ')
                LOAD_FAST                9 (summary)
                LOAD_ATTR               24 (guild_id)
                FORMAT_SIMPLE
                BUILD_STRING             2
                CALL                     1
                POP_TOP

 117            LOAD_FAST                5 (console)
                LOAD_ATTR               23 (info + NULL|self)
                LOAD_CONST               9 ('Favourite GIFs: ')
                LOAD_FAST                9 (summary)
                LOAD_ATTR               26 (favourite_gifs_status)
                FORMAT_SIMPLE
                BUILD_STRING             2
                CALL                     1
                POP_TOP

 118            LOAD_FAST                5 (console)
                LOAD_ATTR               23 (info + NULL|self)

 119            LOAD_FAST                9 (summary)
                LOAD_ATTR               28 (folder_restore_attempted)
                TO_BOOL
                POP_JUMP_IF_FALSE        2 (to L13)
                LOAD_CONST              10 ('Folders restored')
                JUMP_FORWARD             1 (to L14)
       L13:     LOAD_CONST              11 ('Folders skipped')

 120   L14:     LOAD_CONST              12 (2)

 118            LOAD_CONST              13 (('indent',))
                CALL_KW                  2
                POP_TOP

 122            LOAD_FAST                5 (console)
                LOAD_ATTR               23 (info + NULL|self)
                LOAD_CONST              14 ('Duration: ')
                LOAD_FAST                9 (summary)
                LOAD_ATTR               30 (duration)
                LOAD_CONST              15 ('.1f')
                FORMAT_WITH_SPEC
                LOAD_CONST              16 ('s')
                BUILD_STRING             3
                LOAD_CONST              12 (2)
                LOAD_CONST              13 (('indent',))
                CALL_KW                  2
                POP_TOP

 124   L15:     LOAD_FAST                7 (http)
                LOAD_ATTR               33 (aclose + NULL|self)
                CALL                     0
                GET_AWAITABLE            0
                LOAD_CONST               0 (None)
       L16:     SEND                     3 (to L19)
       L17:     YIELD_VALUE              1
       L18:     RESUME                   3
                JUMP_BACKWARD_NO_INTERRUPT 5 (to L16)
       L19:     END_SEND
                POP_TOP
                RETURN_CONST             0 (None)

 107   L20:     CLEANUP_THROW
       L21:     JUMP_BACKWARD_NO_INTERRUPT 224 (to L6)

 110   L22:     CLEANUP_THROW
       L23:     JUMP_BACKWARD_NO_INTERRUPT 174 (to L12)

 124   L24:     CLEANUP_THROW
       L25:     JUMP_BACKWARD_NO_INTERRUPT 9 (to L19)

  --   L26:     PUSH_EXC_INFO

 124            LOAD_FAST                7 (http)
                LOAD_ATTR               33 (aclose + NULL|self)
                CALL                     0
                GET_AWAITABLE            0
                LOAD_CONST               0 (None)
       L27:     SEND                     4 (to L31)
       L28:     YIELD_VALUE              1
       L29:     RESUME                   3
                JUMP_BACKWARD_NO_INTERRUPT 5 (to L27)
       L30:     CLEANUP_THROW
       L31:     END_SEND
                POP_TOP
                RERAISE                  0

  --   L32:     COPY                     3
                POP_EXCEPT
                RERAISE                  1
       L33:     CALL_INTRINSIC_1         3 (INTRINSIC_STOPITERATION_ERROR)
                RERAISE                  1
ExceptionTable:
  L1 to L4 -> L33 [0] lasti
  L4 to L5 -> L20 [2]
  L5 to L7 -> L33 [0] lasti
  L8 to L10 -> L26 [0]
  L10 to L11 -> L22 [2]
  L11 to L15 -> L26 [0]
  L15 to L17 -> L33 [0] lasti
  L17 to L18 -> L24 [2]
  L18 to L21 -> L33 [0] lasti
  L22 to L23 -> L26 [0]
  L24 to L25 -> L33 [0] lasti
  L26 to L28 -> L32 [1] lasti
  L28 to L29 -> L30 [4]
  L29 to L32 -> L32 [1] lasti
  L32 to L33 -> L33 [0] lasti

Disassembly of <code object restore at 0x000001EE5E89C030, file "discord_backup\cli.py", line 127>:
 127           RESUME                   0

 136           LOAD_GLOBAL              1 (_load_config_and_console + NULL)
               CALL                     0
               UNPACK_SEQUENCE          2
               STORE_FAST_STORE_FAST   86 (_, console)

 137           NOP

 138   L1:     LOAD_GLOBAL              2 (asyncio)
               LOAD_ATTR                4 (run)
               PUSH_NULL

 139           LOAD_GLOBAL              7 (_run_restore + NULL)

 140           LOAD_FAST                0 (backup_file)

 141           LOAD_FAST                1 (token)

 142           LOAD_FAST                2 (bot_token)

 143           LOAD_FAST                3 (restore_folders)

 144           LOAD_FAST                4 (allow_version_mismatch)

 145           LOAD_FAST                6 (console)

 139           CALL                     6

 138           CALL                     1
               POP_TOP
       L2:     RETURN_CONST             3 (None)

  --   L3:     PUSH_EXC_INFO

 148           LOAD_GLOBAL              8 (RestoreError)
               CHECK_EXC_MATCH
               POP_JUMP_IF_FALSE       51 (to L6)
               STORE_FAST               7 (exc)

 149   L4:     LOAD_FAST                6 (console)
               LOAD_ATTR               11 (error + NULL|self)
               LOAD_GLOBAL             13 (str + NULL)
               LOAD_FAST                7 (exc)
               CALL                     1
               CALL                     1
               POP_TOP

 150           LOAD_GLOBAL             14 (typer)
               LOAD_ATTR               16 (Exit)
               PUSH_NULL
               LOAD_CONST               1 (1)
               LOAD_CONST               2 (('code',))
               CALL_KW                  1
               RAISE_VARARGS            1

  --   L5:     LOAD_CONST               3 (None)
               STORE_FAST               7 (exc)
               DELETE_FAST              7 (exc)
               RERAISE                  1

 148   L6:     RERAISE                  0

  --   L7:     COPY                     3
               POP_EXCEPT
               RERAISE                  1
ExceptionTable:
  L1 to L2 -> L3 [0]
  L3 to L4 -> L7 [1] lasti
  L4 to L5 -> L5 [1] lasti
  L5 to L7 -> L7 [1] lasti

Disassembly of <code object auto_backup at 0x000001EE5C61BA50, file "discord_backup\cli.py", line 153>:
  --           MAKE_CELL                0 (account_id)
               MAKE_CELL                4 (config)
               MAKE_CELL                5 (console)

 153           RESUME                   0

 159           LOAD_GLOBAL              1 (_load_config_and_console + NULL)
               CALL                     0
               UNPACK_SEQUENCE          2
               STORE_DEREF              4 (config)
               STORE_DEREF              5 (console)

 160           LOAD_FAST                1 (working_dir)
               LOAD_ATTR                3 (resolve + NULL|self)
               CALL                     0
               STORE_FAST               1 (working_dir)

 161           LOAD_FAST                1 (working_dir)
               LOAD_ATTR                5 (exists + NULL|self)
               CALL                     0
               TO_BOOL
               POP_JUMP_IF_FALSE       22 (to L1)

 162           LOAD_CONST               1 (0)
               LOAD_CONST               2 (None)
               IMPORT_NAME              3 (os)
               STORE_FAST               2 (os)

 164           LOAD_FAST                2 (os)
               LOAD_ATTR                9 (chdir + NULL|self)
               LOAD_FAST                1 (working_dir)
               CALL                     1
               POP_TOP
               JUMP_FORWARD            20 (to L2)

 166   L1:     LOAD_DEREF               5 (console)
               LOAD_ATTR               11 (warn + NULL|self)
               LOAD_CONST               3 ('Working directory not found: ')
               LOAD_FAST                1 (working_dir)
               FORMAT_SIMPLE
               BUILD_STRING             2
               CALL                     1
               POP_TOP

 167   L2:     LOAD_CONST               5 (('return', 'None'))
               LOAD_FAST                0 (account_id)
               LOAD_FAST                4 (config)
               LOAD_FAST                5 (console)
               BUILD_TUPLE              3
               LOAD_CONST               4 (<code object runner at 0x000001EE5C72F470, file "discord_backup\cli.py", line 167>)
               MAKE_FUNCTION
               SET_FUNCTION_ATTRIBUTE   8 (closure)
               SET_FUNCTION_ATTRIBUTE   4 (annotations)
               STORE_FAST               3 (runner)

 186           LOAD_GLOBAL             12 (asyncio)
               LOAD_ATTR               14 (run)
               PUSH_NULL
               LOAD_FAST                3 (runner)
               PUSH_NULL
               CALL                     0
               CALL                     1
               POP_TOP
               RETURN_CONST             2 (None)

Disassembly of <code object runner at 0x000001EE5C72F470, file "discord_backup\cli.py", line 167>:
  --            COPY_FREE_VARS           3

 167            RETURN_GENERATOR
                POP_TOP
        L1:     RESUME                   0

 168            LOAD_GLOBAL              0 (DiscordHTTPClient)
                LOAD_ATTR                2 (create)
                PUSH_NULL
                CALL                     0
                GET_AWAITABLE            0
                LOAD_CONST               0 (None)
        L2:     SEND                     3 (to L5)
        L3:     YIELD_VALUE              1
        L4:     RESUME                   3
                JUMP_BACKWARD_NO_INTERRUPT 5 (to L2)
        L5:     END_SEND
                STORE_FAST               0 (http)

 169    L6:     NOP

 170    L7:     LOAD_GLOBAL              5 (discover_tokens + NULL)
                LOAD_FAST                0 (http)
                CALL                     1
                GET_AWAITABLE            0
                LOAD_CONST               0 (None)
        L8:     SEND                     3 (to L11)
        L9:     YIELD_VALUE              1
       L10:     RESUME                   3
                JUMP_BACKWARD_NO_INTERRUPT 5 (to L8)
       L11:     END_SEND
                STORE_FAST               1 (tokens)

 171            LOAD_CONST               0 (None)
                STORE_FAST               2 (token_value)

 172            LOAD_FAST                1 (tokens)
                GET_ITER
       L12:     FOR_ITER                63 (to L15)
                STORE_FAST               3 (item)

 173            LOAD_FAST                3 (item)
                LOAD_ATTR                6 (user_id)
                LOAD_DEREF               6 (account_id)
                COMPARE_OP              88 (bool(==))
       L13:     POP_JUMP_IF_TRUE         2 (to L14)
                JUMP_BACKWARD           21 (to L12)

 174   L14:     LOAD_FAST                3 (item)
                LOAD_ATTR                8 (token)
                STORE_FAST               2 (token_value)

 175            LOAD_DEREF               8 (console)
                LOAD_ATTR               11 (success + NULL|self)
                LOAD_CONST               1 ('Found token for ')
                LOAD_FAST                3 (item)
                LOAD_ATTR               12 (user_tag)
                FORMAT_SIMPLE
                BUILD_STRING             2
                CALL                     1
                POP_TOP

 176            POP_TOP
                JUMP_FORWARD             2 (to L16)

 172   L15:     END_FOR
                POP_TOP

 177   L16:     LOAD_FAST                2 (token_value)
                TO_BOOL
                POP_JUMP_IF_TRUE        43 (to L23)

 178            LOAD_DEREF               8 (console)
                LOAD_ATTR               15 (error + NULL|self)
                LOAD_CONST               2 ('No matching token found for auto-backup')
                CALL                     1
                POP_TOP

 179   L17:     NOP

 185   L18:     LOAD_FAST                0 (http)
                LOAD_ATTR               17 (aclose + NULL|self)
                CALL                     0
                GET_AWAITABLE            0
                LOAD_CONST               0 (None)
       L19:     SEND                     3 (to L22)
       L20:     YIELD_VALUE              1
       L21:     RESUME                   3
                JUMP_BACKWARD_NO_INTERRUPT 5 (to L19)
       L22:     END_SEND
                POP_TOP
                RETURN_CONST             0 (None)

 180   L23:     LOAD_GLOBAL             19 (BackupService + NULL)
                LOAD_FAST_LOAD_FAST      2 (http, token_value)
                LOAD_DEREF               7 (config)
                LOAD_DEREF               8 (console)
                LOAD_CONST               3 (('http', 'token', 'config', 'console'))
                CALL_KW                  4
                STORE_FAST               4 (service)

 181            LOAD_FAST                4 (service)
                LOAD_ATTR               21 (run + NULL|self)
                CALL                     0
                GET_AWAITABLE            0
                LOAD_CONST               0 (None)
       L24:     SEND                     3 (to L27)
       L25:     YIELD_VALUE              1
       L26:     RESUME                   3
                JUMP_BACKWARD_NO_INTERRUPT 5 (to L24)
       L27:     END_SEND
                STORE_FAST               5 (result)

 182            LOAD_FAST                4 (service)
                LOAD_ATTR               23 (save + NULL|self)
                LOAD_FAST                5 (result)
                CALL                     1
                GET_AWAITABLE            0
                LOAD_CONST               0 (None)
       L28:     SEND                     3 (to L31)
       L29:     YIELD_VALUE              1
       L30:     RESUME                   3
                JUMP_BACKWARD_NO_INTERRUPT 5 (to L28)
       L31:     END_SEND
                POP_TOP

 183            LOAD_DEREF               8 (console)
                LOAD_ATTR               11 (success + NULL|self)
                LOAD_CONST               4 ('Auto-backup finished')
                CALL                     1
                POP_TOP

 185   L32:     LOAD_FAST                0 (http)
                LOAD_ATTR               17 (aclose + NULL|self)
                CALL                     0
                GET_AWAITABLE            0
                LOAD_CONST               0 (None)
       L33:     SEND                     3 (to L36)
       L34:     YIELD_VALUE              1
       L35:     RESUME                   3
                JUMP_BACKWARD_NO_INTERRUPT 5 (to L33)
       L36:     END_SEND
                POP_TOP
                RETURN_CONST             0 (None)

 168   L37:     CLEANUP_THROW
       L38:     JUMP_BACKWARD_NO_INTERRUPT 247 (to L5)

 170   L39:     CLEANUP_THROW
       L40:     JUMP_BACKWARD_NO_INTERRUPT 229 (to L11)

 185   L41:     CLEANUP_THROW
       L42:     JUMP_BACKWARD_NO_INTERRUPT 111 (to L22)

 181   L43:     CLEANUP_THROW
       L44:     JUMP_BACKWARD_NO_INTERRUPT 77 (to L27)

 182   L45:     CLEANUP_THROW
       L46:     JUMP_BACKWARD_NO_INTERRUPT 54 (to L31)

 185   L47:     CLEANUP_THROW
       L48:     JUMP_BACKWARD_NO_INTERRUPT 15 (to L36)

  --   L49:     PUSH_EXC_INFO

 185            LOAD_FAST                0 (http)
                LOAD_ATTR               17 (aclose + NULL|self)
                CALL                     0
                GET_AWAITABLE            0
                LOAD_CONST               0 (None)
       L50:     SEND                     4 (to L54)
       L51:     YIELD_VALUE              1
       L52:     RESUME                   3
                JUMP_BACKWARD_NO_INTERRUPT 5 (to L50)
       L53:     CLEANUP_THROW
       L54:     END_SEND
                POP_TOP
                RERAISE                  0

  --   L55:     COPY                     3
                POP_EXCEPT
                RERAISE                  1
       L56:     CALL_INTRINSIC_1         3 (INTRINSIC_STOPITERATION_ERROR)
                RERAISE                  1
ExceptionTable:
  L1 to L3 -> L56 [0] lasti
  L3 to L4 -> L37 [2]
  L4 to L6 -> L56 [0] lasti
  L7 to L9 -> L49 [0]
  L9 to L10 -> L39 [2]
  L10 to L13 -> L49 [0]
  L14 to L17 -> L49 [0]
  L18 to L20 -> L56 [0] lasti
  L20 to L21 -> L41 [2]
  L21 to L23 -> L56 [0] lasti
  L23 to L25 -> L49 [0]
  L25 to L26 -> L43 [2]
  L26 to L29 -> L49 [0]
  L29 to L30 -> L45 [2]
  L30 to L32 -> L49 [0]
  L32 to L34 -> L56 [0] lasti
  L34 to L35 -> L47 [2]
  L35 to L38 -> L56 [0] lasti
  L39 to L40 -> L49 [0]
  L41 to L42 -> L56 [0] lasti
  L43 to L44 -> L49 [0]
  L45 to L46 -> L49 [0]
  L47 to L48 -> L56 [0] lasti
  L49 to L51 -> L55 [1] lasti
  L51 to L52 -> L53 [4]
  L52 to L55 -> L55 [1] lasti
  L55 to L56 -> L56 [0] lasti

Disassembly of <code object startup_add at 0x000001EE5E7F5430, file "discord_backup\cli.py", line 189>:
  --           MAKE_CELL                0 (scan)
               MAKE_CELL                3 (console)

 189           RESUME                   0

 194           LOAD_GLOBAL              1 (_load_config_and_console + NULL)
               CALL                     0
               UNPACK_SEQUENCE          2
               STORE_FAST               1 (config)
               STORE_DEREF              3 (console)

 196           LOAD_CONST               3 (('return', 'None'))
               LOAD_FAST                3 (console)
               LOAD_FAST                0 (scan)
               BUILD_TUPLE              2
               LOAD_CONST               1 (<code object runner at 0x000001EE5C729840, file "discord_backup\cli.py", line 196>)
               MAKE_FUNCTION
               SET_FUNCTION_ATTRIBUTE   8 (closure)
               SET_FUNCTION_ATTRIBUTE   4 (annotations)
               STORE_FAST               2 (runner)

 219           LOAD_GLOBAL              2 (asyncio)
               LOAD_ATTR                4 (run)
               PUSH_NULL
               LOAD_FAST                2 (runner)
               PUSH_NULL
               CALL                     0
               CALL                     1
               POP_TOP
               RETURN_CONST             2 (None)

Disassembly of <code object runner at 0x000001EE5C729840, file "discord_backup\cli.py", line 196>:
  --            COPY_FREE_VARS           2

 196            RETURN_GENERATOR
                POP_TOP
        L1:     RESUME                   0

 197            LOAD_GLOBAL              0 (DiscordHTTPClient)
                LOAD_ATTR                2 (create)
                PUSH_NULL
                CALL                     0
                GET_AWAITABLE            0
                LOAD_CONST               0 (None)
        L2:     SEND                     3 (to L5)
        L3:     YIELD_VALUE              1
        L4:     RESUME                   3
                JUMP_BACKWARD_NO_INTERRUPT 5 (to L2)
        L5:     END_SEND
                STORE_FAST               0 (http)

 198    L6:     NOP

 199    L7:     LOAD_CONST               0 (None)
                STORE_FAST               1 (selection)

 200            LOAD_DEREF               7 (scan)
                TO_BOOL
                POP_JUMP_IF_FALSE       20 (to L12)

 201            LOAD_GLOBAL              5 (_select_token + NULL)
                LOAD_FAST                0 (http)
                LOAD_DEREF               6 (console)
                CALL                     2
                GET_AWAITABLE            0
                LOAD_CONST               0 (None)
        L8:     SEND                     3 (to L11)
        L9:     YIELD_VALUE              1
       L10:     RESUME                   3
                JUMP_BACKWARD_NO_INTERRUPT 5 (to L8)
       L11:     END_SEND
                STORE_FAST               1 (selection)

 202   L12:     LOAD_FAST                1 (selection)
                TO_BOOL
                POP_JUMP_IF_TRUE       103 (to L20)

 203            LOAD_GLOBAL              6 (typer)
                LOAD_ATTR                8 (prompt)
                PUSH_NULL
                LOAD_CONST               1 ('Enter user token for auto-backup')
                LOAD_CONST               2 (True)
                LOAD_CONST               3 (('hide_input',))
                CALL_KW                  2
                STORE_FAST               2 (token_input)

 204            LOAD_FAST                2 (token_input)
                TO_BOOL
                POP_JUMP_IF_TRUE        43 (to L19)

 205            LOAD_DEREF               6 (console)
                LOAD_ATTR               11 (error + NULL|self)
                LOAD_CONST               4 ('Token required for auto-backup')
                CALL                     1
                POP_TOP

 206   L13:     NOP

 217   L14:     LOAD_FAST                0 (http)
                LOAD_ATTR               13 (aclose + NULL|self)
                CALL                     0
                GET_AWAITABLE            0
                LOAD_CONST               0 (None)
       L15:     SEND                     3 (to L18)
       L16:     YIELD_VALUE              1
       L17:     RESUME                   3
                JUMP_BACKWARD_NO_INTERRUPT 5 (to L15)
       L18:     END_SEND
                POP_TOP
                RETURN_CONST             0 (None)

 207   L19:     LOAD_GLOBAL             15 (DiscoveredToken + NULL)
                LOAD_FAST                2 (token_input)
                LOAD_CONST               5 ('manual')
                LOAD_GLOBAL              6 (typer)
                LOAD_ATTR                8 (prompt)
                PUSH_NULL
                LOAD_CONST               6 ('Enter account id')
                CALL                     1
                LOAD_CONST               5 ('manual')
                LOAD_CONST               7 (('token', 'user_tag', 'user_id', 'source'))
                CALL_KW                  4
                STORE_FAST               1 (selection)

 209   L20:     LOAD_GLOBAL             17 (Path + NULL)
                LOAD_GLOBAL             19 (getattr + NULL)
                LOAD_GLOBAL             20 (sys)
                LOAD_CONST               8 ('frozen')
                LOAD_CONST               9 (False)
                CALL                     3
                TO_BOOL
                POP_JUMP_IF_FALSE       16 (to L21)
                LOAD_GLOBAL             20 (sys)
                LOAD_ATTR               22 (executable)
                JUMP_FORWARD            51 (to L22)
       L21:     LOAD_GLOBAL             17 (Path + NULL)
                LOAD_GLOBAL             24 (__file__)
                CALL                     1
                LOAD_ATTR               27 (resolve + NULL|self)
                CALL                     0
                LOAD_ATTR               28 (parent)
                LOAD_ATTR               28 (parent)
                LOAD_CONST              10 ('main.py')
                BINARY_OP               11 (/)
       L22:     CALL                     1
                STORE_FAST               3 (executable)

 210            LOAD_FAST                3 (executable)
                LOAD_ATTR               30 (suffix)
                LOAD_CONST              11 ('.py')
                COMPARE_OP              88 (bool(==))
                POP_JUMP_IF_FALSE       19 (to L23)

 211            LOAD_CONST              12 ('cmd.exe /C python "')
                LOAD_FAST                3 (executable)
                FORMAT_SIMPLE
                LOAD_CONST              13 ('" auto-backup --account-id ')
                LOAD_FAST                1 (selection)
                LOAD_ATTR               32 (user_id)
                FORMAT_SIMPLE
                BUILD_STRING             4
                STORE_FAST               4 (command)
                JUMP_FORWARD            18 (to L24)

 213   L23:     LOAD_CONST              14 ('"')
                LOAD_FAST                3 (executable)
                FORMAT_SIMPLE
                LOAD_CONST              13 ('" auto-backup --account-id ')
                LOAD_FAST                1 (selection)
                LOAD_ATTR               32 (user_id)
                FORMAT_SIMPLE
                BUILD_STRING             4
                STORE_FAST               4 (command)

 214   L24:     LOAD_GLOBAL             35 (write_startup_script + NULL)
                LOAD_FAST                4 (command)
                LOAD_GLOBAL             16 (Path)
                LOAD_ATTR               36 (cwd)
                PUSH_NULL
                CALL                     0
                CALL                     2
                STORE_FAST               5 (script_path)

 215            LOAD_DEREF               6 (console)
                LOAD_ATTR               39 (success + NULL|self)
                LOAD_CONST              15 ('Startup script written to ')
                LOAD_FAST                5 (script_path)
                FORMAT_SIMPLE
                BUILD_STRING             2
                CALL                     1
                POP_TOP

 217   L25:     LOAD_FAST                0 (http)
                LOAD_ATTR               13 (aclose + NULL|self)
                CALL                     0
                GET_AWAITABLE            0
                LOAD_CONST               0 (None)
       L26:     SEND                     3 (to L29)
       L27:     YIELD_VALUE              1
       L28:     RESUME                   3
                JUMP_BACKWARD_NO_INTERRUPT 5 (to L26)
       L29:     END_SEND
                POP_TOP
                RETURN_CONST             0 (None)

 197   L30:     CLEANUP_THROW
       L31:     EXTENDED_ARG             1
                JUMP_BACKWARD_NO_INTERRUPT 373 (to L5)

 201   L32:     CLEANUP_THROW
       L33:     EXTENDED_ARG             1
                JUMP_BACKWARD_NO_INTERRUPT 346 (to L11)

 217   L34:     CLEANUP_THROW
       L35:     EXTENDED_ARG             1
                JUMP_BACKWARD_NO_INTERRUPT 272 (to L18)
       L36:     CLEANUP_THROW
       L37:     JUMP_BACKWARD_NO_INTERRUPT 14 (to L29)

  --   L38:     PUSH_EXC_INFO

 217            LOAD_FAST                0 (http)
                LOAD_ATTR               13 (aclose + NULL|self)
                CALL                     0
                GET_AWAITABLE            0
                LOAD_CONST               0 (None)
       L39:     SEND                     4 (to L43)
       L40:     YIELD_VALUE              1
       L41:     RESUME                   3
                JUMP_BACKWARD_NO_INTERRUPT 5 (to L39)
       L42:     CLEANUP_THROW
       L43:     END_SEND
                POP_TOP
                RERAISE                  0

  --   L44:     COPY                     3
                POP_EXCEPT
                RERAISE                  1
       L45:     CALL_INTRINSIC_1         3 (INTRINSIC_STOPITERATION_ERROR)
                RERAISE                  1
ExceptionTable:
  L1 to L3 -> L45 [0] lasti
  L3 to L4 -> L30 [2]
  L4 to L6 -> L45 [0] lasti
  L7 to L9 -> L38 [0]
  L9 to L10 -> L32 [2]
  L10 to L13 -> L38 [0]
  L14 to L16 -> L45 [0] lasti
  L16 to L17 -> L34 [2]
  L17 to L19 -> L45 [0] lasti
  L19 to L25 -> L38 [0]
  L25 to L27 -> L45 [0] lasti
  L27 to L28 -> L36 [2]
  L28 to L31 -> L45 [0] lasti
  L32 to L33 -> L38 [0]
  L34 to L35 -> L45 [0] lasti
  L36 to L37 -> L45 [0] lasti
  L38 to L40 -> L44 [1] lasti
  L40 to L41 -> L42 [4]
  L41 to L44 -> L44 [1] lasti
  L44 to L45 -> L45 [0] lasti

Disassembly of <code object startup_remove at 0x000001EE5E577DE0, file "discord_backup\cli.py", line 222>:
222           RESUME                   0

225           LOAD_GLOBAL              1 (remove_startup_script + NULL)
              CALL                     0
              TO_BOOL
              POP_JUMP_IF_FALSE       23 (to L1)

226           LOAD_GLOBAL              2 (typer)
              LOAD_ATTR                4 (echo)
              PUSH_NULL
              LOAD_CONST               1 ('Startup script removed')
              CALL                     1
              POP_TOP
              RETURN_CONST             3 (None)

228   L1:     LOAD_GLOBAL              2 (typer)
              LOAD_ATTR                4 (echo)
              PUSH_NULL
              LOAD_CONST               2 ('No startup script found')
              CALL                     1
              POP_TOP
              RETURN_CONST             3 (None)

Disassembly of <code object tokens at 0x000001EE5E8844F0, file "discord_backup\cli.py", line 231>:
  --           MAKE_CELL                2 (console)

 231           RESUME                   0

 234           LOAD_GLOBAL              1 (_load_config_and_console + NULL)
               CALL                     0
               UNPACK_SEQUENCE          2
               STORE_FAST               0 (_)
               STORE_DEREF              2 (console)

 236           LOAD_CONST               3 (('return', 'None'))
               LOAD_FAST                2 (console)
               BUILD_TUPLE              1
               LOAD_CONST               1 (<code object runner at 0x000001EE5E624C00, file "discord_backup\cli.py", line 236>)
               MAKE_FUNCTION
               SET_FUNCTION_ATTRIBUTE   8 (closure)
               SET_FUNCTION_ATTRIBUTE   4 (annotations)
               STORE_FAST               1 (runner)

 248           LOAD_GLOBAL              2 (asyncio)
               LOAD_ATTR                4 (run)
               PUSH_NULL
               LOAD_FAST                1 (runner)
               PUSH_NULL
               CALL                     0
               CALL                     1
               POP_TOP
               RETURN_CONST             2 (None)

Disassembly of <code object runner at 0x000001EE5E624C00, file "discord_backup\cli.py", line 236>:
  --            COPY_FREE_VARS           1

 236            RETURN_GENERATOR
                POP_TOP
        L1:     RESUME                   0

 237            LOAD_GLOBAL              0 (DiscordHTTPClient)
                LOAD_ATTR                2 (create)
                PUSH_NULL
                CALL                     0
                GET_AWAITABLE            0
                LOAD_CONST               0 (None)
        L2:     SEND                     3 (to L5)
        L3:     YIELD_VALUE              1
        L4:     RESUME                   3
                JUMP_BACKWARD_NO_INTERRUPT 5 (to L2)
        L5:     END_SEND
                STORE_FAST               0 (http)

 238    L6:     NOP

 239    L7:     LOAD_GLOBAL              5 (discover_tokens + NULL)
                LOAD_FAST                0 (http)
                CALL                     1
                GET_AWAITABLE            0
                LOAD_CONST               0 (None)
        L8:     SEND                     3 (to L11)
        L9:     YIELD_VALUE              1
       L10:     RESUME                   3
                JUMP_BACKWARD_NO_INTERRUPT 5 (to L8)
       L11:     END_SEND
                STORE_FAST               1 (tokens)

 240            LOAD_FAST                1 (tokens)
                TO_BOOL
                POP_JUMP_IF_TRUE        43 (to L18)

 241            LOAD_DEREF               3 (console)
                LOAD_ATTR                7 (warn + NULL|self)
                LOAD_CONST               1 ('No tokens discovered')
                CALL                     1
                POP_TOP

 242   L12:     NOP

 246   L13:     LOAD_FAST                0 (http)
                LOAD_ATTR                9 (aclose + NULL|self)
                CALL                     0
                GET_AWAITABLE            0
                LOAD_CONST               0 (None)
       L14:     SEND                     3 (to L17)
       L15:     YIELD_VALUE              1
       L16:     RESUME                   3
                JUMP_BACKWARD_NO_INTERRUPT 5 (to L14)
       L17:     END_SEND
                POP_TOP
                RETURN_CONST             0 (None)

 243   L18:     LOAD_FAST                1 (tokens)
                GET_ITER
       L19:     FOR_ITER                58 (to L20)
                STORE_FAST               2 (item)

 244            LOAD_DEREF               3 (console)
                LOAD_ATTR               11 (info + NULL|self)
                LOAD_FAST                2 (item)
                LOAD_ATTR               12 (user_tag)
                FORMAT_SIMPLE
                LOAD_CONST               2 (' (')
                LOAD_FAST                2 (item)
                LOAD_ATTR               14 (user_id)
                FORMAT_SIMPLE
                LOAD_CONST               3 (') - ')
                LOAD_FAST                2 (item)
                LOAD_ATTR               16 (source)
                FORMAT_SIMPLE
                BUILD_STRING             5
                CALL                     1
                POP_TOP
                JUMP_BACKWARD           60 (to L19)

 243   L20:     END_FOR
                POP_TOP

 246   L21:     LOAD_FAST                0 (http)
                LOAD_ATTR                9 (aclose + NULL|self)
                CALL                     0
                GET_AWAITABLE            0
                LOAD_CONST               0 (None)
       L22:     SEND                     3 (to L25)
       L23:     YIELD_VALUE              1
       L24:     RESUME                   3
                JUMP_BACKWARD_NO_INTERRUPT 5 (to L22)
       L25:     END_SEND
                POP_TOP
                RETURN_CONST             0 (None)

 237   L26:     CLEANUP_THROW
       L27:     JUMP_BACKWARD_NO_INTERRUPT 163 (to L5)

 239   L28:     CLEANUP_THROW
       L29:     JUMP_BACKWARD_NO_INTERRUPT 145 (to L11)

 246   L30:     CLEANUP_THROW
       L31:     JUMP_BACKWARD_NO_INTERRUPT 98 (to L17)
       L32:     CLEANUP_THROW
       L33:     JUMP_BACKWARD_NO_INTERRUPT 11 (to L25)

  --   L34:     PUSH_EXC_INFO

 246            LOAD_FAST                0 (http)
                LOAD_ATTR                9 (aclose + NULL|self)
                CALL                     0
                GET_AWAITABLE            0
                LOAD_CONST               0 (None)
       L35:     SEND                     4 (to L39)
       L36:     YIELD_VALUE              1
       L37:     RESUME                   3
                JUMP_BACKWARD_NO_INTERRUPT 5 (to L35)
       L38:     CLEANUP_THROW
       L39:     END_SEND
                POP_TOP
                RERAISE                  0

  --   L40:     COPY                     3
                POP_EXCEPT
                RERAISE                  1
       L41:     CALL_INTRINSIC_1         3 (INTRINSIC_STOPITERATION_ERROR)
                RERAISE                  1
ExceptionTable:
  L1 to L3 -> L41 [0] lasti
  L3 to L4 -> L26 [2]
  L4 to L6 -> L41 [0] lasti
  L7 to L9 -> L34 [0]
  L9 to L10 -> L28 [2]
  L10 to L12 -> L34 [0]
  L13 to L15 -> L41 [0] lasti
  L15 to L16 -> L30 [2]
  L16 to L18 -> L41 [0] lasti
  L18 to L21 -> L34 [0]
  L21 to L23 -> L41 [0] lasti
  L23 to L24 -> L32 [2]
  L24 to L27 -> L41 [0] lasti
  L28 to L29 -> L34 [0]
  L30 to L31 -> L41 [0] lasti
  L32 to L33 -> L41 [0] lasti
  L34 to L36 -> L40 [1] lasti
  L36 to L37 -> L38 [4]
  L37 to L40 -> L40 [1] lasti
  L40 to L41 -> L41 [0] lasti

Disassembly of <code object run at 0x000001EE5E820D50, file "discord_backup\cli.py", line 251>:
251           RESUME                   0

252           LOAD_GLOBAL              1 (app + NULL)
              CALL                     0
              POP_TOP
              RETURN_CONST             0 (None)


# --- Nested: _load_config_and_console ---

 25           RESUME                   0

 26           LOAD_GLOBAL              0 (AppConfig)
              LOAD_ATTR                2 (load)
              PUSH_NULL
              CALL                     0
              STORE_FAST               0 (config)

 27           LOAD_GLOBAL              5 (Console + NULL)
              LOAD_FAST                0 (config)
              LOAD_ATTR                6 (colour)
              LOAD_CONST               1 (('accent',))
              CALL_KW                  1
              STORE_FAST               1 (console)

 28           LOAD_FAST_LOAD_FAST      1 (config, console)
              BUILD_TUPLE              2
              RETURN_VALUE


# --- Nested: _select_token ---

  31            RETURN_GENERATOR
                POP_TOP
        L1:     RESUME                   0

  32            LOAD_GLOBAL              1 (discover_tokens + NULL)
                LOAD_FAST                0 (http)
                CALL                     1
                GET_AWAITABLE            0
                LOAD_CONST               0 (None)
        L2:     SEND                     3 (to L5)
        L3:     YIELD_VALUE              1
        L4:     RESUME                   3
                JUMP_BACKWARD_NO_INTERRUPT 5 (to L2)
        L5:     END_SEND
                STORE_FAST               2 (tokens)

  33            LOAD_FAST                2 (tokens)
                TO_BOOL
                POP_JUMP_IF_TRUE        18 (to L6)

  34            LOAD_FAST                1 (console)
                LOAD_ATTR                3 (warn + NULL|self)
                LOAD_CONST               1 ('No tokens discovered on this system.')
                CALL                     1
                POP_TOP

  35            RETURN_CONST             0 (None)

  36    L6:     LOAD_FAST                1 (console)
                LOAD_ATTR                5 (info + NULL|self)
                LOAD_CONST               2 ('Discovered tokens:')
                CALL                     1
                POP_TOP

  37            LOAD_GLOBAL              7 (enumerate + NULL)
                LOAD_FAST                2 (tokens)
                CALL                     1
                GET_ITER
        L7:     FOR_ITER                51 (to L8)
                UNPACK_SEQUENCE          2
                STORE_FAST_STORE_FAST   52 (idx, info)

  38            LOAD_FAST                1 (console)
                LOAD_ATTR                5 (info + NULL|self)
                LOAD_CONST               3 ('[')
                LOAD_FAST                3 (idx)
                FORMAT_SIMPLE
                LOAD_CONST               4 ('] ')
                LOAD_FAST                4 (info)
                LOAD_ATTR                8 (user_tag)
                FORMAT_SIMPLE
                LOAD_CONST               5 (' (')
                LOAD_FAST                4 (info)
                LOAD_ATTR               10 (source)
                FORMAT_SIMPLE
                LOAD_CONST               6 (')')
                BUILD_STRING             7
                LOAD_CONST               7 (2)
                LOAD_CONST               8 (('indent',))
                CALL_KW                  2
                POP_TOP
                JUMP_BACKWARD           53 (to L7)

  37    L8:     END_FOR
                POP_TOP

  39            LOAD_GLOBAL             12 (typer)
                LOAD_ATTR               14 (prompt)
                PUSH_NULL
                LOAD_CONST               9 ('Select token index')
                LOAD_CONST              10 ('0')
                LOAD_CONST              11 (('default',))
                CALL_KW                  2
                STORE_FAST               5 (choice)

  40    L9:     NOP

  41   L10:     LOAD_FAST                2 (tokens)
                LOAD_GLOBAL             17 (int + NULL)
                LOAD_FAST                5 (choice)
                CALL                     1
                BINARY_SUBSCR
                STORE_FAST               6 (selected)

  42            LOAD_FAST                1 (console)
                LOAD_ATTR               19 (success + NULL|self)
                LOAD_CONST              12 ('Selected ')
                LOAD_FAST                6 (selected)
                LOAD_ATTR                8 (user_tag)
                FORMAT_SIMPLE
                BUILD_STRING             2
                CALL                     1
                POP_TOP

  43            LOAD_FAST                6 (selected)
       L11:     RETURN_VALUE

  32   L12:     CLEANUP_THROW
       L13:     JUMP_BACKWARD_NO_INTERRUPT 180 (to L5)

  --   L14:     PUSH_EXC_INFO

  44            LOAD_GLOBAL             20 (ValueError)
                LOAD_GLOBAL             22 (IndexError)
                BUILD_TUPLE              2
                CHECK_EXC_MATCH
                POP_JUMP_IF_FALSE       20 (to L16)
                POP_TOP

  45            LOAD_FAST                1 (console)
                LOAD_ATTR               25 (error + NULL|self)
                LOAD_CONST              13 ('Invalid selection')
                CALL                     1
                POP_TOP

  46   L15:     POP_EXCEPT
                RETURN_CONST             0 (None)

  44   L16:     RERAISE                  0

  --   L17:     COPY                     3
                POP_EXCEPT
                RERAISE                  1
       L18:     CALL_INTRINSIC_1         3 (INTRINSIC_STOPITERATION_ERROR)
                RERAISE                  1
ExceptionTable:
  L1 to L3 -> L18 [0] lasti
  L3 to L4 -> L12 [2]
  L4 to L9 -> L18 [0] lasti
  L10 to L11 -> L14 [0]
  L11 to L13 -> L18 [0] lasti
  L14 to L15 -> L17 [1] lasti
  L15 to L16 -> L18 [0] lasti
  L16 to L17 -> L17 [1] lasti
  L17 to L18 -> L18 [0] lasti


# --- Nested: _run_backup ---

  49            RETURN_GENERATOR
                POP_TOP
        L1:     RESUME                   0

  50            LOAD_GLOBAL              0 (DiscordHTTPClient)
                LOAD_ATTR                2 (create)
                PUSH_NULL
                CALL                     0
                GET_AWAITABLE            0
                LOAD_CONST               0 (None)
        L2:     SEND                     3 (to L5)
        L3:     YIELD_VALUE              1
        L4:     RESUME                   3
                JUMP_BACKWARD_NO_INTERRUPT 5 (to L2)
        L5:     END_SEND
                STORE_FAST               4 (http)

  51    L6:     NOP

  52    L7:     LOAD_FAST                0 (token)
                STORE_FAST               5 (token_value)

  53            LOAD_FAST                3 (scan)
                TO_BOOL
                POP_JUMP_IF_TRUE         7 (to L8)
                LOAD_FAST                5 (token_value)
                TO_BOOL
                POP_JUMP_IF_TRUE        64 (to L20)

  54    L8:     LOAD_GLOBAL              5 (_select_token + NULL)
                LOAD_FAST_LOAD_FAST     66 (http, console)
                CALL                     2
                GET_AWAITABLE            0
                LOAD_CONST               0 (None)
        L9:     SEND                     3 (to L12)
       L10:     YIELD_VALUE              1
       L11:     RESUME                   3
                JUMP_BACKWARD_NO_INTERRUPT 5 (to L9)
       L12:     END_SEND
                STORE_FAST               6 (selection)

  55            LOAD_FAST                6 (selection)
                TO_BOOL
                POP_JUMP_IF_TRUE        26 (to L19)

  56   L13:     NOP

  78   L14:     LOAD_FAST                4 (http)
                LOAD_ATTR                7 (aclose + NULL|self)
                CALL                     0
                GET_AWAITABLE            0
                LOAD_CONST               0 (None)
       L15:     SEND                     3 (to L18)
       L16:     YIELD_VALUE              1
       L17:     RESUME                   3
                JUMP_BACKWARD_NO_INTERRUPT 5 (to L15)
       L18:     END_SEND
                POP_TOP
                RETURN_CONST             0 (None)

  57   L19:     LOAD_FAST                6 (selection)
                LOAD_ATTR                8 (token)
                STORE_FAST               5 (token_value)

  58   L20:     LOAD_FAST                5 (token_value)
                TO_BOOL
                POP_JUMP_IF_TRUE        43 (to L27)

  59            LOAD_FAST                2 (console)
                LOAD_ATTR               11 (error + NULL|self)
                LOAD_CONST               1 ('Token is required to run a backup.')
                CALL                     1
                POP_TOP

  60   L21:     NOP

  78   L22:     LOAD_FAST                4 (http)
                LOAD_ATTR                7 (aclose + NULL|self)
                CALL                     0
                GET_AWAITABLE            0
                LOAD_CONST               0 (None)
       L23:     SEND                     3 (to L26)
       L24:     YIELD_VALUE              1
       L25:     RESUME                   3
                JUMP_BACKWARD_NO_INTERRUPT 5 (to L23)
       L26:     END_SEND
                POP_TOP
                RETURN_CONST             0 (None)

  62   L27:     LOAD_GLOBAL             13 (BackupService + NULL)
                LOAD_FAST_LOAD_FAST     69 (http, token_value)
                LOAD_FAST_LOAD_FAST     18 (config, console)
                LOAD_CONST               2 (('http', 'token', 'config', 'console'))
                CALL_KW                  4
                STORE_FAST               7 (service)

  63            LOAD_FAST                7 (service)
                LOAD_ATTR               15 (run + NULL|self)
                CALL                     0
                GET_AWAITABLE            0
                LOAD_CONST               0 (None)
       L28:     SEND                     3 (to L31)
       L29:     YIELD_VALUE              1
       L30:     RESUME                   3
                JUMP_BACKWARD_NO_INTERRUPT 5 (to L28)
       L31:     END_SEND
                STORE_FAST               8 (result)

  64            LOAD_FAST                7 (service)
                LOAD_ATTR               17 (save + NULL|self)
                LOAD_FAST                8 (result)
                CALL                     1
                GET_AWAITABLE            0
                LOAD_CONST               0 (None)
       L32:     SEND                     3 (to L35)
       L33:     YIELD_VALUE              1
       L34:     RESUME                   3
                JUMP_BACKWARD_NO_INTERRUPT 5 (to L32)
       L35:     END_SEND
                STORE_FAST               9 (path)

  65            LOAD_FAST                2 (console)
                LOAD_ATTR               19 (info + NULL|self)
                LOAD_CONST               3 ('Backup stored at ')
                LOAD_FAST                9 (path)
                FORMAT_SIMPLE
                BUILD_STRING             2
                CALL                     1
                POP_TOP

  66            LOAD_FAST                8 (result)
                LOAD_ATTR               21 (summary + NULL|self)
                CALL                     0
                STORE_FAST              10 (summary)

  67            LOAD_FAST                2 (console)
                LOAD_ATTR               19 (info + NULL|self)

  68            LOAD_CONST               4 ('Guilds: {success}/{total}')
                LOAD_ATTR               22 (format)
                PUSH_NULL
                LOAD_CONST              13 (())
                BUILD_MAP                0
                LOAD_FAST               10 (summary)
                LOAD_CONST               5 ('guilds')
                BINARY_SUBSCR
                DICT_MERGE               1
                CALL_FUNCTION_EX         1

  69            LOAD_CONST               6 (2)

  67            LOAD_CONST               7 (('indent',))
                CALL_KW                  2
                POP_TOP

  71            LOAD_FAST                2 (console)
                LOAD_ATTR               19 (info + NULL|self)

  72            LOAD_CONST               8 ('Group chats: {success}/{total}')
                LOAD_ATTR               22 (format)
                PUSH_NULL
                LOAD_CONST              13 (())
                BUILD_MAP                0
                LOAD_FAST               10 (summary)
                LOAD_CONST               9 ('group_chats')
                BINARY_SUBSCR
                DICT_MERGE               1
                CALL_FUNCTION_EX         1

  73            LOAD_CONST               6 (2)

  71            LOAD_CONST               7 (('indent',))
                CALL_KW                  2
                POP_TOP

  75            LOAD_FAST                2 (console)
                LOAD_ATTR               19 (info + NULL|self)
                LOAD_CONST              10 ('Duration: ')
                LOAD_FAST                8 (result)
                LOAD_ATTR               24 (duration)
                LOAD_CONST              11 ('.1f')
                FORMAT_WITH_SPEC
                LOAD_CONST              12 ('s')
                BUILD_STRING             3
                LOAD_CONST               6 (2)
                LOAD_CONST               7 (('indent',))
                CALL_KW                  2
                POP_TOP

  76            LOAD_FAST                8 (result)

  78   L36:     LOAD_FAST                4 (http)
                LOAD_ATTR                7 (aclose + NULL|self)
                CALL                     0
                GET_AWAITABLE            0
                LOAD_CONST               0 (None)
       L37:     SEND                     3 (to L40)
       L38:     YIELD_VALUE              1
       L39:     RESUME                   3
                JUMP_BACKWARD_NO_INTERRUPT 5 (to L37)
       L40:     END_SEND
                POP_TOP
                RETURN_VALUE

  50   L41:     CLEANUP_THROW
       L42:     EXTENDED_ARG             1
                JUMP_BACKWARD_NO_INTERRUPT 358 (to L5)

  54   L43:     CLEANUP_THROW
       L44:     EXTENDED_ARG             1
                JUMP_BACKWARD_NO_INTERRUPT 325 (to L12)

  78   L45:     CLEANUP_THROW
       L46:     EXTENDED_ARG             1
                JUMP_BACKWARD_NO_INTERRUPT 296 (to L18)
       L47:     CLEANUP_THROW
       L48:     JUMP_BACKWARD_NO_INTERRUPT 236 (to L26)

  63   L49:     CLEANUP_THROW
       L50:     JUMP_BACKWARD_NO_INTERRUPT 203 (to L31)

  64   L51:     CLEANUP_THROW
       L52:     JUMP_BACKWARD_NO_INTERRUPT 180 (to L35)

  78   L53:     CLEANUP_THROW
       L54:     JUMP_BACKWARD_NO_INTERRUPT 20 (to L40)

  --   L55:     PUSH_EXC_INFO

  78            LOAD_FAST                4 (http)
                LOAD_ATTR                7 (aclose + NULL|self)
                CALL                     0
                GET_AWAITABLE            0
                LOAD_CONST               0 (None)
       L56:     SEND                     4 (to L60)
       L57:     YIELD_VALUE              1
       L58:     RESUME                   3
                JUMP_BACKWARD_NO_INTERRUPT 5 (to L56)
       L59:     CLEANUP_THROW
       L60:     END_SEND
                POP_TOP
                RERAISE                  0

  --   L61:     COPY                     3
                POP_EXCEPT
                RERAISE                  1
       L62:     CALL_INTRINSIC_1         3 (INTRINSIC_STOPITERATION_ERROR)
                RERAISE                  1
ExceptionTable:
  L1 to L3 -> L62 [0] lasti
  L3 to L4 -> L41 [2]
  L4 to L6 -> L62 [0] lasti
  L7 to L10 -> L55 [0]
  L10 to L11 -> L43 [2]
  L11 to L13 -> L55 [0]
  L14 to L16 -> L62 [0] lasti
  L16 to L17 -> L45 [2]
  L17 to L19 -> L62 [0] lasti
  L19 to L21 -> L55 [0]
  L22 to L24 -> L62 [0] lasti
  L24 to L25 -> L47 [2]
  L25 to L27 -> L62 [0] lasti
  L27 to L29 -> L55 [0]
  L29 to L30 -> L49 [2]
  L30 to L33 -> L55 [0]
  L33 to L34 -> L51 [2]
  L34 to L36 -> L55 [0]
  L36 to L38 -> L62 [0] lasti
  L38 to L39 -> L53 [3]
  L39 to L42 -> L62 [0] lasti
  L43 to L44 -> L55 [0]
  L45 to L46 -> L62 [0] lasti
  L47 to L48 -> L62 [0] lasti
  L49 to L50 -> L55 [0]
  L51 to L52 -> L55 [0]
  L53 to L54 -> L62 [0] lasti
  L55 to L57 -> L61 [1] lasti
  L57 to L58 -> L59 [4]
  L58 to L61 -> L61 [1] lasti
  L61 to L62 -> L62 [0] lasti


# --- Nested: backup ---

  81           RESUME                   0

  87           LOAD_GLOBAL              1 (_load_config_and_console + NULL)
               CALL                     0
               UNPACK_SEQUENCE          2
               STORE_FAST_STORE_FAST   35 (config, console)

  88           NOP

  89   L1:     LOAD_GLOBAL              2 (asyncio)
               LOAD_ATTR                4 (run)
               PUSH_NULL
               LOAD_GLOBAL              7 (_run_backup + NULL)
               LOAD_FAST_LOAD_FAST      2 (token, config)
               LOAD_FAST_LOAD_FAST     49 (console, scan)
               CALL                     4
               CALL                     1
               POP_TOP
       L2:     RETURN_CONST             3 (None)

  --   L3:     PUSH_EXC_INFO

  90           LOAD_GLOBAL              8 (BackupError)
               CHECK_EXC_MATCH
               POP_JUMP_IF_FALSE       51 (to L6)
               STORE_FAST               4 (exc)

  91   L4:     LOAD_FAST                3 (console)
               LOAD_ATTR               11 (error + NULL|self)
               LOAD_GLOBAL             13 (str + NULL)
               LOAD_FAST                4 (exc)
               CALL                     1
               CALL                     1
               POP_TOP

  92           LOAD_GLOBAL             14 (typer)
               LOAD_ATTR               16 (Exit)
               PUSH_NULL
               LOAD_CONST               1 (1)
               LOAD_CONST               2 (('code',))
               CALL_KW                  1
               RAISE_VARARGS            1

  --   L5:     LOAD_CONST               3 (None)
               STORE_FAST               4 (exc)
               DELETE_FAST              4 (exc)
               RERAISE                  1

  90   L6:     RERAISE                  0

  --   L7:     COPY                     3
               POP_EXCEPT
               RERAISE                  1
ExceptionTable:
  L1 to L2 -> L3 [0]
  L3 to L4 -> L7 [1] lasti
  L4 to L5 -> L5 [1] lasti
  L5 to L7 -> L7 [1] lasti


# --- Nested: _run_restore ---

  95            RETURN_GENERATOR
                POP_TOP
        L1:     RESUME                   0

 103            LOAD_FAST                0 (backup_path)
                LOAD_ATTR                1 (exists + NULL|self)
                CALL                     0
                TO_BOOL
                POP_JUMP_IF_TRUE        21 (to L2)

 104            LOAD_FAST                5 (console)
                LOAD_ATTR                3 (error + NULL|self)
                LOAD_CONST               1 ('Backup file not found: ')
                LOAD_FAST                0 (backup_path)
                FORMAT_SIMPLE
                BUILD_STRING             2
                CALL                     1
                POP_TOP

 105            RETURN_CONST             0 (None)

 106    L2:     LOAD_GLOBAL              4 (json)
                LOAD_ATTR                6 (loads)
                PUSH_NULL
                LOAD_FAST                0 (backup_path)
                LOAD_ATTR                9 (read_text + NULL|self)
                LOAD_CONST               2 ('utf-8')
                LOAD_CONST               3 (('encoding',))
                CALL_KW                  1
                CALL                     1
                STORE_FAST               6 (data)

 107            LOAD_GLOBAL             10 (DiscordHTTPClient)
                LOAD_ATTR               12 (create)
                PUSH_NULL
                CALL                     0
                GET_AWAITABLE            0
                LOAD_CONST               0 (None)
        L3:     SEND                     3 (to L6)
        L4:     YIELD_VALUE              1
        L5:     RESUME                   3
                JUMP_BACKWARD_NO_INTERRUPT 5 (to L3)
        L6:     END_SEND
                STORE_FAST               7 (http)

 108    L7:     NOP

 109    L8:     LOAD_GLOBAL             15 (RestoreService + NULL)
                LOAD_FAST_LOAD_FAST    113 (http, token)
                LOAD_FAST_LOAD_FAST     38 (bot_token, data)
                LOAD_FAST                5 (console)
                LOAD_CONST               4 (('http', 'token', 'bot_token', 'backup', 'console'))
                CALL_KW                  5
                STORE_FAST               8 (service)

 110            LOAD_FAST                8 (service)
                LOAD_ATTR               17 (run + NULL|self)

 111            LOAD_FAST                3 (restore_folders)

 112            LOAD_FAST                6 (data)
                LOAD_ATTR               19 (get + NULL|self)
                LOAD_CONST               5 ('version')
                CALL                     1

 113            LOAD_FAST                4 (allow_version_mismatch)

 110            LOAD_CONST               6 (('restore_folders', 'expected_version', 'allow_mismatch'))
                CALL_KW                  3
                GET_AWAITABLE            0
                LOAD_CONST               0 (None)
        L9:     SEND                     3 (to L12)
       L10:     YIELD_VALUE              1
       L11:     RESUME                   3
                JUMP_BACKWARD_NO_INTERRUPT 5 (to L9)
       L12:     END_SEND
                STORE_FAST               9 (summary)

 115            LOAD_FAST                5 (console)
                LOAD_ATTR               21 (success + NULL|self)
                LOAD_CONST               7 ('Restore complete')
                CALL                     1
                POP_TOP

 116            LOAD_FAST                5 (console)
                LOAD_ATTR               23 (info + NULL|self)
                LOAD_CONST               8 ('Backup guild id: ')
                LOAD_FAST                9 (summary)
                LOAD_ATTR               24 (guild_id)
                FORMAT_SIMPLE
                BUILD_STRING             2
                CALL                     1
                POP_TOP

 117            LOAD_FAST                5 (console)
                LOAD_ATTR               23 (info + NULL|self)
                LOAD_CONST               9 ('Favourite GIFs: ')
                LOAD_FAST                9 (summary)
                LOAD_ATTR               26 (favourite_gifs_status)
                FORMAT_SIMPLE
                BUILD_STRING             2
                CALL                     1
                POP_TOP

 118            LOAD_FAST                5 (console)
                LOAD_ATTR               23 (info + NULL|self)

 119            LOAD_FAST                9 (summary)
                LOAD_ATTR               28 (folder_restore_attempted)
                TO_BOOL
                POP_JUMP_IF_FALSE        2 (to L13)
                LOAD_CONST              10 ('Folders restored')
                JUMP_FORWARD             1 (to L14)
       L13:     LOAD_CONST              11 ('Folders skipped')

 120   L14:     LOAD_CONST              12 (2)

 118            LOAD_CONST              13 (('indent',))
                CALL_KW                  2
                POP_TOP

 122            LOAD_FAST                5 (console)
                LOAD_ATTR               23 (info + NULL|self)
                LOAD_CONST              14 ('Duration: ')
                LOAD_FAST                9 (summary)
                LOAD_ATTR               30 (duration)
                LOAD_CONST              15 ('.1f')
                FORMAT_WITH_SPEC
                LOAD_CONST              16 ('s')
                BUILD_STRING             3
                LOAD_CONST              12 (2)
                LOAD_CONST              13 (('indent',))
                CALL_KW                  2
                POP_TOP

 124   L15:     LOAD_FAST                7 (http)
                LOAD_ATTR               33 (aclose + NULL|self)
                CALL                     0
                GET_AWAITABLE            0
                LOAD_CONST               0 (None)
       L16:     SEND                     3 (to L19)
       L17:     YIELD_VALUE              1
       L18:     RESUME                   3
                JUMP_BACKWARD_NO_INTERRUPT 5 (to L16)
       L19:     END_SEND
                POP_TOP
                RETURN_CONST             0 (None)

 107   L20:     CLEANUP_THROW
       L21:     JUMP_BACKWARD_NO_INTERRUPT 224 (to L6)

 110   L22:     CLEANUP_THROW
       L23:     JUMP_BACKWARD_NO_INTERRUPT 174 (to L12)

 124   L24:     CLEANUP_THROW
       L25:     JUMP_BACKWARD_NO_INTERRUPT 9 (to L19)

  --   L26:     PUSH_EXC_INFO

 124            LOAD_FAST                7 (http)
                LOAD_ATTR               33 (aclose + NULL|self)
                CALL                     0
                GET_AWAITABLE            0
                LOAD_CONST               0 (None)
       L27:     SEND                     4 (to L31)
       L28:     YIELD_VALUE              1
       L29:     RESUME                   3
                JUMP_BACKWARD_NO_INTERRUPT 5 (to L27)
       L30:     CLEANUP_THROW
       L31:     END_SEND
                POP_TOP
                RERAISE                  0

  --   L32:     COPY                     3
                POP_EXCEPT
                RERAISE                  1
       L33:     CALL_INTRINSIC_1         3 (INTRINSIC_STOPITERATION_ERROR)
                RERAISE                  1
ExceptionTable:
  L1 to L4 -> L33 [0] lasti
  L4 to L5 -> L20 [2]
  L5 to L7 -> L33 [0] lasti
  L8 to L10 -> L26 [0]
  L10 to L11 -> L22 [2]
  L11 to L15 -> L26 [0]
  L15 to L17 -> L33 [0] lasti
  L17 to L18 -> L24 [2]
  L18 to L21 -> L33 [0] lasti
  L22 to L23 -> L26 [0]
  L24 to L25 -> L33 [0] lasti
  L26 to L28 -> L32 [1] lasti
  L28 to L29 -> L30 [4]
  L29 to L32 -> L32 [1] lasti
  L32 to L33 -> L33 [0] lasti


# --- Nested: restore ---

 127           RESUME                   0

 136           LOAD_GLOBAL              1 (_load_config_and_console + NULL)
               CALL                     0
               UNPACK_SEQUENCE          2
               STORE_FAST_STORE_FAST   86 (_, console)

 137           NOP

 138   L1:     LOAD_GLOBAL              2 (asyncio)
               LOAD_ATTR                4 (run)
               PUSH_NULL

 139           LOAD_GLOBAL              7 (_run_restore + NULL)

 140           LOAD_FAST                0 (backup_file)

 141           LOAD_FAST                1 (token)

 142           LOAD_FAST                2 (bot_token)

 143           LOAD_FAST                3 (restore_folders)

 144           LOAD_FAST                4 (allow_version_mismatch)

 145           LOAD_FAST                6 (console)

 139           CALL                     6

 138           CALL                     1
               POP_TOP
       L2:     RETURN_CONST             3 (None)

  --   L3:     PUSH_EXC_INFO

 148           LOAD_GLOBAL              8 (RestoreError)
               CHECK_EXC_MATCH
               POP_JUMP_IF_FALSE       51 (to L6)
               STORE_FAST               7 (exc)

 149   L4:     LOAD_FAST                6 (console)
               LOAD_ATTR               11 (error + NULL|self)
               LOAD_GLOBAL             13 (str + NULL)
               LOAD_FAST                7 (exc)
               CALL                     1
               CALL                     1
               POP_TOP

 150           LOAD_GLOBAL             14 (typer)
               LOAD_ATTR               16 (Exit)
               PUSH_NULL
               LOAD_CONST               1 (1)
               LOAD_CONST               2 (('code',))
               CALL_KW                  1
               RAISE_VARARGS            1

  --   L5:     LOAD_CONST               3 (None)
               STORE_FAST               7 (exc)
               DELETE_FAST              7 (exc)
               RERAISE                  1

 148   L6:     RERAISE                  0

  --   L7:     COPY                     3
               POP_EXCEPT
               RERAISE                  1
ExceptionTable:
  L1 to L2 -> L3 [0]
  L3 to L4 -> L7 [1] lasti
  L4 to L5 -> L5 [1] lasti
  L5 to L7 -> L7 [1] lasti


# --- Nested: auto_backup ---

  --           MAKE_CELL                0 (account_id)
               MAKE_CELL                4 (config)
               MAKE_CELL                5 (console)

 153           RESUME                   0

 159           LOAD_GLOBAL              1 (_load_config_and_console + NULL)
               CALL                     0
               UNPACK_SEQUENCE          2
               STORE_DEREF              4 (config)
               STORE_DEREF              5 (console)

 160           LOAD_FAST                1 (working_dir)
               LOAD_ATTR                3 (resolve + NULL|self)
               CALL                     0
               STORE_FAST               1 (working_dir)

 161           LOAD_FAST                1 (working_dir)
               LOAD_ATTR                5 (exists + NULL|self)
               CALL                     0
               TO_BOOL
               POP_JUMP_IF_FALSE       22 (to L1)

 162           LOAD_CONST               1 (0)
               LOAD_CONST               2 (None)
               IMPORT_NAME              3 (os)
               STORE_FAST               2 (os)

 164           LOAD_FAST                2 (os)
               LOAD_ATTR                9 (chdir + NULL|self)
               LOAD_FAST                1 (working_dir)
               CALL                     1
               POP_TOP
               JUMP_FORWARD            20 (to L2)

 166   L1:     LOAD_DEREF               5 (console)
               LOAD_ATTR               11 (warn + NULL|self)
               LOAD_CONST               3 ('Working directory not found: ')
               LOAD_FAST                1 (working_dir)
               FORMAT_SIMPLE
               BUILD_STRING             2
               CALL                     1
               POP_TOP

 167   L2:     LOAD_CONST               5 (('return', 'None'))
               LOAD_FAST                0 (account_id)
               LOAD_FAST                4 (config)
               LOAD_FAST                5 (console)
               BUILD_TUPLE              3
               LOAD_CONST               4 (<code object runner at 0x000001EE5C72F470, file "discord_backup\cli.py", line 167>)
               MAKE_FUNCTION
               SET_FUNCTION_ATTRIBUTE   8 (closure)
               SET_FUNCTION_ATTRIBUTE   4 (annotations)
               STORE_FAST               3 (runner)

 186           LOAD_GLOBAL             12 (asyncio)
               LOAD_ATTR               14 (run)
               PUSH_NULL
               LOAD_FAST                3 (runner)
               PUSH_NULL
               CALL                     0
               CALL                     1
               POP_TOP
               RETURN_CONST             2 (None)

Disassembly of <code object runner at 0x000001EE5C72F470, file "discord_backup\cli.py", line 167>:
  --            COPY_FREE_VARS           3

 167            RETURN_GENERATOR
                POP_TOP
        L1:     RESUME                   0

 168            LOAD_GLOBAL              0 (DiscordHTTPClient)
                LOAD_ATTR                2 (create)
                PUSH_NULL
                CALL                     0
                GET_AWAITABLE            0
                LOAD_CONST               0 (None)
        L2:     SEND                     3 (to L5)
        L3:     YIELD_VALUE              1
        L4:     RESUME                   3
                JUMP_BACKWARD_NO_INTERRUPT 5 (to L2)
        L5:     END_SEND
                STORE_FAST               0 (http)

 169    L6:     NOP

 170    L7:     LOAD_GLOBAL              5 (discover_tokens + NULL)
                LOAD_FAST                0 (http)
                CALL                     1
                GET_AWAITABLE            0
                LOAD_CONST               0 (None)
        L8:     SEND                     3 (to L11)
        L9:     YIELD_VALUE              1
       L10:     RESUME                   3
                JUMP_BACKWARD_NO_INTERRUPT 5 (to L8)
       L11:     END_SEND
                STORE_FAST               1 (tokens)

 171            LOAD_CONST               0 (None)
                STORE_FAST               2 (token_value)

 172            LOAD_FAST                1 (tokens)
                GET_ITER
       L12:     FOR_ITER                63 (to L15)
                STORE_FAST               3 (item)

 173            LOAD_FAST                3 (item)
                LOAD_ATTR                6 (user_id)
                LOAD_DEREF               6 (account_id)
                COMPARE_OP              88 (bool(==))
       L13:     POP_JUMP_IF_TRUE         2 (to L14)
                JUMP_BACKWARD           21 (to L12)

 174   L14:     LOAD_FAST                3 (item)
                LOAD_ATTR                8 (token)
                STORE_FAST               2 (token_value)

 175            LOAD_DEREF               8 (console)
                LOAD_ATTR               11 (success + NULL|self)
                LOAD_CONST               1 ('Found token for ')
                LOAD_FAST                3 (item)
                LOAD_ATTR               12 (user_tag)
                FORMAT_SIMPLE
                BUILD_STRING             2
                CALL                     1
                POP_TOP

 176            POP_TOP
                JUMP_FORWARD             2 (to L16)

 172   L15:     END_FOR
                POP_TOP

 177   L16:     LOAD_FAST                2 (token_value)
                TO_BOOL
                POP_JUMP_IF_TRUE        43 (to L23)

 178            LOAD_DEREF               8 (console)
                LOAD_ATTR               15 (error + NULL|self)
                LOAD_CONST               2 ('No matching token found for auto-backup')
                CALL                     1
                POP_TOP

 179   L17:     NOP

 185   L18:     LOAD_FAST                0 (http)
                LOAD_ATTR               17 (aclose + NULL|self)
                CALL                     0
                GET_AWAITABLE            0
                LOAD_CONST               0 (None)
       L19:     SEND                     3 (to L22)
       L20:     YIELD_VALUE              1
       L21:     RESUME                   3
                JUMP_BACKWARD_NO_INTERRUPT 5 (to L19)
       L22:     END_SEND
                POP_TOP
                RETURN_CONST             0 (None)

 180   L23:     LOAD_GLOBAL             19 (BackupService + NULL)
                LOAD_FAST_LOAD_FAST      2 (http, token_value)
                LOAD_DEREF               7 (config)
                LOAD_DEREF               8 (console)
                LOAD_CONST               3 (('http', 'token', 'config', 'console'))
                CALL_KW                  4
                STORE_FAST               4 (service)

 181            LOAD_FAST                4 (service)
                LOAD_ATTR               21 (run + NULL|self)
                CALL                     0
                GET_AWAITABLE            0
                LOAD_CONST               0 (None)
       L24:     SEND                     3 (to L27)
       L25:     YIELD_VALUE              1
       L26:     RESUME                   3
                JUMP_BACKWARD_NO_INTERRUPT 5 (to L24)
       L27:     END_SEND
                STORE_FAST               5 (result)

 182            LOAD_FAST                4 (service)
                LOAD_ATTR               23 (save + NULL|self)
                LOAD_FAST                5 (result)
                CALL                     1
                GET_AWAITABLE            0
                LOAD_CONST               0 (None)
       L28:     SEND                     3 (to L31)
       L29:     YIELD_VALUE              1
       L30:     RESUME                   3
                JUMP_BACKWARD_NO_INTERRUPT 5 (to L28)
       L31:     END_SEND
                POP_TOP

 183            LOAD_DEREF               8 (console)
                LOAD_ATTR               11 (success + NULL|self)
                LOAD_CONST               4 ('Auto-backup finished')
                CALL                     1
                POP_TOP

 185   L32:     LOAD_FAST                0 (http)
                LOAD_ATTR               17 (aclose + NULL|self)
                CALL                     0
                GET_AWAITABLE            0
                LOAD_CONST               0 (None)
       L33:     SEND                     3 (to L36)
       L34:     YIELD_VALUE              1
       L35:     RESUME                   3
                JUMP_BACKWARD_NO_INTERRUPT 5 (to L33)
       L36:     END_SEND
                POP_TOP
                RETURN_CONST             0 (None)

 168   L37:     CLEANUP_THROW
       L38:     JUMP_BACKWARD_NO_INTERRUPT 247 (to L5)

 170   L39:     CLEANUP_THROW
       L40:     JUMP_BACKWARD_NO_INTERRUPT 229 (to L11)

 185   L41:     CLEANUP_THROW
       L42:     JUMP_BACKWARD_NO_INTERRUPT 111 (to L22)

 181   L43:     CLEANUP_THROW
       L44:     JUMP_BACKWARD_NO_INTERRUPT 77 (to L27)

 182   L45:     CLEANUP_THROW
       L46:     JUMP_BACKWARD_NO_INTERRUPT 54 (to L31)

 185   L47:     CLEANUP_THROW
       L48:     JUMP_BACKWARD_NO_INTERRUPT 15 (to L36)

  --   L49:     PUSH_EXC_INFO

 185            LOAD_FAST                0 (http)
                LOAD_ATTR               17 (aclose + NULL|self)
                CALL                     0
                GET_AWAITABLE            0
                LOAD_CONST               0 (None)
       L50:     SEND                     4 (to L54)
       L51:     YIELD_VALUE              1
       L52:     RESUME                   3
                JUMP_BACKWARD_NO_INTERRUPT 5 (to L50)
       L53:     CLEANUP_THROW
       L54:     END_SEND
                POP_TOP
                RERAISE                  0

  --   L55:     COPY                     3
                POP_EXCEPT
                RERAISE                  1
       L56:     CALL_INTRINSIC_1         3 (INTRINSIC_STOPITERATION_ERROR)
                RERAISE                  1
ExceptionTable:
  L1 to L3 -> L56 [0] lasti
  L3 to L4 -> L37 [2]
  L4 to L6 -> L56 [0] lasti
  L7 to L9 -> L49 [0]
  L9 to L10 -> L39 [2]
  L10 to L13 -> L49 [0]
  L14 to L17 -> L49 [0]
  L18 to L20 -> L56 [0] lasti
  L20 to L21 -> L41 [2]
  L21 to L23 -> L56 [0] lasti
  L23 to L25 -> L49 [0]
  L25 to L26 -> L43 [2]
  L26 to L29 -> L49 [0]
  L29 to L30 -> L45 [2]
  L30 to L32 -> L49 [0]
  L32 to L34 -> L56 [0] lasti
  L34 to L35 -> L47 [2]
  L35 to L38 -> L56 [0] lasti
  L39 to L40 -> L49 [0]
  L41 to L42 -> L56 [0] lasti
  L43 to L44 -> L49 [0]
  L45 to L46 -> L49 [0]
  L47 to L48 -> L56 [0] lasti
  L49 to L51 -> L55 [1] lasti
  L51 to L52 -> L53 [4]
  L52 to L55 -> L55 [1] lasti
  L55 to L56 -> L56 [0] lasti


# --- Nested: startup_add ---

  --           MAKE_CELL                0 (scan)
               MAKE_CELL                3 (console)

 189           RESUME                   0

 194           LOAD_GLOBAL              1 (_load_config_and_console + NULL)
               CALL                     0
               UNPACK_SEQUENCE          2
               STORE_FAST               1 (config)
               STORE_DEREF              3 (console)

 196           LOAD_CONST               3 (('return', 'None'))
               LOAD_FAST                3 (console)
               LOAD_FAST                0 (scan)
               BUILD_TUPLE              2
               LOAD_CONST               1 (<code object runner at 0x000001EE5C729840, file "discord_backup\cli.py", line 196>)
               MAKE_FUNCTION
               SET_FUNCTION_ATTRIBUTE   8 (closure)
               SET_FUNCTION_ATTRIBUTE   4 (annotations)
               STORE_FAST               2 (runner)

 219           LOAD_GLOBAL              2 (asyncio)
               LOAD_ATTR                4 (run)
               PUSH_NULL
               LOAD_FAST                2 (runner)
               PUSH_NULL
               CALL                     0
               CALL                     1
               POP_TOP
               RETURN_CONST             2 (None)

Disassembly of <code object runner at 0x000001EE5C729840, file "discord_backup\cli.py", line 196>:
  --            COPY_FREE_VARS           2

 196            RETURN_GENERATOR
                POP_TOP
        L1:     RESUME                   0

 197            LOAD_GLOBAL              0 (DiscordHTTPClient)
                LOAD_ATTR                2 (create)
                PUSH_NULL
                CALL                     0
                GET_AWAITABLE            0
                LOAD_CONST               0 (None)
        L2:     SEND                     3 (to L5)
        L3:     YIELD_VALUE              1
        L4:     RESUME                   3
                JUMP_BACKWARD_NO_INTERRUPT 5 (to L2)
        L5:     END_SEND
                STORE_FAST               0 (http)

 198    L6:     NOP

 199    L7:     LOAD_CONST               0 (None)
                STORE_FAST               1 (selection)

 200            LOAD_DEREF               7 (scan)
                TO_BOOL
                POP_JUMP_IF_FALSE       20 (to L12)

 201            LOAD_GLOBAL              5 (_select_token + NULL)
                LOAD_FAST                0 (http)
                LOAD_DEREF               6 (console)
                CALL                     2
                GET_AWAITABLE            0
                LOAD_CONST               0 (None)
        L8:     SEND                     3 (to L11)
        L9:     YIELD_VALUE              1
       L10:     RESUME                   3
                JUMP_BACKWARD_NO_INTERRUPT 5 (to L8)
       L11:     END_SEND
                STORE_FAST               1 (selection)

 202   L12:     LOAD_FAST                1 (selection)
                TO_BOOL
                POP_JUMP_IF_TRUE       103 (to L20)

 203            LOAD_GLOBAL              6 (typer)
                LOAD_ATTR                8 (prompt)
                PUSH_NULL
                LOAD_CONST               1 ('Enter user token for auto-backup')
                LOAD_CONST               2 (True)
                LOAD_CONST               3 (('hide_input',))
                CALL_KW                  2
                STORE_FAST               2 (token_input)

 204            LOAD_FAST                2 (token_input)
                TO_BOOL
                POP_JUMP_IF_TRUE        43 (to L19)

 205            LOAD_DEREF               6 (console)
                LOAD_ATTR               11 (error + NULL|self)
                LOAD_CONST               4 ('Token required for auto-backup')
                CALL                     1
                POP_TOP

 206   L13:     NOP

 217   L14:     LOAD_FAST                0 (http)
                LOAD_ATTR               13 (aclose + NULL|self)
                CALL                     0
                GET_AWAITABLE            0
                LOAD_CONST               0 (None)
       L15:     SEND                     3 (to L18)
       L16:     YIELD_VALUE              1
       L17:     RESUME                   3
                JUMP_BACKWARD_NO_INTERRUPT 5 (to L15)
       L18:     END_SEND
                POP_TOP
                RETURN_CONST             0 (None)

 207   L19:     LOAD_GLOBAL             15 (DiscoveredToken + NULL)
                LOAD_FAST                2 (token_input)
                LOAD_CONST               5 ('manual')
                LOAD_GLOBAL              6 (typer)
                LOAD_ATTR                8 (prompt)
                PUSH_NULL
                LOAD_CONST               6 ('Enter account id')
                CALL                     1
                LOAD_CONST               5 ('manual')
                LOAD_CONST               7 (('token', 'user_tag', 'user_id', 'source'))
                CALL_KW                  4
                STORE_FAST               1 (selection)

 209   L20:     LOAD_GLOBAL             17 (Path + NULL)
                LOAD_GLOBAL             19 (getattr + NULL)
                LOAD_GLOBAL             20 (sys)
                LOAD_CONST               8 ('frozen')
                LOAD_CONST               9 (False)
                CALL                     3
                TO_BOOL
                POP_JUMP_IF_FALSE       16 (to L21)
                LOAD_GLOBAL             20 (sys)
                LOAD_ATTR               22 (executable)
                JUMP_FORWARD            51 (to L22)
       L21:     LOAD_GLOBAL             17 (Path + NULL)
                LOAD_GLOBAL             24 (__file__)
                CALL                     1
                LOAD_ATTR               27 (resolve + NULL|self)
                CALL                     0
                LOAD_ATTR               28 (parent)
                LOAD_ATTR               28 (parent)
                LOAD_CONST              10 ('main.py')
                BINARY_OP               11 (/)
       L22:     CALL                     1
                STORE_FAST               3 (executable)

 210            LOAD_FAST                3 (executable)
                LOAD_ATTR               30 (suffix)
                LOAD_CONST              11 ('.py')
                COMPARE_OP              88 (bool(==))
                POP_JUMP_IF_FALSE       19 (to L23)

 211            LOAD_CONST              12 ('cmd.exe /C python "')
                LOAD_FAST                3 (executable)
                FORMAT_SIMPLE
                LOAD_CONST              13 ('" auto-backup --account-id ')
                LOAD_FAST                1 (selection)
                LOAD_ATTR               32 (user_id)
                FORMAT_SIMPLE
                BUILD_STRING             4
                STORE_FAST               4 (command)
                JUMP_FORWARD            18 (to L24)

 213   L23:     LOAD_CONST              14 ('"')
                LOAD_FAST                3 (executable)
                FORMAT_SIMPLE
                LOAD_CONST              13 ('" auto-backup --account-id ')
                LOAD_FAST                1 (selection)
                LOAD_ATTR               32 (user_id)
                FORMAT_SIMPLE
                BUILD_STRING             4
                STORE_FAST               4 (command)

 214   L24:     LOAD_GLOBAL             35 (write_startup_script + NULL)
                LOAD_FAST                4 (command)
                LOAD_GLOBAL             16 (Path)
                LOAD_ATTR               36 (cwd)
                PUSH_NULL
                CALL                     0
                CALL                     2
                STORE_FAST               5 (script_path)

 215            LOAD_DEREF               6 (console)
                LOAD_ATTR               39 (success + NULL|self)
                LOAD_CONST              15 ('Startup script written to ')
                LOAD_FAST                5 (script_path)
                FORMAT_SIMPLE
                BUILD_STRING             2
                CALL                     1
                POP_TOP

 217   L25:     LOAD_FAST                0 (http)
                LOAD_ATTR               13 (aclose + NULL|self)
                CALL                     0
                GET_AWAITABLE            0
                LOAD_CONST               0 (None)
       L26:     SEND                     3 (to L29)
       L27:     YIELD_VALUE              1
       L28:     RESUME                   3
                JUMP_BACKWARD_NO_INTERRUPT 5 (to L26)
       L29:     END_SEND
                POP_TOP
                RETURN_CONST             0 (None)

 197   L30:     CLEANUP_THROW
       L31:     EXTENDED_ARG             1
                JUMP_BACKWARD_NO_INTERRUPT 373 (to L5)

 201   L32:     CLEANUP_THROW
       L33:     EXTENDED_ARG             1
                JUMP_BACKWARD_NO_INTERRUPT 346 (to L11)

 217   L34:     CLEANUP_THROW
       L35:     EXTENDED_ARG             1
                JUMP_BACKWARD_NO_INTERRUPT 272 (to L18)
       L36:     CLEANUP_THROW
       L37:     JUMP_BACKWARD_NO_INTERRUPT 14 (to L29)

  --   L38:     PUSH_EXC_INFO

 217            LOAD_FAST                0 (http)
                LOAD_ATTR               13 (aclose + NULL|self)
                CALL                     0
                GET_AWAITABLE            0
                LOAD_CONST               0 (None)
       L39:     SEND                     4 (to L43)
       L40:     YIELD_VALUE              1
       L41:     RESUME                   3
                JUMP_BACKWARD_NO_INTERRUPT 5 (to L39)
       L42:     CLEANUP_THROW
       L43:     END_SEND
                POP_TOP
                RERAISE                  0

  --   L44:     COPY                     3
                POP_EXCEPT
                RERAISE                  1
       L45:     CALL_INTRINSIC_1         3 (INTRINSIC_STOPITERATION_ERROR)
                RERAISE                  1
ExceptionTable:
  L1 to L3 -> L45 [0] lasti
  L3 to L4 -> L30 [2]
  L4 to L6 -> L45 [0] lasti
  L7 to L9 -> L38 [0]
  L9 to L10 -> L32 [2]
  L10 to L13 -> L38 [0]
  L14 to L16 -> L45 [0] lasti
  L16 to L17 -> L34 [2]
  L17 to L19 -> L45 [0] lasti
  L19 to L25 -> L38 [0]
  L25 to L27 -> L45 [0] lasti
  L27 to L28 -> L36 [2]
  L28 to L31 -> L45 [0] lasti
  L32 to L33 -> L38 [0]
  L34 to L35 -> L45 [0] lasti
  L36 to L37 -> L45 [0] lasti
  L38 to L40 -> L44 [1] lasti
  L40 to L41 -> L42 [4]
  L41 to L44 -> L44 [1] lasti
  L44 to L45 -> L45 [0] lasti


# --- Nested: startup_remove ---

222           RESUME                   0

225           LOAD_GLOBAL              1 (remove_startup_script + NULL)
              CALL                     0
              TO_BOOL
              POP_JUMP_IF_FALSE       23 (to L1)

226           LOAD_GLOBAL              2 (typer)
              LOAD_ATTR                4 (echo)
              PUSH_NULL
              LOAD_CONST               1 ('Startup script removed')
              CALL                     1
              POP_TOP
              RETURN_CONST             3 (None)

228   L1:     LOAD_GLOBAL              2 (typer)
              LOAD_ATTR                4 (echo)
              PUSH_NULL
              LOAD_CONST               2 ('No startup script found')
              CALL                     1
              POP_TOP
              RETURN_CONST             3 (None)


# --- Nested: tokens ---

  --           MAKE_CELL                2 (console)

 231           RESUME                   0

 234           LOAD_GLOBAL              1 (_load_config_and_console + NULL)
               CALL                     0
               UNPACK_SEQUENCE          2
               STORE_FAST               0 (_)
               STORE_DEREF              2 (console)

 236           LOAD_CONST               3 (('return', 'None'))
               LOAD_FAST                2 (console)
               BUILD_TUPLE              1
               LOAD_CONST               1 (<code object runner at 0x000001EE5E624C00, file "discord_backup\cli.py", line 236>)
               MAKE_FUNCTION
               SET_FUNCTION_ATTRIBUTE   8 (closure)
               SET_FUNCTION_ATTRIBUTE   4 (annotations)
               STORE_FAST               1 (runner)

 248           LOAD_GLOBAL              2 (asyncio)
               LOAD_ATTR                4 (run)
               PUSH_NULL
               LOAD_FAST                1 (runner)
               PUSH_NULL
               CALL                     0
               CALL                     1
               POP_TOP
               RETURN_CONST             2 (None)

Disassembly of <code object runner at 0x000001EE5E624C00, file "discord_backup\cli.py", line 236>:
  --            COPY_FREE_VARS           1

 236            RETURN_GENERATOR
                POP_TOP
        L1:     RESUME                   0

 237            LOAD_GLOBAL              0 (DiscordHTTPClient)
                LOAD_ATTR                2 (create)
                PUSH_NULL
                CALL                     0
                GET_AWAITABLE            0
                LOAD_CONST               0 (None)
        L2:     SEND                     3 (to L5)
        L3:     YIELD_VALUE              1
        L4:     RESUME                   3
                JUMP_BACKWARD_NO_INTERRUPT 5 (to L2)
        L5:     END_SEND
                STORE_FAST               0 (http)

 238    L6:     NOP

 239    L7:     LOAD_GLOBAL              5 (discover_tokens + NULL)
                LOAD_FAST                0 (http)
                CALL                     1
                GET_AWAITABLE            0
                LOAD_CONST               0 (None)
        L8:     SEND                     3 (to L11)
        L9:     YIELD_VALUE              1
       L10:     RESUME                   3
                JUMP_BACKWARD_NO_INTERRUPT 5 (to L8)
       L11:     END_SEND
                STORE_FAST               1 (tokens)

 240            LOAD_FAST                1 (tokens)
                TO_BOOL
                POP_JUMP_IF_TRUE        43 (to L18)

 241            LOAD_DEREF               3 (console)
                LOAD_ATTR                7 (warn + NULL|self)
                LOAD_CONST               1 ('No tokens discovered')
                CALL                     1
                POP_TOP

 242   L12:     NOP

 246   L13:     LOAD_FAST                0 (http)
                LOAD_ATTR                9 (aclose + NULL|self)
                CALL                     0
                GET_AWAITABLE            0
                LOAD_CONST               0 (None)
       L14:     SEND                     3 (to L17)
       L15:     YIELD_VALUE              1
       L16:     RESUME                   3
                JUMP_BACKWARD_NO_INTERRUPT 5 (to L14)
       L17:     END_SEND
                POP_TOP
                RETURN_CONST             0 (None)

 243   L18:     LOAD_FAST                1 (tokens)
                GET_ITER
       L19:     FOR_ITER                58 (to L20)
                STORE_FAST               2 (item)

 244            LOAD_DEREF               3 (console)
                LOAD_ATTR               11 (info + NULL|self)
                LOAD_FAST                2 (item)
                LOAD_ATTR               12 (user_tag)
                FORMAT_SIMPLE
                LOAD_CONST               2 (' (')
                LOAD_FAST                2 (item)
                LOAD_ATTR               14 (user_id)
                FORMAT_SIMPLE
                LOAD_CONST               3 (') - ')
                LOAD_FAST                2 (item)
                LOAD_ATTR               16 (source)
                FORMAT_SIMPLE
                BUILD_STRING             5
                CALL                     1
                POP_TOP
                JUMP_BACKWARD           60 (to L19)

 243   L20:     END_FOR
                POP_TOP

 246   L21:     LOAD_FAST                0 (http)
                LOAD_ATTR                9 (aclose + NULL|self)
                CALL                     0
                GET_AWAITABLE            0
                LOAD_CONST               0 (None)
       L22:     SEND                     3 (to L25)
       L23:     YIELD_VALUE              1
       L24:     RESUME                   3
                JUMP_BACKWARD_NO_INTERRUPT 5 (to L22)
       L25:     END_SEND
                POP_TOP
                RETURN_CONST             0 (None)

 237   L26:     CLEANUP_THROW
       L27:     JUMP_BACKWARD_NO_INTERRUPT 163 (to L5)

 239   L28:     CLEANUP_THROW
       L29:     JUMP_BACKWARD_NO_INTERRUPT 145 (to L11)

 246   L30:     CLEANUP_THROW
       L31:     JUMP_BACKWARD_NO_INTERRUPT 98 (to L17)
       L32:     CLEANUP_THROW
       L33:     JUMP_BACKWARD_NO_INTERRUPT 11 (to L25)

  --   L34:     PUSH_EXC_INFO

 246            LOAD_FAST                0 (http)
                LOAD_ATTR                9 (aclose + NULL|self)
                CALL                     0
                GET_AWAITABLE            0
                LOAD_CONST               0 (None)
       L35:     SEND                     4 (to L39)
       L36:     YIELD_VALUE              1
       L37:     RESUME                   3
                JUMP_BACKWARD_NO_INTERRUPT 5 (to L35)
       L38:     CLEANUP_THROW
       L39:     END_SEND
                POP_TOP
                RERAISE                  0

  --   L40:     COPY                     3
                POP_EXCEPT
                RERAISE                  1
       L41:     CALL_INTRINSIC_1         3 (INTRINSIC_STOPITERATION_ERROR)
                RERAISE                  1
ExceptionTable:
  L1 to L3 -> L41 [0] lasti
  L3 to L4 -> L26 [2]
  L4 to L6 -> L41 [0] lasti
  L7 to L9 -> L34 [0]
  L9 to L10 -> L28 [2]
  L10 to L12 -> L34 [0]
  L13 to L15 -> L41 [0] lasti
  L15 to L16 -> L30 [2]
  L16 to L18 -> L41 [0] lasti
  L18 to L21 -> L34 [0]
  L21 to L23 -> L41 [0] lasti
  L23 to L24 -> L32 [2]
  L24 to L27 -> L41 [0] lasti
  L28 to L29 -> L34 [0]
  L30 to L31 -> L41 [0] lasti
  L32 to L33 -> L41 [0] lasti
  L34 to L36 -> L40 [1] lasti
  L36 to L37 -> L38 [4]
  L37 to L40 -> L40 [1] lasti
  L40 to L41 -> L41 [0] lasti


# --- Nested: run ---

251           RESUME                   0

252           LOAD_GLOBAL              1 (app + NULL)
              CALL                     0
              POP_TOP
              RETURN_CONST             0 (None)
