# Reconstructed from: C:\Users\koufa\Desktop\Apps\discord backup\Unpack\DiscordBackup.exe_extracted\PYZ.pyz_extracted\discord_backup\tui.pyc
# Code object: <module>, filename: discord_backup\tui.py

# const[0]: 0# const[2]: None# const[7]: 1# const[17]: '\\x1b\\[[0-9;]*m'# nested code: _project_root (filename: discord_backup\tui.py)  # const[0]: None  # const[1]: 'frozen'  # const[2]: False  # names: ('getattr', 'sys', 'Path', 'executable', 'resolve', 'parent', '__file__')# nested code: _strip_ansi (filename: discord_backup\tui.py)  # const[0]: None  # names: ('ANSI_RE', 'sub')  # varnames: ('text',)# nested code: _async_discover_tokens (filename: discord_backup\tui.py)  # const[0]: None  # names: ('DiscordHTTPClient', 'create', 'discover_tokens', 'aclose')  # varnames: ('http',)# nested code: _async_run_backup (filename: discord_backup\tui.py)  # const[0]: None  # names: ('DiscordHTTPClient', 'create', 'BackupService', 'run', 'save', 'aclose')  # varnames: ('token', 'config', 'console', 'http', 'service', 'result', 'path')# nested code: _async_run_restore (filename: discord_backup\tui.py)  # const[0]: None  # const[2]: 'version'  # names: ('DiscordHTTPClient', 'create', 'RestoreService', 'run', 'get', 'guild_id', 'favourite_gifs_status', 'folder_restore_attempted', 'duration', 'aclose')  # varnames: ('backup_data', 'token', 'bot_token', 'restore_folders', 'allow_version_mismatch', 'console', 'http', 'service', 'summary')# nested code: _format_backup_summary (filename: discord_backup\tui.py)  # const[0]: None  # const[1]: 'guilds'  # const[2]: 'group_chats'  # const[5]: 'success'  # const[6]: ' / '  # const[7]: 'total'  # const[10]: '.1f'  # names: ('summary', 'duration')  # varnames: ('result', 'path', 'logs', 'summary', 'guilds', 'groups')# nested code: _format_restore_summary (filename: discord_backup\tui.py)  # const[0]: None  # const[4]: 'Yes'  # const[7]: '.1f'  # varnames: ('guild_id', 'gifs_status', 'folders', 'duration', 'logs')# nested code: _show_with_details (filename: discord_backup\tui.py)  # const[0]: None  # const[2]: 0  # const[5]: 'details'  # const[6]: ' ? details'  # names: ('insert', 'button_dialog', 'run', 'message_dialog')  # varnames: ('title', 'summary', 'details', 'buttons', 'choice')# nested code: _show_error (filename: discord_backup\tui.py)  # const[0]: None  # names: ('_strip_ansi', 'str', '_show_with_details')  # varnames: ('title', 'error', 'logs', 'details', 'summary')# nested code: _discover_tokens_with_loading (filename: discord_backup\tui.py)  # const[0]: None  # nested code: worker (filename: discord_backup\tui.py)    # const[0]: None    # const[1]: 'Scanning local storage for Discord tokens...'    # const[2]: 'Found '    # const[3]: ' token(s)'    # const[4]: 0.2    # names: ('update', 'asyncio', 'run', '_async_discover_tokens', 'len', 'sleep')    # varnames: ('handle', 'tokens')  # const[2]: 0  # const[3]: 'Token discovery'  # const[4]: 'Preparing...'  # names: ('time', 'run_with_loading')  # varnames: ('worker',)# nested code: _discover_and_choose_token (filename: discord_backup\tui.py)  # const[0]: None  # const[1]: 'Token discovery failed'  # const[2]: 'No tokens'  # const[3]: 'No Discord tokens were found on this machine.'  # const[7]: 'Select a token (arrow keys + Enter)'  # const[8]: 'Use token'  # const[9]: 'Cancel'  # names: ('_discover_tokens_with_loading', 'Exception', '_show_error', 'message_dialog', 'run', 'enumerate', 'user_tag', 'source', 'radiolist_dialog')  # varnames: ('title', 'tokens', 'exc', 'idx', 'tok', 'values', 'choice')# nested code: _prompt_for_token (filename: discord_backup\tui.py)  # const[0]: None  # const[1]: 'Enter the Discord user token:'  # names: ('input_dialog', 'run', 'strip')  # varnames: ('label', 'token')# nested code: _prompt_for_bot_token (filename: discord_backup\tui.py)  # const[0]: None  # const[1]: 'Bot Token'  # const[2]: 'Enter bot token used for username lookups:'  # names: ('input_dialog', 'run', 'strip')  # varnames: ('token',)# nested code: _run_backup_flow (filename: discord_backup\tui.py)  # const[0]: None  # nested code: worker (filename: discord_backup\tui.py)    # const[0]: None    # nested code: <lambda> (filename: discord_backup\tui.py)      # const[0]: None      # names: ('update', '_strip_ansi')      # varnames: ('msg',)    # const[3]: 'Authenticating token...'    # const[4]: 'Finalising backup...'    # names: ('Console', 'colour', 'update', 'asyncio', 'run', '_async_run_backup')    # varnames: ('handle', 'stripped_update', 'console', 'result', 'path')  # const[2]: 'Backup in progress'  # const[3]: 'Starting backup...'  # const[4]: 'Backup failed'  # const[5]: 'Unexpected error'  # const[6]: -2000  # const[7]: 'Backup complete'  # names: ('AppConfig', 'load', 'io', 'StringIO', 'run_with_loading', 'BackupError', '_strip_ansi', 'getvalue', '_show_error', 'Exception', '_show_with_details', '_format_backup_summary')  # varnames: ('token', 'worker', 'result', 'path', 'exc', 'logs')# nested code: _request_backup_file (filename: discord_backup\tui.py)  # const[0]: None  # const[1]: 'Select backup file'  # const[2]: 'Choose a .bkup file to restore:'  # const[4]: 'Backup file'  # const[5]: 'Enter the full path to the .bkup file:'  # const[7]: 'File not found'  # const[8]: 'Could not find '  # names: ('path_dialog', 'str', '_project_root', 'run', 'input_dialog', 'Path', 'exists', 'message_dialog')  # varnames: ('selection', 'backup_path')# nested code: _run_restore_flow (filename: discord_backup\tui.py)  # const[0]: None  # const[1]: 'utf-8'  # const[3]: 'Invalid backup'  # const[4]: 'User Token'  # const[5]: 'Choose how to supply the user token (arrow keys + Enter)'  # const[8]: 'Continue'  # const[9]: 'Cancel'  # const[11]: 'scan'  # const[12]: 'Select user token'  # const[13]: 'Restore Guild Folders'  # const[14]: 'Restore server folders when possible?'  # const[16]: 'Version Mismatch'  # const[17]: 'Ignore backup version mismatches?'  # nested code: worker (filename: discord_backup\tui.py)    # const[0]: None    # nested code: <lambda> (filename: discord_backup\tui.py)      # const[0]: None      # names: ('update', '_strip_ansi')      # varnames: ('msg',)    # const[3]: 'Preparing restore...'    # const[4]: 'Finishing up...'    # names: ('Console', 'colour', 'update', 'asyncio', 'run', '_async_run_restore')    # varnames: ('handle', 'stripped_update', 'console', 'result')  # const[19]: 'Restoring backup'  # const[20]: 'Starting restore...'  # const[21]: 'Restore failed'  # const[22]: 'Unexpected error'  # const[23]: -2000  # const[24]: 'Restore complete'  # names: ('_request_backup_file', 'json', 'loads', 'read_text', 'Exception', '_show_error', 'radiolist_dialog', 'run', '_discover_and_choose_token', 'token', '_prompt_for_token', '_prompt_for_bot_token', 'yes_no_dialog', 'AppConfig', 'load', 'io', 'StringIO', 'run_with_loading', 'RestoreError', '_strip_ansi', 'getvalue', '_show_with_details', '_format_restore_summary')  # varnames: ('backup_path', 'exc', 'token_option', 'selection', 'worker', 'guild_id', 'gif_status', 'folders', 'duration', 'logs')# nested code: _show_tokens_list (filename: discord_backup\tui.py)  # const[0]: None  # const[1]: 'Token discovery failed'  # const[2]: 'Tokens'  # const[3]: 'No tokens discovered.'  # const[6]: ') - '  # const[7]: 'Discovered Tokens'  # names: ('_discover_tokens_with_loading', 'Exception', '_show_error', 'message_dialog', 'run', 'user_tag', 'user_id', 'source', 'join')  # varnames: ('tokens', 'exc', 'tok', 'lines')# nested code: _handle_startup_add (filename: discord_backup\tui.py)  # const[0]: None  # const[1]: 'Select account for auto-backup'  # const[2]: 'frozen'  # const[3]: False  # const[4]: 'main.py'  # const[5]: '.py'  # const[6]: 'cmd.exe /C python "'  # const[7]: '" auto-backup --account-id '  # const[8]: ' --working-dir "'  # const[10]: 'Startup'  # const[11]: 'Auto-backup script saved to '  # names: ('_discover_and_choose_token', '_project_root', 'Path', 'getattr', 'sys', 'executable', 'suffix', 'user_id', 'write_startup_script', 'message_dialog', 'run')  # varnames: ('selection', 'root', 'executable', 'command', 'script_path')# nested code: _handle_startup_remove (filename: discord_backup\tui.py)  # const[0]: None  # const[1]: 'Startup'  # const[2]: 'Startup script removed.'  # const[4]: 'No startup script found.'  # names: ('remove_startup_script', 'message_dialog', 'run')# nested code: run_tui (filename: discord_backup\tui.py)  # const[0]: None  # const[1]: 'Discord Backup'  # const[2]: 'Select an action (use arrow keys, Enter to confirm)'  # const[4]: 'Select'  # const[5]: 'Quit'  # const[8]: 'Goodbye'  # const[9]: 'Stay safe and keep your backups handy!'  # const[11]: 'backup_scan'  # const[12]: 'Select token for backup'  # const[13]: 'backup_manual'  # const[14]: 'Manual Backup'  # const[15]: 'restore'  # const[16]: 'tokens'  # const[17]: 'startup_add'  # const[18]: 'startup_remove'  # names: ('radiolist_dialog', 'run', 'message_dialog', '_discover_and_choose_token', '_run_backup_flow', 'token', '_prompt_for_token', '_run_restore_flow', '_show_tokens_list', '_handle_startup_add', '_handle_startup_remove')  # varnames: ('action', 'selection', 'token')# const[38]: 'run_tui'# names: ('__future__', 'annotations', 'asyncio', 'io', 'json', 're', 'sys', 'pathlib', 'Path', 'typing', 'Sequence', 'prompt_toolkit.shortcuts.dialogs', 'button_dialog', 'input_dialog', 'message_dialog', 'path_dialog', 'radiolist_dialog', 'yes_no_dialog', 'ImportError', 'backup', 'BackupError', 'BackupService', 'config', 'AppConfig', 'console', 'Console', 'http_client', 'DiscordHTTPClient', 'loading', 'ProgressHandle', 'run_with_loading', 'restore', 'RestoreError', 'RestoreService', 'results', 'BackupResult', 'startup', 'remove_startup_script', 'write_startup_script', 'token_discovery', 'DiscoveredToken', 'discover_tokens', 'compile', 'ANSI_RE', '_project_root', '_strip_ansi', '_async_discover_tokens', '_async_run_backup', '_async_run_restore', '_format_backup_summary', '_format_restore_summary', '_show_with_details', '_show_error', '_discover_tokens_with_loading', '_discover_and_choose_token', '_prompt_for_token', '_prompt_for_bot_token', '_run_backup_flow', '_request_backup_file', '_run_restore_flow', '_show_tokens_list', '_handle_startup_add', '_handle_startup_remove', 'run_tui', '__all__')

# --- Disassembly ---

   0           RESUME                   0

   1           LOAD_CONST               0 (0)
               LOAD_CONST               1 (('annotations',))
               IMPORT_NAME              0 (__future__)
               IMPORT_FROM              1 (annotations)
               STORE_NAME               1 (annotations)
               POP_TOP

   3           LOAD_CONST               0 (0)
               LOAD_CONST               2 (None)
               IMPORT_NAME              2 (asyncio)
               STORE_NAME               2 (asyncio)

   4           LOAD_CONST               0 (0)
               LOAD_CONST               2 (None)
               IMPORT_NAME              3 (io)
               STORE_NAME               3 (io)

   5           LOAD_CONST               0 (0)
               LOAD_CONST               2 (None)
               IMPORT_NAME              4 (json)
               STORE_NAME               4 (json)

   6           LOAD_CONST               0 (0)
               LOAD_CONST               2 (None)
               IMPORT_NAME              5 (re)
               STORE_NAME               5 (re)

   7           LOAD_CONST               0 (0)
               LOAD_CONST               2 (None)
               IMPORT_NAME              6 (sys)
               STORE_NAME               6 (sys)

   8           LOAD_CONST               0 (0)
               LOAD_CONST               3 (('Path',))
               IMPORT_NAME              7 (pathlib)
               IMPORT_FROM              8 (Path)
               STORE_NAME               8 (Path)
               POP_TOP

   9           LOAD_CONST               0 (0)
               LOAD_CONST               4 (('Sequence',))
               IMPORT_NAME              9 (typing)
               IMPORT_FROM             10 (Sequence)
               STORE_NAME              10 (Sequence)
               POP_TOP

  11           NOP

  12   L1:     LOAD_CONST               0 (0)
               LOAD_CONST               5 (('button_dialog', 'input_dialog', 'message_dialog', 'path_dialog', 'radiolist_dialog', 'yes_no_dialog'))
               IMPORT_NAME             11 (prompt_toolkit.shortcuts.dialogs)
               IMPORT_FROM             12 (button_dialog)
               STORE_NAME              12 (button_dialog)
               IMPORT_FROM             13 (input_dialog)
               STORE_NAME              13 (input_dialog)
               IMPORT_FROM             14 (message_dialog)
               STORE_NAME              14 (message_dialog)
               IMPORT_FROM             15 (path_dialog)
               STORE_NAME              15 (path_dialog)
               IMPORT_FROM             16 (radiolist_dialog)
               STORE_NAME              16 (radiolist_dialog)
               IMPORT_FROM             17 (yes_no_dialog)
               STORE_NAME              17 (yes_no_dialog)
               POP_TOP

  31   L2:     LOAD_CONST               7 (1)
               LOAD_CONST               8 (('BackupError', 'BackupService'))
               IMPORT_NAME             19 (backup)
               IMPORT_FROM             20 (BackupError)
               STORE_NAME              20 (BackupError)
               IMPORT_FROM             21 (BackupService)
               STORE_NAME              21 (BackupService)
               POP_TOP

  32           LOAD_CONST               7 (1)
               LOAD_CONST               9 (('AppConfig',))
               IMPORT_NAME             22 (config)
               IMPORT_FROM             23 (AppConfig)
               STORE_NAME              23 (AppConfig)
               POP_TOP

  33           LOAD_CONST               7 (1)
               LOAD_CONST              10 (('Console',))
               IMPORT_NAME             24 (console)
               IMPORT_FROM             25 (Console)
               STORE_NAME              25 (Console)
               POP_TOP

  34           LOAD_CONST               7 (1)
               LOAD_CONST              11 (('DiscordHTTPClient',))
               IMPORT_NAME             26 (http_client)
               IMPORT_FROM             27 (DiscordHTTPClient)
               STORE_NAME              27 (DiscordHTTPClient)
               POP_TOP

  35           LOAD_CONST               7 (1)
               LOAD_CONST              12 (('ProgressHandle', 'run_with_loading'))
               IMPORT_NAME             28 (loading)
               IMPORT_FROM             29 (ProgressHandle)
               STORE_NAME              29 (ProgressHandle)
               IMPORT_FROM             30 (run_with_loading)
               STORE_NAME              30 (run_with_loading)
               POP_TOP

  36           LOAD_CONST               7 (1)
               LOAD_CONST              13 (('RestoreError', 'RestoreService'))
               IMPORT_NAME             31 (restore)
               IMPORT_FROM             32 (RestoreError)
               STORE_NAME              32 (RestoreError)
               IMPORT_FROM             33 (RestoreService)
               STORE_NAME              33 (RestoreService)
               POP_TOP

  37           LOAD_CONST               7 (1)
               LOAD_CONST              14 (('BackupResult',))
               IMPORT_NAME             34 (results)
               IMPORT_FROM             35 (BackupResult)
               STORE_NAME              35 (BackupResult)
               POP_TOP

  38           LOAD_CONST               7 (1)
               LOAD_CONST              15 (('remove_startup_script', 'write_startup_script'))
               IMPORT_NAME             36 (startup)
               IMPORT_FROM             37 (remove_startup_script)
               STORE_NAME              37 (remove_startup_script)
               IMPORT_FROM             38 (write_startup_script)
               STORE_NAME              38 (write_startup_script)
               POP_TOP

  39           LOAD_CONST               7 (1)
               LOAD_CONST              16 (('DiscoveredToken', 'discover_tokens'))
               IMPORT_NAME             39 (token_discovery)
               IMPORT_FROM             40 (DiscoveredToken)
               STORE_NAME              40 (DiscoveredToken)
               IMPORT_FROM             41 (discover_tokens)
               STORE_NAME              41 (discover_tokens)
               POP_TOP

  41           LOAD_NAME                5 (re)
               LOAD_ATTR               84 (compile)
               PUSH_NULL
               LOAD_CONST              17 ('\\x1b\\[[0-9;]*m')
               CALL                     1
               STORE_NAME              43 (ANSI_RE)

  44           LOAD_CONST              39 (('return', 'Path'))
               LOAD_CONST              18 (<code object _project_root at 0x000001EE5C5FFD70, file "discord_backup\tui.py", line 44>)
               MAKE_FUNCTION
               SET_FUNCTION_ATTRIBUTE   4 (annotations)
               STORE_NAME              44 (_project_root)

  50           LOAD_CONST              40 (('text', 'str', 'return', 'str'))
               LOAD_CONST              19 (<code object _strip_ansi at 0x000001EE5E815430, file "discord_backup\tui.py", line 50>)
               MAKE_FUNCTION
               SET_FUNCTION_ATTRIBUTE   4 (annotations)
               STORE_NAME              45 (_strip_ansi)

  54           LOAD_CONST              41 (('return', 'list[DiscoveredToken]'))
               LOAD_CONST              20 (<code object _async_discover_tokens at 0x000001EE5C63FB40, file "discord_backup\tui.py", line 54>)
               MAKE_FUNCTION
               SET_FUNCTION_ATTRIBUTE   4 (annotations)
               STORE_NAME              46 (_async_discover_tokens)

  62           LOAD_CONST              42 (('token', 'str', 'config', 'AppConfig', 'console', 'Console', 'return', 'tuple[BackupResult, Path]'))
               LOAD_CONST              21 (<code object _async_run_backup at 0x000001EE5C72EF80, file "discord_backup\tui.py", line 62>)
               MAKE_FUNCTION
               SET_FUNCTION_ATTRIBUTE   4 (annotations)
               STORE_NAME              47 (_async_run_backup)

  73           NOP

  74           NOP

  73           NOP

  75           NOP

  73           NOP

  76           NOP

  73           NOP

  77           NOP

  73           NOP

  78           NOP

  73           NOP

  79           NOP

  73           NOP

  80           NOP

  73           LOAD_CONST              43 (('backup_data', 'dict', 'token', 'str', 'bot_token', 'str', 'restore_folders', 'bool', 'allow_version_mismatch', 'bool', 'console', 'Console', 'return', 'tuple[str, str, bool, float]'))
               LOAD_CONST              22 (<code object _async_run_restore at 0x000001EE5E621580, file "discord_backup\tui.py", line 73>)
               MAKE_FUNCTION
               SET_FUNCTION_ATTRIBUTE   4 (annotations)
               STORE_NAME              48 (_async_run_restore)

 100           LOAD_CONST              44 (('result', 'BackupResult', 'path', 'Path', 'logs', 'str', 'return', 'str'))
               LOAD_CONST              23 (<code object _format_backup_summary at 0x000001EE5E786810, file "discord_backup\tui.py", line 100>)
               MAKE_FUNCTION
               SET_FUNCTION_ATTRIBUTE   4 (annotations)
               STORE_NAME              49 (_format_backup_summary)

 114           LOAD_CONST              45 (('guild_id', 'str', 'gifs_status', 'str', 'folders', 'bool', 'duration', 'float', 'logs', 'str', 'return', 'str'))
               LOAD_CONST              24 (<code object _format_restore_summary at 0x000001EE5E78F770, file "discord_backup\tui.py", line 114>)
               MAKE_FUNCTION
               SET_FUNCTION_ATTRIBUTE   4 (annotations)
               STORE_NAME              50 (_format_restore_summary)

 125           LOAD_CONST              46 (('title', 'str', 'summary', 'str', 'details', 'str | None', 'return', 'None'))
               LOAD_CONST              25 (<code object _show_with_details at 0x000001EE5E84CB20, file "discord_backup\tui.py", line 125>)
               MAKE_FUNCTION
               SET_FUNCTION_ATTRIBUTE   4 (annotations)
               STORE_NAME              51 (_show_with_details)

 134           LOAD_CONST              47 ((None,))
               LOAD_CONST              48 (('title', 'str', 'error', 'Exception', 'logs', 'str | None', 'return', 'None'))
               LOAD_CONST              26 (<code object _show_error at 0x000001EE5E577DE0, file "discord_backup\tui.py", line 134>)
               MAKE_FUNCTION
               SET_FUNCTION_ATTRIBUTE   4 (annotations)
               SET_FUNCTION_ATTRIBUTE   1 (defaults)
               STORE_NAME              52 (_show_error)

 140           LOAD_CONST              41 (('return', 'list[DiscoveredToken]'))
               LOAD_CONST              27 (<code object _discover_tokens_with_loading at 0x000001EE5E815830, file "discord_backup\tui.py", line 140>)
               MAKE_FUNCTION
               SET_FUNCTION_ATTRIBUTE   4 (annotations)
               STORE_NAME              53 (_discover_tokens_with_loading)

 153           LOAD_CONST              49 (('title', 'str', 'return', 'DiscoveredToken | None'))
               LOAD_CONST              28 (<code object _discover_and_choose_token at 0x000001EE5C72CD60, file "discord_backup\tui.py", line 153>)
               MAKE_FUNCTION
               SET_FUNCTION_ATTRIBUTE   4 (annotations)
               STORE_NAME              54 (_discover_and_choose_token)

 175           LOAD_CONST              50 (('label', 'str', 'return', 'str | None'))
               LOAD_CONST              29 (<code object _prompt_for_token at 0x000001EE5E7F5430, file "discord_backup\tui.py", line 175>)
               MAKE_FUNCTION
               SET_FUNCTION_ATTRIBUTE   4 (annotations)
               STORE_NAME              55 (_prompt_for_token)

 182           LOAD_CONST              51 (('return', 'str | None'))
               LOAD_CONST              30 (<code object _prompt_for_bot_token at 0x000001EE5E7F52F0, file "discord_backup\tui.py", line 182>)
               MAKE_FUNCTION
               SET_FUNCTION_ATTRIBUTE   4 (annotations)
               STORE_NAME              56 (_prompt_for_bot_token)

 189           LOAD_CONST              52 (('token', 'str', 'return', 'None'))
               LOAD_CONST              31 (<code object _run_backup_flow at 0x000001EE5E980B90, file "discord_backup\tui.py", line 189>)
               MAKE_FUNCTION
               SET_FUNCTION_ATTRIBUTE   4 (annotations)
               STORE_NAME              57 (_run_backup_flow)

 216           LOAD_CONST              53 (('return', 'Path | None'))
               LOAD_CONST              32 (<code object _request_backup_file at 0x000001EE5E801E30, file "discord_backup\tui.py", line 216>)
               MAKE_FUNCTION
               SET_FUNCTION_ATTRIBUTE   4 (annotations)
               STORE_NAME              58 (_request_backup_file)

 237           LOAD_CONST              54 (('return', 'None'))
               LOAD_CONST              33 (<code object _run_restore_flow at 0x000001EE5C4B6160, file "discord_backup\tui.py", line 237>)
               MAKE_FUNCTION
               SET_FUNCTION_ATTRIBUTE   4 (annotations)
               STORE_NAME              59 (_run_restore_flow)

 328           LOAD_CONST              54 (('return', 'None'))
               LOAD_CONST              34 (<code object _show_tokens_list at 0x000001EE5C72C8E0, file "discord_backup\tui.py", line 328>)
               MAKE_FUNCTION
               SET_FUNCTION_ATTRIBUTE   4 (annotations)
               STORE_NAME              60 (_show_tokens_list)

 341           LOAD_CONST              54 (('return', 'None'))
               LOAD_CONST              35 (<code object _handle_startup_add at 0x000001EE5C72BFE0, file "discord_backup\tui.py", line 341>)
               MAKE_FUNCTION
               SET_FUNCTION_ATTRIBUTE   4 (annotations)
               STORE_NAME              61 (_handle_startup_add)

 355           LOAD_CONST              54 (('return', 'None'))
               LOAD_CONST              36 (<code object _handle_startup_remove at 0x000001EE5E870810, file "discord_backup\tui.py", line 355>)
               MAKE_FUNCTION
               SET_FUNCTION_ATTRIBUTE   4 (annotations)
               STORE_NAME              62 (_handle_startup_remove)

 362           LOAD_CONST              54 (('return', 'None'))
               LOAD_CONST              37 (<code object run_tui at 0x000001EE5C79A960, file "discord_backup\tui.py", line 362>)
               MAKE_FUNCTION
               SET_FUNCTION_ATTRIBUTE   4 (annotations)
               STORE_NAME              63 (run_tui)

 401           LOAD_CONST              38 ('run_tui')
               BUILD_LIST               1
               STORE_NAME              64 (__all__)
               RETURN_CONST             2 (None)

  --   L3:     PUSH_EXC_INFO

  20           LOAD_NAME               18 (ImportError)
               CHECK_EXC_MATCH
               POP_JUMP_IF_FALSE       19 (to L5)
               POP_TOP

  21           LOAD_CONST               0 (0)
               LOAD_CONST               6 (('button_dialog', 'input_dialog', 'message_dialog', 'radiolist_dialog', 'yes_no_dialog'))
               IMPORT_NAME             11 (prompt_toolkit.shortcuts.dialogs)
               IMPORT_FROM             12 (button_dialog)
               STORE_NAME              12 (button_dialog)
               IMPORT_FROM             13 (input_dialog)
               STORE_NAME              13 (input_dialog)
               IMPORT_FROM             14 (message_dialog)
               STORE_NAME              14 (message_dialog)
               IMPORT_FROM             16 (radiolist_dialog)
               STORE_NAME              16 (radiolist_dialog)
               IMPORT_FROM             17 (yes_no_dialog)
               STORE_NAME              17 (yes_no_dialog)
               POP_TOP

  29           LOAD_CONST               2 (None)
               STORE_NAME              15 (path_dialog)
       L4:     POP_EXCEPT
               JUMP_BACKWARD_NO_INTERRUPT 226 (to L2)

  20   L5:     RERAISE                  0

  --   L6:     COPY                     3
               POP_EXCEPT
               RERAISE                  1
ExceptionTable:
  L1 to L2 -> L3 [0]
  L3 to L4 -> L6 [1] lasti
  L5 to L6 -> L6 [1] lasti

Disassembly of <code object _project_root at 0x000001EE5C5FFD70, file "discord_backup\tui.py", line 44>:
 44           RESUME                   0

 45           LOAD_GLOBAL              1 (getattr + NULL)
              LOAD_GLOBAL              2 (sys)
              LOAD_CONST               1 ('frozen')
              LOAD_CONST               2 (False)
              CALL                     3
              TO_BOOL
              POP_JUMP_IF_FALSE       49 (to L1)

 46           LOAD_GLOBAL              5 (Path + NULL)
              LOAD_GLOBAL              2 (sys)
              LOAD_ATTR                6 (executable)
              CALL                     1
              LOAD_ATTR                9 (resolve + NULL|self)
              CALL                     0
              LOAD_ATTR               10 (parent)
              RETURN_VALUE

 47   L1:     LOAD_GLOBAL              5 (Path + NULL)
              LOAD_GLOBAL             12 (__file__)
              CALL                     1
              LOAD_ATTR                9 (resolve + NULL|self)
              CALL                     0
              LOAD_ATTR               10 (parent)
              LOAD_ATTR               10 (parent)
              RETURN_VALUE

Disassembly of <code object _strip_ansi at 0x000001EE5E815430, file "discord_backup\tui.py", line 50>:
 50           RESUME                   0

 51           LOAD_GLOBAL              0 (ANSI_RE)
              LOAD_ATTR                3 (sub + NULL|self)
              LOAD_CONST               1 ('')
              LOAD_FAST                0 (text)
              CALL                     2
              RETURN_VALUE

Disassembly of <code object _async_discover_tokens at 0x000001EE5C63FB40, file "discord_backup\tui.py", line 54>:
  54            RETURN_GENERATOR
                POP_TOP
        L1:     RESUME                   0

  55            LOAD_GLOBAL              0 (DiscordHTTPClient)
                LOAD_ATTR                2 (create)
                PUSH_NULL
                CALL                     0
                GET_AWAITABLE            0
                LOAD_CONST               0 (None)
        L2:     SEND                     3 (to L5)
        L3:     YIELD_VALUE              1
        L4:     RESUME                   3
                JUMP_BACKWARD_NO_INTERRUPT 5 (to L2)
        L5:     END_SEND
                STORE_FAST               0 (http)

  56    L6:     NOP

  57    L7:     LOAD_GLOBAL              5 (discover_tokens + NULL)
                LOAD_FAST                0 (http)
                CALL                     1
                GET_AWAITABLE            0
                LOAD_CONST               0 (None)
        L8:     SEND                     3 (to L11)
        L9:     YIELD_VALUE              1
       L10:     RESUME                   3
                JUMP_BACKWARD_NO_INTERRUPT 5 (to L8)
       L11:     END_SEND

  59   L12:     LOAD_FAST                0 (http)
                LOAD_ATTR                7 (aclose + NULL|self)
                CALL                     0
                GET_AWAITABLE            0
                LOAD_CONST               0 (None)
       L13:     SEND                     3 (to L16)
       L14:     YIELD_VALUE              1
       L15:     RESUME                   3
                JUMP_BACKWARD_NO_INTERRUPT 5 (to L13)
       L16:     END_SEND
                POP_TOP
                RETURN_VALUE

  55   L17:     CLEANUP_THROW
       L18:     JUMP_BACKWARD_NO_INTERRUPT 48 (to L5)

  57   L19:     CLEANUP_THROW
       L20:     JUMP_BACKWARD_NO_INTERRUPT 30 (to L11)

  59   L21:     CLEANUP_THROW
       L22:     JUMP_BACKWARD_NO_INTERRUPT 9 (to L16)

  --   L23:     PUSH_EXC_INFO

  59            LOAD_FAST                0 (http)
                LOAD_ATTR                7 (aclose + NULL|self)
                CALL                     0
                GET_AWAITABLE            0
                LOAD_CONST               0 (None)
       L24:     SEND                     4 (to L28)
       L25:     YIELD_VALUE              1
       L26:     RESUME                   3
                JUMP_BACKWARD_NO_INTERRUPT 5 (to L24)
       L27:     CLEANUP_THROW
       L28:     END_SEND
                POP_TOP
                RERAISE                  0

  --   L29:     COPY                     3
                POP_EXCEPT
                RERAISE                  1
       L30:     CALL_INTRINSIC_1         3 (INTRINSIC_STOPITERATION_ERROR)
                RERAISE                  1
ExceptionTable:
  L1 to L3 -> L30 [0] lasti
  L3 to L4 -> L17 [2]
  L4 to L6 -> L30 [0] lasti
  L7 to L9 -> L23 [0]
  L9 to L10 -> L19 [2]
  L10 to L12 -> L23 [0]
  L12 to L14 -> L30 [0] lasti
  L14 to L15 -> L21 [3]
  L15 to L18 -> L30 [0] lasti
  L19 to L20 -> L23 [0]
  L21 to L22 -> L30 [0] lasti
  L23 to L25 -> L29 [1] lasti
  L25 to L26 -> L27 [4]
  L26 to L29 -> L29 [1] lasti
  L29 to L30 -> L30 [0] lasti

Disassembly of <code object _async_run_backup at 0x000001EE5C72EF80, file "discord_backup\tui.py", line 62>:
  62            RETURN_GENERATOR
                POP_TOP
        L1:     RESUME                   0

  63            LOAD_GLOBAL              0 (DiscordHTTPClient)
                LOAD_ATTR                2 (create)
                PUSH_NULL
                CALL                     0
                GET_AWAITABLE            0
                LOAD_CONST               0 (None)
        L2:     SEND                     3 (to L5)
        L3:     YIELD_VALUE              1
        L4:     RESUME                   3
                JUMP_BACKWARD_NO_INTERRUPT 5 (to L2)
        L5:     END_SEND
                STORE_FAST               3 (http)

  64    L6:     NOP

  65    L7:     LOAD_GLOBAL              5 (BackupService + NULL)
                LOAD_FAST_LOAD_FAST     48 (http, token)
                LOAD_FAST_LOAD_FAST     18 (config, console)
                LOAD_CONST               1 (('http', 'token', 'config', 'console'))
                CALL_KW                  4
                STORE_FAST               4 (service)

  66            LOAD_FAST                4 (service)
                LOAD_ATTR                7 (run + NULL|self)
                CALL                     0
                GET_AWAITABLE            0
                LOAD_CONST               0 (None)
        L8:     SEND                     3 (to L11)
        L9:     YIELD_VALUE              1
       L10:     RESUME                   3
                JUMP_BACKWARD_NO_INTERRUPT 5 (to L8)
       L11:     END_SEND
                STORE_FAST               5 (result)

  67            LOAD_FAST                4 (service)
                LOAD_ATTR                9 (save + NULL|self)
                LOAD_FAST                5 (result)
                CALL                     1
                GET_AWAITABLE            0
                LOAD_CONST               0 (None)
       L12:     SEND                     3 (to L15)
       L13:     YIELD_VALUE              1
       L14:     RESUME                   3
                JUMP_BACKWARD_NO_INTERRUPT 5 (to L12)
       L15:     END_SEND
                STORE_FAST               6 (path)

  68            LOAD_FAST_LOAD_FAST     86 (result, path)
                BUILD_TUPLE              2

  70   L16:     LOAD_FAST                3 (http)
                LOAD_ATTR               11 (aclose + NULL|self)
                CALL                     0
                GET_AWAITABLE            0
                LOAD_CONST               0 (None)
       L17:     SEND                     3 (to L20)
       L18:     YIELD_VALUE              1
       L19:     RESUME                   3
                JUMP_BACKWARD_NO_INTERRUPT 5 (to L17)
       L20:     END_SEND
                POP_TOP
                RETURN_VALUE

  63   L21:     CLEANUP_THROW
       L22:     JUMP_BACKWARD_NO_INTERRUPT 91 (to L5)

  66   L23:     CLEANUP_THROW
       L24:     JUMP_BACKWARD_NO_INTERRUPT 58 (to L11)

  67   L25:     CLEANUP_THROW
       L26:     JUMP_BACKWARD_NO_INTERRUPT 35 (to L15)

  70   L27:     CLEANUP_THROW
       L28:     JUMP_BACKWARD_NO_INTERRUPT 11 (to L20)

  --   L29:     PUSH_EXC_INFO

  70            LOAD_FAST                3 (http)
                LOAD_ATTR               11 (aclose + NULL|self)
                CALL                     0
                GET_AWAITABLE            0
                LOAD_CONST               0 (None)
       L30:     SEND                     4 (to L34)
       L31:     YIELD_VALUE              1
       L32:     RESUME                   3
                JUMP_BACKWARD_NO_INTERRUPT 5 (to L30)
       L33:     CLEANUP_THROW
       L34:     END_SEND
                POP_TOP
                RERAISE                  0

  --   L35:     COPY                     3
                POP_EXCEPT
                RERAISE                  1
       L36:     CALL_INTRINSIC_1         3 (INTRINSIC_STOPITERATION_ERROR)
                RERAISE                  1
ExceptionTable:
  L1 to L3 -> L36 [0] lasti
  L3 to L4 -> L21 [2]
  L4 to L6 -> L36 [0] lasti
  L7 to L9 -> L29 [0]
  L9 to L10 -> L23 [2]
  L10 to L13 -> L29 [0]
  L13 to L14 -> L25 [2]
  L14 to L16 -> L29 [0]
  L16 to L18 -> L36 [0] lasti
  L18 to L19 -> L27 [3]
  L19 to L22 -> L36 [0] lasti
  L23 to L24 -> L29 [0]
  L25 to L26 -> L29 [0]
  L27 to L28 -> L36 [0] lasti
  L29 to L31 -> L35 [1] lasti
  L31 to L32 -> L33 [4]
  L32 to L35 -> L35 [1] lasti
  L35 to L36 -> L36 [0] lasti

Disassembly of <code object _async_run_restore at 0x000001EE5E621580, file "discord_backup\tui.py", line 73>:
  73            RETURN_GENERATOR
                POP_TOP
        L1:     RESUME                   0

  81            LOAD_GLOBAL              0 (DiscordHTTPClient)
                LOAD_ATTR                2 (create)
                PUSH_NULL
                CALL                     0
                GET_AWAITABLE            0
                LOAD_CONST               0 (None)
        L2:     SEND                     3 (to L5)
        L3:     YIELD_VALUE              1
        L4:     RESUME                   3
                JUMP_BACKWARD_NO_INTERRUPT 5 (to L2)
        L5:     END_SEND
                STORE_FAST               6 (http)

  82    L6:     NOP

  83    L7:     LOAD_GLOBAL              5 (RestoreService + NULL)

  84            LOAD_FAST                6 (http)

  85            LOAD_FAST                1 (token)

  86            LOAD_FAST                2 (bot_token)

  87            LOAD_FAST                0 (backup_data)

  88            LOAD_FAST                5 (console)

  83            LOAD_CONST               1 (('http', 'token', 'bot_token', 'backup', 'console'))
                CALL_KW                  5
                STORE_FAST               7 (service)

  90            LOAD_FAST                7 (service)
                LOAD_ATTR                7 (run + NULL|self)

  91            LOAD_FAST                3 (restore_folders)

  92            LOAD_FAST                0 (backup_data)
                LOAD_ATTR                9 (get + NULL|self)
                LOAD_CONST               2 ('version')
                CALL                     1

  93            LOAD_FAST                4 (allow_version_mismatch)

  90            LOAD_CONST               3 (('restore_folders', 'expected_version', 'allow_mismatch'))
                CALL_KW                  3
                GET_AWAITABLE            0
                LOAD_CONST               0 (None)
        L8:     SEND                     3 (to L11)
        L9:     YIELD_VALUE              1
       L10:     RESUME                   3
                JUMP_BACKWARD_NO_INTERRUPT 5 (to L8)
       L11:     END_SEND
                STORE_FAST               8 (summary)

  95            LOAD_FAST                8 (summary)
                LOAD_ATTR               10 (guild_id)
                LOAD_FAST                8 (summary)
                LOAD_ATTR               12 (favourite_gifs_status)
                LOAD_FAST                8 (summary)
                LOAD_ATTR               14 (folder_restore_attempted)
                LOAD_FAST                8 (summary)
                LOAD_ATTR               16 (duration)
                BUILD_TUPLE              4

  97   L12:     LOAD_FAST                6 (http)
                LOAD_ATTR               19 (aclose + NULL|self)
                CALL                     0
                GET_AWAITABLE            0
                LOAD_CONST               0 (None)
       L13:     SEND                     3 (to L16)
       L14:     YIELD_VALUE              1
       L15:     RESUME                   3
                JUMP_BACKWARD_NO_INTERRUPT 5 (to L13)
       L16:     END_SEND
                POP_TOP
                RETURN_VALUE

  81   L17:     CLEANUP_THROW
       L18:     JUMP_BACKWARD_NO_INTERRUPT 128 (to L5)

  90   L19:     CLEANUP_THROW
       L20:     JUMP_BACKWARD_NO_INTERRUPT 76 (to L11)

  97   L21:     CLEANUP_THROW
       L22:     JUMP_BACKWARD_NO_INTERRUPT 9 (to L16)

  --   L23:     PUSH_EXC_INFO

  97            LOAD_FAST                6 (http)
                LOAD_ATTR               19 (aclose + NULL|self)
                CALL                     0
                GET_AWAITABLE            0
                LOAD_CONST               0 (None)
       L24:     SEND                     4 (to L28)
       L25:     YIELD_VALUE              1
       L26:     RESUME                   3
                JUMP_BACKWARD_NO_INTERRUPT 5 (to L24)
       L27:     CLEANUP_THROW
       L28:     END_SEND
                POP_TOP
                RERAISE                  0

  --   L29:     COPY                     3
                POP_EXCEPT
                RERAISE                  1
       L30:     CALL_INTRINSIC_1         3 (INTRINSIC_STOPITERATION_ERROR)
                RERAISE                  1
ExceptionTable:
  L1 to L3 -> L30 [0] lasti
  L3 to L4 -> L17 [2]
  L4 to L6 -> L30 [0] lasti
  L7 to L9 -> L23 [0]
  L9 to L10 -> L19 [2]
  L10 to L12 -> L23 [0]
  L12 to L14 -> L30 [0] lasti
  L14 to L15 -> L21 [3]
  L15 to L18 -> L30 [0] lasti
  L19 to L20 -> L23 [0]
  L21 to L22 -> L30 [0] lasti
  L23 to L25 -> L29 [1] lasti
  L25 to L26 -> L27 [4]
  L26 to L29 -> L29 [1] lasti
  L29 to L30 -> L30 [0] lasti

Disassembly of <code object _format_backup_summary at 0x000001EE5E786810, file "discord_backup\tui.py", line 100>:
100           RESUME                   0

101           LOAD_FAST                0 (result)
              LOAD_ATTR                1 (summary + NULL|self)
              CALL                     0
              STORE_FAST               3 (summary)

102           LOAD_FAST                3 (summary)
              LOAD_CONST               1 ('guilds')
              BINARY_SUBSCR
              STORE_FAST               4 (guilds)

103           LOAD_FAST                3 (summary)
              LOAD_CONST               2 ('group_chats')
              BINARY_SUBSCR
              STORE_FAST               5 (groups)

105           LOAD_CONST               3 ('Backup completed successfully!\n\nSaved file: ')

106           LOAD_FAST                1 (path)
              FORMAT_SIMPLE
              LOAD_CONST               4 ('\nGuilds: ')

107           LOAD_FAST                4 (guilds)
              LOAD_CONST               5 ('success')
              BINARY_SUBSCR
              FORMAT_SIMPLE
              LOAD_CONST               6 (' / ')
              LOAD_FAST                4 (guilds)
              LOAD_CONST               7 ('total')
              BINARY_SUBSCR
              FORMAT_SIMPLE
              LOAD_CONST               8 ('\nGroup chats: ')

108           LOAD_FAST                5 (groups)
              LOAD_CONST               5 ('success')
              BINARY_SUBSCR
              FORMAT_SIMPLE
              LOAD_CONST               6 (' / ')
              LOAD_FAST                5 (groups)
              LOAD_CONST               7 ('total')
              BINARY_SUBSCR
              FORMAT_SIMPLE
              LOAD_CONST               9 ('\nElapsed: ')

109           LOAD_FAST                0 (result)
              LOAD_ATTR                2 (duration)
              LOAD_CONST              10 ('.1f')
              FORMAT_WITH_SPEC
              LOAD_CONST              11 ('s\n\nLatest activity:\n')

105           BUILD_STRING            13

110           LOAD_FAST                2 (logs)

105           BINARY_OP                0 (+)

104           RETURN_VALUE

Disassembly of <code object _format_restore_summary at 0x000001EE5E78F770, file "discord_backup\tui.py", line 114>:
114           RESUME                   0

116           LOAD_CONST               1 ('Restore completed!\n\nHelper guild id: ')

117           LOAD_FAST                0 (guild_id)
              FORMAT_SIMPLE
              LOAD_CONST               2 ('\nFavourite GIFs: ')

118           LOAD_FAST                1 (gifs_status)
              FORMAT_SIMPLE
              LOAD_CONST               3 ('\nGuild folders restored: ')

119           LOAD_FAST                2 (folders)
              TO_BOOL
              POP_JUMP_IF_FALSE        2 (to L1)
              LOAD_CONST               4 ('Yes')
              JUMP_FORWARD             1 (to L2)
      L1:     LOAD_CONST               5 ('No')
      L2:     FORMAT_SIMPLE
              LOAD_CONST               6 ('\nElapsed: ')

120           LOAD_FAST                3 (duration)
              LOAD_CONST               7 ('.1f')
              FORMAT_WITH_SPEC
              LOAD_CONST               8 ('s\n\nLatest activity:\n')

116           BUILD_STRING             9

121           LOAD_FAST                4 (logs)

116           BINARY_OP                0 (+)

115           RETURN_VALUE

Disassembly of <code object _show_with_details at 0x000001EE5E84CB20, file "discord_backup\tui.py", line 125>:
125           RESUME                   0

126           LOAD_CONST               1 (('Close', 'close'))
              BUILD_LIST               1
              STORE_FAST               3 (buttons)

127           LOAD_FAST                2 (details)
              TO_BOOL
              POP_JUMP_IF_FALSE       18 (to L1)

128           LOAD_FAST                3 (buttons)
              LOAD_ATTR                1 (insert + NULL|self)
              LOAD_CONST               2 (0)
              LOAD_CONST               3 (('View details', 'details'))
              CALL                     2
              POP_TOP

129   L1:     LOAD_GLOBAL              3 (button_dialog + NULL)
              LOAD_FAST_LOAD_FAST      1 (title, summary)
              LOAD_FAST                3 (buttons)
              LOAD_CONST               4 (('title', 'text', 'buttons'))
              CALL_KW                  3
              LOAD_ATTR                5 (run + NULL|self)
              CALL                     0
              STORE_FAST               4 (choice)

130           LOAD_FAST                4 (choice)
              LOAD_CONST               5 ('details')
              COMPARE_OP              88 (bool(==))
              POP_JUMP_IF_FALSE       36 (to L3)
              LOAD_FAST                2 (details)
              TO_BOOL
              POP_JUMP_IF_FALSE       28 (to L2)

131           LOAD_GLOBAL              7 (message_dialog + NULL)
              LOAD_FAST                0 (title)
              FORMAT_SIMPLE
              LOAD_CONST               6 (' ? details')
              BUILD_STRING             2
              LOAD_FAST                2 (details)
              LOAD_CONST               7 (('title', 'text'))
              CALL_KW                  2
              LOAD_ATTR                5 (run + NULL|self)
              CALL                     0
              POP_TOP
              RETURN_CONST             0 (None)

130   L2:     RETURN_CONST             0 (None)
      L3:     RETURN_CONST             0 (None)

Disassembly of <code object _show_error at 0x000001EE5E577DE0, file "discord_backup\tui.py", line 134>:
134           RESUME                   0

135           LOAD_FAST                2 (logs)
              TO_BOOL
              POP_JUMP_IF_FALSE       20 (to L2)
              LOAD_GLOBAL              1 (_strip_ansi + NULL)
              LOAD_FAST                2 (logs)
              COPY                     1
              TO_BOOL
              POP_JUMP_IF_TRUE         2 (to L1)
              POP_TOP
              LOAD_CONST               1 ('')
      L1:     CALL                     1
              JUMP_FORWARD             1 (to L3)
      L2:     LOAD_CONST               0 (None)
      L3:     STORE_FAST               3 (details)

136           LOAD_FAST                3 (details)
              TO_BOOL
              POP_JUMP_IF_FALSE        5 (to L4)
              LOAD_FAST                1 (error)
              FORMAT_SIMPLE
              LOAD_CONST               2 ("\n\nPress 'View details' to see diagnostic output.")
              BUILD_STRING             2
              JUMP_FORWARD            10 (to L5)
      L4:     LOAD_GLOBAL              3 (str + NULL)
              LOAD_FAST                1 (error)
              CALL                     1
      L5:     STORE_FAST               4 (summary)

137           LOAD_GLOBAL              5 (_show_with_details + NULL)
              LOAD_FAST_LOAD_FAST      4 (title, summary)
              LOAD_FAST                3 (details)
              CALL                     3
              POP_TOP
              RETURN_CONST             0 (None)

Disassembly of <code object _discover_tokens_with_loading at 0x000001EE5E815830, file "discord_backup\tui.py", line 140>:
  --           MAKE_CELL                1 (time)

 140           RESUME                   0

 141           LOAD_CONST               5 (('handle', 'ProgressHandle', 'return', 'list[DiscoveredToken]'))
               LOAD_FAST                1 (time)
               BUILD_TUPLE              1
               LOAD_CONST               1 (<code object worker at 0x000001EE5E84CCB0, file "discord_backup\tui.py", line 141>)
               MAKE_FUNCTION
               SET_FUNCTION_ATTRIBUTE   8 (closure)
               SET_FUNCTION_ATTRIBUTE   4 (annotations)
               STORE_FAST               0 (worker)

 148           LOAD_CONST               2 (0)
               LOAD_CONST               0 (None)
               IMPORT_NAME              0 (time)
               STORE_DEREF              1 (time)

 150           LOAD_GLOBAL              3 (run_with_loading + NULL)
               LOAD_CONST               3 ('Token discovery')
               LOAD_CONST               4 ('Preparing...')
               LOAD_FAST                0 (worker)
               CALL                     3
               RETURN_VALUE

Disassembly of <code object worker at 0x000001EE5E84CCB0, file "discord_backup\tui.py", line 141>:
  --           COPY_FREE_VARS           1

 141           RESUME                   0

 142           LOAD_FAST                0 (handle)
               LOAD_ATTR                1 (update + NULL|self)
               LOAD_CONST               1 ('Scanning local storage for Discord tokens...')
               CALL                     1
               POP_TOP

 143           LOAD_GLOBAL              2 (asyncio)
               LOAD_ATTR                4 (run)
               PUSH_NULL
               LOAD_GLOBAL              7 (_async_discover_tokens + NULL)
               CALL                     0
               CALL                     1
               STORE_FAST               1 (tokens)

 144           LOAD_FAST                0 (handle)
               LOAD_ATTR                1 (update + NULL|self)
               LOAD_CONST               2 ('Found ')
               LOAD_GLOBAL              9 (len + NULL)
               LOAD_FAST                1 (tokens)
               CALL                     1
               FORMAT_SIMPLE
               LOAD_CONST               3 (' token(s)')
               BUILD_STRING             3
               CALL                     1
               POP_TOP

 145           LOAD_DEREF               2 (time)
               LOAD_ATTR               11 (sleep + NULL|self)
               LOAD_CONST               4 (0.2)
               CALL                     1
               POP_TOP

 146           LOAD_FAST                1 (tokens)
               RETURN_VALUE

Disassembly of <code object _discover_and_choose_token at 0x000001EE5C72CD60, file "discord_backup\tui.py", line 153>:
 153            RESUME                   0

 154            NOP

 155    L1:     LOAD_GLOBAL              1 (_discover_tokens_with_loading + NULL)
                CALL                     0
                STORE_FAST               1 (tokens)

 159    L2:     LOAD_FAST                1 (tokens)
                TO_BOOL
                POP_JUMP_IF_TRUE        25 (to L3)

 160            LOAD_GLOBAL              7 (message_dialog + NULL)
                LOAD_CONST               2 ('No tokens')
                LOAD_CONST               3 ('No Discord tokens were found on this machine.')
                LOAD_CONST               4 (('title', 'text'))
                CALL_KW                  2
                LOAD_ATTR                9 (run + NULL|self)
                CALL                     0
                POP_TOP

 161            RETURN_CONST             0 (None)

 162    L3:     LOAD_GLOBAL             11 (enumerate + NULL)
                LOAD_FAST                1 (tokens)
                CALL                     1
                GET_ITER
                LOAD_FAST_AND_CLEAR      3 (idx)
                LOAD_FAST_AND_CLEAR      4 (tok)
                SWAP                     3
        L4:     BUILD_LIST               0
                SWAP                     2
                GET_ITER
        L5:     FOR_ITER                34 (to L6)
                UNPACK_SEQUENCE          2
                STORE_FAST_STORE_FAST   52 (idx, tok)
                LOAD_FAST_LOAD_FAST     52 (idx, tok)
                LOAD_ATTR               12 (user_tag)
                FORMAT_SIMPLE
                LOAD_CONST               5 (' (')
                LOAD_FAST                4 (tok)
                LOAD_ATTR               14 (source)
                FORMAT_SIMPLE
                LOAD_CONST               6 (')')
                BUILD_STRING             4
                BUILD_TUPLE              2
                LIST_APPEND              2
                JUMP_BACKWARD           36 (to L5)
        L6:     END_FOR
                POP_TOP
        L7:     STORE_FAST               5 (values)
                STORE_FAST               3 (idx)
                STORE_FAST               4 (tok)

 163            LOAD_GLOBAL             17 (radiolist_dialog + NULL)

 164            LOAD_FAST                0 (title)

 165            LOAD_CONST               7 ('Select a token (arrow keys + Enter)')

 166            LOAD_FAST                5 (values)

 167            LOAD_CONST               8 ('Use token')

 168            LOAD_CONST               9 ('Cancel')

 163            LOAD_CONST              10 (('title', 'text', 'values', 'ok_text', 'cancel_text'))
                CALL_KW                  5

 169            LOAD_ATTR                9 (run + NULL|self)
                CALL                     0

 163            STORE_FAST               6 (choice)

 170            LOAD_FAST                6 (choice)
                POP_JUMP_IF_NOT_NONE     1 (to L8)

 171            RETURN_CONST             0 (None)

 172    L8:     LOAD_FAST_LOAD_FAST     22 (tokens, choice)
                BINARY_SUBSCR
                RETURN_VALUE

  --    L9:     PUSH_EXC_INFO

 156            LOAD_GLOBAL              2 (Exception)
                CHECK_EXC_MATCH
                POP_JUMP_IF_FALSE       22 (to L13)
                STORE_FAST               2 (exc)

 157   L10:     LOAD_GLOBAL              5 (_show_error + NULL)
                LOAD_CONST               1 ('Token discovery failed')
                LOAD_FAST                2 (exc)
                CALL                     2
                POP_TOP

 158   L11:     POP_EXCEPT
                LOAD_CONST               0 (None)
                STORE_FAST               2 (exc)
                DELETE_FAST              2 (exc)
                RETURN_CONST             0 (None)

  --   L12:     LOAD_CONST               0 (None)
                STORE_FAST               2 (exc)
                DELETE_FAST              2 (exc)
                RERAISE                  1

 156   L13:     RERAISE                  0

  --   L14:     COPY                     3
                POP_EXCEPT
                RERAISE                  1
       L15:     SWAP                     2
                POP_TOP

 162            SWAP                     3
                STORE_FAST               4 (tok)
                STORE_FAST               3 (idx)
                RERAISE                  0
ExceptionTable:
  L1 to L2 -> L9 [0]
  L4 to L7 -> L15 [3]
  L9 to L10 -> L14 [1] lasti
  L10 to L11 -> L12 [1] lasti
  L12 to L14 -> L14 [1] lasti

Disassembly of <code object _prompt_for_token at 0x000001EE5E7F5430, file "discord_backup\tui.py", line 175>:
175           RESUME                   0

176           LOAD_GLOBAL              1 (input_dialog + NULL)
              LOAD_FAST                0 (label)
              LOAD_CONST               1 ('Enter the Discord user token:')
              LOAD_CONST               2 (('title', 'text'))
              CALL_KW                  2
              LOAD_ATTR                3 (run + NULL|self)
              CALL                     0
              STORE_FAST               1 (token)

177           LOAD_FAST                1 (token)
              TO_BOOL
              POP_JUMP_IF_FALSE       16 (to L1)

178           LOAD_FAST                1 (token)
              LOAD_ATTR                5 (strip + NULL|self)
              CALL                     0
              STORE_FAST               1 (token)

179   L1:     LOAD_FAST                1 (token)
              COPY                     1
              TO_BOOL
              POP_JUMP_IF_TRUE         2 (to L2)
              POP_TOP
              LOAD_CONST               0 (None)
      L2:     RETURN_VALUE

Disassembly of <code object _prompt_for_bot_token at 0x000001EE5E7F52F0, file "discord_backup\tui.py", line 182>:
182           RESUME                   0

183           LOAD_GLOBAL              1 (input_dialog + NULL)
              LOAD_CONST               1 ('Bot Token')
              LOAD_CONST               2 ('Enter bot token used for username lookups:')
              LOAD_CONST               3 (('title', 'text'))
              CALL_KW                  2
              LOAD_ATTR                3 (run + NULL|self)
              CALL                     0
              STORE_FAST               0 (token)

184           LOAD_FAST                0 (token)
              TO_BOOL
              POP_JUMP_IF_FALSE       16 (to L1)

185           LOAD_FAST                0 (token)
              LOAD_ATTR                5 (strip + NULL|self)
              CALL                     0
              STORE_FAST               0 (token)

186   L1:     LOAD_FAST                0 (token)
              COPY                     1
              TO_BOOL
              POP_JUMP_IF_TRUE         2 (to L2)
              POP_TOP
              LOAD_CONST               0 (None)
      L2:     RETURN_VALUE

Disassembly of <code object _run_backup_flow at 0x000001EE5E980B90, file "discord_backup\tui.py", line 189>:
  --            MAKE_CELL                0 (token)
                MAKE_CELL                6 (buffer)
                MAKE_CELL                7 (config)

 189            RESUME                   0

 190            LOAD_GLOBAL              0 (AppConfig)
                LOAD_ATTR                2 (load)
                PUSH_NULL
                CALL                     0
                STORE_DEREF              7 (config)

 191            LOAD_GLOBAL              4 (io)
                LOAD_ATTR                6 (StringIO)
                PUSH_NULL
                CALL                     0
                STORE_DEREF              6 (buffer)

 193            LOAD_CONST               8 (('handle', 'ProgressHandle', 'return', 'tuple[BackupResult, Path]'))
                LOAD_FAST                6 (buffer)
                LOAD_FAST                7 (config)
                LOAD_FAST                0 (token)
                BUILD_TUPLE              3
                LOAD_CONST               1 (<code object worker at 0x000001EE5C5CE730, file "discord_backup\tui.py", line 193>)
                MAKE_FUNCTION
                SET_FUNCTION_ATTRIBUTE   8 (closure)
                SET_FUNCTION_ATTRIBUTE   4 (annotations)
                STORE_FAST               1 (worker)

 201            NOP

 202    L1:     LOAD_GLOBAL              9 (run_with_loading + NULL)
                LOAD_CONST               2 ('Backup in progress')
                LOAD_CONST               3 ('Starting backup...')
                LOAD_FAST                1 (worker)
                CALL                     3
                UNPACK_SEQUENCE          2
                STORE_FAST_STORE_FAST   35 (result, path)

 212    L2:     LOAD_GLOBAL             13 (_strip_ansi + NULL)
                LOAD_DEREF               6 (buffer)
                LOAD_ATTR               15 (getvalue + NULL|self)
                CALL                     0
                CALL                     1
                LOAD_CONST               6 (-2000)
                LOAD_CONST               0 (None)
                BINARY_SLICE
                STORE_FAST               5 (logs)

 213            LOAD_GLOBAL             21 (_show_with_details + NULL)
                LOAD_CONST               7 ('Backup complete')
                LOAD_GLOBAL             23 (_format_backup_summary + NULL)
                LOAD_FAST_LOAD_FAST     35 (result, path)
                LOAD_FAST                5 (logs)
                CALL                     3
                LOAD_FAST                5 (logs)
                CALL                     3
                POP_TOP
                RETURN_CONST             0 (None)

  --    L3:     PUSH_EXC_INFO

 203            LOAD_GLOBAL             10 (BackupError)
                CHECK_EXC_MATCH
                POP_JUMP_IF_FALSE       47 (to L7)
                STORE_FAST               4 (exc)

 204    L4:     LOAD_GLOBAL             13 (_strip_ansi + NULL)
                LOAD_DEREF               6 (buffer)
                LOAD_ATTR               15 (getvalue + NULL|self)
                CALL                     0
                CALL                     1
                STORE_FAST               5 (logs)

 205            LOAD_GLOBAL             17 (_show_error + NULL)
                LOAD_CONST               4 ('Backup failed')
                LOAD_FAST_LOAD_FAST     69 (exc, logs)
                CALL                     3
                POP_TOP

 206    L5:     POP_EXCEPT
                LOAD_CONST               0 (None)
                STORE_FAST               4 (exc)
                DELETE_FAST              4 (exc)
                RETURN_CONST             0 (None)

  --    L6:     LOAD_CONST               0 (None)
                STORE_FAST               4 (exc)
                DELETE_FAST              4 (exc)
                RERAISE                  1

 207    L7:     LOAD_GLOBAL             18 (Exception)
                CHECK_EXC_MATCH
                POP_JUMP_IF_FALSE       47 (to L11)
                STORE_FAST               4 (exc)

 208    L8:     LOAD_GLOBAL             13 (_strip_ansi + NULL)
                LOAD_DEREF               6 (buffer)
                LOAD_ATTR               15 (getvalue + NULL|self)
                CALL                     0
                CALL                     1
                STORE_FAST               5 (logs)

 209            LOAD_GLOBAL             17 (_show_error + NULL)
                LOAD_CONST               5 ('Unexpected error')
                LOAD_FAST_LOAD_FAST     69 (exc, logs)
                CALL                     3
                POP_TOP

 210    L9:     POP_EXCEPT
                LOAD_CONST               0 (None)
                STORE_FAST               4 (exc)
                DELETE_FAST              4 (exc)
                RETURN_CONST             0 (None)

  --   L10:     LOAD_CONST               0 (None)
                STORE_FAST               4 (exc)
                DELETE_FAST              4 (exc)
                RERAISE                  1

 207   L11:     RERAISE                  0

  --   L12:     COPY                     3
                POP_EXCEPT
                RERAISE                  1
ExceptionTable:
  L1 to L2 -> L3 [0]
  L3 to L4 -> L12 [1] lasti
  L4 to L5 -> L6 [1] lasti
  L6 to L8 -> L12 [1] lasti
  L8 to L9 -> L10 [1] lasti
  L10 to L12 -> L12 [1] lasti

Disassembly of <code object worker at 0x000001EE5C5CE730, file "discord_backup\tui.py", line 193>:
  --           COPY_FREE_VARS           3
               MAKE_CELL                0 (handle)

 193           RESUME                   0

 194           LOAD_FAST                0 (handle)
               BUILD_TUPLE              1
               LOAD_CONST               1 (<code object <lambda> at 0x000001EE5E816730, file "discord_backup\tui.py", line 194>)
               MAKE_FUNCTION
               SET_FUNCTION_ATTRIBUTE   8 (closure)
               STORE_FAST               1 (stripped_update)

 195           LOAD_GLOBAL              1 (Console + NULL)
               LOAD_DEREF               6 (config)
               LOAD_ATTR                2 (colour)
               LOAD_DEREF               5 (buffer)
               LOAD_FAST                1 (stripped_update)
               LOAD_CONST               2 (('accent', 'stream', 'status_callback'))
               CALL_KW                  3
               STORE_FAST               2 (console)

 196           LOAD_DEREF               0 (handle)
               LOAD_ATTR                5 (update + NULL|self)
               LOAD_CONST               3 ('Authenticating token...')
               CALL                     1
               POP_TOP

 197           LOAD_GLOBAL              6 (asyncio)
               LOAD_ATTR                8 (run)
               PUSH_NULL
               LOAD_GLOBAL             11 (_async_run_backup + NULL)
               LOAD_DEREF               7 (token)
               LOAD_DEREF               6 (config)
               LOAD_FAST                2 (console)
               CALL                     3
               CALL                     1
               UNPACK_SEQUENCE          2
               STORE_FAST_STORE_FAST   52 (result, path)

 198           LOAD_DEREF               0 (handle)
               LOAD_ATTR                5 (update + NULL|self)
               LOAD_CONST               4 ('Finalising backup...')
               CALL                     1
               POP_TOP

 199           LOAD_FAST_LOAD_FAST     52 (result, path)
               BUILD_TUPLE              2
               RETURN_VALUE

Disassembly of <code object <lambda> at 0x000001EE5E816730, file "discord_backup\tui.py", line 194>:
  --           COPY_FREE_VARS           1

 194           RESUME                   0
               LOAD_DEREF               1 (handle)
               LOAD_ATTR                1 (update + NULL|self)
               LOAD_GLOBAL              3 (_strip_ansi + NULL)
               LOAD_FAST                0 (msg)
               CALL                     1
               CALL                     1
               RETURN_VALUE

Disassembly of <code object _request_backup_file at 0x000001EE5E801E30, file "discord_backup\tui.py", line 216>:
216           RESUME                   0

217           LOAD_GLOBAL              0 (path_dialog)
              TO_BOOL
              POP_JUMP_IF_FALSE       43 (to L1)

218           LOAD_GLOBAL              1 (path_dialog + NULL)

219           LOAD_CONST               1 ('Select backup file')

220           LOAD_CONST               2 ('Choose a .bkup file to restore:')

221           LOAD_GLOBAL              3 (str + NULL)
              LOAD_GLOBAL              5 (_project_root + NULL)
              CALL                     0
              CALL                     1

218           LOAD_CONST               3 (('title', 'text', 'path'))
              CALL_KW                  3

222           LOAD_ATTR                7 (run + NULL|self)
              CALL                     0

218           STORE_FAST               0 (selection)
              JUMP_FORWARD            24 (to L2)

224   L1:     LOAD_GLOBAL              9 (input_dialog + NULL)

225           LOAD_CONST               4 ('Backup file')

226           LOAD_CONST               5 ('Enter the full path to the .bkup file:')

224           LOAD_CONST               6 (('title', 'text'))
              CALL_KW                  2

227           LOAD_ATTR                7 (run + NULL|self)
              CALL                     0

224           STORE_FAST               0 (selection)

228   L2:     LOAD_FAST                0 (selection)
              TO_BOOL
              POP_JUMP_IF_TRUE         1 (to L3)

229           RETURN_CONST             0 (None)

230   L3:     LOAD_GLOBAL             11 (Path + NULL)
              LOAD_FAST                0 (selection)
              CALL                     1
              STORE_FAST               1 (backup_path)

231           LOAD_FAST                1 (backup_path)
              LOAD_ATTR               13 (exists + NULL|self)
              CALL                     0
              TO_BOOL
              POP_JUMP_IF_TRUE        28 (to L4)

232           LOAD_GLOBAL             15 (message_dialog + NULL)
              LOAD_CONST               7 ('File not found')
              LOAD_CONST               8 ('Could not find ')
              LOAD_FAST                1 (backup_path)
              FORMAT_SIMPLE
              BUILD_STRING             2
              LOAD_CONST               6 (('title', 'text'))
              CALL_KW                  2
              LOAD_ATTR                7 (run + NULL|self)
              CALL                     0
              POP_TOP

233           RETURN_CONST             0 (None)

234   L4:     LOAD_FAST                1 (backup_path)
              RETURN_VALUE

Disassembly of <code object _run_restore_flow at 0x000001EE5C4B6160, file "discord_backup\tui.py", line 237>:
  --            MAKE_CELL               10 (allow_mismatch)
                MAKE_CELL               11 (backup_data)
                MAKE_CELL               12 (bot_token)
                MAKE_CELL               13 (buffer)
                MAKE_CELL               14 (config)
                MAKE_CELL               15 (restore_folders)
                MAKE_CELL               16 (user_token)

 237            RESUME                   0

 238            LOAD_GLOBAL              1 (_request_backup_file + NULL)
                CALL                     0
                STORE_FAST               0 (backup_path)

 239            LOAD_FAST                0 (backup_path)
                TO_BOOL
                POP_JUMP_IF_TRUE         1 (to L1)

 240            RETURN_CONST             0 (None)

 242    L1:     NOP

 243    L2:     LOAD_GLOBAL              2 (json)
                LOAD_ATTR                4 (loads)
                PUSH_NULL
                LOAD_FAST                0 (backup_path)
                LOAD_ATTR                7 (read_text + NULL|self)
                LOAD_CONST               1 ('utf-8')
                LOAD_CONST               2 (('encoding',))
                CALL_KW                  1
                CALL                     1
                STORE_DEREF             11 (backup_data)

 248    L3:     LOAD_GLOBAL             13 (radiolist_dialog + NULL)

 249            LOAD_CONST               4 ('User Token')

 250            LOAD_CONST               5 ('Choose how to supply the user token (arrow keys + Enter)')

 252            LOAD_CONST               6 (('scan', 'Select from discovered tokens'))

 253            LOAD_CONST               7 (('manual', 'Paste token manually'))

 251            BUILD_LIST               2

 255            LOAD_CONST               8 ('Continue')

 256            LOAD_CONST               9 ('Cancel')

 248            LOAD_CONST              10 (('title', 'text', 'values', 'ok_text', 'cancel_text'))
                CALL_KW                  5

 257            LOAD_ATTR               15 (run + NULL|self)
                CALL                     0

 248            STORE_FAST               2 (token_option)

 258            LOAD_FAST                2 (token_option)
                POP_JUMP_IF_NOT_NONE     1 (to L4)

 259            RETURN_CONST             0 (None)

 261    L4:     LOAD_FAST                2 (token_option)
                LOAD_CONST              11 ('scan')
                COMPARE_OP              88 (bool(==))
                POP_JUMP_IF_FALSE       32 (to L6)

 262            LOAD_GLOBAL             17 (_discover_and_choose_token + NULL)
                LOAD_CONST              12 ('Select user token')
                CALL                     1
                STORE_FAST               3 (selection)

 263            LOAD_FAST                3 (selection)
                TO_BOOL
                POP_JUMP_IF_TRUE         1 (to L5)

 264            RETURN_CONST             0 (None)

 265    L5:     LOAD_FAST                3 (selection)
                LOAD_ATTR               18 (token)
                STORE_DEREF             16 (user_token)
                JUMP_FORWARD            19 (to L7)

 267    L6:     LOAD_GLOBAL             21 (_prompt_for_token + NULL)
                LOAD_CONST               4 ('User Token')
                CALL                     1
                STORE_DEREF             16 (user_token)

 268            LOAD_DEREF              16 (user_token)
                TO_BOOL
                POP_JUMP_IF_TRUE         1 (to L7)

 269            RETURN_CONST             0 (None)

 271    L7:     LOAD_GLOBAL             23 (_prompt_for_bot_token + NULL)
                CALL                     0
                STORE_DEREF             12 (bot_token)

 272            LOAD_DEREF              12 (bot_token)
                TO_BOOL
                POP_JUMP_IF_TRUE         1 (to L8)

 273            RETURN_CONST             0 (None)

 275    L8:     LOAD_GLOBAL             25 (yes_no_dialog + NULL)

 276            LOAD_CONST              13 ('Restore Guild Folders')

 277            LOAD_CONST              14 ('Restore server folders when possible?')

 275            LOAD_CONST              15 (('title', 'text'))
                CALL_KW                  2

 278            LOAD_ATTR               15 (run + NULL|self)
                CALL                     0

 275            STORE_DEREF             15 (restore_folders)

 280            LOAD_GLOBAL             25 (yes_no_dialog + NULL)

 281            LOAD_CONST              16 ('Version Mismatch')

 282            LOAD_CONST              17 ('Ignore backup version mismatches?')

 280            LOAD_CONST              15 (('title', 'text'))
                CALL_KW                  2

 283            LOAD_ATTR               15 (run + NULL|self)
                CALL                     0

 280            STORE_DEREF             10 (allow_mismatch)

 285            LOAD_GLOBAL             26 (AppConfig)
                LOAD_ATTR               28 (load)
                PUSH_NULL
                CALL                     0
                STORE_DEREF             14 (config)

 286            LOAD_GLOBAL             30 (io)
                LOAD_ATTR               32 (StringIO)
                PUSH_NULL
                CALL                     0
                STORE_DEREF             13 (buffer)

 288            LOAD_CONST              25 (('handle', 'ProgressHandle', 'return', 'tuple[str, str, bool, float]'))
                LOAD_FAST               10 (allow_mismatch)
                LOAD_FAST               11 (backup_data)
                LOAD_FAST               12 (bot_token)
                LOAD_FAST               13 (buffer)
                LOAD_FAST               14 (config)
                LOAD_FAST               15 (restore_folders)
                LOAD_FAST               16 (user_token)
                BUILD_TUPLE              7
                LOAD_CONST              18 (<code object worker at 0x000001EE5E850B90, file "discord_backup\tui.py", line 288>)
                MAKE_FUNCTION
                SET_FUNCTION_ATTRIBUTE   8 (closure)
                SET_FUNCTION_ATTRIBUTE   4 (annotations)
                STORE_FAST               4 (worker)

 305            NOP

 306    L9:     LOAD_GLOBAL             35 (run_with_loading + NULL)

 307            LOAD_CONST              19 ('Restoring backup')

 308            LOAD_CONST              20 ('Starting restore...')

 309            LOAD_FAST                4 (worker)

 306            CALL                     3
                UNPACK_SEQUENCE          4
                STORE_FAST_STORE_FAST   86 (guild_id, gif_status)
                STORE_FAST_STORE_FAST  120 (folders, duration)

 320   L10:     LOAD_GLOBAL             39 (_strip_ansi + NULL)
                LOAD_DEREF              13 (buffer)
                LOAD_ATTR               41 (getvalue + NULL|self)
                CALL                     0
                CALL                     1
                LOAD_CONST              23 (-2000)
                LOAD_CONST               0 (None)
                BINARY_SLICE
                STORE_FAST               9 (logs)

 321            LOAD_GLOBAL             43 (_show_with_details + NULL)

 322            LOAD_CONST              24 ('Restore complete')

 323            LOAD_GLOBAL             45 (_format_restore_summary + NULL)
                LOAD_FAST_LOAD_FAST     86 (guild_id, gif_status)
                LOAD_FAST_LOAD_FAST    120 (folders, duration)
                LOAD_FAST                9 (logs)
                CALL                     5

 324            LOAD_FAST                9 (logs)

 321            CALL                     3
                POP_TOP
                RETURN_CONST             0 (None)

  --   L11:     PUSH_EXC_INFO

 244            LOAD_GLOBAL              8 (Exception)
                CHECK_EXC_MATCH
                POP_JUMP_IF_FALSE       22 (to L15)
                STORE_FAST               1 (exc)

 245   L12:     LOAD_GLOBAL             11 (_show_error + NULL)
                LOAD_CONST               3 ('Invalid backup')
                LOAD_FAST                1 (exc)
                CALL                     2
                POP_TOP

 246   L13:     POP_EXCEPT
                LOAD_CONST               0 (None)
                STORE_FAST               1 (exc)
                DELETE_FAST              1 (exc)
                RETURN_CONST             0 (None)

  --   L14:     LOAD_CONST               0 (None)
                STORE_FAST               1 (exc)
                DELETE_FAST              1 (exc)
                RERAISE                  1

 244   L15:     RERAISE                  0

  --   L16:     COPY                     3
                POP_EXCEPT
                RERAISE                  1
       L17:     PUSH_EXC_INFO

 311            LOAD_GLOBAL             36 (RestoreError)
                CHECK_EXC_MATCH
                POP_JUMP_IF_FALSE       47 (to L21)
                STORE_FAST               1 (exc)

 312   L18:     LOAD_GLOBAL             39 (_strip_ansi + NULL)
                LOAD_DEREF              13 (buffer)
                LOAD_ATTR               41 (getvalue + NULL|self)
                CALL                     0
                CALL                     1
                STORE_FAST               9 (logs)

 313            LOAD_GLOBAL             11 (_show_error + NULL)
                LOAD_CONST              21 ('Restore failed')
                LOAD_FAST_LOAD_FAST     25 (exc, logs)
                CALL                     3
                POP_TOP

 314   L19:     POP_EXCEPT
                LOAD_CONST               0 (None)
                STORE_FAST               1 (exc)
                DELETE_FAST              1 (exc)
                RETURN_CONST             0 (None)

  --   L20:     LOAD_CONST               0 (None)
                STORE_FAST               1 (exc)
                DELETE_FAST              1 (exc)
                RERAISE                  1

 315   L21:     LOAD_GLOBAL              8 (Exception)
                CHECK_EXC_MATCH
                POP_JUMP_IF_FALSE       47 (to L25)
                STORE_FAST               1 (exc)

 316   L22:     LOAD_GLOBAL             39 (_strip_ansi + NULL)
                LOAD_DEREF              13 (buffer)
                LOAD_ATTR               41 (getvalue + NULL|self)
                CALL                     0
                CALL                     1
                STORE_FAST               9 (logs)

 317            LOAD_GLOBAL             11 (_show_error + NULL)
                LOAD_CONST              22 ('Unexpected error')
                LOAD_FAST_LOAD_FAST     25 (exc, logs)
                CALL                     3
                POP_TOP

 318   L23:     POP_EXCEPT
                LOAD_CONST               0 (None)
                STORE_FAST               1 (exc)
                DELETE_FAST              1 (exc)
                RETURN_CONST             0 (None)

  --   L24:     LOAD_CONST               0 (None)
                STORE_FAST               1 (exc)
                DELETE_FAST              1 (exc)
                RERAISE                  1

 315   L25:     RERAISE                  0

  --   L26:     COPY                     3
                POP_EXCEPT
                RERAISE                  1
ExceptionTable:
  L2 to L3 -> L11 [0]
  L9 to L10 -> L17 [0]
  L11 to L12 -> L16 [1] lasti
  L12 to L13 -> L14 [1] lasti
  L14 to L16 -> L16 [1] lasti
  L17 to L18 -> L26 [1] lasti
  L18 to L19 -> L20 [1] lasti
  L20 to L22 -> L26 [1] lasti
  L22 to L23 -> L24 [1] lasti
  L24 to L26 -> L26 [1] lasti

Disassembly of <code object worker at 0x000001EE5E850B90, file "discord_backup\tui.py", line 288>:
  --           COPY_FREE_VARS           7
               MAKE_CELL                0 (handle)

 288           RESUME                   0

 289           LOAD_FAST                0 (handle)
               BUILD_TUPLE              1
               LOAD_CONST               1 (<code object <lambda> at 0x000001EE5E816D30, file "discord_backup\tui.py", line 289>)
               MAKE_FUNCTION
               SET_FUNCTION_ATTRIBUTE   8 (closure)
               STORE_FAST               1 (stripped_update)

 290           LOAD_GLOBAL              1 (Console + NULL)
               LOAD_DEREF               8 (config)
               LOAD_ATTR                2 (colour)
               LOAD_DEREF               7 (buffer)
               LOAD_FAST                1 (stripped_update)
               LOAD_CONST               2 (('accent', 'stream', 'status_callback'))
               CALL_KW                  3
               STORE_FAST               2 (console)

 291           LOAD_DEREF               0 (handle)
               LOAD_ATTR                5 (update + NULL|self)
               LOAD_CONST               3 ('Preparing restore...')
               CALL                     1
               POP_TOP

 292           LOAD_GLOBAL              6 (asyncio)
               LOAD_ATTR                8 (run)
               PUSH_NULL

 293           LOAD_GLOBAL             11 (_async_run_restore + NULL)

 294           LOAD_DEREF               5 (backup_data)

 295           LOAD_DEREF              10 (user_token)

 296           LOAD_DEREF               6 (bot_token)

 297           LOAD_DEREF               9 (restore_folders)

 298           LOAD_DEREF               4 (allow_mismatch)

 299           LOAD_FAST                2 (console)

 293           CALL                     6

 292           CALL                     1
               STORE_FAST               3 (result)

 302           LOAD_DEREF               0 (handle)
               LOAD_ATTR                5 (update + NULL|self)
               LOAD_CONST               4 ('Finishing up...')
               CALL                     1
               POP_TOP

 303           LOAD_FAST                3 (result)
               RETURN_VALUE

Disassembly of <code object <lambda> at 0x000001EE5E816D30, file "discord_backup\tui.py", line 289>:
  --           COPY_FREE_VARS           1

 289           RESUME                   0
               LOAD_DEREF               1 (handle)
               LOAD_ATTR                1 (update + NULL|self)
               LOAD_GLOBAL              3 (_strip_ansi + NULL)
               LOAD_FAST                0 (msg)
               CALL                     1
               CALL                     1
               RETURN_VALUE

Disassembly of <code object _show_tokens_list at 0x000001EE5C72C8E0, file "discord_backup\tui.py", line 328>:
 328            RESUME                   0

 329            NOP

 330    L1:     LOAD_GLOBAL              1 (_discover_tokens_with_loading + NULL)
                CALL                     0
                STORE_FAST               0 (tokens)

 334    L2:     LOAD_FAST                0 (tokens)
                TO_BOOL
                POP_JUMP_IF_TRUE        25 (to L3)

 335            LOAD_GLOBAL              7 (message_dialog + NULL)
                LOAD_CONST               2 ('Tokens')
                LOAD_CONST               3 ('No tokens discovered.')
                LOAD_CONST               4 (('title', 'text'))
                CALL_KW                  2
                LOAD_ATTR                9 (run + NULL|self)
                CALL                     0
                POP_TOP

 336            RETURN_CONST             0 (None)

 337    L3:     LOAD_FAST                0 (tokens)
                GET_ITER
                LOAD_FAST_AND_CLEAR      2 (tok)
                SWAP                     2
        L4:     BUILD_LIST               0
                SWAP                     2
                GET_ITER
        L5:     FOR_ITER                42 (to L6)
                STORE_FAST_LOAD_FAST    34 (tok, tok)
                LOAD_ATTR               10 (user_tag)
                FORMAT_SIMPLE
                LOAD_CONST               5 (' (')
                LOAD_FAST                2 (tok)
                LOAD_ATTR               12 (user_id)
                FORMAT_SIMPLE
                LOAD_CONST               6 (') - ')
                LOAD_FAST                2 (tok)
                LOAD_ATTR               14 (source)
                FORMAT_SIMPLE
                BUILD_STRING             5
                LIST_APPEND              2
                JUMP_BACKWARD           44 (to L5)
        L6:     END_FOR
                POP_TOP
        L7:     STORE_FAST               3 (lines)
                STORE_FAST               2 (tok)

 338            LOAD_GLOBAL              7 (message_dialog + NULL)
                LOAD_CONST               7 ('Discovered Tokens')
                LOAD_CONST               8 ('\n')
                LOAD_ATTR               17 (join + NULL|self)
                LOAD_FAST                3 (lines)
                CALL                     1
                LOAD_CONST               4 (('title', 'text'))
                CALL_KW                  2
                LOAD_ATTR                9 (run + NULL|self)
                CALL                     0
                POP_TOP
                RETURN_CONST             0 (None)

  --    L8:     PUSH_EXC_INFO

 331            LOAD_GLOBAL              2 (Exception)
                CHECK_EXC_MATCH
                POP_JUMP_IF_FALSE       22 (to L12)
                STORE_FAST               1 (exc)

 332    L9:     LOAD_GLOBAL              5 (_show_error + NULL)
                LOAD_CONST               1 ('Token discovery failed')
                LOAD_FAST                1 (exc)
                CALL                     2
                POP_TOP

 333   L10:     POP_EXCEPT
                LOAD_CONST               0 (None)
                STORE_FAST               1 (exc)
                DELETE_FAST              1 (exc)
                RETURN_CONST             0 (None)

  --   L11:     LOAD_CONST               0 (None)
                STORE_FAST               1 (exc)
                DELETE_FAST              1 (exc)
                RERAISE                  1

 331   L12:     RERAISE                  0

  --   L13:     COPY                     3
                POP_EXCEPT
                RERAISE                  1
       L14:     SWAP                     2
                POP_TOP

 337            SWAP                     2
                STORE_FAST               2 (tok)
                RERAISE                  0
ExceptionTable:
  L1 to L2 -> L8 [0]
  L4 to L7 -> L14 [2]
  L8 to L9 -> L13 [1] lasti
  L9 to L10 -> L11 [1] lasti
  L11 to L13 -> L13 [1] lasti

Disassembly of <code object _handle_startup_add at 0x000001EE5C72BFE0, file "discord_backup\tui.py", line 341>:
341           RESUME                   0

342           LOAD_GLOBAL              1 (_discover_and_choose_token + NULL)
              LOAD_CONST               1 ('Select account for auto-backup')
              CALL                     1
              STORE_FAST               0 (selection)

343           LOAD_FAST                0 (selection)
              TO_BOOL
              POP_JUMP_IF_TRUE         1 (to L1)

344           RETURN_CONST             0 (None)

345   L1:     LOAD_GLOBAL              3 (_project_root + NULL)
              CALL                     0
              STORE_FAST               1 (root)

346           LOAD_GLOBAL              5 (Path + NULL)
              LOAD_GLOBAL              7 (getattr + NULL)
              LOAD_GLOBAL              8 (sys)
              LOAD_CONST               2 ('frozen')
              LOAD_CONST               3 (False)
              CALL                     3
              TO_BOOL
              POP_JUMP_IF_FALSE       16 (to L2)
              LOAD_GLOBAL              8 (sys)
              LOAD_ATTR               10 (executable)
              JUMP_FORWARD             4 (to L3)
      L2:     LOAD_FAST                1 (root)
              LOAD_CONST               4 ('main.py')
              BINARY_OP               11 (/)
      L3:     CALL                     1
              STORE_FAST               2 (executable)

347           LOAD_FAST                2 (executable)
              LOAD_ATTR               12 (suffix)
              LOAD_CONST               5 ('.py')
              COMPARE_OP              88 (bool(==))
              POP_JUMP_IF_FALSE       23 (to L4)

348           LOAD_CONST               6 ('cmd.exe /C python "')
              LOAD_FAST                2 (executable)
              FORMAT_SIMPLE
              LOAD_CONST               7 ('" auto-backup --account-id ')
              LOAD_FAST                0 (selection)
              LOAD_ATTR               14 (user_id)
              FORMAT_SIMPLE
              LOAD_CONST               8 (' --working-dir "')
              LOAD_FAST                1 (root)
              FORMAT_SIMPLE
              LOAD_CONST               9 ('"')
              BUILD_STRING             7
              STORE_FAST               3 (command)
              JUMP_FORWARD            22 (to L5)

350   L4:     LOAD_CONST               9 ('"')
              LOAD_FAST                2 (executable)
              FORMAT_SIMPLE
              LOAD_CONST               7 ('" auto-backup --account-id ')
              LOAD_FAST                0 (selection)
              LOAD_ATTR               14 (user_id)
              FORMAT_SIMPLE
              LOAD_CONST               8 (' --working-dir "')
              LOAD_FAST                1 (root)
              FORMAT_SIMPLE
              LOAD_CONST               9 ('"')
              BUILD_STRING             7
              STORE_FAST               3 (command)

351   L5:     LOAD_GLOBAL             17 (write_startup_script + NULL)
              LOAD_FAST_LOAD_FAST     49 (command, root)
              CALL                     2
              STORE_FAST               4 (script_path)

352           LOAD_GLOBAL             19 (message_dialog + NULL)
              LOAD_CONST              10 ('Startup')
              LOAD_CONST              11 ('Auto-backup script saved to ')
              LOAD_FAST                4 (script_path)
              FORMAT_SIMPLE
              BUILD_STRING             2
              LOAD_CONST              12 (('title', 'text'))
              CALL_KW                  2
              LOAD_ATTR               21 (run + NULL|self)
              CALL                     0
              POP_TOP
              RETURN_CONST             0 (None)

Disassembly of <code object _handle_startup_remove at 0x000001EE5E870810, file "discord_backup\tui.py", line 355>:
355           RESUME                   0

356           LOAD_GLOBAL              1 (remove_startup_script + NULL)
              CALL                     0
              TO_BOOL
              POP_JUMP_IF_FALSE       25 (to L1)

357           LOAD_GLOBAL              3 (message_dialog + NULL)
              LOAD_CONST               1 ('Startup')
              LOAD_CONST               2 ('Startup script removed.')
              LOAD_CONST               3 (('title', 'text'))
              CALL_KW                  2
              LOAD_ATTR                5 (run + NULL|self)
              CALL                     0
              POP_TOP
              RETURN_CONST             0 (None)

359   L1:     LOAD_GLOBAL              3 (message_dialog + NULL)
              LOAD_CONST               1 ('Startup')
              LOAD_CONST               4 ('No startup script found.')
              LOAD_CONST               3 (('title', 'text'))
              CALL_KW                  2
              LOAD_ATTR                5 (run + NULL|self)
              CALL                     0
              POP_TOP
              RETURN_CONST             0 (None)

Disassembly of <code object run_tui at 0x000001EE5C79A960, file "discord_backup\tui.py", line 362>:
 362            RESUME                   0

 363            NOP

 364    L1:     LOAD_GLOBAL              1 (radiolist_dialog + NULL)

 365            LOAD_CONST               1 ('Discord Backup')

 366            LOAD_CONST               2 ('Select an action (use arrow keys, Enter to confirm)')

 367            BUILD_LIST               0
                LOAD_CONST               3 ((('backup_scan', 'Backup (scan tokens on this machine)'), ('backup_manual', 'Backup (paste token manually)'), ('restore', 'Restore from an existing .bkup file'), ('tokens', 'View discovered tokens'), ('startup_add', 'Add auto-backup to Windows startup'), ('startup_remove', 'Remove auto-backup from Windows startup'), ('exit', 'Exit')))
                LIST_EXTEND              1

 376            LOAD_CONST               4 ('Select')

 377            LOAD_CONST               5 ('Quit')

 364            LOAD_CONST               6 (('title', 'text', 'values', 'ok_text', 'cancel_text'))
                CALL_KW                  5

 378            LOAD_ATTR                3 (run + NULL|self)
                CALL                     0

 364            STORE_FAST               0 (action)

 380            LOAD_FAST                0 (action)
                LOAD_CONST               7 ((None, 'exit'))
                CONTAINS_OP              0
                POP_JUMP_IF_FALSE       25 (to L2)

 381            LOAD_GLOBAL              5 (message_dialog + NULL)
                LOAD_CONST               8 ('Goodbye')
                LOAD_CONST               9 ('Stay safe and keep your backups handy!')
                LOAD_CONST              10 (('title', 'text'))
                CALL_KW                  2
                LOAD_ATTR                3 (run + NULL|self)
                CALL                     0
                POP_TOP

 382            RETURN_CONST             0 (None)

 383    L2:     LOAD_FAST                0 (action)
                LOAD_CONST              11 ('backup_scan')
                COMPARE_OP              88 (bool(==))
                POP_JUMP_IF_FALSE       40 (to L4)

 384            LOAD_GLOBAL              7 (_discover_and_choose_token + NULL)
                LOAD_CONST              12 ('Select token for backup')
                CALL                     1
                STORE_FAST               1 (selection)

 385            LOAD_FAST                1 (selection)
                TO_BOOL
                POP_JUMP_IF_FALSE       21 (to L3)

 386            LOAD_GLOBAL              9 (_run_backup_flow + NULL)
                LOAD_FAST                1 (selection)
                LOAD_ATTR               10 (token)
                CALL                     1
                POP_TOP

  --    L3:     JUMP_FORWARD           103 (to L10)

 387    L4:     LOAD_FAST                0 (action)
                LOAD_CONST              13 ('backup_manual')
                COMPARE_OP              88 (bool(==))
                POP_JUMP_IF_FALSE       30 (to L6)

 388            LOAD_GLOBAL             13 (_prompt_for_token + NULL)
                LOAD_CONST              14 ('Manual Backup')
                CALL                     1
                STORE_FAST               2 (token)

 389            LOAD_FAST                2 (token)
                TO_BOOL
                POP_JUMP_IF_FALSE       11 (to L5)

 390            LOAD_GLOBAL              9 (_run_backup_flow + NULL)
                LOAD_FAST                2 (token)
                CALL                     1
                POP_TOP

  --    L5:     JUMP_FORWARD            67 (to L10)

 391    L6:     LOAD_FAST                0 (action)
                LOAD_CONST              15 ('restore')
                COMPARE_OP              88 (bool(==))
                POP_JUMP_IF_FALSE       11 (to L7)

 392            LOAD_GLOBAL             15 (_run_restore_flow + NULL)
                CALL                     0
                POP_TOP
                JUMP_FORWARD            50 (to L10)

 393    L7:     LOAD_FAST                0 (action)
                LOAD_CONST              16 ('tokens')
                COMPARE_OP              88 (bool(==))
                POP_JUMP_IF_FALSE       11 (to L8)

 394            LOAD_GLOBAL             17 (_show_tokens_list + NULL)
                CALL                     0
                POP_TOP
                JUMP_FORWARD            33 (to L10)

 395    L8:     LOAD_FAST                0 (action)
                LOAD_CONST              17 ('startup_add')
                COMPARE_OP              88 (bool(==))
                POP_JUMP_IF_FALSE       11 (to L9)

 396            LOAD_GLOBAL             19 (_handle_startup_add + NULL)
                CALL                     0
                POP_TOP
                JUMP_FORWARD            16 (to L10)

 397    L9:     LOAD_FAST                0 (action)
                LOAD_CONST              18 ('startup_remove')
                COMPARE_OP              88 (bool(==))
                POP_JUMP_IF_FALSE       10 (to L10)

 398            LOAD_GLOBAL             21 (_handle_startup_remove + NULL)
                CALL                     0
                POP_TOP

 363   L10:     JUMP_BACKWARD          211 (to L1)


# --- Nested: _project_root ---

 44           RESUME                   0

 45           LOAD_GLOBAL              1 (getattr + NULL)
              LOAD_GLOBAL              2 (sys)
              LOAD_CONST               1 ('frozen')
              LOAD_CONST               2 (False)
              CALL                     3
              TO_BOOL
              POP_JUMP_IF_FALSE       49 (to L1)

 46           LOAD_GLOBAL              5 (Path + NULL)
              LOAD_GLOBAL              2 (sys)
              LOAD_ATTR                6 (executable)
              CALL                     1
              LOAD_ATTR                9 (resolve + NULL|self)
              CALL                     0
              LOAD_ATTR               10 (parent)
              RETURN_VALUE

 47   L1:     LOAD_GLOBAL              5 (Path + NULL)
              LOAD_GLOBAL             12 (__file__)
              CALL                     1
              LOAD_ATTR                9 (resolve + NULL|self)
              CALL                     0
              LOAD_ATTR               10 (parent)
              LOAD_ATTR               10 (parent)
              RETURN_VALUE


# --- Nested: _strip_ansi ---

 50           RESUME                   0

 51           LOAD_GLOBAL              0 (ANSI_RE)
              LOAD_ATTR                3 (sub + NULL|self)
              LOAD_CONST               1 ('')
              LOAD_FAST                0 (text)
              CALL                     2
              RETURN_VALUE


# --- Nested: _async_discover_tokens ---

  54            RETURN_GENERATOR
                POP_TOP
        L1:     RESUME                   0

  55            LOAD_GLOBAL              0 (DiscordHTTPClient)
                LOAD_ATTR                2 (create)
                PUSH_NULL
                CALL                     0
                GET_AWAITABLE            0
                LOAD_CONST               0 (None)
        L2:     SEND                     3 (to L5)
        L3:     YIELD_VALUE              1
        L4:     RESUME                   3
                JUMP_BACKWARD_NO_INTERRUPT 5 (to L2)
        L5:     END_SEND
                STORE_FAST               0 (http)

  56    L6:     NOP

  57    L7:     LOAD_GLOBAL              5 (discover_tokens + NULL)
                LOAD_FAST                0 (http)
                CALL                     1
                GET_AWAITABLE            0
                LOAD_CONST               0 (None)
        L8:     SEND                     3 (to L11)
        L9:     YIELD_VALUE              1
       L10:     RESUME                   3
                JUMP_BACKWARD_NO_INTERRUPT 5 (to L8)
       L11:     END_SEND

  59   L12:     LOAD_FAST                0 (http)
                LOAD_ATTR                7 (aclose + NULL|self)
                CALL                     0
                GET_AWAITABLE            0
                LOAD_CONST               0 (None)
       L13:     SEND                     3 (to L16)
       L14:     YIELD_VALUE              1
       L15:     RESUME                   3
                JUMP_BACKWARD_NO_INTERRUPT 5 (to L13)
       L16:     END_SEND
                POP_TOP
                RETURN_VALUE

  55   L17:     CLEANUP_THROW
       L18:     JUMP_BACKWARD_NO_INTERRUPT 48 (to L5)

  57   L19:     CLEANUP_THROW
       L20:     JUMP_BACKWARD_NO_INTERRUPT 30 (to L11)

  59   L21:     CLEANUP_THROW
       L22:     JUMP_BACKWARD_NO_INTERRUPT 9 (to L16)

  --   L23:     PUSH_EXC_INFO

  59            LOAD_FAST                0 (http)
                LOAD_ATTR                7 (aclose + NULL|self)
                CALL                     0
                GET_AWAITABLE            0
                LOAD_CONST               0 (None)
       L24:     SEND                     4 (to L28)
       L25:     YIELD_VALUE              1
       L26:     RESUME                   3
                JUMP_BACKWARD_NO_INTERRUPT 5 (to L24)
       L27:     CLEANUP_THROW
       L28:     END_SEND
                POP_TOP
                RERAISE                  0

  --   L29:     COPY                     3
                POP_EXCEPT
                RERAISE                  1
       L30:     CALL_INTRINSIC_1         3 (INTRINSIC_STOPITERATION_ERROR)
                RERAISE                  1
ExceptionTable:
  L1 to L3 -> L30 [0] lasti
  L3 to L4 -> L17 [2]
  L4 to L6 -> L30 [0] lasti
  L7 to L9 -> L23 [0]
  L9 to L10 -> L19 [2]
  L10 to L12 -> L23 [0]
  L12 to L14 -> L30 [0] lasti
  L14 to L15 -> L21 [3]
  L15 to L18 -> L30 [0] lasti
  L19 to L20 -> L23 [0]
  L21 to L22 -> L30 [0] lasti
  L23 to L25 -> L29 [1] lasti
  L25 to L26 -> L27 [4]
  L26 to L29 -> L29 [1] lasti
  L29 to L30 -> L30 [0] lasti


# --- Nested: _async_run_backup ---

  62            RETURN_GENERATOR
                POP_TOP
        L1:     RESUME                   0

  63            LOAD_GLOBAL              0 (DiscordHTTPClient)
                LOAD_ATTR                2 (create)
                PUSH_NULL
                CALL                     0
                GET_AWAITABLE            0
                LOAD_CONST               0 (None)
        L2:     SEND                     3 (to L5)
        L3:     YIELD_VALUE              1
        L4:     RESUME                   3
                JUMP_BACKWARD_NO_INTERRUPT 5 (to L2)
        L5:     END_SEND
                STORE_FAST               3 (http)

  64    L6:     NOP

  65    L7:     LOAD_GLOBAL              5 (BackupService + NULL)
                LOAD_FAST_LOAD_FAST     48 (http, token)
                LOAD_FAST_LOAD_FAST     18 (config, console)
                LOAD_CONST               1 (('http', 'token', 'config', 'console'))
                CALL_KW                  4
                STORE_FAST               4 (service)

  66            LOAD_FAST                4 (service)
                LOAD_ATTR                7 (run + NULL|self)
                CALL                     0
                GET_AWAITABLE            0
                LOAD_CONST               0 (None)
        L8:     SEND                     3 (to L11)
        L9:     YIELD_VALUE              1
       L10:     RESUME                   3
                JUMP_BACKWARD_NO_INTERRUPT 5 (to L8)
       L11:     END_SEND
                STORE_FAST               5 (result)

  67            LOAD_FAST                4 (service)
                LOAD_ATTR                9 (save + NULL|self)
                LOAD_FAST                5 (result)
                CALL                     1
                GET_AWAITABLE            0
                LOAD_CONST               0 (None)
       L12:     SEND                     3 (to L15)
       L13:     YIELD_VALUE              1
       L14:     RESUME                   3
                JUMP_BACKWARD_NO_INTERRUPT 5 (to L12)
       L15:     END_SEND
                STORE_FAST               6 (path)

  68            LOAD_FAST_LOAD_FAST     86 (result, path)
                BUILD_TUPLE              2

  70   L16:     LOAD_FAST                3 (http)
                LOAD_ATTR               11 (aclose + NULL|self)
                CALL                     0
                GET_AWAITABLE            0
                LOAD_CONST               0 (None)
       L17:     SEND                     3 (to L20)
       L18:     YIELD_VALUE              1
       L19:     RESUME                   3
                JUMP_BACKWARD_NO_INTERRUPT 5 (to L17)
       L20:     END_SEND
                POP_TOP
                RETURN_VALUE

  63   L21:     CLEANUP_THROW
       L22:     JUMP_BACKWARD_NO_INTERRUPT 91 (to L5)

  66   L23:     CLEANUP_THROW
       L24:     JUMP_BACKWARD_NO_INTERRUPT 58 (to L11)

  67   L25:     CLEANUP_THROW
       L26:     JUMP_BACKWARD_NO_INTERRUPT 35 (to L15)

  70   L27:     CLEANUP_THROW
       L28:     JUMP_BACKWARD_NO_INTERRUPT 11 (to L20)

  --   L29:     PUSH_EXC_INFO

  70            LOAD_FAST                3 (http)
                LOAD_ATTR               11 (aclose + NULL|self)
                CALL                     0
                GET_AWAITABLE            0
                LOAD_CONST               0 (None)
       L30:     SEND                     4 (to L34)
       L31:     YIELD_VALUE              1
       L32:     RESUME                   3
                JUMP_BACKWARD_NO_INTERRUPT 5 (to L30)
       L33:     CLEANUP_THROW
       L34:     END_SEND
                POP_TOP
                RERAISE                  0

  --   L35:     COPY                     3
                POP_EXCEPT
                RERAISE                  1
       L36:     CALL_INTRINSIC_1         3 (INTRINSIC_STOPITERATION_ERROR)
                RERAISE                  1
ExceptionTable:
  L1 to L3 -> L36 [0] lasti
  L3 to L4 -> L21 [2]
  L4 to L6 -> L36 [0] lasti
  L7 to L9 -> L29 [0]
  L9 to L10 -> L23 [2]
  L10 to L13 -> L29 [0]
  L13 to L14 -> L25 [2]
  L14 to L16 -> L29 [0]
  L16 to L18 -> L36 [0] lasti
  L18 to L19 -> L27 [3]
  L19 to L22 -> L36 [0] lasti
  L23 to L24 -> L29 [0]
  L25 to L26 -> L29 [0]
  L27 to L28 -> L36 [0] lasti
  L29 to L31 -> L35 [1] lasti
  L31 to L32 -> L33 [4]
  L32 to L35 -> L35 [1] lasti
  L35 to L36 -> L36 [0] lasti


# --- Nested: _async_run_restore ---

  73            RETURN_GENERATOR
                POP_TOP
        L1:     RESUME                   0

  81            LOAD_GLOBAL              0 (DiscordHTTPClient)
                LOAD_ATTR                2 (create)
                PUSH_NULL
                CALL                     0
                GET_AWAITABLE            0
                LOAD_CONST               0 (None)
        L2:     SEND                     3 (to L5)
        L3:     YIELD_VALUE              1
        L4:     RESUME                   3
                JUMP_BACKWARD_NO_INTERRUPT 5 (to L2)
        L5:     END_SEND
                STORE_FAST               6 (http)

  82    L6:     NOP

  83    L7:     LOAD_GLOBAL              5 (RestoreService + NULL)

  84            LOAD_FAST                6 (http)

  85            LOAD_FAST                1 (token)

  86            LOAD_FAST                2 (bot_token)

  87            LOAD_FAST                0 (backup_data)

  88            LOAD_FAST                5 (console)

  83            LOAD_CONST               1 (('http', 'token', 'bot_token', 'backup', 'console'))
                CALL_KW                  5
                STORE_FAST               7 (service)

  90            LOAD_FAST                7 (service)
                LOAD_ATTR                7 (run + NULL|self)

  91            LOAD_FAST                3 (restore_folders)

  92            LOAD_FAST                0 (backup_data)
                LOAD_ATTR                9 (get + NULL|self)
                LOAD_CONST               2 ('version')
                CALL                     1

  93            LOAD_FAST                4 (allow_version_mismatch)

  90            LOAD_CONST               3 (('restore_folders', 'expected_version', 'allow_mismatch'))
                CALL_KW                  3
                GET_AWAITABLE            0
                LOAD_CONST               0 (None)
        L8:     SEND                     3 (to L11)
        L9:     YIELD_VALUE              1
       L10:     RESUME                   3
                JUMP_BACKWARD_NO_INTERRUPT 5 (to L8)
       L11:     END_SEND
                STORE_FAST               8 (summary)

  95            LOAD_FAST                8 (summary)
                LOAD_ATTR               10 (guild_id)
                LOAD_FAST                8 (summary)
                LOAD_ATTR               12 (favourite_gifs_status)
                LOAD_FAST                8 (summary)
                LOAD_ATTR               14 (folder_restore_attempted)
                LOAD_FAST                8 (summary)
                LOAD_ATTR               16 (duration)
                BUILD_TUPLE              4

  97   L12:     LOAD_FAST                6 (http)
                LOAD_ATTR               19 (aclose + NULL|self)
                CALL                     0
                GET_AWAITABLE            0
                LOAD_CONST               0 (None)
       L13:     SEND                     3 (to L16)
       L14:     YIELD_VALUE              1
       L15:     RESUME                   3
                JUMP_BACKWARD_NO_INTERRUPT 5 (to L13)
       L16:     END_SEND
                POP_TOP
                RETURN_VALUE

  81   L17:     CLEANUP_THROW
       L18:     JUMP_BACKWARD_NO_INTERRUPT 128 (to L5)

  90   L19:     CLEANUP_THROW
       L20:     JUMP_BACKWARD_NO_INTERRUPT 76 (to L11)

  97   L21:     CLEANUP_THROW
       L22:     JUMP_BACKWARD_NO_INTERRUPT 9 (to L16)

  --   L23:     PUSH_EXC_INFO

  97            LOAD_FAST                6 (http)
                LOAD_ATTR               19 (aclose + NULL|self)
                CALL                     0
                GET_AWAITABLE            0
                LOAD_CONST               0 (None)
       L24:     SEND                     4 (to L28)
       L25:     YIELD_VALUE              1
       L26:     RESUME                   3
                JUMP_BACKWARD_NO_INTERRUPT 5 (to L24)
       L27:     CLEANUP_THROW
       L28:     END_SEND
                POP_TOP
                RERAISE                  0

  --   L29:     COPY                     3
                POP_EXCEPT
                RERAISE                  1
       L30:     CALL_INTRINSIC_1         3 (INTRINSIC_STOPITERATION_ERROR)
                RERAISE                  1
ExceptionTable:
  L1 to L3 -> L30 [0] lasti
  L3 to L4 -> L17 [2]
  L4 to L6 -> L30 [0] lasti
  L7 to L9 -> L23 [0]
  L9 to L10 -> L19 [2]
  L10 to L12 -> L23 [0]
  L12 to L14 -> L30 [0] lasti
  L14 to L15 -> L21 [3]
  L15 to L18 -> L30 [0] lasti
  L19 to L20 -> L23 [0]
  L21 to L22 -> L30 [0] lasti
  L23 to L25 -> L29 [1] lasti
  L25 to L26 -> L27 [4]
  L26 to L29 -> L29 [1] lasti
  L29 to L30 -> L30 [0] lasti


# --- Nested: _format_backup_summary ---

100           RESUME                   0

101           LOAD_FAST                0 (result)
              LOAD_ATTR                1 (summary + NULL|self)
              CALL                     0
              STORE_FAST               3 (summary)

102           LOAD_FAST                3 (summary)
              LOAD_CONST               1 ('guilds')
              BINARY_SUBSCR
              STORE_FAST               4 (guilds)

103           LOAD_FAST                3 (summary)
              LOAD_CONST               2 ('group_chats')
              BINARY_SUBSCR
              STORE_FAST               5 (groups)

105           LOAD_CONST               3 ('Backup completed successfully!\n\nSaved file: ')

106           LOAD_FAST                1 (path)
              FORMAT_SIMPLE
              LOAD_CONST               4 ('\nGuilds: ')

107           LOAD_FAST                4 (guilds)
              LOAD_CONST               5 ('success')
              BINARY_SUBSCR
              FORMAT_SIMPLE
              LOAD_CONST               6 (' / ')
              LOAD_FAST                4 (guilds)
              LOAD_CONST               7 ('total')
              BINARY_SUBSCR
              FORMAT_SIMPLE
              LOAD_CONST               8 ('\nGroup chats: ')

108           LOAD_FAST                5 (groups)
              LOAD_CONST               5 ('success')
              BINARY_SUBSCR
              FORMAT_SIMPLE
              LOAD_CONST               6 (' / ')
              LOAD_FAST                5 (groups)
              LOAD_CONST               7 ('total')
              BINARY_SUBSCR
              FORMAT_SIMPLE
              LOAD_CONST               9 ('\nElapsed: ')

109           LOAD_FAST                0 (result)
              LOAD_ATTR                2 (duration)
              LOAD_CONST              10 ('.1f')
              FORMAT_WITH_SPEC
              LOAD_CONST              11 ('s\n\nLatest activity:\n')

105           BUILD_STRING            13

110           LOAD_FAST                2 (logs)

105           BINARY_OP                0 (+)

104           RETURN_VALUE


# --- Nested: _format_restore_summary ---

114           RESUME                   0

116           LOAD_CONST               1 ('Restore completed!\n\nHelper guild id: ')

117           LOAD_FAST                0 (guild_id)
              FORMAT_SIMPLE
              LOAD_CONST               2 ('\nFavourite GIFs: ')

118           LOAD_FAST                1 (gifs_status)
              FORMAT_SIMPLE
              LOAD_CONST               3 ('\nGuild folders restored: ')

119           LOAD_FAST                2 (folders)
              TO_BOOL
              POP_JUMP_IF_FALSE        2 (to L1)
              LOAD_CONST               4 ('Yes')
              JUMP_FORWARD             1 (to L2)
      L1:     LOAD_CONST               5 ('No')
      L2:     FORMAT_SIMPLE
              LOAD_CONST               6 ('\nElapsed: ')

120           LOAD_FAST                3 (duration)
              LOAD_CONST               7 ('.1f')
              FORMAT_WITH_SPEC
              LOAD_CONST               8 ('s\n\nLatest activity:\n')

116           BUILD_STRING             9

121           LOAD_FAST                4 (logs)

116           BINARY_OP                0 (+)

115           RETURN_VALUE


# --- Nested: _show_with_details ---

125           RESUME                   0

126           LOAD_CONST               1 (('Close', 'close'))
              BUILD_LIST               1
              STORE_FAST               3 (buttons)

127           LOAD_FAST                2 (details)
              TO_BOOL
              POP_JUMP_IF_FALSE       18 (to L1)

128           LOAD_FAST                3 (buttons)
              LOAD_ATTR                1 (insert + NULL|self)
              LOAD_CONST               2 (0)
              LOAD_CONST               3 (('View details', 'details'))
              CALL                     2
              POP_TOP

129   L1:     LOAD_GLOBAL              3 (button_dialog + NULL)
              LOAD_FAST_LOAD_FAST      1 (title, summary)
              LOAD_FAST                3 (buttons)
              LOAD_CONST               4 (('title', 'text', 'buttons'))
              CALL_KW                  3
              LOAD_ATTR                5 (run + NULL|self)
              CALL                     0
              STORE_FAST               4 (choice)

130           LOAD_FAST                4 (choice)
              LOAD_CONST               5 ('details')
              COMPARE_OP              88 (bool(==))
              POP_JUMP_IF_FALSE       36 (to L3)
              LOAD_FAST                2 (details)
              TO_BOOL
              POP_JUMP_IF_FALSE       28 (to L2)

131           LOAD_GLOBAL              7 (message_dialog + NULL)
              LOAD_FAST                0 (title)
              FORMAT_SIMPLE
              LOAD_CONST               6 (' ? details')
              BUILD_STRING             2
              LOAD_FAST                2 (details)
              LOAD_CONST               7 (('title', 'text'))
              CALL_KW                  2
              LOAD_ATTR                5 (run + NULL|self)
              CALL                     0
              POP_TOP
              RETURN_CONST             0 (None)

130   L2:     RETURN_CONST             0 (None)
      L3:     RETURN_CONST             0 (None)


# --- Nested: _show_error ---

134           RESUME                   0

135           LOAD_FAST                2 (logs)
              TO_BOOL
              POP_JUMP_IF_FALSE       20 (to L2)
              LOAD_GLOBAL              1 (_strip_ansi + NULL)
              LOAD_FAST                2 (logs)
              COPY                     1
              TO_BOOL
              POP_JUMP_IF_TRUE         2 (to L1)
              POP_TOP
              LOAD_CONST               1 ('')
      L1:     CALL                     1
              JUMP_FORWARD             1 (to L3)
      L2:     LOAD_CONST               0 (None)
      L3:     STORE_FAST               3 (details)

136           LOAD_FAST                3 (details)
              TO_BOOL
              POP_JUMP_IF_FALSE        5 (to L4)
              LOAD_FAST                1 (error)
              FORMAT_SIMPLE
              LOAD_CONST               2 ("\n\nPress 'View details' to see diagnostic output.")
              BUILD_STRING             2
              JUMP_FORWARD            10 (to L5)
      L4:     LOAD_GLOBAL              3 (str + NULL)
              LOAD_FAST                1 (error)
              CALL                     1
      L5:     STORE_FAST               4 (summary)

137           LOAD_GLOBAL              5 (_show_with_details + NULL)
              LOAD_FAST_LOAD_FAST      4 (title, summary)
              LOAD_FAST                3 (details)
              CALL                     3
              POP_TOP
              RETURN_CONST             0 (None)


# --- Nested: _discover_tokens_with_loading ---

  --           MAKE_CELL                1 (time)

 140           RESUME                   0

 141           LOAD_CONST               5 (('handle', 'ProgressHandle', 'return', 'list[DiscoveredToken]'))
               LOAD_FAST                1 (time)
               BUILD_TUPLE              1
               LOAD_CONST               1 (<code object worker at 0x000001EE5E84CCB0, file "discord_backup\tui.py", line 141>)
               MAKE_FUNCTION
               SET_FUNCTION_ATTRIBUTE   8 (closure)
               SET_FUNCTION_ATTRIBUTE   4 (annotations)
               STORE_FAST               0 (worker)

 148           LOAD_CONST               2 (0)
               LOAD_CONST               0 (None)
               IMPORT_NAME              0 (time)
               STORE_DEREF              1 (time)

 150           LOAD_GLOBAL              3 (run_with_loading + NULL)
               LOAD_CONST               3 ('Token discovery')
               LOAD_CONST               4 ('Preparing...')
               LOAD_FAST                0 (worker)
               CALL                     3
               RETURN_VALUE

Disassembly of <code object worker at 0x000001EE5E84CCB0, file "discord_backup\tui.py", line 141>:
  --           COPY_FREE_VARS           1

 141           RESUME                   0

 142           LOAD_FAST                0 (handle)
               LOAD_ATTR                1 (update + NULL|self)
               LOAD_CONST               1 ('Scanning local storage for Discord tokens...')
               CALL                     1
               POP_TOP

 143           LOAD_GLOBAL              2 (asyncio)
               LOAD_ATTR                4 (run)
               PUSH_NULL
               LOAD_GLOBAL              7 (_async_discover_tokens + NULL)
               CALL                     0
               CALL                     1
               STORE_FAST               1 (tokens)

 144           LOAD_FAST                0 (handle)
               LOAD_ATTR                1 (update + NULL|self)
               LOAD_CONST               2 ('Found ')
               LOAD_GLOBAL              9 (len + NULL)
               LOAD_FAST                1 (tokens)
               CALL                     1
               FORMAT_SIMPLE
               LOAD_CONST               3 (' token(s)')
               BUILD_STRING             3
               CALL                     1
               POP_TOP

 145           LOAD_DEREF               2 (time)
               LOAD_ATTR               11 (sleep + NULL|self)
               LOAD_CONST               4 (0.2)
               CALL                     1
               POP_TOP

 146           LOAD_FAST                1 (tokens)
               RETURN_VALUE


# --- Nested: _discover_and_choose_token ---

 153            RESUME                   0

 154            NOP

 155    L1:     LOAD_GLOBAL              1 (_discover_tokens_with_loading + NULL)
                CALL                     0
                STORE_FAST               1 (tokens)

 159    L2:     LOAD_FAST                1 (tokens)
                TO_BOOL
                POP_JUMP_IF_TRUE        25 (to L3)

 160            LOAD_GLOBAL              7 (message_dialog + NULL)
                LOAD_CONST               2 ('No tokens')
                LOAD_CONST               3 ('No Discord tokens were found on this machine.')
                LOAD_CONST               4 (('title', 'text'))
                CALL_KW                  2
                LOAD_ATTR                9 (run + NULL|self)
                CALL                     0
                POP_TOP

 161            RETURN_CONST             0 (None)

 162    L3:     LOAD_GLOBAL             11 (enumerate + NULL)
                LOAD_FAST                1 (tokens)
                CALL                     1
                GET_ITER
                LOAD_FAST_AND_CLEAR      3 (idx)
                LOAD_FAST_AND_CLEAR      4 (tok)
                SWAP                     3
        L4:     BUILD_LIST               0
                SWAP                     2
                GET_ITER
        L5:     FOR_ITER                34 (to L6)
                UNPACK_SEQUENCE          2
                STORE_FAST_STORE_FAST   52 (idx, tok)
                LOAD_FAST_LOAD_FAST     52 (idx, tok)
                LOAD_ATTR               12 (user_tag)
                FORMAT_SIMPLE
                LOAD_CONST               5 (' (')
                LOAD_FAST                4 (tok)
                LOAD_ATTR               14 (source)
                FORMAT_SIMPLE
                LOAD_CONST               6 (')')
                BUILD_STRING             4
                BUILD_TUPLE              2
                LIST_APPEND              2
                JUMP_BACKWARD           36 (to L5)
        L6:     END_FOR
                POP_TOP
        L7:     STORE_FAST               5 (values)
                STORE_FAST               3 (idx)
                STORE_FAST               4 (tok)

 163            LOAD_GLOBAL             17 (radiolist_dialog + NULL)

 164            LOAD_FAST                0 (title)

 165            LOAD_CONST               7 ('Select a token (arrow keys + Enter)')

 166            LOAD_FAST                5 (values)

 167            LOAD_CONST               8 ('Use token')

 168            LOAD_CONST               9 ('Cancel')

 163            LOAD_CONST              10 (('title', 'text', 'values', 'ok_text', 'cancel_text'))
                CALL_KW                  5

 169            LOAD_ATTR                9 (run + NULL|self)
                CALL                     0

 163            STORE_FAST               6 (choice)

 170            LOAD_FAST                6 (choice)
                POP_JUMP_IF_NOT_NONE     1 (to L8)

 171            RETURN_CONST             0 (None)

 172    L8:     LOAD_FAST_LOAD_FAST     22 (tokens, choice)
                BINARY_SUBSCR
                RETURN_VALUE

  --    L9:     PUSH_EXC_INFO

 156            LOAD_GLOBAL              2 (Exception)
                CHECK_EXC_MATCH
                POP_JUMP_IF_FALSE       22 (to L13)
                STORE_FAST               2 (exc)

 157   L10:     LOAD_GLOBAL              5 (_show_error + NULL)
                LOAD_CONST               1 ('Token discovery failed')
                LOAD_FAST                2 (exc)
                CALL                     2
                POP_TOP

 158   L11:     POP_EXCEPT
                LOAD_CONST               0 (None)
                STORE_FAST               2 (exc)
                DELETE_FAST              2 (exc)
                RETURN_CONST             0 (None)

  --   L12:     LOAD_CONST               0 (None)
                STORE_FAST               2 (exc)
                DELETE_FAST              2 (exc)
                RERAISE                  1

 156   L13:     RERAISE                  0

  --   L14:     COPY                     3
                POP_EXCEPT
                RERAISE                  1
       L15:     SWAP                     2
                POP_TOP

 162            SWAP                     3
                STORE_FAST               4 (tok)
                STORE_FAST               3 (idx)
                RERAISE                  0
ExceptionTable:
  L1 to L2 -> L9 [0]
  L4 to L7 -> L15 [3]
  L9 to L10 -> L14 [1] lasti
  L10 to L11 -> L12 [1] lasti
  L12 to L14 -> L14 [1] lasti


# --- Nested: _prompt_for_token ---

175           RESUME                   0

176           LOAD_GLOBAL              1 (input_dialog + NULL)
              LOAD_FAST                0 (label)
              LOAD_CONST               1 ('Enter the Discord user token:')
              LOAD_CONST               2 (('title', 'text'))
              CALL_KW                  2
              LOAD_ATTR                3 (run + NULL|self)
              CALL                     0
              STORE_FAST               1 (token)

177           LOAD_FAST                1 (token)
              TO_BOOL
              POP_JUMP_IF_FALSE       16 (to L1)

178           LOAD_FAST                1 (token)
              LOAD_ATTR                5 (strip + NULL|self)
              CALL                     0
              STORE_FAST               1 (token)

179   L1:     LOAD_FAST                1 (token)
              COPY                     1
              TO_BOOL
              POP_JUMP_IF_TRUE         2 (to L2)
              POP_TOP
              LOAD_CONST               0 (None)
      L2:     RETURN_VALUE


# --- Nested: _prompt_for_bot_token ---

182           RESUME                   0

183           LOAD_GLOBAL              1 (input_dialog + NULL)
              LOAD_CONST               1 ('Bot Token')
              LOAD_CONST               2 ('Enter bot token used for username lookups:')
              LOAD_CONST               3 (('title', 'text'))
              CALL_KW                  2
              LOAD_ATTR                3 (run + NULL|self)
              CALL                     0
              STORE_FAST               0 (token)

184           LOAD_FAST                0 (token)
              TO_BOOL
              POP_JUMP_IF_FALSE       16 (to L1)

185           LOAD_FAST                0 (token)
              LOAD_ATTR                5 (strip + NULL|self)
              CALL                     0
              STORE_FAST               0 (token)

186   L1:     LOAD_FAST                0 (token)
              COPY                     1
              TO_BOOL
              POP_JUMP_IF_TRUE         2 (to L2)
              POP_TOP
              LOAD_CONST               0 (None)
      L2:     RETURN_VALUE


# --- Nested: _run_backup_flow ---

  --            MAKE_CELL                0 (token)
                MAKE_CELL                6 (buffer)
                MAKE_CELL                7 (config)

 189            RESUME                   0

 190            LOAD_GLOBAL              0 (AppConfig)
                LOAD_ATTR                2 (load)
                PUSH_NULL
                CALL                     0
                STORE_DEREF              7 (config)

 191            LOAD_GLOBAL              4 (io)
                LOAD_ATTR                6 (StringIO)
                PUSH_NULL
                CALL                     0
                STORE_DEREF              6 (buffer)

 193            LOAD_CONST               8 (('handle', 'ProgressHandle', 'return', 'tuple[BackupResult, Path]'))
                LOAD_FAST                6 (buffer)
                LOAD_FAST                7 (config)
                LOAD_FAST                0 (token)
                BUILD_TUPLE              3
                LOAD_CONST               1 (<code object worker at 0x000001EE5C5CE730, file "discord_backup\tui.py", line 193>)
                MAKE_FUNCTION
                SET_FUNCTION_ATTRIBUTE   8 (closure)
                SET_FUNCTION_ATTRIBUTE   4 (annotations)
                STORE_FAST               1 (worker)

 201            NOP

 202    L1:     LOAD_GLOBAL              9 (run_with_loading + NULL)
                LOAD_CONST               2 ('Backup in progress')
                LOAD_CONST               3 ('Starting backup...')
                LOAD_FAST                1 (worker)
                CALL                     3
                UNPACK_SEQUENCE          2
                STORE_FAST_STORE_FAST   35 (result, path)

 212    L2:     LOAD_GLOBAL             13 (_strip_ansi + NULL)
                LOAD_DEREF               6 (buffer)
                LOAD_ATTR               15 (getvalue + NULL|self)
                CALL                     0
                CALL                     1
                LOAD_CONST               6 (-2000)
                LOAD_CONST               0 (None)
                BINARY_SLICE
                STORE_FAST               5 (logs)

 213            LOAD_GLOBAL             21 (_show_with_details + NULL)
                LOAD_CONST               7 ('Backup complete')
                LOAD_GLOBAL             23 (_format_backup_summary + NULL)
                LOAD_FAST_LOAD_FAST     35 (result, path)
                LOAD_FAST                5 (logs)
                CALL                     3
                LOAD_FAST                5 (logs)
                CALL                     3
                POP_TOP
                RETURN_CONST             0 (None)

  --    L3:     PUSH_EXC_INFO

 203            LOAD_GLOBAL             10 (BackupError)
                CHECK_EXC_MATCH
                POP_JUMP_IF_FALSE       47 (to L7)
                STORE_FAST               4 (exc)

 204    L4:     LOAD_GLOBAL             13 (_strip_ansi + NULL)
                LOAD_DEREF               6 (buffer)
                LOAD_ATTR               15 (getvalue + NULL|self)
                CALL                     0
                CALL                     1
                STORE_FAST               5 (logs)

 205            LOAD_GLOBAL             17 (_show_error + NULL)
                LOAD_CONST               4 ('Backup failed')
                LOAD_FAST_LOAD_FAST     69 (exc, logs)
                CALL                     3
                POP_TOP

 206    L5:     POP_EXCEPT
                LOAD_CONST               0 (None)
                STORE_FAST               4 (exc)
                DELETE_FAST              4 (exc)
                RETURN_CONST             0 (None)

  --    L6:     LOAD_CONST               0 (None)
                STORE_FAST               4 (exc)
                DELETE_FAST              4 (exc)
                RERAISE                  1

 207    L7:     LOAD_GLOBAL             18 (Exception)
                CHECK_EXC_MATCH
                POP_JUMP_IF_FALSE       47 (to L11)
                STORE_FAST               4 (exc)

 208    L8:     LOAD_GLOBAL             13 (_strip_ansi + NULL)
                LOAD_DEREF               6 (buffer)
                LOAD_ATTR               15 (getvalue + NULL|self)
                CALL                     0
                CALL                     1
                STORE_FAST               5 (logs)

 209            LOAD_GLOBAL             17 (_show_error + NULL)
                LOAD_CONST               5 ('Unexpected error')
                LOAD_FAST_LOAD_FAST     69 (exc, logs)
                CALL                     3
                POP_TOP

 210    L9:     POP_EXCEPT
                LOAD_CONST               0 (None)
                STORE_FAST               4 (exc)
                DELETE_FAST              4 (exc)
                RETURN_CONST             0 (None)

  --   L10:     LOAD_CONST               0 (None)
                STORE_FAST               4 (exc)
                DELETE_FAST              4 (exc)
                RERAISE                  1

 207   L11:     RERAISE                  0

  --   L12:     COPY                     3
                POP_EXCEPT
                RERAISE                  1
ExceptionTable:
  L1 to L2 -> L3 [0]
  L3 to L4 -> L12 [1] lasti
  L4 to L5 -> L6 [1] lasti
  L6 to L8 -> L12 [1] lasti
  L8 to L9 -> L10 [1] lasti
  L10 to L12 -> L12 [1] lasti

Disassembly of <code object worker at 0x000001EE5C5CE730, file "discord_backup\tui.py", line 193>:
  --           COPY_FREE_VARS           3
               MAKE_CELL                0 (handle)

 193           RESUME                   0

 194           LOAD_FAST                0 (handle)
               BUILD_TUPLE              1
               LOAD_CONST               1 (<code object <lambda> at 0x000001EE5E816730, file "discord_backup\tui.py", line 194>)
               MAKE_FUNCTION
               SET_FUNCTION_ATTRIBUTE   8 (closure)
               STORE_FAST               1 (stripped_update)

 195           LOAD_GLOBAL              1 (Console + NULL)
               LOAD_DEREF               6 (config)
               LOAD_ATTR                2 (colour)
               LOAD_DEREF               5 (buffer)
               LOAD_FAST                1 (stripped_update)
               LOAD_CONST               2 (('accent', 'stream', 'status_callback'))
               CALL_KW                  3
               STORE_FAST               2 (console)

 196           LOAD_DEREF               0 (handle)
               LOAD_ATTR                5 (update + NULL|self)
               LOAD_CONST               3 ('Authenticating token...')
               CALL                     1
               POP_TOP

 197           LOAD_GLOBAL              6 (asyncio)
               LOAD_ATTR                8 (run)
               PUSH_NULL
               LOAD_GLOBAL             11 (_async_run_backup + NULL)
               LOAD_DEREF               7 (token)
               LOAD_DEREF               6 (config)
               LOAD_FAST                2 (console)
               CALL                     3
               CALL                     1
               UNPACK_SEQUENCE          2
               STORE_FAST_STORE_FAST   52 (result, path)

 198           LOAD_DEREF               0 (handle)
               LOAD_ATTR                5 (update + NULL|self)
               LOAD_CONST               4 ('Finalising backup...')
               CALL                     1
               POP_TOP

 199           LOAD_FAST_LOAD_FAST     52 (result, path)
               BUILD_TUPLE              2
               RETURN_VALUE

Disassembly of <code object <lambda> at 0x000001EE5E816730, file "discord_backup\tui.py", line 194>:
  --           COPY_FREE_VARS           1

 194           RESUME                   0
               LOAD_DEREF               1 (handle)
               LOAD_ATTR                1 (update + NULL|self)
               LOAD_GLOBAL              3 (_strip_ansi + NULL)
               LOAD_FAST                0 (msg)
               CALL                     1
               CALL                     1
               RETURN_VALUE


# --- Nested: _request_backup_file ---

216           RESUME                   0

217           LOAD_GLOBAL              0 (path_dialog)
              TO_BOOL
              POP_JUMP_IF_FALSE       43 (to L1)

218           LOAD_GLOBAL              1 (path_dialog + NULL)

219           LOAD_CONST               1 ('Select backup file')

220           LOAD_CONST               2 ('Choose a .bkup file to restore:')

221           LOAD_GLOBAL              3 (str + NULL)
              LOAD_GLOBAL              5 (_project_root + NULL)
              CALL                     0
              CALL                     1

218           LOAD_CONST               3 (('title', 'text', 'path'))
              CALL_KW                  3

222           LOAD_ATTR                7 (run + NULL|self)
              CALL                     0

218           STORE_FAST               0 (selection)
              JUMP_FORWARD            24 (to L2)

224   L1:     LOAD_GLOBAL              9 (input_dialog + NULL)

225           LOAD_CONST               4 ('Backup file')

226           LOAD_CONST               5 ('Enter the full path to the .bkup file:')

224           LOAD_CONST               6 (('title', 'text'))
              CALL_KW                  2

227           LOAD_ATTR                7 (run + NULL|self)
              CALL                     0

224           STORE_FAST               0 (selection)

228   L2:     LOAD_FAST                0 (selection)
              TO_BOOL
              POP_JUMP_IF_TRUE         1 (to L3)

229           RETURN_CONST             0 (None)

230   L3:     LOAD_GLOBAL             11 (Path + NULL)
              LOAD_FAST                0 (selection)
              CALL                     1
              STORE_FAST               1 (backup_path)

231           LOAD_FAST                1 (backup_path)
              LOAD_ATTR               13 (exists + NULL|self)
              CALL                     0
              TO_BOOL
              POP_JUMP_IF_TRUE        28 (to L4)

232           LOAD_GLOBAL             15 (message_dialog + NULL)
              LOAD_CONST               7 ('File not found')
              LOAD_CONST               8 ('Could not find ')
              LOAD_FAST                1 (backup_path)
              FORMAT_SIMPLE
              BUILD_STRING             2
              LOAD_CONST               6 (('title', 'text'))
              CALL_KW                  2
              LOAD_ATTR                7 (run + NULL|self)
              CALL                     0
              POP_TOP

233           RETURN_CONST             0 (None)

234   L4:     LOAD_FAST                1 (backup_path)
              RETURN_VALUE


# --- Nested: _run_restore_flow ---

  --            MAKE_CELL               10 (allow_mismatch)
                MAKE_CELL               11 (backup_data)
                MAKE_CELL               12 (bot_token)
                MAKE_CELL               13 (buffer)
                MAKE_CELL               14 (config)
                MAKE_CELL               15 (restore_folders)
                MAKE_CELL               16 (user_token)

 237            RESUME                   0

 238            LOAD_GLOBAL              1 (_request_backup_file + NULL)
                CALL                     0
                STORE_FAST               0 (backup_path)

 239            LOAD_FAST                0 (backup_path)
                TO_BOOL
                POP_JUMP_IF_TRUE         1 (to L1)

 240            RETURN_CONST             0 (None)

 242    L1:     NOP

 243    L2:     LOAD_GLOBAL              2 (json)
                LOAD_ATTR                4 (loads)
                PUSH_NULL
                LOAD_FAST                0 (backup_path)
                LOAD_ATTR                7 (read_text + NULL|self)
                LOAD_CONST               1 ('utf-8')
                LOAD_CONST               2 (('encoding',))
                CALL_KW                  1
                CALL                     1
                STORE_DEREF             11 (backup_data)

 248    L3:     LOAD_GLOBAL             13 (radiolist_dialog + NULL)

 249            LOAD_CONST               4 ('User Token')

 250            LOAD_CONST               5 ('Choose how to supply the user token (arrow keys + Enter)')

 252            LOAD_CONST               6 (('scan', 'Select from discovered tokens'))

 253            LOAD_CONST               7 (('manual', 'Paste token manually'))

 251            BUILD_LIST               2

 255            LOAD_CONST               8 ('Continue')

 256            LOAD_CONST               9 ('Cancel')

 248            LOAD_CONST              10 (('title', 'text', 'values', 'ok_text', 'cancel_text'))
                CALL_KW                  5

 257            LOAD_ATTR               15 (run + NULL|self)
                CALL                     0

 248            STORE_FAST               2 (token_option)

 258            LOAD_FAST                2 (token_option)
                POP_JUMP_IF_NOT_NONE     1 (to L4)

 259            RETURN_CONST             0 (None)

 261    L4:     LOAD_FAST                2 (token_option)
                LOAD_CONST              11 ('scan')
                COMPARE_OP              88 (bool(==))
                POP_JUMP_IF_FALSE       32 (to L6)

 262            LOAD_GLOBAL             17 (_discover_and_choose_token + NULL)
                LOAD_CONST              12 ('Select user token')
                CALL                     1
                STORE_FAST               3 (selection)

 263            LOAD_FAST                3 (selection)
                TO_BOOL
                POP_JUMP_IF_TRUE         1 (to L5)

 264            RETURN_CONST             0 (None)

 265    L5:     LOAD_FAST                3 (selection)
                LOAD_ATTR               18 (token)
                STORE_DEREF             16 (user_token)
                JUMP_FORWARD            19 (to L7)

 267    L6:     LOAD_GLOBAL             21 (_prompt_for_token + NULL)
                LOAD_CONST               4 ('User Token')
                CALL                     1
                STORE_DEREF             16 (user_token)

 268            LOAD_DEREF              16 (user_token)
                TO_BOOL
                POP_JUMP_IF_TRUE         1 (to L7)

 269            RETURN_CONST             0 (None)

 271    L7:     LOAD_GLOBAL             23 (_prompt_for_bot_token + NULL)
                CALL                     0
                STORE_DEREF             12 (bot_token)

 272            LOAD_DEREF              12 (bot_token)
                TO_BOOL
                POP_JUMP_IF_TRUE         1 (to L8)

 273            RETURN_CONST             0 (None)

 275    L8:     LOAD_GLOBAL             25 (yes_no_dialog + NULL)

 276            LOAD_CONST              13 ('Restore Guild Folders')

 277            LOAD_CONST              14 ('Restore server folders when possible?')

 275            LOAD_CONST              15 (('title', 'text'))
                CALL_KW                  2

 278            LOAD_ATTR               15 (run + NULL|self)
                CALL                     0

 275            STORE_DEREF             15 (restore_folders)

 280            LOAD_GLOBAL             25 (yes_no_dialog + NULL)

 281            LOAD_CONST              16 ('Version Mismatch')

 282            LOAD_CONST              17 ('Ignore backup version mismatches?')

 280            LOAD_CONST              15 (('title', 'text'))
                CALL_KW                  2

 283            LOAD_ATTR               15 (run + NULL|self)
                CALL                     0

 280            STORE_DEREF             10 (allow_mismatch)

 285            LOAD_GLOBAL             26 (AppConfig)
                LOAD_ATTR               28 (load)
                PUSH_NULL
                CALL                     0
                STORE_DEREF             14 (config)

 286            LOAD_GLOBAL             30 (io)
                LOAD_ATTR               32 (StringIO)
                PUSH_NULL
                CALL                     0
                STORE_DEREF             13 (buffer)

 288            LOAD_CONST              25 (('handle', 'ProgressHandle', 'return', 'tuple[str, str, bool, float]'))
                LOAD_FAST               10 (allow_mismatch)
                LOAD_FAST               11 (backup_data)
                LOAD_FAST               12 (bot_token)
                LOAD_FAST               13 (buffer)
                LOAD_FAST               14 (config)
                LOAD_FAST               15 (restore_folders)
                LOAD_FAST               16 (user_token)
                BUILD_TUPLE              7
                LOAD_CONST              18 (<code object worker at 0x000001EE5E850B90, file "discord_backup\tui.py", line 288>)
                MAKE_FUNCTION
                SET_FUNCTION_ATTRIBUTE   8 (closure)
                SET_FUNCTION_ATTRIBUTE   4 (annotations)
                STORE_FAST               4 (worker)

 305            NOP

 306    L9:     LOAD_GLOBAL             35 (run_with_loading + NULL)

 307            LOAD_CONST              19 ('Restoring backup')

 308            LOAD_CONST              20 ('Starting restore...')

 309            LOAD_FAST                4 (worker)

 306            CALL                     3
                UNPACK_SEQUENCE          4
                STORE_FAST_STORE_FAST   86 (guild_id, gif_status)
                STORE_FAST_STORE_FAST  120 (folders, duration)

 320   L10:     LOAD_GLOBAL             39 (_strip_ansi + NULL)
                LOAD_DEREF              13 (buffer)
                LOAD_ATTR               41 (getvalue + NULL|self)
                CALL                     0
                CALL                     1
                LOAD_CONST              23 (-2000)
                LOAD_CONST               0 (None)
                BINARY_SLICE
                STORE_FAST               9 (logs)

 321            LOAD_GLOBAL             43 (_show_with_details + NULL)

 322            LOAD_CONST              24 ('Restore complete')

 323            LOAD_GLOBAL             45 (_format_restore_summary + NULL)
                LOAD_FAST_LOAD_FAST     86 (guild_id, gif_status)
                LOAD_FAST_LOAD_FAST    120 (folders, duration)
                LOAD_FAST                9 (logs)
                CALL                     5

 324            LOAD_FAST                9 (logs)

 321            CALL                     3
                POP_TOP
                RETURN_CONST             0 (None)

  --   L11:     PUSH_EXC_INFO

 244            LOAD_GLOBAL              8 (Exception)
                CHECK_EXC_MATCH
                POP_JUMP_IF_FALSE       22 (to L15)
                STORE_FAST               1 (exc)

 245   L12:     LOAD_GLOBAL             11 (_show_error + NULL)
                LOAD_CONST               3 ('Invalid backup')
                LOAD_FAST                1 (exc)
                CALL                     2
                POP_TOP

 246   L13:     POP_EXCEPT
                LOAD_CONST               0 (None)
                STORE_FAST               1 (exc)
                DELETE_FAST              1 (exc)
                RETURN_CONST             0 (None)

  --   L14:     LOAD_CONST               0 (None)
                STORE_FAST               1 (exc)
                DELETE_FAST              1 (exc)
                RERAISE                  1

 244   L15:     RERAISE                  0

  --   L16:     COPY                     3
                POP_EXCEPT
                RERAISE                  1
       L17:     PUSH_EXC_INFO

 311            LOAD_GLOBAL             36 (RestoreError)
                CHECK_EXC_MATCH
                POP_JUMP_IF_FALSE       47 (to L21)
                STORE_FAST               1 (exc)

 312   L18:     LOAD_GLOBAL             39 (_strip_ansi + NULL)
                LOAD_DEREF              13 (buffer)
                LOAD_ATTR               41 (getvalue + NULL|self)
                CALL                     0
                CALL                     1
                STORE_FAST               9 (logs)

 313            LOAD_GLOBAL             11 (_show_error + NULL)
                LOAD_CONST              21 ('Restore failed')
                LOAD_FAST_LOAD_FAST     25 (exc, logs)
                CALL                     3
                POP_TOP

 314   L19:     POP_EXCEPT
                LOAD_CONST               0 (None)
                STORE_FAST               1 (exc)
                DELETE_FAST              1 (exc)
                RETURN_CONST             0 (None)

  --   L20:     LOAD_CONST               0 (None)
                STORE_FAST               1 (exc)
                DELETE_FAST              1 (exc)
                RERAISE                  1

 315   L21:     LOAD_GLOBAL              8 (Exception)
                CHECK_EXC_MATCH
                POP_JUMP_IF_FALSE       47 (to L25)
                STORE_FAST               1 (exc)

 316   L22:     LOAD_GLOBAL             39 (_strip_ansi + NULL)
                LOAD_DEREF              13 (buffer)
                LOAD_ATTR               41 (getvalue + NULL|self)
                CALL                     0
                CALL                     1
                STORE_FAST               9 (logs)

 317            LOAD_GLOBAL             11 (_show_error + NULL)
                LOAD_CONST              22 ('Unexpected error')
                LOAD_FAST_LOAD_FAST     25 (exc, logs)
                CALL                     3
                POP_TOP

 318   L23:     POP_EXCEPT
                LOAD_CONST               0 (None)
                STORE_FAST               1 (exc)
                DELETE_FAST              1 (exc)
                RETURN_CONST             0 (None)

  --   L24:     LOAD_CONST               0 (None)
                STORE_FAST               1 (exc)
                DELETE_FAST              1 (exc)
                RERAISE                  1

 315   L25:     RERAISE                  0

  --   L26:     COPY                     3
                POP_EXCEPT
                RERAISE                  1
ExceptionTable:
  L2 to L3 -> L11 [0]
  L9 to L10 -> L17 [0]
  L11 to L12 -> L16 [1] lasti
  L12 to L13 -> L14 [1] lasti
  L14 to L16 -> L16 [1] lasti
  L17 to L18 -> L26 [1] lasti
  L18 to L19 -> L20 [1] lasti
  L20 to L22 -> L26 [1] lasti
  L22 to L23 -> L24 [1] lasti
  L24 to L26 -> L26 [1] lasti

Disassembly of <code object worker at 0x000001EE5E850B90, file "discord_backup\tui.py", line 288>:
  --           COPY_FREE_VARS           7
               MAKE_CELL                0 (handle)

 288           RESUME                   0

 289           LOAD_FAST                0 (handle)
               BUILD_TUPLE              1
               LOAD_CONST               1 (<code object <lambda> at 0x000001EE5E816D30, file "discord_backup\tui.py", line 289>)
               MAKE_FUNCTION
               SET_FUNCTION_ATTRIBUTE   8 (closure)
               STORE_FAST               1 (stripped_update)

 290           LOAD_GLOBAL              1 (Console + NULL)
               LOAD_DEREF               8 (config)
               LOAD_ATTR                2 (colour)
               LOAD_DEREF               7 (buffer)
               LOAD_FAST                1 (stripped_update)
               LOAD_CONST               2 (('accent', 'stream', 'status_callback'))
               CALL_KW                  3
               STORE_FAST               2 (console)

 291           LOAD_DEREF               0 (handle)
               LOAD_ATTR                5 (update + NULL|self)
               LOAD_CONST               3 ('Preparing restore...')
               CALL                     1
               POP_TOP

 292           LOAD_GLOBAL              6 (asyncio)
               LOAD_ATTR                8 (run)
               PUSH_NULL

 293           LOAD_GLOBAL             11 (_async_run_restore + NULL)

 294           LOAD_DEREF               5 (backup_data)

 295           LOAD_DEREF              10 (user_token)

 296           LOAD_DEREF               6 (bot_token)

 297           LOAD_DEREF               9 (restore_folders)

 298           LOAD_DEREF               4 (allow_mismatch)

 299           LOAD_FAST                2 (console)

 293           CALL                     6

 292           CALL                     1
               STORE_FAST               3 (result)

 302           LOAD_DEREF               0 (handle)
               LOAD_ATTR                5 (update + NULL|self)
               LOAD_CONST               4 ('Finishing up...')
               CALL                     1
               POP_TOP

 303           LOAD_FAST                3 (result)
               RETURN_VALUE

Disassembly of <code object <lambda> at 0x000001EE5E816D30, file "discord_backup\tui.py", line 289>:
  --           COPY_FREE_VARS           1

 289           RESUME                   0
               LOAD_DEREF               1 (handle)
               LOAD_ATTR                1 (update + NULL|self)
               LOAD_GLOBAL              3 (_strip_ansi + NULL)
               LOAD_FAST                0 (msg)
               CALL                     1
               CALL                     1
               RETURN_VALUE


# --- Nested: _show_tokens_list ---

 328            RESUME                   0

 329            NOP

 330    L1:     LOAD_GLOBAL              1 (_discover_tokens_with_loading + NULL)
                CALL                     0
                STORE_FAST               0 (tokens)

 334    L2:     LOAD_FAST                0 (tokens)
                TO_BOOL
                POP_JUMP_IF_TRUE        25 (to L3)

 335            LOAD_GLOBAL              7 (message_dialog + NULL)
                LOAD_CONST               2 ('Tokens')
                LOAD_CONST               3 ('No tokens discovered.')
                LOAD_CONST               4 (('title', 'text'))
                CALL_KW                  2
                LOAD_ATTR                9 (run + NULL|self)
                CALL                     0
                POP_TOP

 336            RETURN_CONST             0 (None)

 337    L3:     LOAD_FAST                0 (tokens)
                GET_ITER
                LOAD_FAST_AND_CLEAR      2 (tok)
                SWAP                     2
        L4:     BUILD_LIST               0
                SWAP                     2
                GET_ITER
        L5:     FOR_ITER                42 (to L6)
                STORE_FAST_LOAD_FAST    34 (tok, tok)
                LOAD_ATTR               10 (user_tag)
                FORMAT_SIMPLE
                LOAD_CONST               5 (' (')
                LOAD_FAST                2 (tok)
                LOAD_ATTR               12 (user_id)
                FORMAT_SIMPLE
                LOAD_CONST               6 (') - ')
                LOAD_FAST                2 (tok)
                LOAD_ATTR               14 (source)
                FORMAT_SIMPLE
                BUILD_STRING             5
                LIST_APPEND              2
                JUMP_BACKWARD           44 (to L5)
        L6:     END_FOR
                POP_TOP
        L7:     STORE_FAST               3 (lines)
                STORE_FAST               2 (tok)

 338            LOAD_GLOBAL              7 (message_dialog + NULL)
                LOAD_CONST               7 ('Discovered Tokens')
                LOAD_CONST               8 ('\n')
                LOAD_ATTR               17 (join + NULL|self)
                LOAD_FAST                3 (lines)
                CALL                     1
                LOAD_CONST               4 (('title', 'text'))
                CALL_KW                  2
                LOAD_ATTR                9 (run + NULL|self)
                CALL                     0
                POP_TOP
                RETURN_CONST             0 (None)

  --    L8:     PUSH_EXC_INFO

 331            LOAD_GLOBAL              2 (Exception)
                CHECK_EXC_MATCH
                POP_JUMP_IF_FALSE       22 (to L12)
                STORE_FAST               1 (exc)

 332    L9:     LOAD_GLOBAL              5 (_show_error + NULL)
                LOAD_CONST               1 ('Token discovery failed')
                LOAD_FAST                1 (exc)
                CALL                     2
                POP_TOP

 333   L10:     POP_EXCEPT
                LOAD_CONST               0 (None)
                STORE_FAST               1 (exc)
                DELETE_FAST              1 (exc)
                RETURN_CONST             0 (None)

  --   L11:     LOAD_CONST               0 (None)
                STORE_FAST               1 (exc)
                DELETE_FAST              1 (exc)
                RERAISE                  1

 331   L12:     RERAISE                  0

  --   L13:     COPY                     3
                POP_EXCEPT
                RERAISE                  1
       L14:     SWAP                     2
                POP_TOP

 337            SWAP                     2
                STORE_FAST               2 (tok)
                RERAISE                  0
ExceptionTable:
  L1 to L2 -> L8 [0]
  L4 to L7 -> L14 [2]
  L8 to L9 -> L13 [1] lasti
  L9 to L10 -> L11 [1] lasti
  L11 to L13 -> L13 [1] lasti


# --- Nested: _handle_startup_add ---

341           RESUME                   0

342           LOAD_GLOBAL              1 (_discover_and_choose_token + NULL)
              LOAD_CONST               1 ('Select account for auto-backup')
              CALL                     1
              STORE_FAST               0 (selection)

343           LOAD_FAST                0 (selection)
              TO_BOOL
              POP_JUMP_IF_TRUE         1 (to L1)

344           RETURN_CONST             0 (None)

345   L1:     LOAD_GLOBAL              3 (_project_root + NULL)
              CALL                     0
              STORE_FAST               1 (root)

346           LOAD_GLOBAL              5 (Path + NULL)
              LOAD_GLOBAL              7 (getattr + NULL)
              LOAD_GLOBAL              8 (sys)
              LOAD_CONST               2 ('frozen')
              LOAD_CONST               3 (False)
              CALL                     3
              TO_BOOL
              POP_JUMP_IF_FALSE       16 (to L2)
              LOAD_GLOBAL              8 (sys)
              LOAD_ATTR               10 (executable)
              JUMP_FORWARD             4 (to L3)
      L2:     LOAD_FAST                1 (root)
              LOAD_CONST               4 ('main.py')
              BINARY_OP               11 (/)
      L3:     CALL                     1
              STORE_FAST               2 (executable)

347           LOAD_FAST                2 (executable)
              LOAD_ATTR               12 (suffix)
              LOAD_CONST               5 ('.py')
              COMPARE_OP              88 (bool(==))
              POP_JUMP_IF_FALSE       23 (to L4)

348           LOAD_CONST               6 ('cmd.exe /C python "')
              LOAD_FAST                2 (executable)
              FORMAT_SIMPLE
              LOAD_CONST               7 ('" auto-backup --account-id ')
              LOAD_FAST                0 (selection)
              LOAD_ATTR               14 (user_id)
              FORMAT_SIMPLE
              LOAD_CONST               8 (' --working-dir "')
              LOAD_FAST                1 (root)
              FORMAT_SIMPLE
              LOAD_CONST               9 ('"')
              BUILD_STRING             7
              STORE_FAST               3 (command)
              JUMP_FORWARD            22 (to L5)

350   L4:     LOAD_CONST               9 ('"')
              LOAD_FAST                2 (executable)
              FORMAT_SIMPLE
              LOAD_CONST               7 ('" auto-backup --account-id ')
              LOAD_FAST                0 (selection)
              LOAD_ATTR               14 (user_id)
              FORMAT_SIMPLE
              LOAD_CONST               8 (' --working-dir "')
              LOAD_FAST                1 (root)
              FORMAT_SIMPLE
              LOAD_CONST               9 ('"')
              BUILD_STRING             7
              STORE_FAST               3 (command)

351   L5:     LOAD_GLOBAL             17 (write_startup_script + NULL)
              LOAD_FAST_LOAD_FAST     49 (command, root)
              CALL                     2
              STORE_FAST               4 (script_path)

352           LOAD_GLOBAL             19 (message_dialog + NULL)
              LOAD_CONST              10 ('Startup')
              LOAD_CONST              11 ('Auto-backup script saved to ')
              LOAD_FAST                4 (script_path)
              FORMAT_SIMPLE
              BUILD_STRING             2
              LOAD_CONST              12 (('title', 'text'))
              CALL_KW                  2
              LOAD_ATTR               21 (run + NULL|self)
              CALL                     0
              POP_TOP
              RETURN_CONST             0 (None)


# --- Nested: _handle_startup_remove ---

355           RESUME                   0

356           LOAD_GLOBAL              1 (remove_startup_script + NULL)
              CALL                     0
              TO_BOOL
              POP_JUMP_IF_FALSE       25 (to L1)

357           LOAD_GLOBAL              3 (message_dialog + NULL)
              LOAD_CONST               1 ('Startup')
              LOAD_CONST               2 ('Startup script removed.')
              LOAD_CONST               3 (('title', 'text'))
              CALL_KW                  2
              LOAD_ATTR                5 (run + NULL|self)
              CALL                     0
              POP_TOP
              RETURN_CONST             0 (None)

359   L1:     LOAD_GLOBAL              3 (message_dialog + NULL)
              LOAD_CONST               1 ('Startup')
              LOAD_CONST               4 ('No startup script found.')
              LOAD_CONST               3 (('title', 'text'))
              CALL_KW                  2
              LOAD_ATTR                5 (run + NULL|self)
              CALL                     0
              POP_TOP
              RETURN_CONST             0 (None)


# --- Nested: run_tui ---

 362            RESUME                   0

 363            NOP

 364    L1:     LOAD_GLOBAL              1 (radiolist_dialog + NULL)

 365            LOAD_CONST               1 ('Discord Backup')

 366            LOAD_CONST               2 ('Select an action (use arrow keys, Enter to confirm)')

 367            BUILD_LIST               0
                LOAD_CONST               3 ((('backup_scan', 'Backup (scan tokens on this machine)'), ('backup_manual', 'Backup (paste token manually)'), ('restore', 'Restore from an existing .bkup file'), ('tokens', 'View discovered tokens'), ('startup_add', 'Add auto-backup to Windows startup'), ('startup_remove', 'Remove auto-backup from Windows startup'), ('exit', 'Exit')))
                LIST_EXTEND              1

 376            LOAD_CONST               4 ('Select')

 377            LOAD_CONST               5 ('Quit')

 364            LOAD_CONST               6 (('title', 'text', 'values', 'ok_text', 'cancel_text'))
                CALL_KW                  5

 378            LOAD_ATTR                3 (run + NULL|self)
                CALL                     0

 364            STORE_FAST               0 (action)

 380            LOAD_FAST                0 (action)
                LOAD_CONST               7 ((None, 'exit'))
                CONTAINS_OP              0
                POP_JUMP_IF_FALSE       25 (to L2)

 381            LOAD_GLOBAL              5 (message_dialog + NULL)
                LOAD_CONST               8 ('Goodbye')
                LOAD_CONST               9 ('Stay safe and keep your backups handy!')
                LOAD_CONST              10 (('title', 'text'))
                CALL_KW                  2
                LOAD_ATTR                3 (run + NULL|self)
                CALL                     0
                POP_TOP

 382            RETURN_CONST             0 (None)

 383    L2:     LOAD_FAST                0 (action)
                LOAD_CONST              11 ('backup_scan')
                COMPARE_OP              88 (bool(==))
                POP_JUMP_IF_FALSE       40 (to L4)

 384            LOAD_GLOBAL              7 (_discover_and_choose_token + NULL)
                LOAD_CONST              12 ('Select token for backup')
                CALL                     1
                STORE_FAST               1 (selection)

 385            LOAD_FAST                1 (selection)
                TO_BOOL
                POP_JUMP_IF_FALSE       21 (to L3)

 386            LOAD_GLOBAL              9 (_run_backup_flow + NULL)
                LOAD_FAST                1 (selection)
                LOAD_ATTR               10 (token)
                CALL                     1
                POP_TOP

  --    L3:     JUMP_FORWARD           103 (to L10)

 387    L4:     LOAD_FAST                0 (action)
                LOAD_CONST              13 ('backup_manual')
                COMPARE_OP              88 (bool(==))
                POP_JUMP_IF_FALSE       30 (to L6)

 388            LOAD_GLOBAL             13 (_prompt_for_token + NULL)
                LOAD_CONST              14 ('Manual Backup')
                CALL                     1
                STORE_FAST               2 (token)

 389            LOAD_FAST                2 (token)
                TO_BOOL
                POP_JUMP_IF_FALSE       11 (to L5)

 390            LOAD_GLOBAL              9 (_run_backup_flow + NULL)
                LOAD_FAST                2 (token)
                CALL                     1
                POP_TOP

  --    L5:     JUMP_FORWARD            67 (to L10)

 391    L6:     LOAD_FAST                0 (action)
                LOAD_CONST              15 ('restore')
                COMPARE_OP              88 (bool(==))
                POP_JUMP_IF_FALSE       11 (to L7)

 392            LOAD_GLOBAL             15 (_run_restore_flow + NULL)
                CALL                     0
                POP_TOP
                JUMP_FORWARD            50 (to L10)

 393    L7:     LOAD_FAST                0 (action)
                LOAD_CONST              16 ('tokens')
                COMPARE_OP              88 (bool(==))
                POP_JUMP_IF_FALSE       11 (to L8)

 394            LOAD_GLOBAL             17 (_show_tokens_list + NULL)
                CALL                     0
                POP_TOP
                JUMP_FORWARD            33 (to L10)

 395    L8:     LOAD_FAST                0 (action)
                LOAD_CONST              17 ('startup_add')
                COMPARE_OP              88 (bool(==))
                POP_JUMP_IF_FALSE       11 (to L9)

 396            LOAD_GLOBAL             19 (_handle_startup_add + NULL)
                CALL                     0
                POP_TOP
                JUMP_FORWARD            16 (to L10)

 397    L9:     LOAD_FAST                0 (action)
                LOAD_CONST              18 ('startup_remove')
                COMPARE_OP              88 (bool(==))
                POP_JUMP_IF_FALSE       10 (to L10)

 398            LOAD_GLOBAL             21 (_handle_startup_remove + NULL)
                CALL                     0
                POP_TOP

 363   L10:     JUMP_BACKWARD          211 (to L1)
